Workbook
Name page1: BS!#REF!
Name page1: 'BS analysis'!#REF!
Name page4: Notes!#REF!
Name page5: Notes!$A$113
Name page6: Notes!#REF!
Name QBCANSUPPORTUPDATE: TRUE
Name QBCOMPANYFILENAME: "Z:\Intuit\QuickBooks\Company Files\Va8ive Digital Marketing Pvt Ltd.qbw"
Name QBENDDATE: 20201231
Name QBHEADERSONSCREEN: FALSE
Name QBMETADATASIZE: 5914
Name QBPRESERVECOLOR: TRUE
Name QBPRESERVEFONT: TRUE
Name QBPRESERVEROWHEIGHT: TRUE
Name QBPRESERVESPACE: TRUE
Name QBREPORTCOLAXIS: 0
Name QBREPORTCOMPANYID: "a6cce7daed6d426fb8540acc6752ea7a"
Name QBREPORTCOMPARECOL_ANNUALBUDGET: FALSE
Name QBREPORTCOMPARECOL_AVGCOGS: FALSE
Name QBREPORTCOMPARECOL_AVGPRICE: FALSE
Name QBREPORTCOMPARECOL_BUDDIFF: FALSE
Name QBREPORTCOMPARECOL_BUDGET: FALSE
Name QBREPORTCOMPARECOL_BUDPCT: FALSE
Name QBREPORTCOMPARECOL_COGS: FALSE
Name QBREPORTCOMPARECOL_EXCLUDEAMOUNT: FALSE
Name QBREPORTCOMPARECOL_EXCLUDECURPERIOD: FALSE
Name QBREPORTCOMPARECOL_FORECAST: FALSE
Name QBREPORTCOMPARECOL_GROSSMARGIN: FALSE
Name QBREPORTCOMPARECOL_GROSSMARGINPCT: FALSE
Name QBREPORTCOMPARECOL_HOURS: FALSE
Name QBREPORTCOMPARECOL_PCTCOL: FALSE
Name QBREPORTCOMPARECOL_PCTEXPENSE: FALSE
Name QBREPORTCOMPARECOL_PCTINCOME: FALSE
Name QBREPORTCOMPARECOL_PCTOFSALES: FALSE
Name QBREPORTCOMPARECOL_PCTROW: FALSE
Name QBREPORTCOMPARECOL_PPDIFF: FALSE
Name QBREPORTCOMPARECOL_PPPCT: FALSE
Name QBREPORTCOMPARECOL_PREVPERIOD: FALSE
Name QBREPORTCOMPARECOL_PREVYEAR: FALSE
Name QBREPORTCOMPARECOL_PYDIFF: FALSE
Name QBREPORTCOMPARECOL_PYPCT: FALSE
Name QBREPORTCOMPARECOL_QTY: FALSE
Name QBREPORTCOMPARECOL_RATE: FALSE
Name QBREPORTCOMPARECOL_TRIPBILLEDMILES: FALSE
Name QBREPORTCOMPARECOL_TRIPBILLINGAMOUNT: FALSE
Name QBREPORTCOMPARECOL_TRIPMILES: FALSE
Name QBREPORTCOMPARECOL_TRIPNOTBILLABLEMILES: FALSE
Name QBREPORTCOMPARECOL_TRIPTAXDEDUCTIBLEAMOUNT: FALSE
Name QBREPORTCOMPARECOL_TRIPUNBILLEDMILES: FALSE
Name QBREPORTCOMPARECOL_YTD: FALSE
Name QBREPORTCOMPARECOL_YTDBUDGET: FALSE
Name QBREPORTCOMPARECOL_YTDPCT: FALSE
Name QBREPORTROWAXIS: 12
Name QBREPORTSUBCOLAXIS: 23
Name QBREPORTTYPE: 27
Name QBROWHEADERS: 2
Name QBSTARTDATE: 20200701

Sheet Main Sheet
A15: Entity Name
A17: FINANCIAL STATEMENTS
A19: Period

Sheet BS
A1: ENTITY NAME
A2: BALANCE SHEET
A3: AS AT MARCH 31, 2022
C4: MARCH | E4: JUNE
C5: 2022 | E5: 2021
B6: Note | C6: (Rupees) | E6: (Rupees)
A7: ASSETS
A8: NON-CURRENT ASSETS
A10: Property, plant and equipment | B10: 1 | C10: =+Notes!C19 -> 36188824 | E10: 22993036 | F10: 22993036 | G10: =E10-F10 -> 0
A11: Intangible Assets | C11: 0 | E11: 0
A12: Long Term Deposit | B12: 3 | C12: =+Notes!C27 -> 4158000 | E12: =+Notes!E27 -> 0
C13: =SUM(C10:C12) -> 40346824 | E13: =SUM(E10:E12) -> 22993036
A14: CURRENT ASSETS
A16: Cash and bank balances | B16: 2 | C16: =+Notes!C43 -> 22595976 | E16: 30348317 | F16: 30348317 | G16: =E16-F16 -> 0
A17: Investment | B17: 3 | C17: =+Notes!C49 -> 18500000 | E17: 18500000 | F17: 18500000 | G17: =E17-F17 -> 0
A18: Accrued markup on short-term investment | C18: 214618 | E18: 214618 | F18: 0 | G18: =E18-F18 -> 214618
A19: Advances and prepayments | B19: 4 | C19: =+Notes!C54 -> 1375929 | E19: 545100 | F19: 545100 | G19: =E19-F19 -> 0
A20: Receivable from Innovate under cost + 20% | C20: =+Notes!C98+360031 -> 1.2949452e+08 | E20: 65941521 | G20: =E20-F20 -> 65941521 | P20: =+C20/183.48 -> 705769.14
A21: Short-term loan | C21: 0 | E21: 0 | G21: =E21-F21 -> 0
A22: Loan to 8th Loop | C22: =+Notes!K29 -> 30157677 | E22: 40157677 | H22: 40000000
A23: Other receivables | C23: =+Notes!C60 -> 177000 | E23: 0
C24: =SUM(C16:C23) -> 2.0251572e+08 | E24: =SUM(E16:E23) -> 155707233
A26: TOTAL ASSETS | C26: =C13+C24 -> 2.4286255e+08 | E26: =E13+E24 -> 178700269
A28: CAPITAL AND RESERVES
A29: Authorized Capital 350,000 (2020: 350,000) Ordinary shares of Rs. 100/- | C29: 35000000 | E29: 35000000
A30: Issued, subscribed and paid-up capital | C30: =+Notes!L70+Notes!L71 -> 137443539 | E30: 31412500 | F30: =C30-E30 -> 106031039 | I30: =C30-E30 -> 106031039
A31: Share premium | C31: 0 | E31: 0
A32: Accumulated profit | C32: =+E32+PnL!C31 -> 82369892 | E32: 55183646 | J32: =C32-I32 -> 82369892 | N32: 54823615 | O32: =C32-N32 -> 27546277
A33: Advance against equity | C33: 0 | E33: 84000000 | F33: =C33-E33 -> -84000000 | I33: =C33-E33 -> -84000000
C34: =SUM(C30:C33) -> 2.1981343e+08 | E34: =SUM(E30:E33) -> 170596146
A35: NON-CURRENT LIABILITES
A37: Long Term Loan | C37: =+Notes!L66 -> 1943523 | E37: 1943519
C38: =C37 -> 1943523 | E38: =E37 -> 1943519
A40: CURRENT LIABILITIES | O40: =#REF!-O32 -> #REF!
A42: Trade and other payables | B42: 5 | C42: =+Notes!C80 -> 13383837 | E42: 2273567
A43: First Habib Modarba | C43: =+Notes!L68 -> 6750000 | E43: 0
A44: SBP Loan | C44: =+Notes!L65 -> 971754.89 | E44: 3887037
C45: =SUM(C42:C44) -> 21105592 | E45: =SUM(E42:E44) -> 6160604
A47: TOTAL EQUITY AND LIABILITIES | C47: =C34+C38+C45 -> 2.4286255e+08 | E47: =E34+E38+E45 -> 178700269
C49: =C26-C47 -> -0.25999999 | E49: =E26-E47 -> 0

Sheet BS analysis
A1: ENTITY NAME
A2: BALANCE SHEET
A3: AS AT MARCH 31, 2022
C4: MARCH | E4: JUNE
C5: 2022 | E5: 2021
B6: Note | C6: (Rupees) | E6: (Rupees)
A7: ASSETS
A8: NON-CURRENT ASSETS
A10: Property, plant and equipment | B10: 1 | C10: =+Notes!C19 -> 36188824 | E10: 22993036 | F10: 22993036 | G10: =E10-F10 -> 0
A11: Intangible Assets | C11: 0 | E11: 0
A12: Long Term Deposit | B12: 3 | C12: =+Notes!C27 -> 4158000 | E12: =+Notes!E27 -> 0
C13: =SUM(C10:C12) -> 40346824 | E13: =SUM(E10:E12) -> 22993036
A14: CURRENT ASSETS
A16: Cash and bank balances | B16: 2 | C16: =+Notes!C43 -> 22595976 | E16: 30348317 | F16: 30348317 | G16: =E16-F16 -> 0
A17: Investment | B17: 3 | C17: =+Notes!C49 -> 18500000 | E17: 18500000 | F17: 18500000 | G17: =E17-F17 -> 0
A18: Accrued markup on short-term investment | C18: 214618 | E18: 214618 | F18: 0 | G18: =E18-F18 -> 214618
A19: Advances and prepayments | B19: 4 | C19: =+Notes!C54 -> 1375929 | E19: 545100 | F19: 545100 | G19: =E19-F19 -> 0
A20: Receivable from Innovate under cost + 20% | C20: =+Notes!C98+360031 -> 1.2949452e+08 | E20: 65941521 | G20: =E20-F20 -> 65941521 | P20: =+C20/183.48 -> 705769.14
A21: Short-term loan | C21: 0 | E21: 0 | G21: =E21-F21 -> 0
A22: Loan to 8th Loop | C22: =+Notes!K29 -> 30157677 | E22: 40157677 | H22: 40000000
A23: Other receivables | C23: =+Notes!C60 -> 177000 | E23: 0
C24: =SUM(C16:C23) -> 2.0251572e+08 | E24: =SUM(E16:E23) -> 155707233
A26: TOTAL ASSETS | C26: =C13+C24 -> 2.4286255e+08 | E26: =E13+E24 -> 178700269
A28: CAPITAL AND RESERVES
A29: Authorized Capital 350,000 (2020: 350,000) Ordinary shares of Rs. 100/- | C29: 35000000 | E29: 35000000
A30: Issued, subscribed and paid-up capital | C30: =+Notes!L70+Notes!L71 -> 137443539 | E30: 31412500 | F30: =C30-E30 -> 106031039 | I30: =C30-E30 -> 106031039
A31: Share premium | C31: 0 | E31: 0
A32: Accumulated profit | C32: =+E32+PnL!C31 -> 82369892 | E32: 55183646 | J32: =C32-I32 -> 82369892 | N32: 54823615 | O32: =C32-N32 -> 27546277
A33: Advance against equity | C33: 0 | E33: 84000000 | F33: =C33-E33 -> -84000000 | I33: =C33-E33 -> -84000000
C34: =SUM(C30:C33) -> 2.1981343e+08 | E34: =SUM(E30:E33) -> 170596146
A35: NON-CURRENT LIABILITES
A37: Long Term Loan | C37: =+Notes!L66 -> 1943523 | E37: 1943519
C38: =C37 -> 1943523 | E38: =E37 -> 1943519
A40: CURRENT LIABILITIES | O40: =#REF!-O32 -> #REF!
A42: Trade and other payables | B42: 5 | C42: =+Notes!C80 -> 13383837 | E42: 2273567
A43: First Habib Modarba | C43: =+Notes!L68 -> 6750000 | E43: 0
A44: SBP Loan | C44: =+Notes!L65 -> 971754.89 | E44: 3887037
C45: =SUM(C42:C44) -> 21105592 | E45: =SUM(E42:E44) -> 6160604
A47: TOTAL EQUITY AND LIABILITIES | C47: =C34+C38+C45 -> 2.4286255e+08 | E47: =E34+E38+E45 -> 178700269
C49: =C26-C47 -> -0.25999999 | E49: =E26-E47 -> 0

Sheet PnL
A1: VA8IVE (PVT.) LIMITED
A2: PROFIT AND LOSS ACCOUNT
A3: FOR NINE MONTHS ENDED MARCH 31, 2022
B8: Note | C8: MARCH | E8: MARCH
C9: 2022 | E9: 2021
C10: (Rupees) | E10: (Rupees)
A11: Revenue (Cost + 20%) | B11: 6 | C11: =+Notes!C85 -> 1.520594e+08 | E11: =+Notes!E98 -> 37449354 | G11: =+C11/171.47 -> 886798.88 | I11: =+C11/183.48 -> 828751.92
A12: Interest Income | B12: 7 | C12: =+Notes!C107 -> 1843012.2 | E12: =+Notes!E107 -> 762211.93
A13: Land Rent | E13: -
C14: =SUM(C11:C13) -> 1.5390242e+08 | E14: =SUM(E11:E12) -> 38211566
A16: GROSS COSTS
A18: Payroll | C18: 0 | E18: 0
A19: ABC | C19: 0 | E19: 0
A20: XYZ | C20: 0 | E20: 0
C21: =SUM(C18:C20) -> 0 | E21: =SUM(E18:E20) -> 0
A23: GROSS PROFIT | C23: =+C14-C21 -> 1.5390242e+08 | E23: =+E14-E21 -> 38211566
A25: Operational Cost | B25: 8 | C25: =+Notes!C134 -> 1.1719688e+08 | E25: =+Notes!E134 -> 30996237
A26: Administrative Cost | B26: 9 | C26: =+Notes!C171 -> 9516959.4 | E26: =+Notes!E171 -> 6273632
A27: Finance Charges Cost | B27: 10 | C27: =+Notes!C184 -> 2327.8 | E27: 0
A28: Other Expenses | C28: =+[1]Notes!C196 -> 0 | E28: 0
C29: =SUM(C25:C28) -> 1.2671617e+08 | E29: =SUM(E25:E28) -> 37269869
A31: Profit / Loss for the Period | C31: =+C23-C29 -> 27186246 | E31: =+E23-E29 -> 941696.4
C35: =+Notes!L144 -> -36006723
C36: =C31-C35 -> 63192969

Sheet PnL Analysis
A1: VA8IVE (PVT.) LIMITED
A2: PROFIT AND LOSS ACCOUNT
A3: FOR NINE MONTHS ENDED MARCH 31, 2022
B8: Note | C8: MARCH | E8: MARCH
C9: 2022 | E9: 2021
C10: (Rupees) | E10: (Rupees)
A11: Revenue (Cost + 20%) | B11: 6 | C11: =+Notes!C85 -> 1.520594e+08 | E11: =+Notes!E98 -> 37449354 | G11: =+C11/171.47 -> 886798.88 | I11: =+C11/183.48 -> 828751.92
A12: Interest Income | B12: 7 | C12: =+Notes!C107 -> 1843012.2 | E12: =+Notes!E107 -> 762211.93
A13: Land Rent | E13: -
C14: =SUM(C11:C13) -> 1.5390242e+08 | E14: =SUM(E11:E12) -> 38211566
A16: GROSS COSTS
A18: Payroll | C18: 0 | E18: 0
A19: ABC | C19: 0 | E19: 0
A20: XYZ | C20: 0 | E20: 0
C21: =SUM(C18:C20) -> 0 | E21: =SUM(E18:E20) -> 0
A23: GROSS PROFIT | C23: =+C14-C21 -> 1.5390242e+08 | E23: =+E14-E21 -> 38211566
A25: Operational Cost | B25: 8 | C25: =+Notes!C134 -> 1.1719688e+08 | E25: =+Notes!E134 -> 30996237
A26: Administrative Cost | B26: 9 | C26: =+Notes!C171 -> 9516959.4 | E26: =+Notes!E171 -> 6273632
A27: Finance Charges Cost | B27: 10 | C27: =+Notes!C184 -> 2327.8 | E27: 0
A28: Other Expenses | C28: =+[1]Notes!C196 -> 0 | E28: 0
C29: =SUM(C25:C28) -> 1.2671617e+08 | E29: =SUM(E25:E28) -> 37269869
A31: Profit / Loss for the Period | C31: =+C23-C29 -> 27186246 | E31: =+E23-E29 -> 941696.4
C35: =+Notes!L144 -> -36006723
C36: =C31-C35 -> 63192969

Sheet Notes
A1: VA8IVE (PVT.) LIMITED
A2: NOTES TO THE FINANCIAL STATEMENTS | K2: Mar 31, 22
A3: FOR THE PERIOD ENDED MARCH 31, 2022 | K3: Debit | L3: Credit
J4: Treasury Account:Treasury Account # 6915-01-9 | K4: 778.64
J5: Treasury Account:Treasury Account # 5804-01-3 | K5: 85829.58
C6: MARCH | E6: JUNE | J6: Bank & Cash:BAHL # 04018 | K6: 22340813
A7: 1 Property, plant and equipment | C7: 2022 | E7: 2021 | J7: Bank & Cash:BAHL # 15014 | K7: 130726.57
C8: (Rupees) | E8: (Rupees) | J8: Bank & Cash:Petty Cash | K8: 37828.2
J9: Bank & Cash:PR Bank | K9: 0
A10: Building - Improvement | C10: =K13 -> 11504191 | E10: 9837940.8 | J10: Generator | K10: 1150000
A11: Computer & Accessories | C11: =+K15 -> 7027994 | E11: 4345390 | J11: Solar Panel | K11: 2537000
A12: Furniture and Equipment | C12: =K16+K31 -> 7359169.2 | E12: 8693140.2 | J12: Appliances | K12: 31649
A13: Vehicle | C13: =+K18+K19+K20+K17 -> 13893000 | E13: 5852000 | J13: Building - Improvement | K13: 11504191
A14: Solar Panel | C14: =+K11 -> 2537000 | E14: 2537000 | J14: Building - Improvement:Cameras | K14: 300216
A15: Building - Improvement:Cameras | C15: =+K14 -> 300216 | E15: 278716 | J15: Computer & Accessories | K15: 7027994
A16: Generrator | C16: =K10 -> 1150000 | E16: 1150000 | J16: Furniture and Equipment | K16: 7359169.2
A17: Others | C17: =+K12 -> 31649 | E17: 31649 | J17: Vehicle:Hilux Revo | K17: 8041000
A18: Less: Accumulated Deprecitaion | C18: =-L21 -> -7614395 | E18: -4745182 | G18: =E18/SUM(E10:E17)*100 -> -14.499804 | H18: =C18/SUM(C10:C17)*100 -> -17.383186 | J18: Vehicle:Kia Sportage | K18: 4318000
C19: =SUM(C10:C18) -> 36188824 | E19: =SUM(E10:E18) -> 27980654 | G19: =SUM(C10:C17)*10/100/2 -> 2190160.9 | H19: =C18+H17 -> -7614395 | J19: Vehicle:Bike | K19: 95000
G20: =E18-C18-595878 -> 2273335 | J20: Vehicle:Changan Van | K20: 1439000
A21: 2 Intangible Assets | C21: =+K22 -> 0 | E21: 0 | J21: Accumulated Depreciation | L21: 7614395
A22: Less: Accumulated Intangible Assets | C22: 0 | E22: 0 | J22: Intangible Asset
J23: TDR # 3457 | K23: 10000000
A24: 2 Intangible Assets | C24: 0 | E24: 0 | J24: TDR # 3446 | K24: 8500000
J25: Accrued Markup On TDR | K25: 214617.82
A26: 2 Long Term Deposit | C26: =+K32 -> 4158000 | E26: 0 | J26: Receivable From Innova8e | K26: 65941521
A27: Tenancy Deposit | C27: =C26 -> 4158000 | E27: =E26 -> 0 | J27: Other Receivables:Content Hub | K27: 177000
J28: Loan:Syed Ali Naqi | L28: 8320052
J29: Loan:8TH Loop Ventures | K29: 30157677
J30: Prepayment
J31: Advance to CEO
A32: 2 CASH AND BANK BALANCES With banks: | J32: Advance Rent | K32: 4158000
A33: with banks: | J33: Advance to CEO:Loan to Employee:Ahsan Ullah | K33: 104000
A34: BAHL # 04018 | C34: =K6 -> 22340813 | E34: 29379878 | J34: Advance to CEO:Loan to Employee:Ammar Ali | K34: 12500
A35: BAHL # 15014 | C35: =+K7 -> 130726.57 | E35: 125879.67 | J35: Advance to CEO:Loan to Employee:Amin Khan | K35: 50000
C36: =SUM(C34:C35) -> 22471540 | E36: =SUM(E34:E35) -> 29505758 | J36: Advance to CEO:Loan to Employee:Atif Hussain | K36: 235200
A37: Treasury Accounts | J37: Advance to CEO:Loan to Employee:Rajab Ahmed | K37: 12500
A38: Treasury Account # 6915-01-9 | C38: =K4 -> 778.64 | E38: 483.73 | J38: Advance to CEO:Loan to Employee:Hashim Raza | K38: 84000
A39: Treasury Account # 5804-01-3 | C39: =+K5 -> 85829.58 | E39: 215100.12 | J39: Advance to CEO:Loan to Employee:Junaid Gill | K39: 3600
C40: =SUM(C38:C39) -> 86608.22 | E40: 30161341 | J40: Advance to CEO:Loan to Employee:Jackson | K40: 28000
A41: In hand | C41: =+K8 -> 37828.2 | E41: 186976 | J41: Advance to CEO:Loan to Employee:Meer Umair Ali | K41: 48000
J42: Advance to CEO:Loan to Employee:M Faisal | K42: 99000
C43: =C36+C40+C41 -> 22595976 | E43: =E40+E41 -> 30348317 | J43: Advance to CEO:Loan to Employee:Murtaza Haider | K43: 280000
J44: Advance to CEO:Loan to Employee:Shuja Ur Rehman | K44: 110000
J45: Advance to CEO:Loan to Employee:Syed Irteza | K45: 240000
A46: 3 INVESTMENTS | J46: Advance to CEO:Loan to Employee:Umer Javed | K46: 29129
A47: TDR # 3457 | C47: =K23 -> 10000000 | E47: 10095781 | J47: Advance to CEO:Loan to Employee:Zeeshan | K47: 40000
A48: TDR # 3446 | C48: =+K24 -> 8500000 | E48: 8618837 | G48: =C48-E48 -> -118837 | J48: Rent Payable
C49: =SUM(C47:C48) -> 18500000 | E49: 18500000 | J49: Accrued Expense | L49: 0
J50: Accrued Expense:Grant Thornton (G.T) | L50: 199080
A51: 4 ADVANCE & PREPAYMENTS | J51: Accrued Interest | L51: 34053
A52: Advances/Loan to Employees | C52: =+SUM(K33:K47) -> 1375929 | E52: 658707 | J52: Provisions:License and Permit
A53: Advance W/Tax Cash | C53: 0 | E53: 440000 | J53: Entertainment Fund | L53: 596026.5
C54: =SUM(C52:C53) -> 1375929 | E54: 545100 | J54: Creditors
J55: Loan From Sharholders
A56: 5 OTHER RECEIVABLE | J56: Payroll Liabilities | L56: 0
J57: WithHolding Tax - Contribution:WHT-SST | L57: 800
A58: Loan to OFL Security | C58: 0 | E58: 17155 | J58: WithHolding Tax - Contribution:EOBI - Contribution | L58: 68167
A59: Other Receivables:Content Hub | C59: =+K27 -> 177000 | E59: 0 | J59: WithHolding Tax - Contribution:Payroll - WHT Sec(149) | L59: 220357
C60: =SUM(C58:C59) -> 177000 | E60: =SUM(E58:E59) -> 17155 | J60: WithHolding Tax - Contribution:Purchase of Goods - WHT | L60: 72922
J61: Accrued Expense:Provision For Taxation | L61: 203367.88
J62: Rent - WHT FBR Sec (155) | L62: 232500
J63: PF Payable | L63: 3436511.2
J65: SBP Loan Current | L65: 971754.89
J66: SBP Loan | L66: 1943523
C67: MARCH | E67: JUNE | J67: Loan from Elevation Venture
C68: 2022 | E68: 2021 | J68: First Habib Modarba | L68: 6750000
C69: (Rupees) | E69: (Rupees) | J69: Murtaza Haider
A70: 5 TRADE & OTHER PAYABLES | J70: Paid up Capital | L70: 31412898
J71: Share Premium/Share Application Money | L71: 106030641
A72: Accrued Expenses | C72: =+L49+L50+L51+L61 -> 436500.88 | E72: 124140 | J72: Retained Earnings | L72: 54823615
A73: Rent Payable | C73: =+L48 -> 0 | E73: 1080000 | J73: Sales - Software:AdmitAd | L73: 2088794.6
A74: Loan (Syed Ali Naqi) | C74: =+L28 -> 8320052 | E74: 0 | J74: Sales - Software:AffiliateGateway | L74: 1759091.5
A75: Entertainment Fund | C75: =+L53 -> 596026.5 | E75: 561055 | J75: Sales - Software:Brand Reward | L75: 569904.16
A76: Payroll Liabilities | C76: =+L56 -> 0 | E76: 309932.33 | J76: Sales - Software:Duomai | L76: 13303706
A77: PF Payable | C77: =+L63 -> 3436511.2 | E77: 0 | J77: Sales - Software:Indoleads | L77: 1587778.7
A78: EOBI - Contribution | C78: =+L58 -> 68167 | E78: 31507 | J78: Sales - Software:Innova8e | L78: 44477881
A79: WithHolding Tax -Payable | C79: =+L57+L60+L62+L59 -> 526579 | E79: =113101+244800 -> 357901 | J79: Sales - Software:Trade Doubler | L79: 10169126
C80: =SUM(C72:C79) -> 13383837 | E80: =SUM(E72:E79) -> 2464535.3 | J80: Sales - Software:Daraz | L80: 101340
J81: Sales - Software:Ali Express | L81: 14808812
A82: 6 RECEIVABLE FROM INNOVA8E | J82: Interest Income:Interest Inome-TDRs
J83: Interest Income:T-Call # 6915-01-9 | L83: 6421.44
A84: Opening Balance | C84: =+BS!E20 -> 65941521 | E84: 0 | J84: Interest Income:T-Call # 5804-01-03 | L84: 1836590.8
A85: Cost + 20% | C85: =+PnL!C29*1.2 -> 1.520594e+08 | E85: 0 | J85: Google Adwords | K85: 75292286
J86: Security Expense | K86: 407880
A87: Sales - Software:AdmitAd | C87: =L73 -> 2088794.6 | E87: 2742436.3 | J87: Uniform
A88: Sales - Software:AffiliateGateway | C88: =L74 -> 1759091.5 | E88: 7632638.3 | J88: Delivery Charge | K88: 2500
A89: Sales - Software:Brand Reward | C89: =L75 -> 569904.16 | E89: 0 | J89: Auditor Fees
A90: Sales - Software:Duomai | C90: =L76 -> 13303706 | E90: 9329353.3 | J90: Bank Service Charges | K90: 2327.8
A91: Sales - Software:Indoleads | C91: =L77 -> 1587778.7 | E91: 7529549.3 | J91: Office Expenses | K91: 92500
A92: Sales - Software:Innova8e | C92: =L78 -> 44477881 | E92: 5607192 | J92: Computer and Internet Expenses | K92: 1112661
A93: Sales - Software:Trade Doubler | C93: =L79 -> 10169126 | E93: 4608184.3 | J93: Computer and Internet Expenses:Atlassian
A94: Sales - Software:Daraz | C94: =L80 -> 101340 | E94: 0
A95: Sales - Software:Ali Express | C95: =L81 -> 14808812 | J95: Dues and Subscriptions:Google Asia Pacific | K95: 48906.81
J96: Dues and Subscriptions:Linkedin | K96: 7373.62
C97: =SUM(C87:C95) -> 88866434 | E97: =SUM(E87:E95) -> 37449354 | J97: Dues and Subscriptions:Bluehost | K97: 12238.21
C98: =+C84+C85-C97 -> 1.2913449e+08 | E98: =E97 -> 37449354 | J98: Dues and Subscriptions:Google SG | K98: 31016.41
J99: Dues and Subscriptions:Google Gsuite | K99: 58241.24
C100: MARCH | E100: MARCH | J100: Dues and Subscriptions:Seo Expense | K100: 13599
C101: 2022 | E101: 2021 | J101: Dues and Subscriptions:Google Storage | K101: 418
...

Sheet Va8ive
C1: Mar 31, 22
C2: Debit | E2: Credit
B3: Treasury Account:Treasury Account # 6915-01-9 | C3: 778.64
B4: Treasury Account:Treasury Account # 5804-01-3 | C4: 85829.58
B5: Bank & Cash:BAHL # 04018 | C5: 22340813
B6: Bank & Cash:BAHL # 15014 | C6: 130726.57
B7: Bank & Cash:Petty Cash | C7: 37828.2
B8: Receivable From Innova8e | C8: 65941521
B9: Other Receivables:Content Hub | C9: 177000
B10: Generator | C10: 1150000
B11: Solar Panel | C11: 2537000
B12: Appliances | C12: 31649
B13: Building - Improvement | C13: 11504191
B14: Building - Improvement:Cameras | C14: 300216
... B20: Vehicle:Changan Van | C20: 1439000
B21: Accumulated Depreciation | E21: 7614395
B22: Advance Rent | C22: 4158000
B23: Accrued Markup On TDR | C23: 214617.82
B24: Loan:8TH Loop Ventures | C24: 30157677
B25: TDR # 3457 | C25: 10000000
B26: TDR # 3446 | C26: 8500000
B27: Advance to CEO:Loan to Employee:Ahsan Ullah | C27: 104000
B28: Advance to CEO:Loan to Employee:Ammar Ali | C28: 12500
B29: Advance to CEO:Loan to Employee:Amin Khan | C29: 50000
B30: Advance to CEO:Loan to Employee:Atif Hussain | C30: 235200
B31: Advance to CEO:Loan to Employee:Rajab Ahmed | C31: 12500
B32: Advance to CEO:Loan to Employee:Hashim Raza | C32: 84000
B33: Advance to CEO:Loan to Employee:Junaid Gill | C33: 3600
... B41: Advance to CEO:Loan to Employee:Zeeshan | C41: 40000
B42: Syed Ali Naqi. | E42: 8320052
B43: Accrued Expense:Accrued Interest | E43: 34053
B44: Accrued Expense:Provision For Taxation | E44: 203367.88
B45: Accrued Expense:Grant Thornton (G.T) | E45: 199080
B46: Entertainment Fund | E46: 596026.5
B47: Provident Fund Payable | E47: 3436511.2
B48: Rent - WHT SRB | E48: =286500-54000 -> 232500
B49: SBP Loan Current | E49: 971754.89
B50: WithHolding Tax - Contribution:WHT-SST | E50: 800
B51: WithHolding Tax - Contribution:EOBI - Contribution | E51: 68167
B52: WithHolding Tax - Contribution:Payroll - WHT Sec(149) | E52: 220357
B53: WithHolding Tax - Contribution:Purchase of Goods - WHT | E53: 72922
B54: First Habib Modaraba | E54: 6750000
B55: SBP Loan | E55: 1943523
B56: Share Application Money | E56: 106030641
B57: Paid up Capital | E57: 31412898
B58: Retained Earnings | E58: 54823615
B59: Sales - Software:Ali Express | E59: 14808812
B60: Sales - Software:AdmitAd | E60: 2088794.6
... B69: Interest Income:T-Call # 5804-01-03 | E69: 1836590.8
B70: Office Expense | C70: 92500
B71: Google Adwords | C71: 75292286
B72: Security Expense | C72: 407880
B73: Delivery Charge | C73: 2500
B74: Bank Service Charges | C74: 2327.8
B75: Business Tax | C75: 366000
B76: Computer and Internet Expenses | C76: 1112661
B77: Donation | C77: 31200
B78: Dues and Subscriptions:Google Asia Pacific | C78: 48906.81
B79: Dues and Subscriptions:Linkedin | C79: 7373.62
B80: Dues and Subscriptions:Bluehost | C80: 12238.21
B81: Dues and Subscriptions:Google SG | C81: 31016.41
... B110: Other Deduction:Interest WHT # 5804-01-3 | C110: 275488.62
A111: TOTAL | C111: =ROUND(SUM(C3:C110),5) -> 3.1364011e+08 | E111: =ROUND(SUM(E3:E110),5) -> 3.1364011e+08
C113: =SUM(C59:C110) -> 1.2671617e+08 | E113: =SUM(E59:E110) -> 90709446
E114: =C113-E113 -> 36006723
