Workbook

Sheet P&L Cash Flow Annual
A2: Condition One
A3: Cash Flow Annual
B8: 2021 | C8: 2022 | D8: 2023 | E8: 2024 | F8: 2025 | G8: 2026 | H8: 2027
A10: Sales | L10: 216.15
A11: Gyms | B11: =SUM('P&L Cash Flow Monthly'!K11:V11) -> 133087.11 | C11: =+'P&L Cash Flow Monthly'!W11+'P&L Cash Flow Monthly'!X11+'P&L Cash Flow Monthly'!Y11+'P&L Cash Flow Monthly'!Z11+'P&L Cash Flow Monthly'!AA11+'P&L Cash Flow Monthly'!AB11+'P&L Cash Flow Monthly'!AC11+'P&L Cash Flow Monthly'!AD11+'P&L Cash Flow Monthly'!AE11+'P&L Cash Flow Monthly'!AF11+'P&L Cash Flow Monthly'!AG11+'P&L Cash Flow Monthly'!AH11 -> 127294.62 | D11: =+'P&L Cash Flow Monthly'!AI11+'P&L Cash Flow Monthly'!AJ11+'P&L Cash Flow Monthly'!AK11+'P&L Cash Flow Monthly'!AL11+'P&L Cash Flow Monthly'!AM11+'P&L Cash Flow Monthly'!AN11+'P&L Cash Flow Monthly'!AO11+'P&L Cash Flow Monthly'!AP11+'P&L Cash Flow Monthly'!AQ11+'P&L Cash Flow Monthly'!AR11+'P&L Cash Flow Monthly'!AS11+'P&L Cash Flow Monthly'!AT11 -> 90473.632 | E11: =+'P&L Cash Flow Monthly'!AU11+'P&L Cash Flow Monthly'!AV11+'P&L Cash Flow Monthly'!AW11+'P&L Cash Flow Monthly'!AX11+'P&L Cash Flow Monthly'!AY11+'P&L Cash Flow Monthly'!AZ11+'P&L Cash Flow Monthly'!BA11+'P&L Cash Flow Monthly'!BB11+'P&L Cash Flow Monthly'!BC11+'P&L Cash Flow Monthly'!BD11+'P&L Cash Flow Monthly'!BE11+'P&L Cash Flow Monthly'!BF11 -> 132743.05 | F11: =+'P&L Cash Flow Monthly'!BG11+'P&L Cash Flow Monthly'!BH11+'P&L Cash Flow Monthly'!BI11+'P&L Cash Flow Monthly'!BJ11+'P&L Cash Flow Monthly'!BK11+'P&L Cash Flow Monthly'!BL11+'P&L Cash Flow Monthly'!BM11+'P&L Cash Flow Monthly'!BN11+'P&L Cash Flow Monthly'!BO11+'P&L Cash Flow Monthly'!BP11+'P&L Cash Flow Monthly'!BQ11+'P&L Cash Flow Monthly'!BR11 -> 128606.49 | G11: =SUM('P&L Cash Flow Monthly'!BS11:CD11) -> 201224.06 | H11: =SUM('P&L Cash Flow Monthly'!CE11:CP11) -> 317836.39 | L11: 60
A12: E-commerce | B12: =SUM('P&L Cash Flow Monthly'!K12:V12) -> 910216.47 | C12: =+'P&L Cash Flow Monthly'!W12+'P&L Cash Flow Monthly'!X12+'P&L Cash Flow Monthly'!Y12+'P&L Cash Flow Monthly'!Z12+'P&L Cash Flow Monthly'!AA12+'P&L Cash Flow Monthly'!AB12+'P&L Cash Flow Monthly'!AC12+'P&L Cash Flow Monthly'!AD12+'P&L Cash Flow Monthly'!AE12+'P&L Cash Flow Monthly'!AF12+'P&L Cash Flow Monthly'!AG12+'P&L Cash Flow Monthly'!AH12 -> 891020.34 | D12: =+'P&L Cash Flow Monthly'!AI12+'P&L Cash Flow Monthly'!AJ12+'P&L Cash Flow Monthly'!AK12+'P&L Cash Flow Monthly'!AL12+'P&L Cash Flow Monthly'!AM12+'P&L Cash Flow Monthly'!AN12+'P&L Cash Flow Monthly'!AO12+'P&L Cash Flow Monthly'!AP12+'P&L Cash Flow Monthly'!AQ12+'P&L Cash Flow Monthly'!AR12+'P&L Cash Flow Monthly'!AS12+'P&L Cash Flow Monthly'!AT12 -> 633273.42 | E12: =+'P&L Cash Flow Monthly'!AU12+'P&L Cash Flow Monthly'!AV12+'P&L Cash Flow Monthly'!AW12+'P&L Cash Flow Monthly'!AX12+'P&L Cash Flow Monthly'!AY12+'P&L Cash Flow Monthly'!AZ12+'P&L Cash Flow Monthly'!BA12+'P&L Cash Flow Monthly'!BB12+'P&L Cash Flow Monthly'!BC12+'P&L Cash Flow Monthly'!BD12+'P&L Cash Flow Monthly'!BE12+'P&L Cash Flow Monthly'!BF12 -> 929159.32 | F12: =+'P&L Cash Flow Monthly'!BG12+'P&L Cash Flow Monthly'!BH12+'P&L Cash Flow Monthly'!BI12+'P&L Cash Flow Monthly'!BJ12+'P&L Cash Flow Monthly'!BK12+'P&L Cash Flow Monthly'!BL12+'P&L Cash Flow Monthly'!BM12+'P&L Cash Flow Monthly'!BN12+'P&L Cash Flow Monthly'!BO12+'P&L Cash Flow Monthly'!BP12+'P&L Cash Flow Monthly'!BQ12+'P&L Cash Flow Monthly'!BR12 -> 900203.45 | G12: =SUM('P&L Cash Flow Monthly'!BS12:CD12) -> 1408526.4 | H12: =SUM('P&L Cash Flow Monthly'!CE12:CP12) -> 2224812.7 | L12: 117.15
L13: 252
L14: 8.99
A15: Sales | B15: =SUM(B11:B12) -> 1043303.6 | C15: =SUM(C11:C12) -> 1018315 | D15: =SUM(D11:D12) -> 723747.05 | E15: =SUM(E11:E12) -> 1061902.4 | F15: =SUM(F11:F12) -> 1028809.9 | G15: =SUM(G11:G12) -> 1609750.5 | H15: =SUM(H11:H12) -> 2542649.1
A17: Cost of goods sold | B17: =SUM('P&L Cash Flow Monthly'!K17:V17) -> 748803.02 | C17: =+'P&L Cash Flow Monthly'!W17+'P&L Cash Flow Monthly'!X17+'P&L Cash Flow Monthly'!Y17+'P&L Cash Flow Monthly'!Z17+'P&L Cash Flow Monthly'!AA17+'P&L Cash Flow Monthly'!AB17+'P&L Cash Flow Monthly'!AC17+'P&L Cash Flow Monthly'!AD17+'P&L Cash Flow Monthly'!AE17+'P&L Cash Flow Monthly'!AF17+'P&L Cash Flow Monthly'!AG17+'P&L Cash Flow Monthly'!AH17 -> 716210.63 | D17: =+'P&L Cash Flow Monthly'!AI17+'P&L Cash Flow Monthly'!AJ17+'P&L Cash Flow Monthly'!AK17+'P&L Cash Flow Monthly'!AL17+'P&L Cash Flow Monthly'!AM17+'P&L Cash Flow Monthly'!AN17+'P&L Cash Flow Monthly'!AO17+'P&L Cash Flow Monthly'!AP17+'P&L Cash Flow Monthly'!AQ17+'P&L Cash Flow Monthly'!AR17+'P&L Cash Flow Monthly'!AS17+'P&L Cash Flow Monthly'!AT17 -> 436657.1 | E17: =+'P&L Cash Flow Monthly'!AU17+'P&L Cash Flow Monthly'!AV17+'P&L Cash Flow Monthly'!AW17+'P&L Cash Flow Monthly'!AX17+'P&L Cash Flow Monthly'!AY17+'P&L Cash Flow Monthly'!AZ17+'P&L Cash Flow Monthly'!BA17+'P&L Cash Flow Monthly'!BB17+'P&L Cash Flow Monthly'!BC17+'P&L Cash Flow Monthly'!BD17+'P&L Cash Flow Monthly'!BE17+'P&L Cash Flow Monthly'!BF17 -> 640677.47 | F17: =+'P&L Cash Flow Monthly'!BG17+'P&L Cash Flow Monthly'!BH17+'P&L Cash Flow Monthly'!BI17+'P&L Cash Flow Monthly'!BJ17+'P&L Cash Flow Monthly'!BK17+'P&L Cash Flow Monthly'!BL17+'P&L Cash Flow Monthly'!BM17+'P&L Cash Flow Monthly'!BN17+'P&L Cash Flow Monthly'!BO17+'P&L Cash Flow Monthly'!BP17+'P&L Cash Flow Monthly'!BQ17+'P&L Cash Flow Monthly'!BR17 -> 526500.94 | G17: =SUM('P&L Cash Flow Monthly'!BS17:CD17) -> 706946.13 | H17: =SUM('P&L Cash Flow Monthly'!CE17:CP17) -> 1116644.1
A19: Gross margin | B19: =+B15-B17 -> 294500.56 | C19: =+C15-C17 -> 302104.32 | D19: =+D15-D17 -> 287089.95 | E19: =+E15-E17 -> 421224.89 | F19: =+F15-F17 -> 502309.01 | G19: =+G15-G17 -> 902804.38 | H19: =+H15-H17 -> 1426005
A21: Expenses (see tab for detail) | B21: =SUM('P&L Cash Flow Monthly'!K21:V21) -> 654881.9 | C21: =+'P&L Cash Flow Monthly'!W21+'P&L Cash Flow Monthly'!X21+'P&L Cash Flow Monthly'!Y21+'P&L Cash Flow Monthly'!Z21+'P&L Cash Flow Monthly'!AA21+'P&L Cash Flow Monthly'!AB21+'P&L Cash Flow Monthly'!AC21+'P&L Cash Flow Monthly'!AD21+'P&L Cash Flow Monthly'!AE21+'P&L Cash Flow Monthly'!AF21+'P&L Cash Flow Monthly'!AG21+'P&L Cash Flow Monthly'!AH21 -> 648488.75 | D21: =+'P&L Cash Flow Monthly'!AI21+'P&L Cash Flow Monthly'!AJ21+'P&L Cash Flow Monthly'!AK21+'P&L Cash Flow Monthly'!AL21+'P&L Cash Flow Monthly'!AM21+'P&L Cash Flow Monthly'!AN21+'P&L Cash Flow Monthly'!AO21+'P&L Cash Flow Monthly'!AP21+'P&L Cash Flow Monthly'!AQ21+'P&L Cash Flow Monthly'!AR21+'P&L Cash Flow Monthly'!AS21+'P&L Cash Flow Monthly'!AT21 -> 365212.56 | E21: =+'P&L Cash Flow Monthly'!AU21+'P&L Cash Flow Monthly'!AV21+'P&L Cash Flow Monthly'!AW21+'P&L Cash Flow Monthly'!AX21+'P&L Cash Flow Monthly'!AY21+'P&L Cash Flow Monthly'!AZ21+'P&L Cash Flow Monthly'!BA21+'P&L Cash Flow Monthly'!BB21+'P&L Cash Flow Monthly'!BC21+'P&L Cash Flow Monthly'!BD21+'P&L Cash Flow Monthly'!BE21+'P&L Cash Flow Monthly'!BF21 -> 621502.52 | F21: =+'P&L Cash Flow Monthly'!BG21+'P&L Cash Flow Monthly'!BH21+'P&L Cash Flow Monthly'!BI21+'P&L Cash Flow Monthly'!BJ21+'P&L Cash Flow Monthly'!BK21+'P&L Cash Flow Monthly'!BL21+'P&L Cash Flow Monthly'!BM21+'P&L Cash Flow Monthly'!BN21+'P&L Cash Flow Monthly'!BO21+'P&L Cash Flow Monthly'!BP21+'P&L Cash Flow Monthly'!BQ21+'P&L Cash Flow Monthly'!BR21 -> 604084.51 | G21: =SUM('P&L Cash Flow Monthly'!BS21:CD21) -> 902177.81 | H21: =SUM('P&L Cash Flow Monthly'!CE21:CP21) -> 1297152.5
A23: Net income/EBITDA | B23: =+B19-B21 -> -360381.34 | C23: =+C19-C21 -> -346384.42 | D23: =+D19-D21 -> -78122.61 | E23: =+E19-E21 -> -200277.63 | F23: =+F19-F21 -> -101775.5 | G23: =+G19-G21 -> 626.56788 | H23: =+H19-H21 -> 128852.49
A25: Adjustments to convert net income to cash flow
A26: COGS | B26: =SUM('P&L Cash Flow Monthly'!K26:V26) -> 748803.02 | C26: =+'P&L Cash Flow Monthly'!W26+'P&L Cash Flow Monthly'!X26+'P&L Cash Flow Monthly'!Y26+'P&L Cash Flow Monthly'!Z26+'P&L Cash Flow Monthly'!AA26+'P&L Cash Flow Monthly'!AB26+'P&L Cash Flow Monthly'!AC26+'P&L Cash Flow Monthly'!AD26+'P&L Cash Flow Monthly'!AE26+'P&L Cash Flow Monthly'!AF26+'P&L Cash Flow Monthly'!AG26+'P&L Cash Flow Monthly'!AH26 -> 716210.63 | D26: =+'P&L Cash Flow Monthly'!AI26+'P&L Cash Flow Monthly'!AJ26+'P&L Cash Flow Monthly'!AK26+'P&L Cash Flow Monthly'!AL26+'P&L Cash Flow Monthly'!AM26+'P&L Cash Flow Monthly'!AN26+'P&L Cash Flow Monthly'!AO26+'P&L Cash Flow Monthly'!AP26+'P&L Cash Flow Monthly'!AQ26+'P&L Cash Flow Monthly'!AR26+'P&L Cash Flow Monthly'!AS26+'P&L Cash Flow Monthly'!AT26 -> 436657.1 | E26: =+'P&L Cash Flow Monthly'!AU26+'P&L Cash Flow Monthly'!AV26+'P&L Cash Flow Monthly'!AW26+'P&L Cash Flow Monthly'!AX26+'P&L Cash Flow Monthly'!AY26+'P&L Cash Flow Monthly'!AZ26+'P&L Cash Flow Monthly'!BA26+'P&L Cash Flow Monthly'!BB26+'P&L Cash Flow Monthly'!BC26+'P&L Cash Flow Monthly'!BD26+'P&L Cash Flow Monthly'!BE26+'P&L Cash Flow Monthly'!BF26 -> 640677.47 | F26: =+'P&L Cash Flow Monthly'!BG26+'P&L Cash Flow Monthly'!BH26+'P&L Cash Flow Monthly'!BI26+'P&L Cash Flow Monthly'!BJ26+'P&L Cash Flow Monthly'!BK26+'P&L Cash Flow Monthly'!BL26+'P&L Cash Flow Monthly'!BM26+'P&L Cash Flow Monthly'!BN26+'P&L Cash Flow Monthly'!BO26+'P&L Cash Flow Monthly'!BP26+'P&L Cash Flow Monthly'!BQ26+'P&L Cash Flow Monthly'!BR26 -> 526500.94 | G26: =SUM('P&L Cash Flow Monthly'!BS26:CD26) -> 706946.13 | H26: =SUM('P&L Cash Flow Monthly'!CE26:CP26) -> 1116644.1
A27: Payment for COGS | B27: =SUM('P&L Cash Flow Monthly'!K27:V27) -> -773403.12 | C27: =+'P&L Cash Flow Monthly'!W27+'P&L Cash Flow Monthly'!X27+'P&L Cash Flow Monthly'!Y27+'P&L Cash Flow Monthly'!Z27+'P&L Cash Flow Monthly'!AA27+'P&L Cash Flow Monthly'!AB27+'P&L Cash Flow Monthly'!AC27+'P&L Cash Flow Monthly'!AD27+'P&L Cash Flow Monthly'!AE27+'P&L Cash Flow Monthly'!AF27+'P&L Cash Flow Monthly'!AG27+'P&L Cash Flow Monthly'!AH27 -> -695924.67 | D27: =+'P&L Cash Flow Monthly'!AI27+'P&L Cash Flow Monthly'!AJ27+'P&L Cash Flow Monthly'!AK27+'P&L Cash Flow Monthly'!AL27+'P&L Cash Flow Monthly'!AM27+'P&L Cash Flow Monthly'!AN27+'P&L Cash Flow Monthly'!AO27+'P&L Cash Flow Monthly'!AP27+'P&L Cash Flow Monthly'!AQ27+'P&L Cash Flow Monthly'!AR27+'P&L Cash Flow Monthly'!AS27+'P&L Cash Flow Monthly'!AT27 -> -413845.89 | E27: =+'P&L Cash Flow Monthly'!AU27+'P&L Cash Flow Monthly'!AV27+'P&L Cash Flow Monthly'!AW27+'P&L Cash Flow Monthly'!AX27+'P&L Cash Flow Monthly'!AY27+'P&L Cash Flow Monthly'!AZ27+'P&L Cash Flow Monthly'!BA27+'P&L Cash Flow Monthly'!BB27+'P&L Cash Flow Monthly'!BC27+'P&L Cash Flow Monthly'!BD27+'P&L Cash Flow Monthly'!BE27+'P&L Cash Flow Monthly'!BF27 -> -694703.01 | F27: =+'P&L Cash Flow Monthly'!BG27+'P&L Cash Flow Monthly'!BH27+'P&L Cash Flow Monthly'!BI27+'P&L Cash Flow Monthly'!BJ27+'P&L Cash Flow Monthly'!BK27+'P&L Cash Flow Monthly'!BL27+'P&L Cash Flow Monthly'!BM27+'P&L Cash Flow Monthly'!BN27+'P&L Cash Flow Monthly'!BO27+'P&L Cash Flow Monthly'!BP27+'P&L Cash Flow Monthly'!BQ27+'P&L Cash Flow Monthly'!BR27 -> -489003.94 | G27: =SUM('P&L Cash Flow Monthly'!BS27:CD27) -> -774169.54 | H27: =SUM('P&L Cash Flow Monthly'!CE27:CP27) -> -1187655.1
A28: Marketing ad spend | B28: =SUM('P&L Cash Flow Monthly'!K28:V28) -> 175000 | C28: =+'P&L Cash Flow Monthly'!W28+'P&L Cash Flow Monthly'!X28+'P&L Cash Flow Monthly'!Y28+'P&L Cash Flow Monthly'!Z28+'P&L Cash Flow Monthly'!AA28+'P&L Cash Flow Monthly'!AB28+'P&L Cash Flow Monthly'!AC28+'P&L Cash Flow Monthly'!AD28+'P&L Cash Flow Monthly'!AE28+'P&L Cash Flow Monthly'!AF28+'P&L Cash Flow Monthly'!AG28+'P&L Cash Flow Monthly'!AH28 -> 118000 | D28: =+'P&L Cash Flow Monthly'!AI28+'P&L Cash Flow Monthly'!AJ28+'P&L Cash Flow Monthly'!AK28+'P&L Cash Flow Monthly'!AL28+'P&L Cash Flow Monthly'!AM28+'P&L Cash Flow Monthly'!AN28+'P&L Cash Flow Monthly'!AO28+'P&L Cash Flow Monthly'!AP28+'P&L Cash Flow Monthly'!AQ28+'P&L Cash Flow Monthly'!AR28+'P&L Cash Flow Monthly'!AS28+'P&L Cash Flow Monthly'!AT28 -> 79000 | E28: =+'P&L Cash Flow Monthly'!AU28+'P&L Cash Flow Monthly'!AV28+'P&L Cash Flow Monthly'!AW28+'P&L Cash Flow Monthly'!AX28+'P&L Cash Flow Monthly'!AY28+'P&L Cash Flow Monthly'!AZ28+'P&L Cash Flow Monthly'!BA28+'P&L Cash Flow Monthly'!BB28+'P&L Cash Flow Monthly'!BC28+'P&L Cash Flow Monthly'!BD28+'P&L Cash Flow Monthly'!BE28+'P&L Cash Flow Monthly'!BF28 -> 233000 | F28: =+'P&L Cash Flow Monthly'!BG28+'P&L Cash Flow Monthly'!BH28+'P&L Cash Flow Monthly'!BI28+'P&L Cash Flow Monthly'!BJ28+'P&L Cash Flow Monthly'!BK28+'P&L Cash Flow Monthly'!BL28+'P&L Cash Flow Monthly'!BM28+'P&L Cash Flow Monthly'!BN28+'P&L Cash Flow Monthly'!BO28+'P&L Cash Flow Monthly'!BP28+'P&L Cash Flow Monthly'!BQ28+'P&L Cash Flow Monthly'!BR28 -> 150000 | G28: =SUM('P&L Cash Flow Monthly'!BS28:CD28) -> 305000 | H28: =SUM('P&L Cash Flow Monthly'!CE28:CP28) -> 530000
A29: Payment for Marketing ad spend | B29: =SUM('P&L Cash Flow Monthly'!K29:V29) -> -170000 | C29: =+'P&L Cash Flow Monthly'!W29+'P&L Cash Flow Monthly'!X29+'P&L Cash Flow Monthly'!Y29+'P&L Cash Flow Monthly'!Z29+'P&L Cash Flow Monthly'!AA29+'P&L Cash Flow Monthly'!AB29+'P&L Cash Flow Monthly'!AC29+'P&L Cash Flow Monthly'!AD29+'P&L Cash Flow Monthly'!AE29+'P&L Cash Flow Monthly'!AF29+'P&L Cash Flow Monthly'!AG29+'P&L Cash Flow Monthly'!AH29 -> -118000 | D29: =+'P&L Cash Flow Monthly'!AI29+'P&L Cash Flow Monthly'!AJ29+'P&L Cash Flow Monthly'!AK29+'P&L Cash Flow Monthly'!AL29+'P&L Cash Flow Monthly'!AM29+'P&L Cash Flow Monthly'!AN29+'P&L Cash Flow Monthly'!AO29+'P&L Cash Flow Monthly'!AP29+'P&L Cash Flow Monthly'!AQ29+'P&L Cash Flow Monthly'!AR29+'P&L Cash Flow Monthly'!AS29+'P&L Cash Flow Monthly'!AT29 -> -77000 | E29: =+'P&L Cash Flow Monthly'!AU29+'P&L Cash Flow Monthly'!AV29+'P&L Cash Flow Monthly'!AW29+'P&L Cash Flow Monthly'!AX29+'P&L Cash Flow Monthly'!AY29+'P&L Cash Flow Monthly'!AZ29+'P&L Cash Flow Monthly'!BA29+'P&L Cash Flow Monthly'!BB29+'P&L Cash Flow Monthly'!BC29+'P&L Cash Flow Monthly'!BD29+'P&L Cash Flow Monthly'!BE29+'P&L Cash Flow Monthly'!BF29 -> -250000 | F29: =+'P&L Cash Flow Monthly'!BG29+'P&L Cash Flow Monthly'!BH29+'P&L Cash Flow Monthly'!BI29+'P&L Cash Flow Monthly'!BJ29+'P&L Cash Flow Monthly'!BK29+'P&L Cash Flow Monthly'!BL29+'P&L Cash Flow Monthly'!BM29+'P&L Cash Flow Monthly'!BN29+'P&L Cash Flow Monthly'!BO29+'P&L Cash Flow Monthly'!BP29+'P&L Cash Flow Monthly'!BQ29+'P&L Cash Flow Monthly'!BR29 -> -140000 | G29: =SUM('P&L Cash Flow Monthly'!BS29:CD29) -> -325000 | H29: =SUM('P&L Cash Flow Monthly'!CE29:CP29) -> -495000
A30: Initial up front costs | B30: =SUM('P&L Cash Flow Monthly'!K30:V30) -> 0 | C30: =+'P&L Cash Flow Monthly'!W30+'P&L Cash Flow Monthly'!X30+'P&L Cash Flow Monthly'!Y30+'P&L Cash Flow Monthly'!Z30+'P&L Cash Flow Monthly'!AA30+'P&L Cash Flow Monthly'!AB30+'P&L Cash Flow Monthly'!AC30+'P&L Cash Flow Monthly'!AD30+'P&L Cash Flow Monthly'!AE30+'P&L Cash Flow Monthly'!AF30+'P&L Cash Flow Monthly'!AG30+'P&L Cash Flow Monthly'!AH30 -> 0 | D30: =+'P&L Cash Flow Monthly'!AI30+'P&L Cash Flow Monthly'!AJ30+'P&L Cash Flow Monthly'!AK30+'P&L Cash Flow Monthly'!AL30+'P&L Cash Flow Monthly'!AM30+'P&L Cash Flow Monthly'!AN30+'P&L Cash Flow Monthly'!AO30+'P&L Cash Flow Monthly'!AP30+'P&L Cash Flow Monthly'!AQ30+'P&L Cash Flow Monthly'!AR30+'P&L Cash Flow Monthly'!AS30+'P&L Cash Flow Monthly'!AT30 -> 0 | E30: =+'P&L Cash Flow Monthly'!AU30+'P&L Cash Flow Monthly'!AV30+'P&L Cash Flow Monthly'!AW30+'P&L Cash Flow Monthly'!AX30+'P&L Cash Flow Monthly'!AY30+'P&L Cash Flow Monthly'!AZ30+'P&L Cash Flow Monthly'!BA30+'P&L Cash Flow Monthly'!BB30+'P&L Cash Flow Monthly'!BC30+'P&L Cash Flow Monthly'!BD30+'P&L Cash Flow Monthly'!BE30+'P&L Cash Flow Monthly'!BF30 -> 0 | F30: =+'P&L Cash Flow Monthly'!BG30+'P&L Cash Flow Monthly'!BH30+'P&L Cash Flow Monthly'!BI30+'P&L Cash Flow Monthly'!BJ30+'P&L Cash Flow Monthly'!BK30+'P&L Cash Flow Monthly'!BL30+'P&L Cash Flow Monthly'!BM30+'P&L Cash Flow Monthly'!BN30+'P&L Cash Flow Monthly'!BO30+'P&L Cash Flow Monthly'!BP30+'P&L Cash Flow Monthly'!BQ30+'P&L Cash Flow Monthly'!BR30 -> 0 | G30: =SUM('P&L Cash Flow Monthly'!BS30:CD30) -> 0 | H30: =SUM('P&L Cash Flow Monthly'!CE30:CP30) -> 0
A31: Tax distribution | B31: =SUM('P&L Cash Flow Monthly'!K31:V31) -> 0 | C31: =+'P&L Cash Flow Monthly'!W31+'P&L Cash Flow Monthly'!X31+'P&L Cash Flow Monthly'!Y31+'P&L Cash Flow Monthly'!Z31+'P&L Cash Flow Monthly'!AA31+'P&L Cash Flow Monthly'!AB31+'P&L Cash Flow Monthly'!AC31+'P&L Cash Flow Monthly'!AD31+'P&L Cash Flow Monthly'!AE31+'P&L Cash Flow Monthly'!AF31+'P&L Cash Flow Monthly'!AG31+'P&L Cash Flow Monthly'!AH31 -> 0 | D31: =+'P&L Cash Flow Monthly'!AI31+'P&L Cash Flow Monthly'!AJ31+'P&L Cash Flow Monthly'!AK31+'P&L Cash Flow Monthly'!AL31+'P&L Cash Flow Monthly'!AM31+'P&L Cash Flow Monthly'!AN31+'P&L Cash Flow Monthly'!AO31+'P&L Cash Flow Monthly'!AP31+'P&L Cash Flow Monthly'!AQ31+'P&L Cash Flow Monthly'!AR31+'P&L Cash Flow Monthly'!AS31+'P&L Cash Flow Monthly'!AT31 -> 0 | E31: =+'P&L Cash Flow Monthly'!AU31+'P&L Cash Flow Monthly'!AV31+'P&L Cash Flow Monthly'!AW31+'P&L Cash Flow Monthly'!AX31+'P&L Cash Flow Monthly'!AY31+'P&L Cash Flow Monthly'!AZ31+'P&L Cash Flow Monthly'!BA31+'P&L Cash Flow Monthly'!BB31+'P&L Cash Flow Monthly'!BC31+'P&L Cash Flow Monthly'!BD31+'P&L Cash Flow Monthly'!BE31+'P&L Cash Flow Monthly'!BF31 -> 0 | F31: =+'P&L Cash Flow Monthly'!BG31+'P&L Cash Flow Monthly'!BH31+'P&L Cash Flow Monthly'!BI31+'P&L Cash Flow Monthly'!BJ31+'P&L Cash Flow Monthly'!BK31+'P&L Cash Flow Monthly'!BL31+'P&L Cash Flow Monthly'!BM31+'P&L Cash Flow Monthly'!BN31+'P&L Cash Flow Monthly'!BO31+'P&L Cash Flow Monthly'!BP31+'P&L Cash Flow Monthly'!BQ31+'P&L Cash Flow Monthly'!BR31 -> 0 | G31: =SUM('P&L Cash Flow Monthly'!BS31:CD31) -> 0 | H31: =SUM('P&L Cash Flow Monthly'!CE31:CP31) -> 0
A32: Capital investment | B32: =SUM('P&L Cash Flow Monthly'!K32:V32) -> 400000 | C32: =+'P&L Cash Flow Monthly'!W32+'P&L Cash Flow Monthly'!X32+'P&L Cash Flow Monthly'!Y32+'P&L Cash Flow Monthly'!Z32+'P&L Cash Flow Monthly'!AA32+'P&L Cash Flow Monthly'!AB32+'P&L Cash Flow Monthly'!AC32+'P&L Cash Flow Monthly'!AD32+'P&L Cash Flow Monthly'!AE32+'P&L Cash Flow Monthly'!AF32+'P&L Cash Flow Monthly'!AG32+'P&L Cash Flow Monthly'!AH32 -> 285000 | D32: =+'P&L Cash Flow Monthly'!AI32+'P&L Cash Flow Monthly'!AJ32+'P&L Cash Flow Monthly'!AK32+'P&L Cash Flow Monthly'!AL32+'P&L Cash Flow Monthly'!AM32+'P&L Cash Flow Monthly'!AN32+'P&L Cash Flow Monthly'!AO32+'P&L Cash Flow Monthly'!AP32+'P&L Cash Flow Monthly'!AQ32+'P&L Cash Flow Monthly'!AR32+'P&L Cash Flow Monthly'!AS32+'P&L Cash Flow Monthly'!AT32 -> -14589 | E32: =+'P&L Cash Flow Monthly'!AU32+'P&L Cash Flow Monthly'!AV32+'P&L Cash Flow Monthly'!AW32+'P&L Cash Flow Monthly'!AX32+'P&L Cash Flow Monthly'!AY32+'P&L Cash Flow Monthly'!AZ32+'P&L Cash Flow Monthly'!BA32+'P&L Cash Flow Monthly'!BB32+'P&L Cash Flow Monthly'!BC32+'P&L Cash Flow Monthly'!BD32+'P&L Cash Flow Monthly'!BE32+'P&L Cash Flow Monthly'!BF32 -> 400000 | F32: =+'P&L Cash Flow Monthly'!BG32+'P&L Cash Flow Monthly'!BH32+'P&L Cash Flow Monthly'!BI32+'P&L Cash Flow Monthly'!BJ32+'P&L Cash Flow Monthly'!BK32+'P&L Cash Flow Monthly'!BL32+'P&L Cash Flow Monthly'!BM32+'P&L Cash Flow Monthly'!BN32+'P&L Cash Flow Monthly'!BO32+'P&L Cash Flow Monthly'!BP32+'P&L Cash Flow Monthly'!BQ32+'P&L Cash Flow Monthly'!BR32 -> -15000 | G32: =SUM('P&L Cash Flow Monthly'!BS32:CD32) -> 0 | H32: =SUM('P&L Cash Flow Monthly'!CE32:CP32) -> 0
A35: Annual cash flow | B35: =SUM(B23:B33) -> 20018.56 | C35: =SUM(C23:C33) -> -41098.458 | D35: =SUM(D23:D33) -> -67900.402 | E35: =SUM(E23:E33) -> 128696.84 | F35: =SUM(F23:F33) -> -69278.499 | G35: =SUM(G23:G33) -> -86596.848 | H35: =SUM(H23:H33) -> 92841.443
A37: Cash beginning of year | B37: ='P&L Cash Flow Monthly'!K37:K38 -> 179360.01 | C37: =+B39 -> 199378.57 | D37: =+C39 -> 158280.11 | E37: =+D39 -> 90379.707 | F37: =+E39 -> 219076.54 | G37: =+F39 -> 149798.04 | H37: =+G39 -> 63201.197
A39: Cash end of year | B39: =SUM(B35:B37) -> 199378.57 | C39: =SUM(C35:C37) -> 158280.11 | D39: =SUM(D35:D37) -> 90379.707 | E39: =SUM(E35:E37) -> 219076.54 | F39: =SUM(F35:F37) -> 149798.04 | G39: =SUM(G35:G37) -> 63201.197 | H39: =SUM(H35:H37) -> 156042.64
A42: Gross Profit % | B42: =B19/B15 -> 0.28227695 | C42: =C19/C15 -> 0.29667081 | D42: =D19/D15 -> 0.39667167 | E42: =E19/E15 -> 0.39667008 | F42: =F19/F15 -> 0.48824276 | G42: =G19/G15 -> 0.56083497 | H42: =H19/H15 -> 0.56083437
A44: Net Profit % | B44: =B23/B15 -> -0.34542328 | C44: =C23/C15 -> -0.34015451 | D44: =D23/D15 -> -0.10794187 | E44: =E23/E15 -> -0.18860267 | F44: =F23/F15 -> -0.098925459 | G44: =G23/G15 -> 0.00038923292 | H44: =H23/H15 -> 0.050676472

Sheet P&L Cash Flow Monthly
A2: Condition One | N2: Condition One | AA2: Condition One | AN2: Condition One
A3: Cash Flow Monthly | N3: Cash Flow Monthly | AA3: Cash Flow Monthly | AN3: Cash Flow Monthly
B8: 43951 | C8: 43982 | D8: 44012 | E8: 44043 | F8: 44074 | G8: 44104 | H8: 44135 | I8: 44165 | J8: 44196 | K8: 44227 | L8: 44255 | M8: 44286 | N8: 44316 | O8: 44347 | P8: 44377 | Q8: 44408 | R8: 44439 | S8: 44469 | T8: 44500 | U8: 44530 | V8: 44561 | W8: 44592 | X8: 44620 | Y8: 44651 | Z8: 44681 | AA8: 44712 | AB8: 44742 | AC8: 44773 | AD8: 44804 | AE8: 44834 | AF8: 44865 | AG8: 44895 | AH8: 44926 | AI8: 44957 | AJ8: 44985 | AK8: 45016 | AL8: 45046 | AM8: 45077 | AN8: 45107 | AO8: 45138 | AP8: 45169 | AQ8: 45199 | AR8: 45230 | AS8: 45260 | AT8: 45291 | AU8: 45322 | AV8: 45351 | AW8: 45382 | AX8: 45412 | AY8: 45443 | AZ8: 45473 | BA8: 45504 | BB8: 45535 | BC8: 45565 | BD8: 45596 | BE8: 45626 | BF8: 45657 | BG8: 45688 | BH8: 45716 | BI8: 45747 | BJ8: 45777 | BK8: 45808 | BL8: 45838 | BM8: 45869 | BN8: 45900 | BO8: 45930 | BP8: 45961 | BQ8: 45991 | BR8: 46022 | BS8: 46053 | BT8: 46081 | BU8: 46112 | BV8: 46142 | BW8: 46173 | BX8: 46203 | BY8: 46234 | BZ8: 46265 | CA8: 46295 | CB8: 46326 | CC8: 46356 | CD8: 46387 | CE8: 46418 | CF8: 46446 | CG8: 46477 | CH8: 46507 | CI8: 46538 | CJ8: 46568 | CK8: 46599 | CL8: 46630 | CM8: 46660 | CN8: 46691 | CO8: 46721 | CP8: 46752 | CQ8: 46753 | CR8: 46754 | CS8: 46755
A10: Sales
A11: Gyms | C11: =+'Rev 2'!V13 -> 65.084987 | D11: =+'Rev 2'!W13 -> 782.69595 | E11: =+'Rev 2'!X13 -> 1192.7594 | F11: =+'Rev 2'!Y13 -> 1545.4617 | G11: =+'Rev 2'!Z13 -> 1523.2111 | H11: =+'Rev 2'!AA13 -> 2184.1721 | I11: =+'Rev 2'!AB13 -> 4280.355 | J11: =+'Rev 2'!AC13 -> 4144.1221 | ... CP11: =+'Rev 2'!DI13 -> 31502.36
A12: E-commerce | B12: 2770.21 | C12: 3324.68 | D12: 5292.33 | E12: 10996.11 | F12: 17836.54 | G12: 20272.6 | H12: 20869.28 | I12: 34588 | J12: 22500 | K12: 25500 | L12: =+'Rev 2'!AE18 -> 59003.591 | M12: =+'Rev 2'!AF18 -> 83902.828 | N12: =+'Rev 2'!AG18 -> 83920.74 | O12: =+'Rev 2'!AH18 -> 73894.487 | P12: =+'Rev 2'!AI18 -> 63868.234 | Q12: =+'Rev 2'!AJ18 -> 59100.083 | R12: =+'Rev 2'!AK18 -> 67881.498 | S12: =+'Rev 2'!AL18 -> 83839.023 | ... CP12: =+'Rev 2'!DI18 -> 220513.02
A15: Sales | B15: =SUM(B11:B13) -> 2770.21 | C15: =SUM(C11:C13) -> 3389.765 | D15: =SUM(D11:D13) -> 6075.026 | E15: =SUM(E11:E13) -> 12188.869 | F15: =SUM(F11:F13) -> 19382.002 | G15: =SUM(G11:G13) -> 21795.811 | H15: =SUM(H11:H13) -> 23053.452 | I15: =SUM(I11:I13) -> 38868.355 | ... CS15: =SUM(CS11:CS13) -> 0
A17: Cost of goods sold | B17: =+'Rev 2'!U21*COGS!B28 -> 0 | C17: =+'Rev 2'!V21*COGS!B28 -> 440.90018 | D17: =+COGS!B23 -> 5339.791 | E17: =+COGS!C23 -> 8139.1572 | F17: =+COGS!D23 -> 9928.9536 | G17: =+COGS!E23 -> 9785.9566 | H17: =+COGS!F23 -> 14033.733 | I17: =+COGS!G23 -> 24081.317 | J17: =+COGS!H23 -> 23314.78 | K17: =+COGS!I23 -> 37659.495 | ... CP17: =+COGS!CN23 -> 110676.53
A19: Gross margin | B19: =+B15-B17 -> 2770.21 | C19: =+C15-C17 -> 2948.8648 | D19: =+D15-D17 -> 735.23493 | E19: =+E15-E17 -> 4049.7121 | F19: =+F15-F17 -> 9453.0481 | G19: =+G15-G17 -> 12009.854 | H19: =+H15-H17 -> 9019.7195 | I19: =+I15-I17 -> 14787.038 | ... CP19: =+CP15-CP17 -> 141338.84
A21: Expenses (see tab for detail) | B21: =+'Expenses 2'!B102 -> 29693.703 | C21: =+'Expenses 2'!C102 -> 26720.251 | D21: =+'Expenses 2'!D102 -> 26835.315 | E21: =+'Expenses 2'!E102 -> 25597.293 | F21: =+'Expenses 2'!F102 -> 25905.519 | G21: =+'Expenses 2'!G102 -> 27008.951 | H21: =+'Expenses 2'!H102 -> 32062.84 | I21: =+'Expenses 2'!I102 -> 40740.509 | ... CP21: =+'Expenses 2'!CP102 -> 118398.86
A23: Net income/EBITDA | B23: =+B19-B21 -> -26923.494 | C23: =+C19-C21 -> -23771.387 | D23: =+D19-D21 -> -26100.08 | E23: =+E19-E21 -> -21547.581 | F23: =+F19-F21 -> -16452.471 | G23: =+G19-G21 -> -14999.096 | H23: =+H19-H21 -> -23043.121 | I23: =+I19-I21 -> -25953.471 | ... CP23: =+CP19-CP21 -> 22939.985
A25: Adjustments to convert net income to cash flow
A26: COGS | B26: =+B17 -> 0 | C26: =+C17 -> 440.90018 | D26: =+D17 -> 5339.791 | E26: =+E17 -> 8139.1572 | F26: =+F17 -> 9928.9536 | G26: =+G17 -> 9785.9566 | H26: =+H17 -> 14033.733 | I26: =+I17 -> 24081.317 | ... CP26: =+CP17 -> 110676.53
A27: Payment for COGS | B27: =-COGS!B32-COGS!B23 -> -6120.4822 | C27: =-COGS!C23 -> -8139.1572 | D27: =-COGS!D23 -> -9928.9536 | E27: =-COGS!E23 -> -9785.9566 | F27: =-COGS!F23 -> -14033.733 | G27: =-COGS!G23 -> -24081.317 | H27: =-COGS!H23 -> -23314.78 | I27: =-COGS!I23 -> -37659.495 | J27: =-COGS!J23 -> -47427.648 | ... CP27: =-COGS!CP23 -> -110676.53
A28: Marketing ad spend | B28: ='Expenses 2'!B89 -> 1500 | C28: ='Expenses 2'!C89 -> 3500 | D28: ='Expenses 2'!D89 -> 3500 | E28: ='Expenses 2'!E89 -> 2000 | F28: ='Expenses 2'!F89 -> 2000 | G28: ='Expenses 2'!G89 -> 3000 | H28: ='Expenses 2'!H89 -> 5000 | I28: ='Expenses 2'!I89 -> 12000 | ... AG28: ='Expenses 2'!AG89 -> 10000 | AH28: ='Expenses 2'!AH28 -> 10000 | AI28: ='Expenses 2'!AI28 -> 10000 | AJ28: ='Expenses 2'!AJ28 -> 5000 | AK28: ='Expenses 2'!AK28 -> 5000 | AL28: ='Expenses 2'!AL28 -> 5000 | AM28: ='Expenses 2'!AM28 -> 7000 | AN28: ='Expenses 2'!AN28 -> 7000 | AO28: ='Expenses 2'!AO28 -> 7000 | ... CP28: ='Expenses 2'!CP28 -> 50000
A29: Payment for Marketing ad spend | B29: =-'Expenses 2'!C89 -> -3500 | C29: =-'Expenses 2'!D89 -> -3500 | D29: =-'Expenses 2'!E89 -> -2000 | E29: =-'Expenses 2'!F89 -> -2000 | F29: =-'Expenses 2'!G89 -> -3000 | G29: =-'Expenses 2'!H89 -> -5000 | H29: =-'Expenses 2'!I89 -> -12000 | I29: =-'Expenses 2'!J89 -> -2000 | ... AF29: =-'Expenses 2'!AG89 -> -10000 | AG29: =-'Expenses 2'!AH28 -> -10000 | AH29: =-'Expenses 2'!AI28 -> -10000 | AI29: =-'Expenses 2'!AJ28 -> -5000 | AJ29: =-'Expenses 2'!AK28 -> -5000 | AK29: =-'Expenses 2'!AL28 -> -5000 | AL29: =-'Expenses 2'!AM28 -> -7000 | AM29: =-'Expenses 2'!AN28 -> -7000 | AN29: =-'Expenses 2'!AO28 -> -7000 | ... CO29: =-'Expenses 2'!CP28 -> -50000 | CP29: =-'Expenses 2'!CQ89 -> 0
A30: Initial up front costs | B30: =-'Up front costs'!B20 -> 0
A31: Tax distribution | K31: =-Taxes!D32 -> 0 | L31: =-Taxes!E32 -> 0 | M31: =-Taxes!F32 -> 0 | N31: =-Taxes!G32 -> 0 | O31: =-Taxes!H32 -> 0 | P31: =-Taxes!I32 -> 0 | Q31: =-Taxes!J32 -> 0 | R31: =-Taxes!K32 -> 0 | ... CP31: =-Taxes!CI32 -> 0
A32: Capital investment | B32: 375000 | J32: 100000 | N32: 10000 | O32: 50000 | P32: 80000 | R32: 260000 | W32: 150000 | AA32: 35000 | AB32: 100000 | AL32: 25000 | AN32: -139589 | AO32: 25000 | AR32: 25000 | AT32: 50000 | AU32: 100000 | AV32: 150000 | AW32: 0 | AX32: 0 | AY32: 0 | AZ32: 0 | BA32: 0 | BC32: -15000 | BD32: 80000 | BE32: 100000 | BF32: -15000 | BG32: -15000 | BH32: -15000 | BI32: -15000 | BJ32: -15000 | BK32: -15000 | BL32: -15000 | BM32: -15000 | BN32: -15000 | BO32: -15000 | BP32: -15000 | BQ32: -15000 | BR32: 150000 | BT32: 0 | BU32: 0 | BV32: 0 | BW32: 0 | BX32: 0 | BY32: 0 | BZ32: 0 | CA32: 0 | CB32: 0 | CC32: 0 | CD32: 0 | CE32: 0 | CF32: 0 | CG32: 0 | CH32: 0 | CI32: 0 | CJ32: 0
L33: Note 1
A35: Monthly cash flow | B35: =SUM(B23:B33) -> 339956.02 | C35: =SUM(C23:C33) -> -31469.644 | D35: =SUM(D23:D33) -> -29189.242 | E35: =SUM(E23:E33) -> -23194.38 | F35: =SUM(F23:F33) -> -21557.25 | G35: =SUM(G23:G33) -> -31294.457 | H35: =SUM(H23:H33) -> -39324.169 | I35: =SUM(I23:I33) -> -29531.649 | ... CP35: =SUM(CP23:CP33) -> 72939.985
A37: Cash beginning of month | B37: 6965 | C37: =+B39 -> 346921.02 | D37: =+C39 -> 315451.38 | E37: =+D39 -> 286262.14 | F37: =+E39 -> 263067.76 | G37: =+F39 -> 241510.51 | H37: =+G39 -> 210216.05 | I37: =+H39 -> 170891.88 | J37: =+I39 -> 141360.23 | ... CP37: =+CO39 -> 83102.656
A39: Cash end of month | B39: =SUM(B35:B37) -> 346921.02 | C39: =SUM(C35:C37) -> 315451.38 | D39: =SUM(D35:D37) -> 286262.14 | E39: =SUM(E35:E37) -> 263067.76 | F39: =SUM(F35:F37) -> 241510.51 | G39: =SUM(G35:G37) -> 210216.05 | H39: =SUM(H35:H37) -> 170891.88 | I39: =SUM(I35:I37) -> 141360.23 | ... CP39: =SUM(CP35:CP37) -> 156042.64
A42: Gross Profit % | B42: =B19/B15 -> 1 | C42: =C19/C15 -> 0.86993193 | D42: =D19/D15 -> 0.12102581 | E42: =E19/E15 -> 0.33224674 | F42: =F19/F15 -> 0.487723 | G42: =G19/G15 -> 0.55101664 | H42: =H19/H15 -> 0.39125245 | I42: =I19/I15 -> 0.38043899 | ... CP42: =CP19/CP15 -> 0.5608342
A44: Net Profit % | B44: =B23/B15 -> -9.7189359 | C44: =C23/C15 -> -7.0126946 | D44: =D23/D15 -> -4.2962911 | E44: =E23/E15 -> -1.767808 | F44: =F23/F15 -> -0.84885302 | G44: =G23/G15 -> -0.68816416 | H44: =H23/H15 -> -0.99955186 | I44: =I23/I15 -> -0.66772755 | ... CP44: =CP23/CP15 -> 0.09102613
BQ49: =SUM(BF32,BG32,BH32,BJ32,BK32,BL32,BM31,BM31,BM32,BN32,BO32,BP32,BQ32,) -> -165000

Sheet Rev 2
A2: Condition One
A3: I
D8: March | E8: April | F8: May | G8: June | H8: July | I8: August | J8: Spetember | K8: October | L8: Novemeber | M8: December | N8: January | O8: February | P8: March | Q8: April | R8: May | S8: June | T8: 43647 | U8: =+'P&L Cash Flow Monthly'!B8 -> 43951 | V8: =+'P&L Cash Flow Monthly'!C8 -> 43982 | W8: =+'P&L Cash Flow Monthly'!D8 -> 44012 | X8: =+'P&L Cash Flow Monthly'!E8 -> 44043 | Y8: =+'P&L Cash Flow Monthly'!F8 -> 44074 | Z8: =+'P&L Cash Flow Monthly'!G8 -> 44104 | AA8: =+'P&L Cash Flow Monthly'!H8 -> 44135 | AB8: =+'P&L Cash Flow Monthly'!I8 -> 44165 | ... DI8: =+'P&L Cash Flow Monthly'!CP8 -> 46752 | DJ8: 46783 | DK8: 46811 | DL8: 46843
A13: Effect on gross sales by increasing sales over base selling procew per bar | V13: =+V21*$I25+$J29 -> 65.084987 | W13: =+W21*$I25+$J29 -> 782.69595 | X13: =+X21*$I25+$J29 -> 1192.7594 | Y13: =+Y21*$I25+$J29 -> 1545.4617 | Z13: =+Z21*$I25+$J29 -> 1523.2111 | AA13: =+AA21*$I25+$J29 -> 2184.1721 | AB13: =+AB21*$I25+$J29 -> 4280.355 | AC13: =+AC21*$I25+$J29 -> 4144.1221 | ... DL13: =+DL21*$I25+$J29 -> 0.5
A16: E-Commerce Revenue
A17: Number of customers added | T17: 80 | V17: ='Expenses 2'!C89/V42 -> 11.666667 | W17: ='Expenses 2'!D89/W42 -> 129.62963 | X17: ='Expenses 2'!E89/X42 -> 74.074074 | Y17: ='Expenses 2'!F89/Y42 -> 74.074074 | Z17: ='Expenses 2'!G89/Z42 -> 111.11111 | AA17: ='Expenses 2'!H89/AA42 -> 185.18519 | AB17: ='Expenses 2'!I89/AB42 -> 444.44444 | AC17: ='Expenses 2'!J89/AC42 -> 74.074074 | ... AZ17: ='Expenses 2'!AG89/AZ42 -> 285.71429 | BA17: ='Expenses 2'!AH28/BA42 -> 285.71429 | BB17: ='Expenses 2'!AI28/BB42 -> 250 | BC17: ='Expenses 2'!AJ28/BC42 -> 125 | BD17: ='Expenses 2'!AK28/BD42 -> 125 | BE17: ='Expenses 2'!AL28/BE42 -> 125 | BF17: ='Expenses 2'!AM28/BF42 -> 175 | BG17: ='Expenses 2'!AN28/BG42 -> 175 | BH17: ='Expenses 2'!AO28/BH42 -> 200 | ... DI17: ='Expenses 2'!CP28/DI42 -> 1250
A18: Ecommcer rev | V18: =+V530 -> 452.09491 | W18: =+W530 -> 5475.3717 | X18: =+X530 -> 8345.8155 | Y18: =+Y530 -> 10814.732 | Z18: =+Z530 -> 10658.978 | AA18: =+AA530 -> 15285.705 | AB18: =+AB530 -> 29958.985 | AC18: =+AC530 -> 29005.355 | ... DI18: =+DI530 -> 220513.02
A19: Bars sold | T19: =SUM(T17*10) -> 800 | V19: =+V18*$B32 -> 129.16997 | W19: =+W18*$B32 -> 1564.3919 | X19: =+X18*$B32 -> 2384.5187 | Y19: =+Y18*$B32 -> 3089.9233 | Z19: =+Z18*$B32 -> 3045.4222 | AA19: =+AA18*$B32 -> 4367.3442 | AB19: =+AB18*$B32 -> 8559.71 | AC19: =+AC18*$B32 -> 8287.2442 | ... DI19: =+DI18*$B32 -> 63003.719 | DJ19: =DI19 -> 63003.719 | DK19: =DJ19 -> 63003.719 | DL19: =DK19 -> 63003.719
A21: Total Bars Sold per month | V21: =+V19+V14 -> 129.16997 | W21: =+W19+W14 -> 1564.3919 | X21: =+X19+X14 -> 2384.5187 | Y21: =+Y19+Y14 -> 3089.9233 | Z21: =+Z19+Z14 -> 3045.4222 | AA21: =+AA19+AA14 -> 4367.3442 | AB21: =+AB19+AB14 -> 8559.71 | AC21: =+AC19+AC14 -> 8287.2442 | ... DI21: =+DI19+DI14 -> 63003.719
A23: Total Gross Revenue per month. | I23: % sales | V23: =+V13+V18 -> 517.17989 | W23: =+W13+W18 -> 6258.0676 | X23: =+X13+X18 -> 9538.5749 | Y23: =+Y13+Y18 -> 12360.193 | Z23: =+Z13+Z18 -> 12182.189 | AA23: =+AA13+AA18 -> 17469.877 | AB23: =+AB13+AB18 -> 34239.34 | AC23: =+AC13+AC18 -> 33149.477 | ... DI23: =+DI13+DI18 -> 252015.38 | DJ23: =DI23 -> 252015.38 | DK23: =DJ23 -> 252015.38 | DL23: =DK23 -> 252015.38
D24: Base selling price | H24: =+B31 -> 3.5 | I24: 0.5 | J24: =+H24*I24 -> 1.75
D25: Higher selling price | H25: 4.5 | I25: 0.5 | J25: =+H25*I25 -> 2.25
H26: 0
D28: New weighted average selling price | J28: =+J24+J25 -> 4
D29: Adjustment to selling proce | J29: =+J28-B31 -> 0.5
A30: ECOMM Figures
A31: Price per bar | B31: 3.5 | C31: 3.7
A32: Bars per $1 of sales | B32: =1/B31 -> 0.28571429
A35: GYMs figures
A36: Whole sale price per bar | B36: 2.5
A37: Bars per minum order | B37: 60
A38: Minum gym order value | B38: =SUM(B36*B37) -> 150
A42: Cost to Acquire customer | U42: 30 | V42: 300 | W42: 27 | X42: 27 | Y42: 27 | Z42: 27 | AA42: 27 | AB42: 27 | AC42: 27 | AD42: 24 | AE42: 24 | AF42: 24 | AG42: 27 | AH42: 27 | AI42: 27 | AJ42: 27 | AK42: 27 | AL42: 27 | AM42: 27 | AN42: 30 | AO42: 30 | AP42: 27 | AQ42: 27 | AR42: 27 | AS42: 27 | AT42: 27 | AU42: 27 | AV42: 27 | AW42: 27 | AX42: 27 | AY42: 27 | AZ42: 35 | BA42: 35 | BB42: 40 | BC42: 40 | BD42: 40 | BE42: 40 | BF42: 40 | BG42: 40 | BH42: 35 | BI42: 35 | BJ42: 35 | BK42: 35 | BL42: 40 | BM42: 40 | BN42: 40 | BO42: 50 | BP42: 50 | BQ42: 50 | BR42: 45 | BS42: 45 | BT42: 40 | BU42: 35 | BV42: 35 | BW42: 35 | BX42: 40 | BY42: 40 | BZ42: 35 | CA42: 35 | CB42: 35 | CC42: 35 | CD42: 35 | CE42: 35 | CF42: 35 | CG42: 35 | CH42: 35 | CI42: 35 | CJ42: 35 | CK42: 35 | CL42: 35 | CM42: 35 | CN42: 35 | CO42: 35 | CP42: 35 | CQ42: 35 | CR42: 35 | CS42: 35 | CT42: 35 | CU42: 35 | CV42: 35 | CW42: 35 | CX42: 40 | CY42: 40 | CZ42: 40 | DA42: 40 | DB42: 40 | DC42: 40 | DD42: 40 | DE42: 40 | DF42: 40 | DG42: 40 | DH42: 40 | DI42: 40
A44: Cost to aquire gym | B44: =SUM(CAC!B10) -> 20
A47: Total gyms | B47: =SUM(D10:M10) -> 0
A49: Gym attrition rate per year | B49: 0.1
A53: New customers | U53: ='Expenses 2'!B89/U42 -> 50 | V53: ='Expenses 2'!C89/V42 -> 11.666667 | W53: ='Expenses 2'!D89/W42 -> 129.62963 | X53: ='Expenses 2'!E89/X42 -> 74.074074 | Y53: ='Expenses 2'!F89/Y42 -> 74.074074 | Z53: ='Expenses 2'!G89/Z42 -> 111.11111 | AA53: ='Expenses 2'!H89/AA42 -> 185.18519 | AB53: ='Expenses 2'!I89/AB42 -> 444.44444 | ... AZ53: ='Expenses 2'!AG89/AZ42 -> 285.71429 | BA53: ='Expenses 2'!AH28/BA42 -> 285.71429 | BB53: ='Expenses 2'!AI28/BB42 -> 250 | BC53: ='Expenses 2'!AJ28/BC42 -> 125 | BD53: ='Expenses 2'!AK28/BD42 -> 125 | BE53: ='Expenses 2'!AL28/BE42 -> 125 | BF53: ='Expenses 2'!AM28/BF42 -> 175 | BG53: ='Expenses 2'!AN28/BG42 -> 175 | BH53: ='Expenses 2'!AO28/BH42 -> 200 | ... DI53: ='Expenses 2'!CP28/DI42 -> 1250
A54: Total active customers | U54: =U53 -> 50 | V54: =U54+V53 -> 61.666667 | W54: =V54+W53 -> 191.2963 | X54: =W54+X53 -> 265.37037 | Y54: =X54+Y53 -> 339.44444 | Z54: =Y54+Z53 -> 450.55556 | AA54: =Z54+AA53 -> 635.74074 | AB54: =AA54+AB53 -> 1080.1852 | AC54: =AB54+AC53 -> 1154.2593 | ... DI54: =DH54+DI53 -> 45886.931
B56: # years | U56: % new customers | V56: # months | W56: Total LT value | X56: Monthly LT value | Y56: wieghted average
A57: Values for each new customers | AB57: First months sales new customers | AD57: =($U58*$X58+$U59*$X59+$U60*$X60+$U61*$X61)*AD53 -> 24219.37 | AE57: =($U58*$X58+$U59*$X59+$U60*$X60+$U61*$X61)*AE53 -> 27448.619 | AF57: =($U58*$X58+$U59*$X59+$U60*$X60+$U61*$X61)*AF53 -> 27448.619 | AG57: =($U58*$X58+$U59*$X59+$U60*$X60+$U61*$X61)*AG53 -> 21528.329 | AH57: =($U58*$X58+$U59*$X59+$U60*$X60+$U61*$X61)*AH53 -> 14352.219 | AI57: =($U58*$X58+$U59*$X59+$U60*$X60+$U61*$X61)*AI53 -> 14352.219 | AJ57: =($U58*$X58+$U59*$X59+$U60*$X60+$U61*$X61)*AJ53 -> 14352.219 | AK57: =($U58*$X58+$U59*$X59+$U60*$X60+$U61*$X61)*AK53 -> 21528.329 | ... DI57: =($U58*$X58+$U59*$X59+$U60*$X60+$U61*$X61)*DI53 -> 48438.74
B58: 3.5 | U58: 0.01 | V58: =+B58*12 -> 42 | W58: 1774 | X58: =+W58/V58 -> 42.238095 | Y58: =W58*U58 -> 17.74
B59: 2.5 | U59: 0.035 | V59: =+B59*12 -> 30 | W59: 1075 | X59: =+W59/V59 -> 35.833333 | Y59: =W59*U59 -> 37.625 | AB59: Social media account manager | AD59: 2000 | AE59: 2000 | AF59: 2000 | AG59: =IF(AG57<83333,AG57*0.1,100000/12) -> 2152.8329 | AH59: =IF(AH57<83333,AH57*0.1,100000/12) -> 1435.2219 | AI59: =IF(AI57<83333,AI57*0.1,100000/12) -> 1435.2219 | AJ59: =IF(AJ57<83333,AJ57*0.1,100000/12) -> 1435.2219 | AK59: =IF(AK57<83333,AK57*0.1,100000/12) -> 2152.8329 | AL59: =IF(AL57<83333,AL57*0.1,100000/12) -> 2870.4439 | AM59: =IF(AM57<83333,AM57*0.1,100000/12) -> 4305.6658 | AN59: =IF(AN57<83333,AN57*0.1,100000/12) -> 1033.3598 | ... DI59: =IF(DI57<83333,DI57*0.1,100000/12) -> 4843.874
B60: 1.5 | U60: 0.08 | V60: =+B60*12 -> 18 | W60: 598 | X60: =+W60/V60 -> 33.222222 | Y60: =W60*U60 -> 47.84
B61: 0.25 | U61: 0.875 | V61: =+B61*12 -> 3 | W61: 118 | X61: =+W61/V61 -> 39.333333 | Y61: =W61*U61 -> 103.25
U64: =SUM(U58:U63) -> 1 | Y64: =SUM(Y58:Y61) -> 206.455
U68: From
A69: Returning Customers | U69: =+U8 -> 43951 | V69: =+#REF!-#REF!*#REF!/12 -> #REF! | W69: =IF(V69>0.005,(V69-#REF!*#REF!/12),0) -> #REF! | X69: =IF(W69>0.005,(W69-#REF!*#REF!/12),0) -> #REF! | Y69: =IF(X69>0.005,(X69-#REF!*#REF!/12),0) -> #REF! | Z69: =IF(Y69>0.005,(Y69-#REF!*#REF!/12),0) -> #REF! | AA69: =IF(Z69>0.005,(Z69-#REF!*#REF!/12),0) -> #REF! | AB69: =IF(AA69>0.005,(AA69-#REF!*#REF!/12),0) -> #REF! | AC69: =IF(AB69>0.005,(AB69-#REF!*#REF!/12),0) -> #REF! | AD69: =IF(AC69>0.005,(AC69-#REF!*#REF!/12),0) -> #REF! | ... CB69: =IF(CA69>0.005,(CA69-#REF!*#REF!/12),0) -> #REF!
U70: 43982 | V70: =+U17*#REF! -> #REF! | W70: =IF(V70>0.005,(V70-$V70*#REF!/12),0) -> #REF! | X70: =IF(W70>0.005,(W70-$V70*#REF!/12),0) -> #REF! | Y70: =IF(X70>0.005,(X70-$V70*#REF!/12),0) -> #REF! | Z70: =IF(Y70>0.005,(Y70-$V70*#REF!/12),0) -> #REF! | AA70: =IF(Z70>0.005,(Z70-$V70*#REF!/12),0) -> #REF! | AB70: =IF(AA70>0.005,(AA70-$V70*#REF!/12),0) -> #REF! | AC70: =IF(AB70>0.005,(AB70-$V70*#REF!/12),0) -> #REF! | AD70: =IF(AC70>0.005,(AC70-$V70*#REF!/12),0) -> #REF! | ... CB70: =IF(CA70>0.005,(CA70-$V70*#REF!/12),0) -> #REF!
U71: 44012 | W71: =+V$17*#REF! -> #REF! | X71: =IF(W71>0.005,(W71-$W71*#REF!/12),0) -> #REF! | Y71: =IF(X71>0.005,(X71-$W71*#REF!/12),0) -> #REF! | Z71: =IF(Y71>0.005,(Y71-$W71*#REF!/12),0) -> #REF! | AA71: =IF(Z71>0.005,(Z71-$W71*#REF!/12),0) -> #REF! | AB71: =IF(AA71>0.005,(AA71-$W71*#REF!/12),0) -> #REF! | AC71: =IF(AB71>0.005,(AB71-$W71*#REF!/12),0) -> #REF! | AD71: =IF(AC71>0.005,(AC71-$W71*#REF!/12),0) -> #REF! | AE71: =IF(AD71>0.005,(AD71-$W71*#REF!/12),0) -> #REF! | ... CB71: =IF(CA71>0.005,(CA71-$W71*#REF!/12),0) -> #REF!
U72: 44043 | X72: =+W$17*#REF! -> #REF! | Y72: =IF(X72>0.005,(X72-$X72*#REF!/12),0) -> #REF! | Z72: =IF(Y72>0.005,(Y72-$X72*#REF!/12),0) -> #REF! | AA72: =IF(Z72>0.005,(Z72-$X72*#REF!/12),0) -> #REF! | AB72: =IF(AA72>0.005,(AA72-$X72*#REF!/12),0) -> #REF! | AC72: =IF(AB72>0.005,(AB72-$X72*#REF!/12),0) -> #REF! | AD72: =IF(AC72>0.005,(AC72-$X72*#REF!/12),0) -> #REF! | AE72: =IF(AD72>0.005,(AD72-$X72*#REF!/12),0) -> #REF! | AF72: =IF(AE72>0.005,(AE72-$X72*#REF!/12),0) -> #REF! | ... CB72: =IF(CA72>0.005,(CA72-$X72*#REF!/12),0) -> #REF!
U73: 44074 | Y73: =+X$17*#REF! -> #REF! | Z73: =IF(Y73>0.005,(Y73-$Y73*#REF!/12),0) -> #REF! | AA73: =IF(Z73>0.005,(Z73-$Y73*#REF!/12),0) -> #REF! | AB73: =IF(AA73>0.005,(AA73-$Y73*#REF!/12),0) -> #REF! | AC73: =IF(AB73>0.005,(AB73-$Y73*#REF!/12),0) -> #REF! | AD73: =IF(AC73>0.005,(AC73-$Y73*#REF!/12),0) -> #REF! | AE73: =IF(AD73>0.005,(AD73-$Y73*#REF!/12),0) -> #REF! | AF73: =IF(AE73>0.005,(AE73-$Y73*#REF!/12),0) -> #REF! | AG73: =IF(AF73>0.005,(AF73-$Y73*#REF!/12),0) -> #REF! | ... CB73: =IF(CA73>0.005,(CA73-$Y73*#REF!/12),0) -> #REF!
U74: 44104 | Z74: =+Y$17*#REF! -> #REF! | AA74: =IF(Z74>0.005,(Z74-$Z74*#REF!/12),0) -> #REF! | AB74: =IF(AA74>0.005,(AA74-$Z74*#REF!/12),0) -> #REF! | AC74: =IF(AB74>0.005,(AB74-$Z74*#REF!/12),0) -> #REF! | AD74: =IF(AC74>0.005,(AC74-$Z74*#REF!/12),0) -> #REF! | AE74: =IF(AD74>0.005,(AD74-$Z74*#REF!/12),0) -> #REF! | AF74: =IF(AE74>0.005,(AE74-$Z74*#REF!/12),0) -> #REF! | AG74: =IF(AF74>0.005,(AF74-$Z74*#REF!/12),0) -> #REF! | AH74: =IF(AG74>0.005,(AG74-$Z74*#REF!/12),0) -> #REF! | ... CB74: =IF(CA74>0.005,(CA74-$Z74*#REF!/12),0) -> #REF!
U75: 44135 | AA75: =+Z$17*#REF! -> #REF! | AB75: =IF(AA75>0.005,(AA75-$AA75*#REF!/12),0) -> #REF! | AC75: =IF(AB75>0.005,(AB75-$AA75*#REF!/12),0) -> #REF! | AD75: =IF(AC75>0.005,(AC75-$AA75*#REF!/12),0) -> #REF! | AE75: =IF(AD75>0.005,(AD75-$AA75*#REF!/12),0) -> #REF! | AF75: =IF(AE75>0.005,(AE75-$AA75*#REF!/12),0) -> #REF! | AG75: =IF(AF75>0.005,(AF75-$AA75*#REF!/12),0) -> #REF! | AH75: =IF(AG75>0.005,(AG75-$AA75*#REF!/12),0) -> #REF! | AI75: =IF(AH75>0.005,(AH75-$AA75*#REF!/12),0) -> #REF! | ... CB75: =IF(CA75>0.005,(CA75-$AA75*#REF!/12),0) -> #REF!
U76: 44165 | AB76: =+AA$17*#REF! -> #REF! | AC76: =IF(AB76>0.005,(AB76-$AB76*#REF!/12),0) -> #REF! | AD76: =IF(AC76>0.005,(AC76-$AB76*#REF!/12),0) -> #REF! | AE76: =IF(AD76>0.005,(AD76-$AB76*#REF!/12),0) -> #REF! | AF76: =IF(AE76>0.005,(AE76-$AB76*#REF!/12),0) -> #REF! | AG76: =IF(AF76>0.005,(AF76-$AB76*#REF!/12),0) -> #REF! | AH76: =IF(AG76>0.005,(AG76-$AB76*#REF!/12),0) -> #REF! | AI76: =IF(AH76>0.005,(AH76-$AB76*#REF!/12),0) -> #REF! | AJ76: =IF(AI76>0.005,(AI76-$AB76*#REF!/12),0) -> #REF! | ... CB76: =IF(CA76>0.005,(CA76-$AB76*#REF!/12),0) -> #REF!
U77: 44196 | AC77: =+AB$17*#REF! -> #REF! | AD77: =IF(AC77>0.005,(AC77-$AC77*#REF!/12),0) -> #REF! | AE77: =IF(AD77>0.005,(AD77-$AC77*#REF!/12),0) -> #REF! | AF77: =IF(AE77>0.005,(AE77-$AC77*#REF!/12),0) -> #REF! | AG77: =IF(AF77>0.005,(AF77-$AC77*#REF!/12),0) -> #REF! | AH77: =IF(AG77>0.005,(AG77-$AC77*#REF!/12),0) -> #REF! | AI77: =IF(AH77>0.005,(AH77-$AC77*#REF!/12),0) -> #REF! | AJ77: =IF(AI77>0.005,(AI77-$AC77*#REF!/12),0) -> #REF! | AK77: =IF(AJ77>0.005,(AJ77-$AC77*#REF!/12),0) -> #REF! | ... CB77: =IF(CA77>0.005,(CA77-$AC77*#REF!/12),0) -> #REF!
U78: 44227 | AD78: =+AC$17*#REF! -> #REF! | AE78: =IF(AD78>0.005,(AD78-$AD78*#REF!/12),0) -> #REF! | AF78: =IF(AE78>0.005,(AE78-$AD78*#REF!/12),0) -> #REF! | AG78: =IF(AF78>0.005,(AF78-$AD78*#REF!/12),0) -> #REF! | AH78: =IF(AG78>0.005,(AG78-$AD78*#REF!/12),0) -> #REF! | AI78: =IF(AH78>0.005,(AH78-$AD78*#REF!/12),0) -> #REF! | AJ78: =IF(AI78>0.005,(AI78-$AD78*#REF!/12),0) -> #REF! | AK78: =IF(AJ78>0.005,(AJ78-$AD78*#REF!/12),0) -> #REF! | AL78: =IF(AK78>0.005,(AK78-$AD78*#REF!/12),0) -> #REF! | ... CB78: =IF(CA78>0.005,(CA78-$AD78*#REF!/12),0) -> #REF!
U79: 44255 | AE79: =+AD$17*#REF! -> #REF! | AF79: =IF(AE79>0.005,(AE79-$AE79*#REF!/12),0) -> #REF! | AG79: =IF(AF79>0.005,(AF79-$AE79*#REF!/12),0) -> #REF! | AH79: =IF(AG79>0.005,(AG79-$AE79*#REF!/12),0) -> #REF! | AI79: =IF(AH79>0.005,(AH79-$AE79*#REF!/12),0) -> #REF! | AJ79: =IF(AI79>0.005,(AI79-$AE79*#REF!/12),0) -> #REF! | AK79: =IF(AJ79>0.005,(AJ79-$AE79*#REF!/12),0) -> #REF! | AL79: =IF(AK79>0.005,(AK79-$AE79*#REF!/12),0) -> #REF! | AM79: =IF(AL79>0.005,(AL79-$AE79*#REF!/12),0) -> #REF! | ... CB79: =IF(CA79>0.005,(CA79-$AE79*#REF!/12),0) -> #REF!
U80: 44286 | AF80: =+AE$17*#REF! -> #REF! | AG80: =IF(AF80>0.005,(AF80-$AF80*#REF!/12),0) -> #REF! | AH80: =IF(AG80>0.005,(AG80-$AF80*#REF!/12),0) -> #REF! | AI80: =IF(AH80>0.005,(AH80-$AF80*#REF!/12),0) -> #REF! | AJ80: =IF(AI80>0.005,(AI80-$AF80*#REF!/12),0) -> #REF! | AK80: =IF(AJ80>0.005,(AJ80-$AF80*#REF!/12),0) -> #REF! | AL80: =IF(AK80>0.005,(AK80-$AF80*#REF!/12),0) -> #REF! | AM80: =IF(AL80>0.005,(AL80-$AF80*#REF!/12),0) -> #REF! | AN80: =IF(AM80>0.005,(AM80-$AF80*#REF!/12),0) -> #REF! | ... CB80: =IF(CA80>0.005,(CA80-$AF80*#REF!/12),0) -> #REF!
U81: 44316 | AG81: =+AF$17*#REF! -> #REF! | AH81: =IF(AG81>0.005,(AG81-$AG81*#REF!/12),0) -> #REF! | AI81: =IF(AH81>0.005,(AH81-$AG81*#REF!/12),0) -> #REF! | AJ81: =IF(AI81>0.005,(AI81-$AG81*#REF!/12),0) -> #REF! | AK81: =IF(AJ81>0.005,(AJ81-$AG81*#REF!/12),0) -> #REF! | AL81: =IF(AK81>0.005,(AK81-$AG81*#REF!/12),0) -> #REF! | AM81: =IF(AL81>0.005,(AL81-$AG81*#REF!/12),0) -> #REF! | AN81: =IF(AM81>0.005,(AM81-$AG81*#REF!/12),0) -> #REF! | AO81: =IF(AN81>0.005,(AN81-$AG81*#REF!/12),0) -> #REF! | ... CC81: =IF(CB81>0.005,(CB81-$AG81*#REF!/12),0) -> #REF!
U82: 44347 | AH82: =+AG$17*#REF! -> #REF! | AI82: =IF(AH82>0.005,(AH82-$AH82*#REF!/12),0) -> #REF! | AJ82: =IF(AI82>0.005,(AI82-$AH82*#REF!/12),0) -> #REF! | AK82: =IF(AJ82>0.005,(AJ82-$AH82*#REF!/12),0) -> #REF! | AL82: =IF(AK82>0.005,(AK82-$AH82*#REF!/12),0) -> #REF! | AM82: =IF(AL82>0.005,(AL82-$AH82*#REF!/12),0) -> #REF! | AN82: =IF(AM82>0.005,(AM82-$AH82*#REF!/12),0) -> #REF! | AO82: =IF(AN82>0.005,(AN82-$AH82*#REF!/12),0) -> #REF! | AP82: =IF(AO82>0.005,(AO82-$AH82*#REF!/12),0) -> #REF! | ... CD82: =IF(CC82>0.005,(CC82-$AH82*#REF!/12),0) -> #REF!
U83: 44377 | AI83: =+AH$17*#REF! -> #REF! | AJ83: =IF(AI83>0.005,(AI83-$AI83*#REF!/12),0) -> #REF! | AK83: =IF(AJ83>0.005,(AJ83-$AI83*#REF!/12),0) -> #REF! | AL83: =IF(AK83>0.005,(AK83-$AI83*#REF!/12),0) -> #REF! | AM83: =IF(AL83>0.005,(AL83-$AI83*#REF!/12),0) -> #REF! | AN83: =IF(AM83>0.005,(AM83-$AI83*#REF!/12),0) -> #REF! | AO83: =IF(AN83>0.005,(AN83-$AI83*#REF!/12),0) -> #REF! | AP83: =IF(AO83>0.005,(AO83-$AI83*#REF!/12),0) -> #REF! | AQ83: =IF(AP83>0.005,(AP83-$AI83*#REF!/12),0) -> #REF! | ... CE83: =IF(CD83>0.005,(CD83-$AI83*#REF!/12),0) -> #REF!
U84: 44408 | AJ84: =+AI$17*#REF! -> #REF! | AK84: =IF(AJ84>0.005,(AJ84-$AJ84*#REF!/12),0) -> #REF! | AL84: =IF(AK84>0.005,(AK84-$AJ84*#REF!/12),0) -> #REF! | AM84: =IF(AL84>0.005,(AL84-$AJ84*#REF!/12),0) -> #REF! | AN84: =IF(AM84>0.005,(AM84-$AJ84*#REF!/12),0) -> #REF! | AO84: =IF(AN84>0.005,(AN84-$AJ84*#REF!/12),0) -> #REF! | AP84: =IF(AO84>0.005,(AO84-$AJ84*#REF!/12),0) -> #REF! | AQ84: =IF(AP84>0.005,(AP84-$AJ84*#REF!/12),0) -> #REF! | AR84: =IF(AQ84>0.005,(AQ84-$AJ84*#REF!/12),0) -> #REF! | ... CF84: =IF(CE84>0.005,(CE84-$AJ84*#REF!/12),0) -> #REF!
U85: 44439 | AK85: =+AJ$17*#REF! -> #REF! | AL85: =IF(AK85>0.005,(AK85-$AK85*#REF!/12),0) -> #REF! | AM85: =IF(AL85>0.005,(AL85-$AK85*#REF!/12),0) -> #REF! | AN85: =IF(AM85>0.005,(AM85-$AK85*#REF!/12),0) -> #REF! | AO85: =IF(AN85>0.005,(AN85-$AK85*#REF!/12),0) -> #REF! | AP85: =IF(AO85>0.005,(AO85-$AK85*#REF!/12),0) -> #REF! | AQ85: =IF(AP85>0.005,(AP85-$AK85*#REF!/12),0) -> #REF! | AR85: =IF(AQ85>0.005,(AQ85-$AK85*#REF!/12),0) -> #REF! | AS85: =IF(AR85>0.005,(AR85-$AK85*#REF!/12),0) -> #REF! | ... CG85: =IF(CF85>0.005,(CF85-$AK85*#REF!/12),0) -> #REF!
U86: 44469 | AL86: =+AK$17*#REF! -> #REF! | AM86: =IF(AL86>0.005,(AL86-$AL86*#REF!/12),0) -> #REF! | AN86: =IF(AM86>0.005,(AM86-$AL86*#REF!/12),0) -> #REF! | AO86: =IF(AN86>0.005,(AN86-$AL86*#REF!/12),0) -> #REF! | AP86: =IF(AO86>0.005,(AO86-$AL86*#REF!/12),0) -> #REF! | AQ86: =IF(AP86>0.005,(AP86-$AL86*#REF!/12),0) -> #REF! | AR86: =IF(AQ86>0.005,(AQ86-$AL86*#REF!/12),0) -> #REF! | AS86: =IF(AR86>0.005,(AR86-$AL86*#REF!/12),0) -> #REF! | AT86: =IF(AS86>0.005,(AS86-$AL86*#REF!/12),0) -> #REF! | ... CH86: =IF(CG86>0.005,(CG86-$AL86*#REF!/12),0) -> #REF!
U87: 44500 | AM87: =+AL$17*#REF! -> #REF! | AN87: =IF(AM87>0.005,(AM87-$AM87*#REF!/12),0) -> #REF! | AO87: =IF(AN87>0.005,(AN87-$AM87*#REF!/12),0) -> #REF! | AP87: =IF(AO87>0.005,(AO87-$AM87*#REF!/12),0) -> #REF! | AQ87: =IF(AP87>0.005,(AP87-$AM87*#REF!/12),0) -> #REF! | AR87: =IF(AQ87>0.005,(AQ87-$AM87*#REF!/12),0) -> #REF! | AS87: =IF(AR87>0.005,(AR87-$AM87*#REF!/12),0) -> #REF! | AT87: =IF(AS87>0.005,(AS87-$AM87*#REF!/12),0) -> #REF! | AU87: =IF(AT87>0.005,(AT87-$AM87*#REF!/12),0) -> #REF! | ... CI87: =IF(CH87>0.005,(CH87-$AM87*#REF!/12),0) -> #REF!
U88: 44530 | AN88: =+AM$17*#REF! -> #REF! | AO88: =IF(AN88>0.005,(AN88-$AN88*#REF!/12),0) -> #REF! | AP88: =IF(AO88>0.005,(AO88-$AN88*#REF!/12),0) -> #REF! | AQ88: =IF(AP88>0.005,(AP88-$AN88*#REF!/12),0) -> #REF! | AR88: =IF(AQ88>0.005,(AQ88-$AN88*#REF!/12),0) -> #REF! | AS88: =IF(AR88>0.005,(AR88-$AN88*#REF!/12),0) -> #REF! | AT88: =IF(AS88>0.005,(AS88-$AN88*#REF!/12),0) -> #REF! | AU88: =IF(AT88>0.005,(AT88-$AN88*#REF!/12),0) -> #REF! | AV88: =IF(AU88>0.005,(AU88-$AN88*#REF!/12),0) -> #REF! | ... CJ88: =IF(CI88>0.005,(CI88-$AN88*#REF!/12),0) -> #REF!
U89: 44561 | AO89: =+AN$17*#REF! -> #REF! | AP89: =IF(AO89>0.005,(AO89-$AO89*#REF!/12),0) -> #REF! | AQ89: =IF(AP89>0.005,(AP89-$AO89*#REF!/12),0) -> #REF! | AR89: =IF(AQ89>0.005,(AQ89-$AO89*#REF!/12),0) -> #REF! | AS89: =IF(AR89>0.005,(AR89-$AO89*#REF!/12),0) -> #REF! | AT89: =IF(AS89>0.005,(AS89-$AO89*#REF!/12),0) -> #REF! | AU89: =IF(AT89>0.005,(AT89-$AO89*#REF!/12),0) -> #REF! | AV89: =IF(AU89>0.005,(AU89-$AO89*#REF!/12),0) -> #REF! | AW89: =IF(AV89>0.005,(AV89-$AO89*#REF!/12),0) -> #REF! | ... CK89: =IF(CJ89>0.005,(CJ89-$AO89*#REF!/12),0) -> #REF!
U90: 44592 | AP90: =+AO$17*#REF! -> #REF! | AQ90: =IF(AP90>0.005,(AP90-$AP90*#REF!/12),0) -> #REF! | AR90: =IF(AQ90>0.005,(AQ90-$AP90*#REF!/12),0) -> #REF! | AS90: =IF(AR90>0.005,(AR90-$AP90*#REF!/12),0) -> #REF! | AT90: =IF(AS90>0.005,(AS90-$AP90*#REF!/12),0) -> #REF! | AU90: =IF(AT90>0.005,(AT90-$AP90*#REF!/12),0) -> #REF! | AV90: =IF(AU90>0.005,(AU90-$AP90*#REF!/12),0) -> #REF! | AW90: =IF(AV90>0.005,(AV90-$AP90*#REF!/12),0) -> #REF! | AX90: =IF(AW90>0.005,(AW90-$AP90*#REF!/12),0) -> #REF! | ... CL90: =IF(CK90>0.005,(CK90-$AP90*#REF!/12),0) -> #REF!
U91: 44620 | AQ91: =+AP$17*#REF! -> #REF! | AR91: =IF(AQ91>0.005,(AQ91-$AQ91*#REF!/12),0) -> #REF! | AS91: =IF(AR91>0.005,(AR91-$AQ91*#REF!/12),0) -> #REF! | AT91: =IF(AS91>0.005,(AS91-$AQ91*#REF!/12),0) -> #REF! | AU91: =IF(AT91>0.005,(AT91-$AQ91*#REF!/12),0) -> #REF! | AV91: =IF(AU91>0.005,(AU91-$AQ91*#REF!/12),0) -> #REF! | AW91: =IF(AV91>0.005,(AV91-$AQ91*#REF!/12),0) -> #REF! | AX91: =IF(AW91>0.005,(AW91-$AQ91*#REF!/12),0) -> #REF! | AY91: =IF(AX91>0.005,(AX91-$AQ91*#REF!/12),0) -> #REF! | ... CM91: =IF(CL91>0.005,(CL91-$AQ91*#REF!/12),0) -> #REF!
U92: 44651 | AR92: =+AQ$17*#REF! -> #REF! | AS92: =IF(AR92>0.005,(AR92-$AR92*#REF!/12),0) -> #REF! | AT92: =IF(AS92>0.005,(AS92-$AR92*#REF!/12),0) -> #REF! | AU92: =IF(AT92>0.005,(AT92-$AR92*#REF!/12),0) -> #REF! | AV92: =IF(AU92>0.005,(AU92-$AR92*#REF!/12),0) -> #REF! | AW92: =IF(AV92>0.005,(AV92-$AR92*#REF!/12),0) -> #REF! | AX92: =IF(AW92>0.005,(AW92-$AR92*#REF!/12),0) -> #REF! | AY92: =IF(AX92>0.005,(AX92-$AR92*#REF!/12),0) -> #REF! | AZ92: =IF(AY92>0.005,(AY92-$AR92*#REF!/12),0) -> #REF! | ... CN92: =IF(CM92>0.005,(CM92-$AR92*#REF!/12),0) -> #REF!
U93: 44681 | AS93: =+AR$17*#REF! -> #REF! | AT93: =IF(AS93>0.005,(AS93-$AS93*#REF!/12),0) -> #REF! | AU93: =IF(AT93>0.005,(AT93-$AS93*#REF!/12),0) -> #REF! | AV93: =IF(AU93>0.005,(AU93-$AS93*#REF!/12),0) -> #REF! | AW93: =IF(AV93>0.005,(AV93-$AS93*#REF!/12),0) -> #REF! | AX93: =IF(AW93>0.005,(AW93-$AS93*#REF!/12),0) -> #REF! | AY93: =IF(AX93>0.005,(AX93-$AS93*#REF!/12),0) -> #REF! | AZ93: =IF(AY93>0.005,(AY93-$AS93*#REF!/12),0) -> #REF! | BA93: =IF(AZ93>0.005,(AZ93-$AS93*#REF!/12),0) -> #REF! | ... CO93: =IF(CN93>0.005,(CN93-$AS93*#REF!/12),0) -> #REF!
U94: 44712 | AT94: =+AS$17*#REF! -> #REF! | AU94: =IF(AT94>0.005,(AT94-$AT94*#REF!/12),0) -> #REF! | AV94: =IF(AU94>0.005,(AU94-$AT94*#REF!/12),0) -> #REF! | AW94: =IF(AV94>0.005,(AV94-$AT94*#REF!/12),0) -> #REF! | AX94: =IF(AW94>0.005,(AW94-$AT94*#REF!/12),0) -> #REF! | AY94: =IF(AX94>0.005,(AX94-$AT94*#REF!/12),0) -> #REF! | AZ94: =IF(AY94>0.005,(AY94-$AT94*#REF!/12),0) -> #REF! | BA94: =IF(AZ94>0.005,(AZ94-$AT94*#REF!/12),0) -> #REF! | BB94: =IF(BA94>0.005,(BA94-$AT94*#REF!/12),0) -> #REF! | ... CP94: =IF(CO94>0.005,(CO94-$AT94*#REF!/12),0) -> #REF!
U95: 44742 | AU95: =+AT$17*#REF! -> #REF! | AV95: =IF(AU95>0.005,(AU95-$AU95*#REF!/12),0) -> #REF! | AW95: =IF(AV95>0.005,(AV95-$AU95*#REF!/12),0) -> #REF! | AX95: =IF(AW95>0.005,(AW95-$AU95*#REF!/12),0) -> #REF! | AY95: =IF(AX95>0.005,(AX95-$AU95*#REF!/12),0) -> #REF! | AZ95: =IF(AY95>0.005,(AY95-$AU95*#REF!/12),0) -> #REF! | BA95: =IF(AZ95>0.005,(AZ95-$AU95*#REF!/12),0) -> #REF! | BB95: =IF(BA95>0.005,(BA95-$AU95*#REF!/12),0) -> #REF! | BC95: =IF(BB95>0.005,(BB95-$AU95*#REF!/12),0) -> #REF! | ... CQ95: =IF(CP95>0.005,(CP95-$AU95*#REF!/12),0) -> #REF!
U96: 44773 | AV96: =+AU$17*#REF! -> #REF! | AW96: =IF(AV96>0.005,(AV96-$AV96*#REF!/12),0) -> #REF! | AX96: =IF(AW96>0.005,(AW96-$AV96*#REF!/12),0) -> #REF! | AY96: =IF(AX96>0.005,(AX96-$AV96*#REF!/12),0) -> #REF! | AZ96: =IF(AY96>0.005,(AY96-$AV96*#REF!/12),0) -> #REF! | BA96: =IF(AZ96>0.005,(AZ96-$AV96*#REF!/12),0) -> #REF! | BB96: =IF(BA96>0.005,(BA96-$AV96*#REF!/12),0) -> #REF! | BC96: =IF(BB96>0.005,(BB96-$AV96*#REF!/12),0) -> #REF! | BD96: =IF(BC96>0.005,(BC96-$AV96*#REF!/12),0) -> #REF! | ... CR96: =IF(CQ96>0.005,(CQ96-$AV96*#REF!/12),0) -> #REF!
U97: 44804 | AW97: =+AV$17*#REF! -> #REF! | AX97: =IF(AW97>0.005,(AW97-$AW97*#REF!/12),0) -> #REF! | AY97: =IF(AX97>0.005,(AX97-$AW97*#REF!/12),0) -> #REF! | AZ97: =IF(AY97>0.005,(AY97-$AW97*#REF!/12),0) -> #REF! | BA97: =IF(AZ97>0.005,(AZ97-$AW97*#REF!/12),0) -> #REF! | BB97: =IF(BA97>0.005,(BA97-$AW97*#REF!/12),0) -> #REF! | BC97: =IF(BB97>0.005,(BB97-$AW97*#REF!/12),0) -> #REF! | BD97: =IF(BC97>0.005,(BC97-$AW97*#REF!/12),0) -> #REF! | BE97: =IF(BD97>0.005,(BD97-$AW97*#REF!/12),0) -> #REF! | ... CS97: =IF(CR97>0.005,(CR97-$AW97*#REF!/12),0) -> #REF!
U98: 44834 | AX98: =+AW$17*#REF! -> #REF! | AY98: =IF(AX98>0.005,(AX98-$AX98*#REF!/12),0) -> #REF! | AZ98: =IF(AY98>0.005,(AY98-$AX98*#REF!/12),0) -> #REF! | BA98: =IF(AZ98>0.005,(AZ98-$AX98*#REF!/12),0) -> #REF! | BB98: =IF(BA98>0.005,(BA98-$AX98*#REF!/12),0) -> #REF! | BC98: =IF(BB98>0.005,(BB98-$AX98*#REF!/12),0) -> #REF! | BD98: =IF(BC98>0.005,(BC98-$AX98*#REF!/12),0) -> #REF! | BE98: =IF(BD98>0.005,(BD98-$AX98*#REF!/12),0) -> #REF! | BF98: =IF(BE98>0.005,(BE98-$AX98*#REF!/12),0) -> #REF! | ... CT98: =IF(CS98>0.005,(CS98-$AX98*#REF!/12),0) -> #REF!
U99: 44865 | AY99: =+AX$17*#REF! -> #REF! | AZ99: =IF(AY99>0.005,(AY99-$AY99*#REF!/12),0) -> #REF! | BA99: =IF(AZ99>0.005,(AZ99-$AY99*#REF!/12),0) -> #REF! | BB99: =IF(BA99>0.005,(BA99-$AY99*#REF!/12),0) -> #REF! | BC99: =IF(BB99>0.005,(BB99-$AY99*#REF!/12),0) -> #REF! | BD99: =IF(BC99>0.005,(BC99-$AY99*#REF!/12),0) -> #REF! | BE99: =IF(BD99>0.005,(BD99-$AY99*#REF!/12),0) -> #REF! | BF99: =IF(BE99>0.005,(BE99-$AY99*#REF!/12),0) -> #REF! | BG99: =IF(BF99>0.005,(BF99-$AY99*#REF!/12),0) -> #REF! | ... CU99: =IF(CT99>0.005,(CT99-$AY99*#REF!/12),0) -> #REF!
U100: 44895 | AZ100: =+AY$17*#REF! -> #REF! | BA100: =IF(AZ100>0.005,(AZ100-$AZ100*#REF!/12),0) -> #REF! | BB100: =IF(BA100>0.005,(BA100-$AZ100*#REF!/12),0) -> #REF! | BC100: =IF(BB100>0.005,(BB100-$AZ100*#REF!/12),0) -> #REF! | BD100: =IF(BC100>0.005,(BC100-$AZ100*#REF!/12),0) -> #REF! | BE100: =IF(BD100>0.005,(BD100-$AZ100*#REF!/12),0) -> #REF! | BF100: =IF(BE100>0.005,(BE100-$AZ100*#REF!/12),0) -> #REF! | BG100: =IF(BF100>0.005,(BF100-$AZ100*#REF!/12),0) -> #REF! | BH100: =IF(BG100>0.005,(BG100-$AZ100*#REF!/12),0) -> #REF! | ... CV100: =IF(CU100>0.005,(CU100-$AZ100*#REF!/12),0) -> #REF!
U101: 44926 | BA101: =+AZ$17*#REF! -> #REF! | BB101: =IF(BA101>0.005,(BA101-$BA101*#REF!/12),0) -> #REF! | BC101: =IF(BB101>0.005,(BB101-$BA101*#REF!/12),0) -> #REF! | BD101: =IF(BC101>0.005,(BC101-$BA101*#REF!/12),0) -> #REF! | BE101: =IF(BD101>0.005,(BD101-$BA101*#REF!/12),0) -> #REF! | BF101: =IF(BE101>0.005,(BE101-$BA101*#REF!/12),0) -> #REF! | BG101: =IF(BF101>0.005,(BF101-$BA101*#REF!/12),0) -> #REF! | BH101: =IF(BG101>0.005,(BG101-$BA101*#REF!/12),0) -> #REF! | BI101: =IF(BH101>0.005,(BH101-$BA101*#REF!/12),0) -> #REF! | ... CW101: =IF(CV101>0.005,(CV101-$BA101*#REF!/12),0) -> #REF!
U102: 44957 | BB102: =+BA$17*#REF! -> #REF! | BC102: =IF(BB102>0.005,(BB102-$BB102*#REF!/12),0) -> #REF! | BD102: =IF(BC102>0.005,(BC102-$BB102*#REF!/12),0) -> #REF! | BE102: =IF(BD102>0.005,(BD102-$BB102*#REF!/12),0) -> #REF! | BF102: =IF(BE102>0.005,(BE102-$BB102*#REF!/12),0) -> #REF! | BG102: =IF(BF102>0.005,(BF102-$BB102*#REF!/12),0) -> #REF! | BH102: =IF(BG102>0.005,(BG102-$BB102*#REF!/12),0) -> #REF! | BI102: =IF(BH102>0.005,(BH102-$BB102*#REF!/12),0) -> #REF! | BJ102: =IF(BI102>0.005,(BI102-$BB102*#REF!/12),0) -> #REF! | ... CX102: =IF(CW102>0.005,(CW102-$BB102*#REF!/12),0) -> #REF!
U103: 44985 | BC103: =+BB$17*#REF! -> #REF! | BD103: =IF(BC103>0.005,(BC103-$BC103*#REF!/12),0) -> #REF! | BE103: =IF(BD103>0.005,(BD103-$BC103*#REF!/12),0) -> #REF! | BF103: =IF(BE103>0.005,(BE103-$BC103*#REF!/12),0) -> #REF! | BG103: =IF(BF103>0.005,(BF103-$BC103*#REF!/12),0) -> #REF! | BH103: =IF(BG103>0.005,(BG103-$BC103*#REF!/12),0) -> #REF! | BI103: =IF(BH103>0.005,(BH103-$BC103*#REF!/12),0) -> #REF! | BJ103: =IF(BI103>0.005,(BI103-$BC103*#REF!/12),0) -> #REF! | BK103: =IF(BJ103>0.005,(BJ103-$BC103*#REF!/12),0) -> #REF! | ... CY103: =IF(CX103>0.005,(CX103-$BC103*#REF!/12),0) -> #REF!
U104: 45016 | BD104: =+BC$17*#REF! -> #REF! | BE104: =IF(BD104>0.005,(BD104-$BD104*#REF!/12),0) -> #REF! | BF104: =IF(BE104>0.005,(BE104-$BD104*#REF!/12),0) -> #REF! | BG104: =IF(BF104>0.005,(BF104-$BD104*#REF!/12),0) -> #REF! | BH104: =IF(BG104>0.005,(BG104-$BD104*#REF!/12),0) -> #REF! | BI104: =IF(BH104>0.005,(BH104-$BD104*#REF!/12),0) -> #REF! | BJ104: =IF(BI104>0.005,(BI104-$BD104*#REF!/12),0) -> #REF! | BK104: =IF(BJ104>0.005,(BJ104-$BD104*#REF!/12),0) -> #REF! | BL104: =IF(BK104>0.005,(BK104-$BD104*#REF!/12),0) -> #REF! | ... CZ104: =IF(CY104>0.005,(CY104-$BD104*#REF!/12),0) -> #REF!
U105: 45046 | BE105: =+BD$17*#REF! -> #REF! | BF105: =IF(BE105>0.005,(BE105-$BE105*#REF!/12),0) -> #REF! | BG105: =IF(BF105>0.005,(BF105-$BE105*#REF!/12),0) -> #REF! | BH105: =IF(BG105>0.005,(BG105-$BE105*#REF!/12),0) -> #REF! | BI105: =IF(BH105>0.005,(BH105-$BE105*#REF!/12),0) -> #REF! | BJ105: =IF(BI105>0.005,(BI105-$BE105*#REF!/12),0) -> #REF! | BK105: =IF(BJ105>0.005,(BJ105-$BE105*#REF!/12),0) -> #REF! | BL105: =IF(BK105>0.005,(BK105-$BE105*#REF!/12),0) -> #REF! | BM105: =IF(BL105>0.005,(BL105-$BE105*#REF!/12),0) -> #REF! | ... DA105: =IF(CZ105>0.005,(CZ105-$BE105*#REF!/12),0) -> #REF!
U106: 45077 | BF106: =+BE$17*#REF! -> #REF! | BG106: =IF(BF106>0.005,(BF106-$BF106*#REF!/12),0) -> #REF! | BH106: =IF(BG106>0.005,(BG106-$BF106*#REF!/12),0) -> #REF! | BI106: =IF(BH106>0.005,(BH106-$BF106*#REF!/12),0) -> #REF! | BJ106: =IF(BI106>0.005,(BI106-$BF106*#REF!/12),0) -> #REF! | BK106: =IF(BJ106>0.005,(BJ106-$BF106*#REF!/12),0) -> #REF! | BL106: =IF(BK106>0.005,(BK106-$BF106*#REF!/12),0) -> #REF! | BM106: =IF(BL106>0.005,(BL106-$BF106*#REF!/12),0) -> #REF! | BN106: =IF(BM106>0.005,(BM106-$BF106*#REF!/12),0) -> #REF! | ... DB106: =IF(DA106>0.005,(DA106-$BF106*#REF!/12),0) -> #REF!
U107: 45107 | BG107: =+BF$17*#REF! -> #REF! | BH107: =IF(BG107>0.005,(BG107-$BG107*#REF!/12),0) -> #REF! | BI107: =IF(BH107>0.005,(BH107-$BG107*#REF!/12),0) -> #REF! | BJ107: =IF(BI107>0.005,(BI107-$BG107*#REF!/12),0) -> #REF! | BK107: =IF(BJ107>0.005,(BJ107-$BG107*#REF!/12),0) -> #REF! | BL107: =IF(BK107>0.005,(BK107-$BG107*#REF!/12),0) -> #REF! | BM107: =IF(BL107>0.005,(BL107-$BG107*#REF!/12),0) -> #REF! | BN107: =IF(BM107>0.005,(BM107-$BG107*#REF!/12),0) -> #REF! | BO107: =IF(BN107>0.005,(BN107-$BG107*#REF!/12),0) -> #REF! | ... DC107: =IF(DB107>0.005,(DB107-$BG107*#REF!/12),0) -> #REF!
U108: 45138 | BH108: =+BG$17*#REF! -> #REF! | BI108: =IF(BH108>0.005,(BH108-$BH108*#REF!/12),0) -> #REF! | BJ108: =IF(BI108>0.005,(BI108-$BH108*#REF!/12),0) -> #REF! | BK108: =IF(BJ108>0.005,(BJ108-$BH108*#REF!/12),0) -> #REF! | BL108: =IF(BK108>0.005,(BK108-$BH108*#REF!/12),0) -> #REF! | BM108: =IF(BL108>0.005,(BL108-$BH108*#REF!/12),0) -> #REF! | BN108: =IF(BM108>0.005,(BM108-$BH108*#REF!/12),0) -> #REF! | BO108: =IF(BN108>0.005,(BN108-$BH108*#REF!/12),0) -> #REF! | BP108: =IF(BO108>0.005,(BO108-$BH108*#REF!/12),0) -> #REF! | ... DD108: =IF(DC108>0.005,(DC108-$BH108*#REF!/12),0) -> #REF!
U109: 45169 | BI109: =+BH$17*#REF! -> #REF! | BJ109: =IF(BI109>0.005,(BI109-$BI109*#REF!/12),0) -> #REF! | BK109: =IF(BJ109>0.005,(BJ109-$BI109*#REF!/12),0) -> #REF! | BL109: =IF(BK109>0.005,(BK109-$BI109*#REF!/12),0) -> #REF! | BM109: =IF(BL109>0.005,(BL109-$BI109*#REF!/12),0) -> #REF! | BN109: =IF(BM109>0.005,(BM109-$BI109*#REF!/12),0) -> #REF! | BO109: =IF(BN109>0.005,(BN109-$BI109*#REF!/12),0) -> #REF! | BP109: =IF(BO109>0.005,(BO109-$BI109*#REF!/12),0) -> #REF! | BQ109: =IF(BP109>0.005,(BP109-$BI109*#REF!/12),0) -> #REF! | ... DE109: =IF(DD109>0.005,(DD109-$BI109*#REF!/12),0) -> #REF!
U110: 45199 | BJ110: =+BI$17*#REF! -> #REF! | BK110: =IF(BJ110>0.005,(BJ110-$BJ110*#REF!/12),0) -> #REF! | BL110: =IF(BK110>0.005,(BK110-$BJ110*#REF!/12),0) -> #REF! | BM110: =IF(BL110>0.005,(BL110-$BJ110*#REF!/12),0) -> #REF! | BN110: =IF(BM110>0.005,(BM110-$BJ110*#REF!/12),0) -> #REF! | BO110: =IF(BN110>0.005,(BN110-$BJ110*#REF!/12),0) -> #REF! | BP110: =IF(BO110>0.005,(BO110-$BJ110*#REF!/12),0) -> #REF! | BQ110: =IF(BP110>0.005,(BP110-$BJ110*#REF!/12),0) -> #REF! | BR110: =IF(BQ110>0.005,(BQ110-$BJ110*#REF!/12),0) -> #REF! | ... DF110: =IF(DE110>0.005,(DE110-$BJ110*#REF!/12),0) -> #REF!
U111: 45230 | BK111: =+BJ$17*#REF! -> #REF! | BL111: =IF(BK111>0.005,(BK111-$BK111*#REF!/12),0) -> #REF! | BM111: =IF(BL111>0.005,(BL111-$BL111*#REF!/12),0) -> #REF! | BN111: =IF(BM111>0.005,(BM111-$BK111*#REF!/12),0) -> #REF! | BO111: =IF(BN111>0.005,(BN111-$BK111*#REF!/12),0) -> #REF! | BP111: =IF(BO111>0.005,(BO111-$BK111*#REF!/12),0) -> #REF! | BQ111: =IF(BP111>0.005,(BP111-$BK111*#REF!/12),0) -> #REF! | BR111: =IF(BQ111>0.005,(BQ111-$BK111*#REF!/12),0) -> #REF! | BS111: =IF(BR111>0.005,(BR111-$BK111*#REF!/12),0) -> #REF! | BT111: =IF(BS111>0.005,(BS111-$BK111*#REF!/12),0) -> #REF! | BU111: =IF(BT111>0.005,(BT111-$BK111*#REF!/12),0) -> #REF! | ... DG111: =IF(DF111>0.005,(DF111-$BK111*#REF!/12),0) -> #REF!
U112: 45260 | BL112: =+BK$17*#REF! -> #REF! | BM112: =IF(BL112>0.005,(BL112-$BL112*#REF!/12),0) -> #REF! | BN112: =IF(BM112>0.005,(BM112-$BL112*#REF!/12),0) -> #REF! | BO112: =IF(BN112>0.005,(BN112-$BL112*#REF!/12),0) -> #REF! | BP112: =IF(BO112>0.005,(BO112-$BL112*#REF!/12),0) -> #REF! | BQ112: =IF(BP112>0.005,(BP112-$BL112*#REF!/12),0) -> #REF! | BR112: =IF(BQ112>0.005,(BQ112-$BL112*#REF!/12),0) -> #REF! | BS112: =IF(BR112>0.005,(BR112-$BL112*#REF!/12),0) -> #REF! | BT112: =IF(BS112>0.005,(BS112-$BL112*#REF!/12),0) -> #REF! | ... DI112: =IF(DH112>0.005,(DH112-$BL112*#REF!/12),0) -> #REF!
U113: 45291 | BM113: =+BL$17*#REF! -> #REF! | BN113: =IF(BM113>0.005,(BM113-$BM113*#REF!/12),0) -> #REF! | BO113: =IF(BN113>0.005,(BN113-$BM113*#REF!/12),0) -> #REF! | BP113: =IF(BO113>0.005,(BO113-$BM113*#REF!/12),0) -> #REF! | BQ113: =IF(BP113>0.005,(BP113-$BM113*#REF!/12),0) -> #REF! | BR113: =IF(BQ113>0.005,(BQ113-$BM113*#REF!/12),0) -> #REF! | BS113: =IF(BR113>0.005,(BR113-$BM113*#REF!/12),0) -> #REF! | BT113: =IF(BS113>0.005,(BS113-$BM113*#REF!/12),0) -> #REF! | BU113: =IF(BT113>0.005,(BT113-$BM113*#REF!/12),0) -> #REF! | ... DI113: =IF(DH113>0.005,(DH113-$BM113*#REF!/12),0) -> #REF!
U114: 45322 | BN114: =+BM$17*#REF! -> #REF! | BO114: =IF(BN114>0.005,(BN114-$BN114*#REF!/12),0) -> #REF! | BP114: =IF(BO114>0.005,(BO114-$BN114*#REF!/12),0) -> #REF! | BQ114: =IF(BP114>0.005,(BP114-$BN114*#REF!/12),0) -> #REF! | BR114: =IF(BQ114>0.005,(BQ114-$BN114*#REF!/12),0) -> #REF! | BS114: =IF(BR114>0.005,(BR114-$BN114*#REF!/12),0) -> #REF! | BT114: =IF(BS114>0.005,(BS114-$BN114*#REF!/12),0) -> #REF! | BU114: =IF(BT114>0.005,(BT114-$BN114*#REF!/12),0) -> #REF! | BV114: =IF(BU114>0.005,(BU114-$BN114*#REF!/12),0) -> #REF! | ... DJ114: =IF(DI114>0.005,(DI114-$BN114*#REF!/12),0) -> #REF!
U115: 45351 | BO115: =+BN$17*#REF! -> #REF! | BP115: =IF(BO115>0.005,(BO115-$BO115*#REF!/12),0) -> #REF! | BQ115: =IF(BP115>0.005,(BP115-$BO115*#REF!/12),0) -> #REF! | BR115: =IF(BQ115>0.005,(BQ115-$BO115*#REF!/12),0) -> #REF! | BS115: =IF(BR115>0.005,(BR115-$BO115*#REF!/12),0) -> #REF! | BT115: =IF(BS115>0.005,(BS115-$BO115*#REF!/12),0) -> #REF! | BU115: =IF(BT115>0.005,(BT115-$BO115*#REF!/12),0) -> #REF! | BV115: =IF(BU115>0.005,(BU115-$BO115*#REF!/12),0) -> #REF! | BW115: =IF(BV115>0.005,(BV115-$BO115*#REF!/12),0) -> #REF! | ... DK115: =IF(DJ115>0.005,(DJ115-$BO115*#REF!/12),0) -> #REF!
U116: 45382 | BP116: =+BO$17*#REF! -> #REF! | BQ116: =IF(BP116>0.005,(BP116-$BP116*#REF!/12),0) -> #REF! | BR116: =IF(BQ116>0.005,(BQ116-$BP116*#REF!/12),0) -> #REF! | BS116: =IF(BR116>0.005,(BR116-$BP116*#REF!/12),0) -> #REF! | BT116: =IF(BS116>0.005,(BS116-$BP116*#REF!/12),0) -> #REF! | BU116: =IF(BT116>0.005,(BT116-$BP116*#REF!/12),0) -> #REF! | BV116: =IF(BU116>0.005,(BU116-$BP116*#REF!/12),0) -> #REF! | BW116: =IF(BV116>0.005,(BV116-$BP116*#REF!/12),0) -> #REF! | BX116: =IF(BW116>0.005,(BW116-$BP116*#REF!/12),0) -> #REF! | ... DL116: =IF(DK116>0.005,(DK116-$BP116*#REF!/12),0) -> #REF!
U117: 45412 | BQ117: =+BP$17*#REF! -> #REF! | BR117: =IF(BQ117>0.005,(BQ117-$BQ117*#REF!/12),0) -> #REF! | BS117: =IF(BR117>0.005,(BR117-$BQ117*#REF!/12),0) -> #REF! | BT117: =IF(BS117>0.005,(BS117-$BQ117*#REF!/12),0) -> #REF! | BU117: =IF(BT117>0.005,(BT117-$BQ117*#REF!/12),0) -> #REF! | BV117: =IF(BU117>0.005,(BU117-$BQ117*#REF!/12),0) -> #REF! | BW117: =IF(BV117>0.005,(BV117-$BQ117*#REF!/12),0) -> #REF! | BX117: =IF(BW117>0.005,(BW117-$BQ117*#REF!/12),0) -> #REF! | BY117: =IF(BX117>0.005,(BX117-$BQ117*#REF!/12),0) -> #REF! | ... DM117: =IF(DL117>0.005,(DL117-$BQ117*#REF!/12),0) -> #REF!
U118: 45443 | BR118: =+BQ$17*#REF! -> #REF! | BS118: =IF(BR118>0.005,(BR118-$BR118*#REF!/12),0) -> #REF! | BT118: =IF(BS118>0.005,(BS118-$BR118*#REF!/12),0) -> #REF! | BU118: =IF(BT118>0.005,(BT118-$BR118*#REF!/12),0) -> #REF! | BV118: =IF(BU118>0.005,(BU118-$BR118*#REF!/12),0) -> #REF! | BW118: =IF(BV118>0.005,(BV118-$BR118*#REF!/12),0) -> #REF! | BX118: =IF(BW118>0.005,(BW118-$BR118*#REF!/12),0) -> #REF! | BY118: =IF(BX118>0.005,(BX118-$BR118*#REF!/12),0) -> #REF! | BZ118: =IF(BY118>0.005,(BY118-$BR118*#REF!/12),0) -> #REF! | ... DN118: =IF(DM118>0.005,(DM118-$BR118*#REF!/12),0) -> #REF!
U119: 45473 | BS119: =+BR$17*#REF! -> #REF! | BT119: =IF(BS119>0.005,(BS119-$BS119*#REF!/12),0) -> #REF! | BU119: =IF(BT119>0.005,(BT119-$BS119*#REF!/12),0) -> #REF! | BV119: =IF(BU119>0.005,(BU119-$BS119*#REF!/12),0) -> #REF! | BW119: =IF(BV119>0.005,(BV119-$BS119*#REF!/12),0) -> #REF! | BX119: =IF(BW119>0.005,(BW119-$BS119*#REF!/12),0) -> #REF! | BY119: =IF(BX119>0.005,(BX119-$BS119*#REF!/12),0) -> #REF! | BZ119: =IF(BY119>0.005,(BY119-$BS119*#REF!/12),0) -> #REF! | CA119: =IF(BZ119>0.005,(BZ119-$BS119*#REF!/12),0) -> #REF! | ... DO119: =IF(DN119>0.005,(DN119-$BS119*#REF!/12),0) -> #REF!
U120: 45504 | BT120: =+BS$17*#REF! -> #REF! | BU120: =IF(BT120>0.005,(BT120-$BT120*#REF!/12),0) -> #REF! | BV120: =IF(BU120>0.005,(BU120-$BT120*#REF!/12),0) -> #REF! | BW120: =IF(BV120>0.005,(BV120-$BT120*#REF!/12),0) -> #REF! | BX120: =IF(BW120>0.005,(BW120-$BT120*#REF!/12),0) -> #REF! | BY120: =IF(BX120>0.005,(BX120-$BT120*#REF!/12),0) -> #REF! | BZ120: =IF(BY120>0.005,(BY120-$BT120*#REF!/12),0) -> #REF! | CA120: =IF(BZ120>0.005,(BZ120-$BT120*#REF!/12),0) -> #REF! | CB120: =IF(CA120>0.005,(CA120-$BT120*#REF!/12),0) -> #REF! | ... DP120: =IF(DO120>0.005,(DO120-$BT120*#REF!/12),0) -> #REF!
U121: 45535 | BU121: =+BT$17*#REF! -> #REF! | BV121: =IF(BU121>0.005,(BU121-$BU121*#REF!/12),0) -> #REF! | BW121: =IF(BV121>0.005,(BV121-$BU121*#REF!/12),0) -> #REF! | BX121: =IF(BW121>0.005,(BW121-$BU121*#REF!/12),0) -> #REF! | BY121: =IF(BX121>0.005,(BX121-$BU121*#REF!/12),0) -> #REF! | BZ121: =IF(BY121>0.005,(BY121-$BU121*#REF!/12),0) -> #REF! | CA121: =IF(BZ121>0.005,(BZ121-$BU121*#REF!/12),0) -> #REF! | CB121: =IF(CA121>0.005,(CA121-$BU121*#REF!/12),0) -> #REF! | CC121: =IF(CB121>0.005,(CB121-$BU121*#REF!/12),0) -> #REF! | ... DQ121: =IF(DP121>0.005,(DP121-$BU121*#REF!/12),0) -> #REF!
U122: 45565 | BV122: =+BU$17*#REF! -> #REF! | BW122: =IF(BV122>0.005,(BV122-$BV122*#REF!/12),0) -> #REF! | BX122: =IF(BW122>0.005,(BW122-$BV122*#REF!/12),0) -> #REF! | BY122: =IF(BX122>0.005,(BX122-$BV122*#REF!/12),0) -> #REF! | BZ122: =IF(BY122>0.005,(BY122-$BV122*#REF!/12),0) -> #REF! | CA122: =IF(BZ122>0.005,(BZ122-$BV122*#REF!/12),0) -> #REF! | CB122: =IF(CA122>0.005,(CA122-$BV122*#REF!/12),0) -> #REF! | CC122: =IF(CB122>0.005,(CB122-$BV122*#REF!/12),0) -> #REF! | CD122: =IF(CC122>0.005,(CC122-$BV122*#REF!/12),0) -> #REF! | ... DR122: =IF(DQ122>0.005,(DQ122-$BV122*#REF!/12),0) -> #REF!
U123: 45596 | BW123: =+BV$17*#REF! -> #REF! | BX123: =IF(BW123>0.005,(BW123-$BW123*#REF!/12),0) -> #REF! | BY123: =IF(BX123>0.005,(BX123-$BW123*#REF!/12),0) -> #REF! | BZ123: =IF(BY123>0.005,(BY123-$BW123*#REF!/12),0) -> #REF! | CA123: =IF(BZ123>0.005,(BZ123-$BW123*#REF!/12),0) -> #REF! | CB123: =IF(CA123>0.005,(CA123-$BW123*#REF!/12),0) -> #REF! | CC123: =IF(CB123>0.005,(CB123-$BW123*#REF!/12),0) -> #REF! | CD123: =IF(CC123>0.005,(CC123-$BW123*#REF!/12),0) -> #REF! | CE123: =IF(CD123>0.005,(CD123-$BW123*#REF!/12),0) -> #REF! | ... DS123: =IF(DR123>0.005,(DR123-$BW123*#REF!/12),0) -> #REF!
U124: 45626 | BX124: =+BW$17*#REF! -> #REF! | BY124: =IF(BX124>0.005,(BX124-$BX124*#REF!/12),0) -> #REF! | BZ124: =IF(BY124>0.005,(BY124-$BX124*#REF!/12),0) -> #REF! | CA124: =IF(BZ124>0.005,(BZ124-$BX124*#REF!/12),0) -> #REF! | CB124: =IF(CA124>0.005,(CA124-$BX124*#REF!/12),0) -> #REF! | CC124: =IF(CB124>0.005,(CB124-$BX124*#REF!/12),0) -> #REF! | CD124: =IF(CC124>0.005,(CC124-$BX124*#REF!/12),0) -> #REF! | CE124: =IF(CD124>0.005,(CD124-$BX124*#REF!/12),0) -> #REF! | CF124: =IF(CE124>0.005,(CE124-$BX124*#REF!/12),0) -> #REF! | ... DT124: =IF(DS124>0.005,(DS124-$BX124*#REF!/12),0) -> #REF!
U125: 45657 | BY125: =+BX$17*#REF! -> #REF! | BZ125: =IF(BY125>0.005,(BY125-$BY125*#REF!/12),0) -> #REF! | CA125: =IF(BZ125>0.005,(BZ125-$BY125*#REF!/12),0) -> #REF! | CB125: =IF(CA125>0.005,(CA125-$BY125*#REF!/12),0) -> #REF! | CC125: =IF(CB125>0.005,(CB125-$BY125*#REF!/12),0) -> #REF! | CD125: =IF(CC125>0.005,(CC125-$BY125*#REF!/12),0) -> #REF! | CE125: =IF(CD125>0.005,(CD125-$BY125*#REF!/12),0) -> #REF! | CF125: =IF(CE125>0.005,(CE125-$BY125*#REF!/12),0) -> #REF! | CG125: =IF(CF125>0.005,(CF125-$BY125*#REF!/12),0) -> #REF! | ... DU125: =IF(DT125>0.005,(DT125-$BY125*#REF!/12),0) -> #REF!
U126: 45688 | BZ126: =+BY$17*#REF! -> #REF! | CA126: =IF(BZ126>0.005,(BZ126-$BZ126*#REF!/12),0) -> #REF! | CB126: =IF(CA126>0.005,(CA126-$BZ126*#REF!/12),0) -> #REF! | CC126: =IF(CB126>0.005,(CB126-$BZ126*#REF!/12),0) -> #REF! | CD126: =IF(CC126>0.005,(CC126-$BZ126*#REF!/12),0) -> #REF! | CE126: =IF(CD126>0.005,(CD126-$BZ126*#REF!/12),0) -> #REF! | CF126: =IF(CE126>0.005,(CE126-$BZ126*#REF!/12),0) -> #REF! | CG126: =IF(CF126>0.005,(CF126-$BZ126*#REF!/12),0) -> #REF! | CH126: =IF(CG126>0.005,(CG126-$BZ126*#REF!/12),0) -> #REF! | ... DV126: =IF(DU126>0.005,(DU126-$BZ126*#REF!/12),0) -> #REF!
U127: 45716 | CA127: =+BZ$17*#REF! -> #REF! | CB127: =IF(CA127>0.005,(CA127-$CA127*#REF!/12),0) -> #REF! | CC127: =IF(CB127>0.005,(CB127-$CA127*#REF!/12),0) -> #REF! | CD127: =IF(CC127>0.005,(CC127-$CA127*#REF!/12),0) -> #REF! | CE127: =IF(CD127>0.005,(CD127-$CA127*#REF!/12),0) -> #REF! | CF127: =IF(CE127>0.005,(CE127-$CA127*#REF!/12),0) -> #REF! | CG127: =IF(CF127>0.005,(CF127-$CA127*#REF!/12),0) -> #REF! | CH127: =IF(CG127>0.005,(CG127-$CA127*#REF!/12),0) -> #REF! | CI127: =IF(CH127>0.005,(CH127-$CA127*#REF!/12),0) -> #REF! | ... DW127: =IF(DV127>0.005,(DV127-$CA127*#REF!/12),0) -> #REF!
U128: 45747
U129: 45777
U130: 45808
U131: 45838
U132: 45869
...

Sheet COGS
A3: COGS Projections
B9: =+'P&L Cash Flow Monthly'!B8 -> 43951 | C9: =+'P&L Cash Flow Monthly'!C8 -> 43982 | D9: =+'P&L Cash Flow Monthly'!D8 -> 44012 | E9: =+'P&L Cash Flow Monthly'!E8 -> 44043 | F9: =+'P&L Cash Flow Monthly'!F8 -> 44074 | G9: =+'P&L Cash Flow Monthly'!G8 -> 44104 | H9: =+'P&L Cash Flow Monthly'!H8 -> 44135 | I9: =+'P&L Cash Flow Monthly'!I8 -> 44165 | ... CP9: =+'P&L Cash Flow Monthly'!CP8 -> 46752
A10: Labor & Fullment cost per bar | B10: 2.25 | C10: 2.25 | D10: 2.05 | E10: 2.05 | F10: 2.05 | G10: 1.65 | H10: 1.65 | I10: 1.65 | J10: 1.65 | K10: 1.65 | L10: 1.65 | M10: 1.65 | N10: 1.65 | O10: 1.65 | P10: 1.65 | Q10: 1.65 | R10: 1.65 | S10: 1.65 | T10: 1.65 | U10: 1.65 | V10: 1.65 | W10: 1.65 | X10: 1.65 | Y10: 1.65 | Z10: 1.65 | AA10: 1.65 | AB10: 1.65 | AC10: 1.65 | AD10: 1.65 | AE10: 1.65 | AF10: 1.65 | AG10: 1.25 | AH10: 1.25 | AI10: 1.25 | AJ10: 1.25 | AK10: 1.25 | AL10: 1.25 | AM10: 1.25 | AN10: 1.25 | AO10: 1.25 | AP10: 1.25 | AQ10: 1.25 | AR10: 1.25 | AS10: 1.25 | AT10: 1.25 | AU10: 1.25 | AV10: 1.25 | AW10: 1.25 | AX10: 1.25 | AY10: 1.25 | AZ10: 1.25 | BA10: 1.25 | BB10: 1.25 | BC10: 1.25 | BD10: 1.25 | BE10: 1.25 | BF10: 1.25 | BG10: 0.94 | BH10: 0.94 | BI10: 0.94 | BJ10: 0.94 | BK10: 0.94 | BL10: 0.94 | BM10: 0.94 | BN10: 0.94 | BO10: 0.94 | BP10: 0.94 | BQ10: 0.94 | BR10: 0.94 | BS10: 0.94 | BT10: 0.94 | BU10: 0.94 | BV10: 0.94 | BW10: 0.94 | BX10: 0.94 | BY10: 0.94 | BZ10: 0.94 | CA10: 0.94 | CB10: 0.94 | CC10: 0.94 | CD10: 0.94 | CE10: 0.94 | CF10: 0.94 | CG10: 0.94 | CH10: 0.94 | CI10: 0.94 | CJ10: 0.94 | CK10: 0.94 | CL10: 0.94 | CM10: 0.94 | CN10: 0.94 | CO10: 0.94 | CP10: 0.94
A12: Ingredients and packging cost per bar | B12: =+$B41 -> 1.1633333 | C12: =+$B41 -> 1.1633333 | D12: =+$B41 -> 1.1633333 | E12: =+$B41 -> 1.1633333 | F12: =+$B41 -> 1.1633333 | G12: =+$B41 -> 1.1633333 | H12: =+$B41 -> 1.1633333 | I12: =+$B41 -> 1.1633333 | ... L12: =+$B41 -> 1.1633333 | M12: =+B41 -> 1.1633333 | N12: =+B41 -> 1.1633333 | O12: =+$B41 -> 1.1633333 | P12: =+$B41 -> 1.1633333 | Q12: =+$B41 -> 1.1633333 | R12: =+$B41 -> 1.1633333 | S12: =+$B41 -> 1.1633333 | T12: =+$B41 -> 1.1633333 | U12: =+$B41 -> 1.1633333 | V12: =+$B41 -> 1.1633333 | ... BL12: =+$B41 -> 1.1633333 | BM12: =+$C41 -> 0.81666667 | BN12: =+$C41 -> 0.81666667 | BO12: =+$C41 -> 0.81666667 | BP12: =+$C41 -> 0.81666667 | BQ12: =+$C41 -> 0.81666667 | BR12: =+$C41 -> 0.81666667 | BS12: =+$C41 -> 0.81666667 | BT12: =+$C41 -> 0.81666667 | ... CP12: =+$C41 -> 0.81666667
A14: total cost per bar | B14: =+B10+$B41 -> 3.4133333 | C14: =+C10+$B41 -> 3.4133333 | D14: =+D10+$B41 -> 3.2133333 | E14: =+E10+$B41 -> 3.2133333 | F14: =+F10+$B41 -> 3.2133333 | G14: =+G10+$B41 -> 2.8133333 | H14: =+H10+$B41 -> 2.8133333 | I14: =SUM(I10:I12) -> 2.8133333 | J14: =SUM(J10:J12) -> 2.8133333 | K14: =SUM(K10:K12) -> 2.8133333 | L14: =SUM(L10:L12) -> 2.8133333 | M14: =SUM(M10:M12) -> 2.8133333 | N14: =SUM(N10:N12) -> 2.8133333 | O14: =SUM(O10:O12) -> 2.8133333 | P14: =SUM(P10:P12) -> 2.8133333 | ... CP14: =SUM(CP10:CP12) -> 1.7566667
A17: For sales in month | B17: =+D9 -> 44012 | C17: =+E9 -> 44043 | D17: =+F9 -> 44074 | E17: =+G9 -> 44104 | F17: =+H9 -> 44135 | G17: =+I9 -> 44165 | H17: =+J9 -> 44196 | I17: =+K9 -> 44227 | ... CP17: =+CR9
A19: Produced third month prior to sale
A20: Ingredietns Purchase three months forward
A21: # bars produced | B21: =+'Rev 2'!W19 -> 1564.3919 | C21: =+'Rev 2'!X19 -> 2384.5187 | D21: =+'Rev 2'!Y19 -> 3089.9233 | E21: =+'Rev 2'!Z19 -> 3045.4222 | F21: =+'Rev 2'!AA19 -> 4367.3442 | G21: =+'Rev 2'!AB19 -> 8559.71 | H21: =+'Rev 2'!AC19 -> 8287.2442 | I21: =+'Rev 2'!AD19 -> 13386.077 | ... CP21: =+'Rev 2'!DK19 -> 63003.719
B23: =+B21*B14 -> 5339.791 | C23: =+C21*C14 -> 8139.1572 | D23: =+D21*D14 -> 9928.9536 | E23: =+E21*E14 -> 9785.9566 | F23: =+F21*F14 -> 14033.733 | G23: =+G21*G14 -> 24081.317 | H23: =+H21*H14 -> 23314.78 | I23: =+I21*I14 -> 37659.495 | ... CP23: =+CP21*CP14 -> 110676.53
A26: Additional production month 1
A27: # bars to be sold months 1 and 2 | B27: =+'Rev 2'!V19+'Rev 2'!W19 -> 1693.5619
A28: Cost per bar | B28: =+B14 -> 3.4133333
B29: =+B27*B28 -> 5780.6912
A30: Cost of inventory on hand | B30: -5000
A31: Additional production costs for first
A32: two months sales | B32: =SUM(B29:B30) -> 780.6912
C34: economy of scale
C35: %30 reduction
A36: Bar cost break down per bar
A37: ingredients | B37: 0.95 | C37: 0.65
A38: flow wrap and label | B38: 0.13 | C38: 0.1
A39: display box | B39: =0.15/6 -> 0.025 | C39: =+B39*0.8 -> 0.02
A40: Shipper box | B40: =0.35/6 -> 0.058333333 | C40: =+B40*0.8 -> 0.046666667
A41: total material cost per bar | B41: =SUM(B37:B40) -> 1.1633333 | C41: =SUM(C37:C40) -> 0.81666667

Sheet Expenses 2
A4: Expense Projections
B9: =+'P&L Cash Flow Monthly'!B8 -> 43951 | C9: =+'P&L Cash Flow Monthly'!C8 -> 43982 | D9: =+'P&L Cash Flow Monthly'!D8 -> 44012 | E9: =+'P&L Cash Flow Monthly'!E8 -> 44043 | F9: =+'P&L Cash Flow Monthly'!F8 -> 44074 | G9: =+'P&L Cash Flow Monthly'!G8 -> 44104 | H9: =+'P&L Cash Flow Monthly'!H8 -> 44135 | I9: =+'P&L Cash Flow Monthly'!I8 -> 44165 | ... CP9: =+'P&L Cash Flow Monthly'!CP8 -> 46752
A10: Expense
A13: Salaries
A14: Executive
A15: COO | AJ15: 0 | AL15: 0 | AU15: 2000 | AV15: 2000 | AW15: 2000 | AX15: 2000 | AY15: 2000 | AZ15: 2000 | BA15: 2000 | BB15: 2000 | BC15: 2000 | BD15: 2000 | BE15: 2000 | BF15: 2000 | BG15: 2000 | BH15: 2000 | BI15: 2000 | BJ15: 2000 | BK15: 2000 | BL15: 2000 | BM15: 2000 | BN15: 3000 | BO15: 3000 | BP15: 3000 | BQ15: 3000 | BR15: 3000 | BS15: 3000 | BT15: 3000 | BU15: 3000 | BV15: 3000 | BW15: 3000 | BX15: 3000 | BY15: 3000 | BZ15: 3000 | CA15: 3000 | CB15: 3000 | CC15: 3000 | CD15: 3000 | CE15: 6000 | CF15: 6000 | CG15: 6000 | CH15: 6000 | CI15: 6000 | CJ15: 6000 | CK15: 6000 | CL15: 6000 | CM15: 6000 | CN15: 6000 | CO15: 6000 | CP15: 6000
A16: CFO
A17: Sales
A18: Director
A19: Sales representive | AO19: 0
A20: Marketing | AO20: 0
A21: Director | AJ21: 0 | AK21: 0 | AL21: 0 | AM21: 0 | AN21: 0 | AO21: 0 | AP21: 0 | AQ21: 0 | AR21: 0 | AS21: 0 | AT21: 0 | AU21: 0 | AV21: 0 | AW21: 0 | AX21: 0 | AY21: 0 | AZ21: 0 | BA21: 0 | BB21: 0 | BC21: 0 | BD21: 0 | BE21: 0 | BF21: 0 | BG21: 0 | BH21: 0 | BI21: 0 | BJ21: 0 | BK21: 0 | BL21: 0 | BM21: 0 | BN21: 0 | BO21: 0 | BP21: 0 | BQ21: 0 | BR21: 0 | BS21: 0 | BT21: 0 | BU21: 0 | BV21: 0 | BW21: 0 | BX21: 0 | BY21: 0 | BZ21: 0 | CA21: 0 | CB21: 0 | CC21: 0 | CD21: 0 | CE21: 0 | CF21: 0 | CG21: 0 | CH21: 0 | CI21: 0 | CJ21: 0 | CK21: 0 | CL21: 0 | CM21: 0 | CN21: 0 | CO21: 0 | CP21: 0 | CQ21: 0
A22: SEO manager | AI22: 1500 | AJ22: 1500 | AK22: 1500 | AL22: 1500 | AM22: 1500 | AN22: 1500 | AO22: 1500 | AP22: 1500 | AQ22: 1500 | AR22: 1500 | AS22: 1500 | AT22: 1500 | AU22: 1500 | AV22: 1500 | AW22: 1500 | AX22: 1500 | AY22: 1500 | AZ22: 1500 | BA22: 1500 | BB22: 1500 | BC22: 1500 | BD22: 1500 | BE22: 1500 | BF22: 1500 | BG22: 1500 | BH22: 1500 | BI22: 1500 | BJ22: 1500 | BK22: 1500 | BL22: 1500 | BM22: 1500 | BN22: 1500 | BO22: 1500 | BP22: 1500 | BQ22: 3000 | BR22: 3000 | BS22: 3000 | BT22: 3000 | BU22: 3000 | BV22: 3000 | BW22: 3000 | BX22: 3000 | BY22: 3000 | BZ22: 3000 | CA22: 3000 | CB22: 3000 | CC22: 3000 | CD22: 3000 | CE22: 3000 | CF22: 3000 | CG22: 3000 | CH22: 3000 | CI22: 3000 | CJ22: 3000 | CK22: 3000 | CL22: 3000 | CM22: 3000 | CN22: 3000 | CO22: 3000 | CP22: 3000
A23: Social media manager | B23: 3000 | C23: 3000 | D23: 3000 | E23: 3000 | F23: 3000 | G23: 3000 | H23: 3000 | I23: 3000 | J23: 3000 | K23: 3000 | L23: 3000 | M23: 3000 | N23: 3000 | O23: 3000 | P23: 3000 | Q23: 3000 | R23: 3000 | S23: 3000 | T23: 3000 | U23: 3000 | V23: 3000 | W23: 3000 | X23: 3000 | Y23: 3000 | Z23: 3000 | AA23: 3000 | AB23: 3000 | AC23: 3000 | AD23: 3000 | AE23: 3000 | AF23: 3000 | AG23: 3000 | AI23: 1500 | AJ23: 1500 | AK23: 1500 | AL23: 1500 | AM23: 1500 | AN23: 1500 | AO23: 1500 | AP23: 1500 | AQ23: 1500 | AR23: 1500 | AS23: 1500 | AT23: 1500 | AU23: 1500 | AV23: 1500 | AW23: 1500 | AX23: 1500 | AY23: 1500 | AZ23: 1500 | BA23: 1500 | BB23: 1500 | BC23: 1500 | BD23: 1500 | BE23: 1500 | BF23: 1500 | BG23: 1500 | BH23: 1500 | BI23: 1500 | BJ23: 1500 | BK23: 1500 | BL23: 1500 | BM23: 1500 | BN23: 1500 | BO23: 1500 | BP23: 2000 | BQ23: 2000 | BR23: 2000 | BS23: 2000 | BT23: 2000 | BU23: 2000 | BV23: 2000 | BW23: 2000 | BX23: 2000 | BY23: 2000 | BZ23: 2000 | CA23: 2000 | CB23: 2000 | CC23: 2000 | CD23: 2000 | CE23: 2000 | CF23: 2000 | CG23: 2000 | CH23: 2000 | CI23: 2000 | CJ23: 2000 | CK23: 2000 | CL23: 2000 | CM23: 2000 | CN23: 2000 | CO23: 2000 | CP23: 2000
A24: Tier 1 customer support
A26: Marketing expenses
A27: Content creation | AH27: 0 | AI27: 1000 | AJ27: 1000 | AK27: 1000 | AL27: 1000 | AM27: 1000 | AN27: 1000 | AO27: 1000 | AP27: 10000 | AQ27: 2000 | AR27: 2000 | AS27: 2000 | AT27: 2000 | AU27: 2000 | AV27: 2000 | AW27: 2000 | AX27: 2000 | AY27: 2000 | AZ27: 2000 | BA27: 2000 | BB27: 5000 | BC27: 5000 | BD27: 5000 | BE27: 5000 | BF27: 5000 | BG27: 5000 | BH27: 5000 | BI27: 5000 | BJ27: 3000 | BK27: 3000 | BL27: 3000 | BM27: 3000 | BN27: 3000 | BO27: 3000 | BP27: 3000 | BQ27: 3000 | BR27: 3000 | BS27: 3000 | BT27: 3000 | BU27: 3000 | BV27: 3000 | BW27: 3000 | BX27: 3000 | BY27: 3000 | BZ27: 3000 | CA27: 3000 | CB27: 3000 | CC27: 3000 | CD27: 3000 | CE27: 3000 | CF27: 3000 | CG27: 3000 | CH27: 10000 | CI27: 10000 | CJ27: 10000 | CK27: 10000 | CL27: 10000 | CM27: 10000 | CN27: 10000 | CO27: 10000 | CP27: 10000
A28: Marketing at spend | AH28: 10000 | AI28: 10000 | AJ28: 5000 | AK28: 5000 | AL28: 5000 | AM28: 7000 | AN28: 7000 | AO28: 7000 | AP28: 7000 | AQ28: 7000 | AR28: 7000 | AS28: 7000 | AT28: 5000 | AU28: 8000 | AV28: 15000 | AW28: 25000 | AX28: 25000 | AY28: 25000 | AZ28: 25000 | BA28: 25000 | BB28: 25000 | BC28: 15000 | BD28: 15000 | BE28: 15000 | BF28: 15000 | BG28: 25000 | BH28: 10000 | BI28: 10000 | BJ28: 10000 | BK28: 10000 | BL28: 10000 | BM28: 10000 | BN28: 10000 | BO28: 10000 | BP28: 15000 | BQ28: 15000 | BR28: 15000 | BS28: 15000 | BT28: 15000 | BU28: 20000 | BV28: 25000 | BW28: 25000 | BX28: 25000 | BY28: 30000 | BZ28: 30000 | CA28: 30000 | CB28: 30000 | CC28: 30000 | CD28: 30000 | CE28: 35000 | CF28: 35000 | CG28: 40000 | CH28: 40000 | CI28: 40000 | CJ28: 45000 | CK28: 45000 | CL28: 50000 | CM28: 50000 | CN28: 50000 | CO28: 50000 | CP28: 50000
A29: Instagram
A30: Facebook
A31: TikTok
A32: Brand Ambassador | AH32: 0 | AI32: 0 | AJ32: 0 | AK32: 0 | AL32: 0 | AM32: 0 | AN32: 0 | AO32: 0 | AP32: 0 | AQ32: 0 | AR32: 0 | AS32: 0 | AT32: 0 | AU32: 0 | AV32: 0 | AW32: 0 | AX32: 0 | AY32: 0 | AZ32: 0 | BA32: 0 | BB32: 0 | BC32: 0 | BD32: 0 | BE32: 0 | BF32: 0 | BG32: 0 | BH32: 0 | BI32: 0 | BJ32: 0 | BK32: 0 | BL32: 0 | BM32: 0 | BN32: 0 | BO32: 0 | BP32: 0 | BQ32: 0 | BR32: 0 | BS32: 0 | BT32: 0 | BU32: 0 | BV32: 0 | BW32: 0 | BX32: 0 | BY32: 0 | BZ32: 0 | CA32: 0 | CB32: 0 | CC32: 0 | CD32: 0 | CE32: 0 | CF32: 0 | CG32: 0 | CH32: 0 | CI32: 0 | CJ32: 0 | CK32: 0 | CL32: 0 | CM32: 0 | CN32: 0 | CO32: 0 | CP32: 0 | CQ32: 0 | CR32: 0 | CS32: 0 | CT32: 0 | CU32: 0 | CV32: 0 | CW32: 0 | CX32: 0
A33: Operations
A34: Website maintenance and design | AH34: 1500 | AI34: 1500 | AJ34: 1500 | AK34: 1500 | AL34: 1500 | AM34: 1500 | AN34: 1500 | AO34: 1500 | AP34: 1500 | AQ34: 1500 | AR34: 1500 | AS34: 1500 | AT34: 1500 | AU34: 2500 | AV34: 2500 | AW34: 2500 | AX34: 2500 | AY34: 2500 | AZ34: 2500 | BA34: 2500 | BB34: 2500 | BC34: 2500 | BD34: 2500 | BE34: 2500 | BF34: 2500 | BG34: 2500 | BH34: 2500 | BI34: 2500 | BJ34: 2500 | BK34: 2500 | BL34: 2500 | BM34: 2500 | BN34: 2500 | BO34: 2500 | BP34: 2500 | BQ34: 2500 | BR34: 2500 | BS34: 2500 | BT34: 2500 | BU34: 2500 | BV34: 2500 | BW34: 2500 | BX34: 2500 | BY34: 2500 | BZ34: 2500 | CA34: 2500 | CB34: 2500 | CC34: 2500 | CD34: 2500 | CE34: 2500 | CF34: 2500 | CG34: 2500 | CH34: 2500 | CI34: 2500 | CJ34: 2500 | CK34: 2500 | CL34: 2500 | CM34: 2500 | CN34: 2500 | CO34: 2500 | CP34: 2500
A35: Website hosting
A36: Website utility and operations platform | AH36: 0 | AI36: 0 | AJ36: 0 | AK36: 0 | AL36: 0 | AM36: 0 | AN36: 0 | AO36: 0 | AP36: 0 | AQ36: 0 | AR36: 0 | AS36: 0 | AT36: 0 | AU36: 0 | AV36: 2000 | AW36: 2000 | AX36: 2000 | AY36: 2000 | AZ36: 2000 | BA36: 2000 | BB36: 2000 | BC36: 2000 | BD36: 2000 | BE36: 2000 | BF36: 2000 | BG36: 2000 | BH36: 2000 | BI36: 2000 | BJ36: 2000 | BK36: 2000 | BL36: 2000 | BM36: 2000 | BN36: 2000 | BO36: 2000 | BP36: 2000 | BQ36: 1000 | BR36: 1000 | BS36: 1000 | BT36: 1000 | BU36: 1000 | BV36: 1000 | BW36: 1000 | BX36: 1000 | BY36: 1000 | BZ36: 1000 | CA36: 1000 | CB36: 1000 | CC36: 1000 | CD36: 1000 | CE36: 1000 | CF36: 1000 | CG36: 1000 | CH36: 1000 | CI36: 1000 | CJ36: 1000 | CK36: 1000 | CL36: 1000 | CM36: 1000 | CN36: 1000 | CO36: 1000 | CP36: 1000
A37: Marketing events and sponsorships
A38: Public relations | AI38: 0 | AJ38: 0 | AK38: 0 | AL38: 0 | AM38: 0 | AN38: 0 | AO38: 0 | AP38: 0 | AQ38: 0 | AR38: 0 | AS38: 0 | AT38: 0 | AU38: 0 | AV38: 0 | AW38: 0 | AX38: 0 | AY38: 0 | AZ38: 0 | BA38: 0 | BB38: 0 | BC38: 0 | BD38: 0 | BE38: 0 | BF38: 0 | BG38: 0 | BH38: 0 | BI38: 0 | BJ38: 0 | BK38: 0 | BL38: 0 | BM38: 0 | BN38: 0 | BO38: 0 | BP38: 0 | BQ38: 0 | BR38: 0 | BS38: 0 | BT38: 0 | BU38: 0 | BV38: 0 | BW38: 0 | BX38: 0 | BY38: 0 | BZ38: 0 | CA38: 0 | CB38: 0 | CC38: 0 | CD38: 0 | CE38: 0 | CF38: 0 | CG38: 0 | CH38: 0 | CI38: 0 | CJ38: 0 | CK38: 0 | CL38: 0 | CM38: 0 | CN38: 0 | CO38: 0 | CP38: 0
A40: Selling and G&A expenses
A41: Salaries
A42: Officer, administration and customer service | AH42: 3000 | AI42: 3000 | AJ42: 3000 | AK42: 3000 | AL42: 3000 | AM42: 3000 | AN42: 3000 | AO42: 3000 | AP42: 3000 | AQ42: 3000 | AR42: 3000 | AS42: 3000 | AT42: 3000 | AU42: 3000 | AV42: 3000 | AW42: 3000 | AX42: 3000 | AY42: 3000 | AZ42: 3000 | BA42: 3000 | BB42: 3000 | BC42: 3000 | BD42: 3000 | BE42: 3000 | BF42: 3000 | BG42: 5000 | BH42: 5000 | BI42: 5000 | BJ42: 5000 | BK42: 5000 | BL42: 5000 | BM42: 5000 | BN42: 5000 | BO42: 5000 | BP42: 5000 | BQ42: 5000 | BR42: 5000 | BS42: 5000 | BT42: 5000 | BU42: 5000 | BV42: 5000 | BW42: 5000 | BX42: 5000 | BY42: 5000 | BZ42: 5000 | CA42: 5000 | CB42: 5000 | CC42: 5000 | CD42: 5000 | CE42: 5000 | CF42: 5000 | CG42: 5000 | CH42: 5000 | CI42: 5000 | CJ42: 5000 | CK42: 5000 | CL42: 5000 | CM42: 5000 | CN42: 5000 | CO42: 5000 | CP42: 5000
A43: Credit card processing fees | AH43: =+'P&L Cash Flow Monthly'!AH15*0.04 -> 3593.9679 | AI43: =+'P&L Cash Flow Monthly'!AI15*0.04 -> 3113.516 | AJ43: =+'P&L Cash Flow Monthly'!AJ15*0.04 -> 2813.6804 | AK43: =+'P&L Cash Flow Monthly'!AK15*0.04 -> 2489.2217 | AL43: =+'P&L Cash Flow Monthly'!AL15*0.04 -> 2171.707 | AM43: =+'P&L Cash Flow Monthly'!AM15*0.04 -> 2227.1673 | AN43: =+'P&L Cash Flow Monthly'!AN15*0.04 -> 2303.862 | AO43: =+'P&L Cash Flow Monthly'!AO15*0.04 -> 2380.6574 | ... CP43: =+'P&L Cash Flow Monthly'!CP15*0.04 -> 10080.615
A44: Warehousing | AH44: 200 | AI44: 200 | AJ44: 200 | AK44: 200 | AL44: 200 | AM44: 200 | AN44: 200 | AO44: 200 | AP44: 200 | AQ44: 200 | AR44: 200 | AS44: 200 | AT44: 200 | AU44: 1200 | AV44: 1200 | AW44: 1200 | AX44: 1200 | AY44: 1200 | AZ44: 1200 | BA44: 1200 | BB44: 1200 | BC44: 1200 | BD44: 1200 | BE44: 1200 | BF44: 1200 | BG44: 1200 | BH44: 1200 | BI44: 1200 | BJ44: 1200 | BK44: 1200 | BL44: 1200 | BM44: 1200 | BN44: 1200 | BO44: 1200 | BP44: 1200 | BQ44: 2400 | BR44: 2400 | BS44: 5500 | BT44: 5500 | BU44: 5500 | BV44: 5500 | BW44: 5500 | BX44: 5500 | BY44: 5500 | BZ44: 5500 | CA44: 5500 | CB44: 5500 | CC44: 5500 | CD44: 5500 | CE44: 5500 | CF44: 5500 | CG44: 5500 | CH44: 5500 | CI44: 5500 | CJ44: 5500 | CK44: 5500 | CL44: 5500 | CM44: 5500 | CN44: 5500 | CO44: 5500 | CP44: 5500
A45: E-commerce platform (ie Shopify) | AH45: 1200 | AI45: 1200 | AJ45: 1200 | AK45: 1200 | AL45: 1200 | AM45: 1200 | AN45: 1200 | AO45: 1200 | AP45: 1200 | AQ45: 1200 | AR45: 1200 | AS45: 1200 | AT45: 1200 | AU45: 1200 | AV45: 1200 | AW45: 1200 | AX45: 1200 | AY45: 1200 | AZ45: 1200 | BA45: 1200 | BB45: 1200 | BC45: 1200 | BD45: 1200 | BE45: 1200 | BF45: 1200 | BG45: 1200 | BH45: 1200 | BI45: 1200 | BJ45: 1200 | BK45: 1200 | BL45: 1200 | BM45: 1200 | BN45: 1200 | BO45: 1200 | BP45: 1200 | BQ45: 1200 | BR45: 1200 | BS45: 1200 | BT45: 1200 | BU45: 1200 | BV45: 1200 | BW45: 1200 | BX45: 1200 | BY45: 1200 | BZ45: 1200 | CA45: 1200 | CB45: 1200 | CC45: 1200 | CD45: 1200 | CE45: 1200 | CF45: 1200 | CG45: 1200 | CH45: 1200 | CI45: 1200 | CJ45: 1200 | CK45: 1200 | CL45: 1200 | CM45: 1200 | CN45: 1200 | CO45: 1200 | CP45: 1200
A46: Rent | AH46: 1300 | AI46: 1300 | AJ46: 1300 | AK46: 1300 | AL46: 1300 | AM46: 1300 | AN46: 1300 | AO46: 1300 | AP46: 1300 | AQ46: 1300 | AR46: 1300 | AS46: 1300 | AT46: 1300 | AU46: 1300 | AV46: 1300 | AW46: 1300 | AX46: 1300 | AY46: 1300 | AZ46: 1300 | BA46: 1300 | BB46: 1300 | BC46: 1300 | BD46: 1300 | BE46: 1300 | BF46: 1300 | BG46: 1300 | BH46: 1300 | BI46: 1300 | BJ46: 1300 | BK46: 1300 | BL46: 1300 | BM46: 1300 | BN46: 1300 | BO46: 1300 | BP46: 1300 | BQ46: 5000 | BR46: 5000 | BS46: 5000 | BT46: 5000 | BU46: 5000 | BV46: 5000 | BW46: 5000 | BX46: 5000 | BY46: 5000 | BZ46: 5000 | CA46: 5000 | CB46: 5000 | CC46: 5000 | CD46: 5000 | CE46: 5000 | CF46: 5000 | CG46: 5000 | CH46: 5000 | CI46: 5000 | CJ46: 5000 | CK46: 5000 | CL46: 5000 | CM46: 5000 | CN46: 5000 | CO46: 5000 | CP46: 5000
A47: Utilities | AH47: 200 | AI47: 200 | AJ47: 200 | AK47: 200 | AL47: 200 | AM47: 1500 | AN47: 1500 | AO47: 1500 | AP47: 1500 | AQ47: 1500 | AR47: 1500 | AS47: 1500 | AT47: 1500 | AU47: 1500 | AV47: 1500 | AW47: 1500 | AX47: 1500 | AY47: 1500 | AZ47: 1500 | BA47: 1500 | BB47: 1500 | BC47: 1500 | BD47: 1500 | BE47: 1500 | BF47: 1500 | BG47: 1500 | BH47: 1500 | BI47: 1500 | BJ47: 1500 | BK47: 1500 | BL47: 1500 | BM47: 1500 | BN47: 1500 | BO47: 1500 | BP47: 3000 | BQ47: 3000 | BR47: 3000 | BS47: 3000 | BT47: 3000 | BU47: 3000 | BV47: 3000 | BW47: 3000 | BX47: 3000 | BY47: 3000 | BZ47: 3000 | CA47: 3000 | CB47: 3000 | CC47: 3000 | CD47: 3000 | CE47: 3000 | CF47: 3000 | CG47: 3000 | CH47: 3000 | CI47: 3000 | CJ47: 3000 | CK47: 3000 | CL47: 3000 | CM47: 3000 | CN47: 3000 | CO47: 3000 | CP47: 3000
A48: Internet, cable and phone | AH48: 400 | AI48: 400 | AJ48: 400 | AK48: 400 | AL48: 400 | AM48: 800 | AN48: 800 | AO48: 800 | AP48: 800 | AQ48: 800 | AR48: 800 | AS48: 800 | AT48: 800 | AU48: 800 | AV48: 800 | AW48: 800 | AX48: 800 | AY48: 800 | AZ48: 800 | BA48: 800 | BB48: 800 | BC48: 800 | BD48: 800 | BE48: 800 | BF48: 800 | BG48: 1400 | BH48: 1400 | BI48: 1400 | BJ48: 1400 | BK48: 1400 | BL48: 1400 | BM48: 1400 | BN48: 1400 | BO48: 1400 | BP48: 1400 | BQ48: 1400 | BR48: 1400 | BS48: 1400 | BT48: 1400 | BU48: 1400 | BV48: 1400 | BW48: 1400 | BX48: 1400 | BY48: 1400 | BZ48: 1400 | CA48: 1400 | CB48: 1400 | CC48: 1400 | CD48: 1400 | CE48: 1400 | CF48: 1400 | CG48: 1400 | CH48: 1400 | CI48: 1400 | CJ48: 1400 | CK48: 1400 | CL48: 1400 | CM48: 1400 | CN48: 1400 | CO48: 1400 | CP48: 1400
A49: Computer | AH49: 500 | AI49: 500 | AJ49: 500 | AK49: 500 | AL49: 500 | AM49: 500 | AN49: 500 | AO49: 500 | AP49: 500 | AQ49: 500 | AR49: 500 | AS49: 500 | AT49: 500 | AU49: 500 | AV49: 500 | AW49: 500 | AX49: 500 | AY49: 500 | AZ49: 500 | BA49: 500 | BB49: 500 | BC49: 500 | BD49: 500 | BE49: 500 | BF49: 500 | BG49: 500 | BH49: 500 | BI49: 500 | BJ49: 500 | BK49: 500 | BL49: 500 | BM49: 500 | BN49: 500 | BO49: 500 | BP49: 500 | BQ49: 2500 | BR49: 2500 | BS49: 2500 | BT49: 2500 | BU49: 2500 | BV49: 2500 | BW49: 2500 | BX49: 2500 | BY49: 2500 | BZ49: 2500 | CA49: 2500 | CB49: 2500 | CC49: 2500 | CD49: 2500 | CE49: 2500 | CF49: 2500 | CG49: 2500 | CH49: 2500 | CI49: 2500 | CJ49: 2500 | CK49: 2500 | CL49: 2500 | CM49: 2500 | CN49: 2500 | CO49: 2500 | CP49: 2500
A50: Insurance | AH50: ='P&L Cash Flow Monthly'!AH15*0.00285 -> 256.07022 | AI50: ='P&L Cash Flow Monthly'!AI15*0.00285 -> 221.83802 | AJ50: ='P&L Cash Flow Monthly'!AJ15*0.00285 -> 200.47473 | AK50: ='P&L Cash Flow Monthly'!AK15*0.00285 -> 177.35704 | AL50: ='P&L Cash Flow Monthly'!AL15*0.00285 -> 154.73413 | AM50: ='P&L Cash Flow Monthly'!AM15*0.00285 -> 158.68567 | AN50: ='P&L Cash Flow Monthly'!AN15*0.00285 -> 164.15017 | AO50: ='P&L Cash Flow Monthly'!AO15*0.00285 -> 169.62184 | ... CP50: ='P&L Cash Flow Monthly'!CP15*0.00285 -> 718.24382
A51: Travel | AH51: 2000 | AI51: 2000 | AJ51: 2000 | AK51: 2000 | AL51: 2000 | AM51: 2000 | AN51: 2000 | AO51: 2000 | AP51: 2000 | AQ51: 2000 | AR51: 2000 | AS51: 2000 | AT51: 2000 | AU51: 2000 | AV51: 2000 | AW51: 2000 | AX51: 2000 | AY51: 2000 | AZ51: 2000 | BA51: 2000 | BB51: 2000 | BC51: 2000 | BD51: 2000 | BE51: 2000 | BF51: 2000 | BG51: 2000 | BH51: 2000 | BI51: 2000 | BJ51: 2000 | BK51: 2000 | BL51: 2000 | BM51: 2000 | BN51: 1000 | BO51: 1000 | BP51: 1000 | BQ51: 1000 | BR51: 1000 | BS51: 1000 | BT51: 1000 | BU51: 1000 | BV51: 1000 | BW51: 1000 | BX51: 1000 | BY51: 1000 | BZ51: 1000 | CA51: 1000 | CB51: 1000 | CC51: 1000 | CD51: 1000 | CE51: 1000 | CF51: 1000 | CG51: 1000 | CH51: 1000 | CI51: 1000 | CJ51: 1000 | CK51: 1000 | CL51: 1000 | CM51: 1000 | CN51: 1000 | CO51: 1000 | CP51: 1000
A52: Accounting | AH52: 500 | AI52: 1000 | AJ52: 1000 | AK52: 1000 | AL52: 1000 | AM52: 1000 | AN52: 1000 | AO52: 1000 | AP52: 1000 | AQ52: 1000 | AR52: 1000 | AS52: 1000 | AT52: 1000 | AU52: 1000 | AV52: 1000 | AW52: 1000 | AX52: 1000 | AY52: 1000 | AZ52: 1000 | BA52: 1000 | BB52: 1000 | BC52: 1000 | BD52: 1000 | BE52: 1000 | BF52: 1000 | BG52: 1000 | BH52: 1000 | BI52: 1000 | BJ52: 1000 | BK52: 1000 | BL52: 1000 | BM52: 1000 | BN52: 1000 | BO52: 1000 | BP52: 1000 | BQ52: 1000 | BR52: 1000 | BS52: 1000 | BT52: 1000 | BU52: 1000 | BV52: 1000 | BW52: 1000 | BX52: 1000 | BY52: 1000 | BZ52: 1000 | CA52: 1000 | CB52: 1000 | CC52: 1000 | CD52: 1000 | CE52: 2000 | CF52: 2000 | CG52: 2000 | CH52: 2000 | CI52: 2000 | CJ52: 2000 | CK52: 2000 | CL52: 2000 | CM52: 2000 | CN52: 2000 | CO52: 2000 | CP52: 2000
A53: Legal | BX53: 1000 | BY53: 1000 | BZ53: 1000 | CA53: 0 | CC53: 1000 | CD53: 1000 | CF53: 1000 | CG53: 1000 | CI53: 1000 | CJ53: 1000 | CK53: 1000 | CL53: 1000 | CM53: 1000 | CN53: 1000 | CO53: 1000 | CP53: 1000
A54: 5% donation to veteran non-profits | AH54: =+IF('P&L Cash Flow Monthly'!AG39>2000000,'P&L Cash Flow Monthly'!AG23*0.05,0) -> 0 | AI54: =+IF('P&L Cash Flow Monthly'!AH39>2000000,'P&L Cash Flow Monthly'!AH23*0.05,0) -> 0 | AJ54: =+IF('P&L Cash Flow Monthly'!AI39>2000000,'P&L Cash Flow Monthly'!AI23*0.05,0) -> 0 | AK54: =+IF('P&L Cash Flow Monthly'!AJ39>2000000,'P&L Cash Flow Monthly'!AJ23*0.05,0) -> 0 | AL54: =+IF('P&L Cash Flow Monthly'!AK39>2000000,'P&L Cash Flow Monthly'!AK23*0.05,0) -> 0 | AM54: =+IF('P&L Cash Flow Monthly'!AL39>2000000,'P&L Cash Flow Monthly'!AL23*0.05,0) -> 0 | AN54: =+IF('P&L Cash Flow Monthly'!AM39>2000000,'P&L Cash Flow Monthly'!AM23*0.05,0) -> 0 | AO54: =+IF('P&L Cash Flow Monthly'!AN39>2000000,'P&L Cash Flow Monthly'!AN23*0.05,0) -> 0 | ... CP54: =+IF('P&L Cash Flow Monthly'!CO39>2000000,'P&L Cash Flow Monthly'!CO23*0.05,0) -> 0
A55: Miscellaneous | AE55: 7000 | AF55: 70000 | AG55: 25000 | AH55: 3500 | AI55: 3500 | AJ55: 3500 | AK55: 3500 | AL55: 3500 | AM55: 3500 | AN55: 3500 | AO55: 3500 | AP55: 3500 | AQ55: 3500 | AR55: 3500 | AS55: 3500 | AT55: 3500 | AU55: 3500 | AV55: 3500 | AW55: 3500 | AX55: 3500 | AY55: 3500 | AZ55: 3500 | BA55: 3500 | BB55: 3500 | BC55: 3500 | BD55: 3500 | BE55: 3500 | BF55: 3500 | BG55: 3500 | BH55: 3500 | BI55: 3500 | BJ55: 3500 | BK55: 3500 | BL55: 3500 | BM55: 3500 | BN55: 3500 | BO55: 3500 | BP55: 3500 | BQ55: 3500 | BR55: 3500 | BS55: 3500 | BT55: 3500 | BU55: 3500 | BV55: 3500 | BW55: 3500 | BX55: 3500 | BY55: 3500 | BZ55: 3500 | CA55: 3500 | CB55: 3500 | CC55: 3500 | CD55: 3500 | CE55: 3500 | CF55: 3500 | CG55: 3500 | CH55: 3500 | CI55: 3500 | CJ55: 3500 | CK55: 3500 | CL55: 3500 | CM55: 3500 | CN55: 3500 | CO55: 3500 | CP55: 3500
A57: Research and development
A58: Food and product development | AH58: 0 | AI58: 0 | AJ58: 0 | AK58: 0 | AL58: 0 | AM58: 0 | AP58: 1000 | AR58: 1000 | AT58: 1000 | AU58: 0 | AV58: 0 | AW58: 0 | AX58: 0 | AY58: 0 | AZ58: 0 | BA58: 0 | BB58: 0 | BC58: 0 | BD58: 0 | BE58: 0 | BF58: 0 | BG58: 2000 | BI58: 2000 | BK58: 2000 | BM58: 2000 | BO58: 2000 | CJ58: 2000 | CK58: 2000 | CL58: 2000 | CM58: 2000 | CN58: 2000 | CO58: 2000 | CP58: 2000
A60: Capital expenses
A61: Manfacturing equipment
A71: Website maintance & Design | B71: 1500 | C71: 1500 | D71: 1500 | E71: 1500 | F71: 1500 | G71: 1500 | H71: 1500 | I71: 1500 | J71: 1500 | K71: 1500 | L71: 1500 | M71: 1500 | N71: 1500 | O71: 1500 | P71: 1500 | Q71: 1500 | R71: 1500 | S71: 1500 | T71: 1500 | U71: 1500 | V71: 1500 | W71: 1500 | X71: 1500 | Y71: 1500 | Z71: 1500 | AA71: 1500 | AB71: 1500 | AC71: 1500 | AD71: 1500 | AE71: 1500 | AF71: 1500 | AG71: 1500
A72: Marketing director | B72: 0 | C72: 0 | D72: 0 | E72: 0 | F72: 0 | G72: 0 | H72: 0 | I72: 0 | J72: 0 | K72: 0 | L72: 0 | M72: 0 | N72: 0 | O72: 0 | P72: 0 | Q72: 0 | R72: 0 | S72: 0 | T72: 0 | U72: 0 | V72: 0 | W72: 0 | X72: 0 | Y72: 0 | Z72: 0 | AA72: 0 | AB72: 0 | AC72: 0 | AD72: 0 | AE72: 0 | AF72: 0 | AG72: 0
A73: SEO manager | B73: 1275 | C73: 1275 | D73: 1275 | E73: 1275 | F73: 1275 | G73: 1275 | H73: 1275 | I73: 1275 | J73: 1275 | K73: 1275 | L73: 1275 | M73: 1275 | N73: 1275 | O73: 1275 | P73: 1275 | Q73: 1275 | R73: 1275 | S73: 1275 | T73: 1275 | U73: 1275 | V73: 1275 | W73: 1275 | X73: 1275 | Y73: 1275 | Z73: 1275 | AA73: 0 | AB73: 0 | AC73: 0 | AD73: 0 | AE73: 0 | AF73: 0 | AG73: 0
A74: Executive salary | B74: 0 | C74: 0 | D74: 0 | E74: 0 | F74: 0 | G74: 0 | H74: 0 | I74: 0
A75: Social Media Manager (Kyle) | H75: 3000 | I75: 3000 | J75: 3000 | K75: 3000 | L75: 3000 | M75: 3000 | N75: 3000 | O75: 3000 | P75: 3000 | Q75: 3000 | R75: 3000 | S75: 3000 | T75: 3000 | U75: 3000 | V75: 3000 | W75: 3000 | X75: 3000 | Y75: 0 | Z75: 0 | AA75: 0 | AB75: 0 | AC75: 0 | AD75: 0 | AE75: 0 | AF75: 0 | AG75: 1500
A76: Food & Product Development | B76: 1000 | C76: 1000 | D76: 1000 | E76: 1000 | F76: 1000 | G76: 1000 | H76: 1000 | K76: 0 | L76: 0 | M76: 0 | N76: 0 | O76: 0 | P76: 0 | Q76: 0 | R76: 0 | S76: 0 | T76: 0 | U76: 0 | V76: 0 | W76: 0 | X76: 0 | Y76: 0 | Z76: 0 | AA76: 0 | AB76: 0 | AC76: 0 | AD76: 0 | AE76: 0 | AF76: 0 | AG76: 0
A77: Rent | B77: 1300 | C77: 1300 | D77: 1300 | E77: 1300 | F77: 1300 | G77: 1300 | H77: 1300 | I77: 1300 | J77: 1300 | K77: 1300 | L77: 1300 | M77: 1300 | N77: 1300 | O77: 1300 | P77: 1300 | Q77: 1300 | R77: 1300 | S77: 1300 | T77: 1300 | U77: 1300 | V77: 1300 | W77: 1300 | X77: 1300 | Y77: 1300 | Z77: 1300 | AA77: 1300 | AB77: 1300 | AC77: 1300 | AD77: 1300 | AE77: 1300 | AF77: 1300 | AG77: 1300
A78: Utilities | B78: 200 | C78: 200 | D78: 200 | E78: 200 | F78: 200 | G78: 200 | H78: 200 | I78: 200 | J78: 200 | K78: 200 | L78: 200 | M78: 200 | N78: 200 | O78: 200 | P78: 200 | Q78: 200 | R78: 200 | S78: 200 | T78: 200 | U78: 200 | V78: 200 | W78: 200 | X78: 200 | Y78: 200 | Z78: 200 | AA78: 200 | AB78: 200 | AC78: 200 | AD78: 200 | AE78: 200 | AF78: 200 | AG78: 200
A79: Internet cable and Phone service | B79: 400 | C79: 400 | D79: 400 | E79: 400 | F79: 400 | G79: 400 | H79: 400 | I79: 400 | J79: 400 | K79: 400 | L79: 400 | M79: 400 | N79: 400 | O79: 400 | P79: 400 | Q79: 400 | R79: 400 | S79: 400 | T79: 400 | U79: 400 | V79: 400 | W79: 400 | X79: 400 | Y79: 400 | Z79: 400 | AA79: 400 | AB79: 400 | AC79: 400 | AD79: 400 | AE79: 400 | AF79: 400 | AG79: 400
A80: Warehousing | B80: 200 | C80: 200 | D80: 200 | E80: 200 | F80: 200 | G80: 200 | H80: 200 | I80: 200 | J80: 200 | K80: 200 | L80: 200 | M80: 200 | N80: 200 | O80: 200 | P80: 200 | Q80: 200 | R80: 200 | S80: 200 | T80: 200 | U80: 200 | V80: 200 | W80: 200 | X80: 200 | Y80: 200 | Z80: 200 | AA80: 200 | AB80: 200 | AC80: 200 | AD80: 200 | AE80: 200 | AF80: 200 | AG80: 200
A81: Insurance | B81: ='P&L Cash Flow Monthly'!B15*0.00285 -> 7.8950985 | C81: ='P&L Cash Flow Monthly'!C15*0.00285 -> 9.6608302 | D81: ='P&L Cash Flow Monthly'!D15*0.00285 -> 17.313824 | E81: ='P&L Cash Flow Monthly'!E15*0.00285 -> 34.738278 | F81: ='P&L Cash Flow Monthly'!F15*0.00285 -> 55.238705 | G81: ='P&L Cash Flow Monthly'!G15*0.00285 -> 62.118062 | H81: ='P&L Cash Flow Monthly'!H15*0.00285 -> 65.702338 | I81: ='P&L Cash Flow Monthly'!I15*0.00285 -> 110.77481 | ... AG81: ='P&L Cash Flow Monthly'!AG15*0.00285 -> 286.02159
A82: Shopify | B82: 1200 | C82: 1200 | D82: 1200 | E82: 1200 | F82: 1200 | G82: 1200 | H82: 1200 | I82: 1200 | J82: 1200 | K82: 1200 | L82: 1200 | M82: 1200 | N82: 1200 | O82: 1200 | P82: 1200 | Q82: 1200 | R82: 1200 | S82: 1200 | T82: 1200 | U82: 1200 | V82: 1200 | W82: 1200 | X82: 1200 | Y82: 1200 | Z82: 1200 | AA82: 1200 | AB82: 1200 | AC82: 1200 | AD82: 1200 | AE82: 1200 | AF82: 1200 | AG82: 1200
A83: Miscellaneous | B83: 3500 | C83: 3500 | D83: 3500 | E83: 3500 | F83: 3500 | G83: 3500 | H83: 3500 | I83: 3500 | J83: 3500 | K83: 3500 | L83: 3500 | M83: 3500 | N83: 3500 | O83: 3500 | P83: 3500 | Q83: 3500 | R83: 3500 | S83: 3500 | T83: 3500 | U83: 3500 | V83: 3500 | W83: 3500 | X83: 3500 | Y83: 3500 | Z83: 3500 | AA83: 3500 | AB83: 3500 | AC83: 3500 | AD83: 3500 | AE83: 3500 | AF83: 3500 | AG83: 3500
A84: Office, administration and customer serivce | B84: 2500 | C84: 2500 | D84: 2500 | E84: 2500 | F84: 2500 | G84: 2500 | H84: 2500 | I84: 2500 | J84: 2500 | K84: 2500 | L84: 2500 | M84: 2500 | N84: 2500 | O84: 2500 | P84: 2500 | Q84: 2500 | R84: 2500 | S84: 2500 | T84: 2500 | U84: 2500 | V84: 2500 | W84: 2500 | X84: 2500 | Y84: 2500 | Z84: 2500 | AA84: 2500 | AB84: 2500 | AC84: 2500 | AD84: 2500 | AE84: 2500 | AF84: 2500 | AG84: 2500
A85: Sales director
A86: Sales representatives | B86: =+B113 -> 0 | C86: =+C113 -> 0 | D86: =+D113 -> 0 | E86: =+E113 -> 0 | F86: =+F113 -> 0 | G86: =+G113 -> 0 | H86: =+H113 -> 0 | I86: =+I113 -> 0 | ... AN86: =+AN113 -> 0 | AO86: =+AN113 -> 0 | AP86: =+AN113 -> 0 | AQ86: =+AN113 -> 0 | AR86: =+AN113 -> 0 | AS86: =+AN113 -> 0 | AT86: =+AN113 -> 0 | AU86: =+AN113 -> 0 | AV86: =+AN113 -> 0 | AW86: =+AN113 -> 0 | AX86: =+AN113 -> 0 | AY86: =+AN113 -> 0 | AZ86: =+AN113 -> 0 | BA86: =+AN113 -> 0 | BB86: =+AO113 -> 0 | BC86: =+AP113 -> 0 | BD86: =+AQ113 -> 0 | BE86: =+AR113 -> 0 | BF86: =+AS113 -> 0 | BG86: =+AT113 -> 0 | BH86: =+AU113 -> 0 | ... CP86: =+CC113 -> 0
A87: Web untiliy & anayltics platforms (netsuit | B87: 1000 | C87: 1000 | D87: 1000 | E87: 1000 | F87: 1000 | G87: 1000 | H87: 1000 | I87: 1000 | J87: 1000 | K87: 1000 | L87: 1000 | M87: 1000 | N87: 1000 | O87: 1000 | P87: 1000 | Q87: 1000 | R87: 1000 | S87: 1000 | T87: 1000 | U87: 1000 | V87: 1000 | W87: 1000 | X87: 1000 | Y87: 1000 | AA87: 0 | AB87: 0 | AC87: 0 | AD87: 0 | AE87: 0 | AF87: 0 | AG87: 0
A88: Brand ambassadors | B88: 5000 | C88: 5000 | D88: 5000 | E88: 5000 | F88: 5000 | G88: 5000 | H88: 5000 | I88: 5000 | J88: 5000 | K88: 5000 | L88: 5000 | M88: 5000 | N88: 5000 | O88: 5000 | P88: 8000 | Q88: 8000 | R88: 8000 | S88: 8000 | T88: 8000 | U88: 8000 | V88: 8000 | W88: 8000 | X88: 8000 | Y88: 0 | Z88: 0 | AA88: 0 | AB88: 0 | AC88: 0 | AD88: 0 | AE88: 0 | AF88: 0 | AG88: 0
A89: Monthly Marketing Ad Spend | B89: 1500 | C89: 3500 | D89: 3500 | E89: 2000 | F89: 2000 | G89: 3000 | H89: 5000 | I89: 12000 | J89: 2000 | K89: 15000 | L89: 17000 | M89: 17000 | N89: 15000 | O89: 10000 | P89: 10000 | Q89: 10000 | R89: 15000 | S89: 20000 | T89: 30000 | U89: 8000 | V89: 8000 | W89: 10000 | X89: 10000 | Y89: 10000 | Z89: 10000 | AA89: 10000 | AB89: 5000 | AC89: 5000 | AD89: 8000 | AE89: 15000 | AF89: 15000 | AG89: 10000
A90: Computer expense | M90: 500 | N90: 500 | O90: 500 | P90: 500 | Q90: 500 | R90: 500 | S90: 500 | T90: 500 | U90: 500 | V90: 500 | W90: 500 | X90: 500 | Y90: 500 | Z90: 500 | AA90: 500 | AB90: 500 | AC90: 500 | AD90: 500 | AE90: 500 | AF90: 500 | AG90: 500
A91: Accounting | W91: 500 | X91: 500 | Y91: 500 | Z91: 500 | AA91: 500 | AB91: 500 | AC91: 500 | AD91: 500 | AE91: 500 | AF91: 500 | AG91: 500
A92: Processing fee based 4% month Rev | B92: =+'P&L Cash Flow Monthly'!B15*0.04 -> 110.8084 | C92: =+'P&L Cash Flow Monthly'!C15*0.04 -> 135.5906 | D92: =+'P&L Cash Flow Monthly'!D15*0.04 -> 243.00104 | E92: =+'P&L Cash Flow Monthly'!E15*0.04 -> 487.55477 | F92: =+'P&L Cash Flow Monthly'!F15*0.04 -> 775.28007 | G92: =+'P&L Cash Flow Monthly'!G15*0.04 -> 871.83244 | H92: =+'P&L Cash Flow Monthly'!H15*0.04 -> 922.13808 | I92: =+'P&L Cash Flow Monthly'!I15*0.04 -> 1554.7342 | ... P92: =+'P&L Cash Flow Monthly'!P15*0.04 -> 2919.7107 | Q92: =+'P&L Cash Flow Monthly'!Q15*0.17 -> 11482.387 | R92: =+'P&L Cash Flow Monthly'!R15*0.17 -> 13188.49 | S92: =+'P&L Cash Flow Monthly'!S15*0.17 -> 16288.81 | T92: =+'P&L Cash Flow Monthly'!T15*0.17 -> 22177.56 | U92: =+'P&L Cash Flow Monthly'!U15*0.17 -> 20464.391 | V92: =+'P&L Cash Flow Monthly'!V15*0.17 -> 17452.039 | W92: =+'P&L Cash Flow Monthly'!W15*0.17 -> 12772.591 | X92: =+'P&L Cash Flow Monthly'!X15*0.17 -> 13739.661 | ... AF92: =+'P&L Cash Flow Monthly'!AF15*0.17 -> 17085.186 | AG92: =+'P&L Cash Flow Monthly'!AG15*0.04 -> 4014.3381
A93: Legal | R93: 30000
A94: 5% Donations to Veteran Non Profits | D94: 0 | E94: 0 | F94: 0 | G94: 0 | H94: 0 | I94: 0 | J94: 0 | K94: =+IF('P&L Cash Flow Monthly'!J39>2000000,'P&L Cash Flow Monthly'!J23*0.05,0) -> 0 | L94: =+IF('P&L Cash Flow Monthly'!K39>2000000,'P&L Cash Flow Monthly'!K23*0.05,0) -> 0 | M94: =+IF('P&L Cash Flow Monthly'!L39>2000000,'P&L Cash Flow Monthly'!L23*0.05,0) -> 0 | N94: =+IF('P&L Cash Flow Monthly'!M39>2000000,'P&L Cash Flow Monthly'!M23*0.05,0) -> 0 | O94: =+IF('P&L Cash Flow Monthly'!N39>2000000,'P&L Cash Flow Monthly'!N23*0.05,0) -> 0 | P94: =+IF('P&L Cash Flow Monthly'!O39>2000000,'P&L Cash Flow Monthly'!O23*0.05,0) -> 0 | Q94: =+IF('P&L Cash Flow Monthly'!P39>2000000,'P&L Cash Flow Monthly'!P23*0.05,0) -> 0 | R94: =+IF('P&L Cash Flow Monthly'!Q39>2000000,'P&L Cash Flow Monthly'!Q23*0.05,0) -> 0 | ... AG94: =+IF('P&L Cash Flow Monthly'!AF39>2000000,'P&L Cash Flow Monthly'!AF23*0.05,0) -> 0
A95: Travel | B95: 1000 | C95: 1000 | D95: 1000 | E95: 1000 | F95: 1000 | G95: 1000 | H95: 1000 | I95: 1000 | J95: 1000 | K95: 1000 | L95: 1000 | M95: 1000 | N95: 1000 | O95: 1000 | P95: 1000 | Q95: 1000 | R95: 1000 | S95: 1000 | T95: 1000 | U95: 1000 | V95: 2000 | W95: 2000 | X95: 2000 | Y95: 2000 | Z95: 2000 | AA95: 2000 | AB95: 2000 | AC95: 2000 | AD95: 2000 | AE95: 2000 | AF95: 2000 | AG95: 2000
A96: PR | W96: 5500 | X96: 5500 | Y96: 5500
A97: Manufacturing Equipment | B97: 5000 | I97: 2000 | W97: 30000
A102: Total monthly expense (Includes fixed expenses) | B102: =SUM(B13:B100) -> 29693.703 | C102: =SUM(C13:C100) -> 26720.251 | D102: =SUM(D13:D100) -> 26835.315 | E102: =SUM(E13:E100) -> 25597.293 | F102: =SUM(F13:F100) -> 25905.519 | G102: =SUM(G13:G100) -> 27008.951 | H102: =SUM(H13:H100) -> 32062.84 | I102: =SUM(I13:I100) -> 40740.509 | ... CP102: =SUM(CP13:CP100) -> 118398.86
A104: Fixed monthly expenses | B104: =SUM(B86,B85,B84,B83,B82,B81,B80,B79,B78,B77,B76,B75,B74,B73,B72,B71,#REF!) -> #REF! | C104: =SUM(C86,C85,C84,C83,C82,C81,C80,C79,C78,C77,C76,C75,C74,C73,C72,C71,#REF!) -> #REF! | D104: =SUM(D86,D85,D84,D83,D82,D81,D80,D79,D78,D77,D76,D75,D74,D73,D72,D71,#REF!) -> #REF! | E104: =SUM(E86,E85,E84,E83,E82,E81,E80,E79,E78,E77,E76,E75,E74,E73,E72,E71,#REF!) -> #REF! | F104: =SUM(F86,F85,F84,F83,F82,F81,F80,F79,F78,F77,F76,F75,F74,F73,F72,F71,#REF!) -> #REF! | G104: =SUM(G86,G85,G84,G83,G82,G81,G80,G79,G78,G77,G76,G75,G74,G73,G72,G71,#REF!) -> #REF! | H104: =SUM(H86,H85,H84,H83,H82,H81,H80,H79,H78,H77,H76,H75,H74,H73,H72,H71,#REF!) -> #REF! | I104: =SUM(I86,I85,I84,I83,I82,I81,I80,I79,I78,I77,I76,I75,I74,I73,I72,I71,#REF!) -> #REF! | ... AG104: =SUM(AG86,AG85,AG84,AG83,AG82,AG81,AG80,AG79,AG78,AG77,AG76,AG75,AG74,AG73,AG72,AG71,#REF!) -> #REF! | AH104: =+AH27+AH34+AH21+AH22+AH15+AH23+AH58+AH46+AH47+AH48+AH50+AH45+AH55+AH42+AH20 -> 11356.07 | AI104: =+AI27+AI34+AI21+AI22+AI15+AI23+AI58+AI46+AI47+AI48+AI50+AI45+AI55+AI42 -> 15321.838 | AJ104: =+AJ27+AJ34+AJ21+AJ22+AJ15+AJ23+AJ58+AJ46+AJ47+AJ48+AJ50+AJ45+AJ55+AJ42 -> 15300.475 | AK104: =+AK27+AK34+AK21+AK22+AK15+AK23+AK58+AK46+AK47+AK48+AK50+AK45+AK55+AK42 -> 15277.357 | AL104: =+AL27+AL34+AL21+AL22+AL15+AL23+AL58+AL46+AL47+AL48+AL50+AL45+AL55+AL42 -> 15254.734 | AM104: =+AM27+AM34+AM21+AM22+AM15+AM23+AM58+AM46+AM47+AM48+AM50+AM45+AM55+AM42 -> 16958.686 | AN104: =+AN27+AN34+AN21+AN22+AN15+AN23+AN58+AN46+AN47+AN48+AN50+AN45+AN55+AN42 -> 16964.15 | AO104: =+AO27+AO34+AO21+AO22+AO15+AO23+AO58+AO46+AO47+AO48+AO50+AO45+AO55+AO42 -> 16969.622 | AP104: =+AP27+AP34+AP21+AP22+AP15+AP23+AP58+AP46+AP47+AP48+AP50+AP45+AP55+AP42 -> 26969.148 | ... CP104: =+CP27+CP34+CP21+CP22+CP15+CP23+CP58+CP46+CP47+CP48+CP50+CP45+CP55+CP42 -> 45318.244
A106: Sales representatives for gym sales
A107: # representatives
A108: Base pay per representative | B108: 3500 | C108: 3500 | D108: 3500 | E108: 3500 | F108: 3500 | G108: 3500 | H108: 3500 | I108: 3500 | J108: 3500 | K108: 3500 | L108: 3500 | M108: 3500 | N108: 3500 | O108: 3500 | P108: 3500 | Q108: 3500 | R108: 3500 | S108: 3500 | T108: 3500 | U108: 3500 | V108: 3500 | W108: 3500 | X108: 3500 | Y108: 3500 | Z108: 3500 | AA108: 3500 | AB108: 3500 | AC108: 3500 | AD108: 3500 | AE108: 3500 | AF108: 3500 | AG108: 3500 | AH108: 3500 | AI108: 3500 | AJ108: 3500 | AK108: 3500 | AL108: 3500 | AM108: 3500 | AN108: 3500 | AO108: 3500 | AP108: 3500 | AQ108: 3500 | AR108: 3500 | AS108: 3500 | AT108: 3500 | AU108: 3500 | AV108: 3500 | AW108: 3500 | AX108: 3500 | AY108: 3500 | AZ108: 3500 | BA108: 3500 | BB108: 3500 | BC108: 3500 | BD108: 3500 | BE108: 3500 | BF108: 3500 | BG108: 3500 | BH108: 3500 | BI108: 3500 | BJ108: 3500 | BK108: 3500 | BL108: 3500 | BM108: 3500 | BN108: 3500 | BO108: 3500 | BP108: 3500 | BQ108: 3500 | BR108: 3500 | BS108: 3500 | BT108: 3500 | BU108: 3500 | BV108: 3500 | BW108: 3500 | BX108: 3500 | BY108: 3500 | BZ108: 3500 | CA108: 3500 | CB108: 3500 | CC108: 3500 | CD108: 3500 | CE108: 3500 | CF108: 3500 | CG108: 3500 | CH108: 3500 | CI108: 3500 | CJ108: 3500 | CK108: 3500 | CL108: 3500 | CM108: 3500 | CN108: 3500 | CO108: 3500 | CP108: 3500
A109: Commission for each representative | B109: 0.05 | C109: 0.05 | D109: 0.05 | E109: 0.05 | F109: 0.05 | G109: 0.05 | H109: 0.05 | I109: 0.05 | J109: 0.05 | K109: 0.05 | L109: 0.05 | M109: 0.05 | N109: 0.05 | O109: 0.05 | P109: 0.05 | Q109: 0.05 | R109: 0.05 | S109: 0.05 | T109: 0.05 | U109: 0.05 | V109: 0.05 | W109: 0.05 | X109: 0.05 | Y109: 0.05 | Z109: 0.05 | AA109: 0.05 | AB109: 0.05 | AC109: 0.05 | AD109: 0.05 | AE109: 0.05 | AF109: 0.05 | AG109: 0.05 | AH109: 0.05 | AI109: 0.05 | AJ109: 0.05 | AK109: 0.05 | AL109: 0.05 | AM109: 0.05 | AN109: 0.05 | AO109: 0.05 | AP109: 0.05 | AQ109: 0.05 | AR109: 0.05 | AS109: 0.05 | AT109: 0.05 | AU109: 0.05 | AV109: 0.05 | AW109: 0.05 | AX109: 0.05 | AY109: 0.05 | AZ109: 0.05 | BA109: 0.05 | BB109: 0.05 | BC109: 0.05 | BD109: 0.05 | BE109: 0.05 | BF109: 0.05 | BG109: 0.05 | BH109: 0.05 | BI109: 0.05 | BJ109: 0.05 | BK109: 0.05 | BL109: 0.05 | BM109: 0.05 | BN109: 0.05 | BO109: 0.05 | BP109: 0.05 | BQ109: 0.05 | BR109: 0.05 | BS109: 0.05 | BT109: 0.05 | BU109: 0.05 | BV109: 0.05 | BW109: 0.05 | BX109: 0.05 | BY109: 0.05 | BZ109: 0.05 | CA109: 0.05 | CB109: 0.05 | CC109: 0.05 | CD109: 0.05 | CE109: 0.05 | CF109: 0.05 | CG109: 0.05 | CH109: 0.05 | CI109: 0.05 | CJ109: 0.05 | CK109: 0.05 | CL109: 0.05 | CM109: 0.05 | CN109: 0.05 | CO109: 0.05 | CP109: 0.05
A111: Sales per month | B111: =+'Rev 2'!U13 | C111: =+'Rev 2'!V13 -> 65.084987 | D111: =+'Rev 2'!W13 -> 782.69595 | E111: =+'Rev 2'!X13 -> 1192.7594 | F111: =+'Rev 2'!Y13 -> 1545.4617 | G111: =+'Rev 2'!Z13 -> 1523.2111 | H111: =+'Rev 2'!AA13 -> 2184.1721 | I111: =+'Rev 2'!AB13 -> 4280.355 | ... CP111: =+'Rev 2'!DI13 -> 31502.36
A113: Total compensation per representative | B113: =IF(B107=0,0,B107*B108+B111*B109) -> 0 | C113: =IF(C107=0,0,C107*C108+C111*C109) -> 0 | D113: =IF(D107=0,0,D107*D108+D111*D109) -> 0 | E113: =IF(E107=0,0,E107*E108+E111*E109) -> 0 | F113: =IF(F107=0,0,F107*F108+F111*F109) -> 0 | G113: =IF(G107=0,0,G107*G108+G111*G109) -> 0 | H113: =IF(H107=0,0,H107*H108+H111*H109) -> 0 | I113: =IF(I107=0,0,I107*I108+I111*I109) -> 0 | ... CP113: =IF(CP107=0,0,CP107*CP108+CP111*CP109) -> 0
P123: =SUM(#REF!) -> #REF! | Q123: =SUM(K13:V75) -> 105300

Sheet Overhead
A4: Overhead Projections
A10: Monthly Overhead
A12: Internet cable and Phone service | B12: 400 | C12: x
A13: Insurance | B13: 250 | C13: x
A14: Warehousing | B14: 200 | C14: x
A15: Food | B15: 1200
A16: Website hosting | B16: 100
A17: ADOBE | B17: 40
A18: Quickbooks | B18: 50
A19: SUShio | B19: 25
A20: RENT | B20: 1300 | C20: x
A21: credit card | B21: 500
A22: Shipstation (shipping platform) | B22: 45
A23: GYM | B23: 55
A24: Shopify (web plaform) | B24: 589 | C24: x
A25: Square (payment processing) | B25: 40
A26: HW St john | B26: 100
A27: GAS | B27: 400
A28: Google Adwords | B28: 400
A29: Refersion (ambassador tracking) | B29: 40
A30: KUdo (site review plug in) | B30: 20
A31: ingredient storage cost | B31: 200 | C31: x
A32: Buffer | B32: 60
A33: Zendesk (web tracking) | B33: 29
B34: =SUM(B12:B33) -> 6043
A36: Use | B36: 7000 | D36: =B15+B16+B17+B18+B19+B21+B22+B23+B25+B26+B27+B28+B29+B30+B32+B33 -> 3104
A39: Utilities
A40: Payroll
A41: Delivery
A42: Advertising
A43: Postage/fedx
A44: Office supplies
A45: Office cleaning
A46: Computer expense
A47: Accounting
A48: Legal
A49: Bank fees
A50: Taxes
A51: Waste

Sheet Taxes
C11: 44196 | D11: 44227 | E11: 44255 | F11: 44286 | G11: 44316 | H11: 44347 | I11: 44377 | J11: 44408 | K11: 44439 | L11: 44469 | M11: 44500 | N11: 44530 | O11: 44561 | P11: 44592 | Q11: 44620 | R11: 44651 | S11: 44681 | T11: 44712 | U11: 44742 | V11: 44773 | W11: 44804 | X11: 44834 | Y11: 44865 | Z11: 44895 | AA11: 44926 | AB11: 44957 | AC11: 44985 | AD11: 45016 | AE11: 45046 | AF11: 45077 | AG11: 45107 | AH11: 45138 | AI11: 45169 | AJ11: 45199 | AK11: 45230 | AL11: 45260 | AM11: 45291 | AN11: 45322 | AO11: 45351 | AP11: 45382 | AQ11: 45412 | AR11: 45443 | AS11: 45473 | AT11: 45504 | AU11: 45535 | AV11: 45565 | AW11: 45596 | AX11: 45626 | AY11: 45657 | AZ11: 45688 | BA11: 45716 | BB11: 45747 | BC11: 45777 | BD11: 45808 | BE11: 45838 | BF11: 45869 | BG11: 45900 | BH11: 45930 | BI11: 45961 | BJ11: 45991 | BK11: 46022 | BL11: 46053 | BM11: 46081 | BN11: 46112 | BO11: 46142 | BP11: 46173 | BQ11: 46203 | BR11: 46234 | BS11: 46265 | BT11: 46295 | BU11: 46326 | BV11: 46356 | BW11: 46387 | BX11: 46418 | BY11: 46446 | BZ11: 46477 | CA11: 46507 | CB11: 46538 | CC11: 46568 | CD11: 46599 | CE11: 46630 | CF11: 46660 | CG11: 46691 | CH11: 46721 | CI11: 46752
A13: Net income | D13: =+'P&L Cash Flow Monthly'!K23 -> -46920.45 | E13: =+'P&L Cash Flow Monthly'!L23 -> -24958.984 | F13: =+'P&L Cash Flow Monthly'!M23 -> -18236.309 | G13: =+'P&L Cash Flow Monthly'!N23 -> -16231.113 | H13: =+'P&L Cash Flow Monthly'!O23 -> -14139.49 | I13: =+'P&L Cash Flow Monthly'!P23 -> -20047.867 | J13: =+'P&L Cash Flow Monthly'!Q23 -> -30211.643 | K13: =+'P&L Cash Flow Monthly'!R23 -> -63969.031 | ... CI13: =+'P&L Cash Flow Monthly'!CP23 -> 22939.985
F16: =SUM(D13:F13) -> -90115.744 | H16: =SUM(G13:H13) -> -30370.603 | K16: =SUM(I13:K13) -> -114228.54 | O16: =SUM(L13:O13) -> -125666.45 | R16: =SUM(P13:R13) -> -125716.71 | T16: =SUM(S13:T13) -> -33104.316 | W16: =SUM(U13:W13) -> -40594.543 | AA16: =SUM(X13:AA13) -> -146968.85 | AD16: =SUM(AB13:AD13) -> -1952.37 | AF16: =SUM(AE13:AF13) -> -12389.521 | AI16: =+AG13+AH13+AI13 -> -30063.476 | AM16: =SUM(AJ13:AM13) -> -33717.244 | AP16: =SUM(AN13:AP13) -> -63992.594 | AR16: =SUM(AQ13:AR13) -> -42358.43 | AU16: =+AS13+AT13+AU13 -> -49082.726 | AY16: =SUM(AV13:AY13) -> -44843.875 | BB16: =SUM(AZ13:BB13) -> -36848.354 | BD16: =+BC13+BD13 -> -17610.679 | BG16: =+BE13+BF13+BG13 -> -24252.431 | BK16: =SUM(BH13:BK13) -> -23064.032 | BN16: =SUM(BL13:BN13) -> -30453.174 | BP16: =+BO13+BP13 -> -12332.96 | BS16: =+BQ13+BR13+BS13 -> 2717.935 | BW16: =SUM(BT13:BW13) -> 40694.767 | BZ16: =SUM(BX13:BZ13) -> 16635.224 | CB16: =+CA13+CB13 -> 10277.426
A18: Cummulative net income | F18: =+F16 -> -90115.744 | H18: =+H16+F18 -> -120486.35 | K18: =+K16+H18 -> -234714.89 | O18: =+O16+K18 -> -360381.34 | R18: =+R16+O18 -> -486098.06 | T18: =+T16+R18 -> -519202.37 | W18: =+W16+T18 -> -559796.92 | AA18: =+AA16+W18 -> -706765.76 | AD18: =+AD16+AA18 -> -708718.13 | AF18: =+AF16+AD18 -> -721107.66 | AI18: =+AI16+AF18 -> -751171.13 | AM18: =+AM16+AI18 -> -784888.37 | AP18: =+AP16+AM18 -> -848880.97 | AR18: =+AR16+AP18 -> -891239.4 | AU18: =+AU16+AR18 -> -940322.12 | AY18: =+AY16+AU18 -> -985166 | BB18: =+BB16+AY18 -> -1022014.4 | BD18: =+BD16+BB18 -> -1039625 | BG18: =+BG16+BD18 -> -1063877.5 | BK18: =+BK16+BG18 -> -1086941.5 | BN18: =+BN16+BK18 -> -1117394.7 | BP18: =+BP16+BN18 -> -1129727.6 | BS18: =+BS16+BP18 -> -1127009.7 | BW18: =+BW16+BS18 -> -1086314.9 | BZ18: =+BZ16+BW18 -> -1069679.7 | CB18: =+CB16+BZ18 -> -1059402.3
A20: Tax rate | F20: 0.4 | G20: =+$F20 -> 0.4 | H20: =+$F20 -> 0.4 | I20: =+$F20 -> 0.4 | J20: =+$F20 -> 0.4 | K20: =+$F20 -> 0.4 | L20: =+$F20 -> 0.4 | M20: =+$F20 -> 0.4 | N20: =+$F20 -> 0.4 | ... CI20: =+$F20 -> 0.4
A23: Tax | F23: =IF(F18<0,0,F18*F20) -> 0 | G23: =IF(G18<0,0,G18*G20) -> 0 | H23: =IF(H18<0,0,H18*H20) -> 0 | I23: =IF(I18<0,0,I18*I20) -> 0 | J23: =IF(J18<0,0,J18*J20) -> 0 | K23: =IF(K18<0,0,K18*K20) -> 0 | L23: =IF(L18<0,0,L18*L20) -> 0 | M23: =IF(M18<0,0,M18*M20) -> 0 | ... CP23: =IF(CP18<0,0,CP18*CP20) -> 0
A26: Cummulative tax | F26: =SUM(D23:F23) -> 0 | H26: =+F26+H23 -> 0 | K26: =+K23+H26 -> 0 | O26: =+O23+K26 -> 0 | R26: =SUM(P23:R23) -> 0 | T26: =SUM(S23:T23) -> 0 | W26: =SUM(U23:W23) -> 0 | AA26: =SUM(X23:AA23) -> 0 | AD26: =SUM(AB23:AD23) -> 0 | AF26: =SUM(AE23:AF23) -> 0 | AI26: =+AG23+AH23+AI23 -> 0 | AM26: =SUM(AJ23:AM23) -> 0 | AP26: =SUM(AN23:AP23) -> 0 | AR26: =SUM(AQ23:AR23) -> 0 | AU26: =+AS23+AT23+AU23 -> 0 | AY26: =SUM(AV23:AY23) -> 0 | BB26: =SUM(AZ23:BB23) -> 0 | BD26: =+BC23+BD23 -> 0 | BG26: =+BE23+BF23+BG23 -> 0 | BK26: =SUM(BH23:BK23) -> 0 | BN26: =SUM(BL23:BN23) -> 0 | BP26: =+BO23+BP23 -> 0 | BS26: =+BQ23+BR23+BS23 -> 0 | BW26: =SUM(BT23:BW23) -> 0 | BZ26: =SUM(BX23:BZ23) -> 0 | CB26: =+CA23+CB23 -> 0 | CE26: =+CC23+CD23+CE23 -> 0 | CI26: =SUM(CF23:CI23) -> 0 | CL26: =SUM(CJ23:CL23) -> 0 | CN26: =+CM23+CN23 -> 0
A28: Previous cummulative tax | F28: =IF(F26<0,0,0) -> 0 | H28: =IF(H26<0,0,F26) -> 0 | K28: =IF(K26<0,0,H26) -> 0 | O28: =IF(O26<0,0,K26) -> 0 | R28: =IF(R26<0,0,O26) -> 0 | T28: =IF(T26<0,0,R26) -> 0 | W28: =IF(W26<0,0,T26) -> 0 | AA28: =IF(AA26<0,0,W26) -> 0 | AD28: =IF(AD26<0,0,AA26) -> 0 | AF28: =IF(AF26<0,0,AD26) -> 0 | AI28: =IF(AI26<0,0,AF26) -> 0 | AM28: =IF(AM26<0,0,AI26) -> 0 | AP28: =IF(AP26<0,0,AM26) -> 0 | AR28: =IF(AR26<0,0,AP26) -> 0 | AU28: =IF(AU26<0,0,AR26) -> 0 | AY28: =IF(AY26<0,0,AU26) -> 0 | BB28: =IF(BB26<0,0,AY26) -> 0 | BD28: =IF(BD26<0,0,BB26) -> 0 | BG28: =IF(BG26<0,0,BD26) -> 0 | BK28: =IF(BK26<0,0,BG26) -> 0 | BN28: =IF(BN26<0,0,BK26) -> 0 | BP28: =IF(BP26<0,0,BN26) -> 0 | BS28: =IF(BS26<0,0,BP26) -> 0 | BW28: =IF(BW26<0,0,BS26) -> 0 | BZ28: =IF(BZ26<0,0,BW26) -> 0 | CB28: =IF(CB26<0,0,BZ26) -> 0 | CE28: =IF(CE26<0,0,CB26) -> 0 | CI28: =IF(CI26<0,0,CE26) -> 0 | CL28: =IF(CL26<0,0,CI26) -> 0 | CN28: =IF(CN26<0,0,CL26) -> 0
A30: Current period tax | F30: =+F26-F28 -> 0 | H30: =+H26-H28 -> 0 | K30: =+K26-K28 -> 0 | O30: =+O26-O28 -> 0 | R30: =+R26-R28 -> 0 | T30: =+T26-T28 -> 0 | W30: =+W26-W28 -> 0 | AA30: =+AA26-AA28 -> 0 | AD30: =+AD26-AD28 -> 0 | AF30: =+AF26-AF28 -> 0 | AI30: =+AI26-AI28 -> 0 | AM30: =+AM26-AM28 -> 0 | AP30: =+AP26-AP28 -> 0 | AR30: =+AR26-AR28 -> 0 | AU30: =+AU26-AU28 -> 0 | AY30: =+AY26-AY28 -> 0 | BB30: =+BB26-BB28 -> 0 | BD30: =+BD26-BD28 -> 0 | BG30: =+BG26-BG28 -> 0 | BK30: =+BK26-BK28 -> 0 | BN30: =+BN26-BN28 -> 0 | BP30: =+BP26-BP28 -> 0 | BS30: =+BS26-BS28 -> 0 | BW30: =+BW26-BW28 -> 0 | BZ30: =+BZ26-BZ28 -> 0 | CB30: =+CB26-CB28 -> 0 | CE30: =+CE26-CE28 -> 0 | CI30: =+CI26-CI28 -> 0 | CL30: =+CL26-CL28 -> 0 | CN30: =+CN26-CN28 -> 0
A32: Tax distribution | G32: =IF(F30<0,0,F30) -> 0 | I32: =IF(H30<0,0,H30) -> 0 | L32: =IF(K30<0,0,K30) -> 0 | P32: =IF(O30<0,0,O30) -> 0 | S32: =IF(R30<0,0,R30) -> 0 | U32: =IF(T30<0,0,T30) -> 0 | X32: =IF(W30<0,0,W30) -> 0 | AB32: =IF(AA30<0,0,AA30) -> 0 | AE32: =IF(AD30<0,0,AD30) -> 0 | AG32: =IF(AF30<0,0,AF30) -> 0 | AJ32: =IF(AI30<0,0,AI30) -> 0 | AN32: =IF(AM30<0,0,AM30) -> 0 | AQ32: =IF(AP30<0,0,AP30) -> 0 | AS32: =IF(AR30<0,0,AR30) -> 0 | AV32: =IF(AU30<0,0,AU30) -> 0 | AZ32: =IF(AY30<0,0,AY30) -> 0 | BC32: =IF(BB30<0,0,BB30) -> 0 | BE32: =IF(BD30<0,0,BD30) -> 0 | BH32: =IF(BG30<0,0,BG30) -> 0 | BL32: =IF(BK30<0,0,BK30) -> 0 | BO32: =IF(BN30<0,0,BN30) -> 0 | BQ32: =IF(BP30<0,0,BP30) -> 0 | BT32: =IF(BS30<0,0,BS30) -> 0 | BX32: =IF(BW30<0,0,BW30) -> 0 | CA32: =IF(BZ30<0,0,BZ30) -> 0 | CC32: =IF(CB30<0,0,CB30) -> 0 | CF32: =IF(CE30<0,0,CE30) -> 0 | CJ32: =IF(CI30<0,0,CI30) -> 0 | CM32: =IF(CL30<0,0,CL30) -> 0 | CO32: =IF(CN30<0,0,CN30) -> 0

Sheet Graph

Sheet Facility cost
A1: Food Production equipment | B1: Cost | C1: Bars per hour
A2: Food tools Granola Press | B2: 36000 | C2: 12600
A3: Unifiller Depositor | B3: 95000 | C3: 21000
A4: Bakery and Food Grade Conveyors | B4: 40000
A5: Tumble Mixer | B5: 15000
A6: Food tools sonic cutter | B6: 85000 | C6: 15120
A7: Industrail double rack convection oven | B7: 45000
A8: hobart mixer | B8: 10000
A9: Kettle mixer | B9: 20000
A10: Sheet, trayes, tools, misc | B10: 10000
A12: total | B12: =SUM(B2:B10) -> 356000
A15: Order fullfiment equipment | C15: Boxes per min
A16: Computers, printers, etc | B16: 5000
A17: High speed thermal lable maker | B17: 2000
A18: Little David box maker and sealer | B18: 7000 | C18: 26
A19: Roller converyers | B19: 5000
A20: Misc | B20: 10000
A22: total | B22: =SUM(B16:B20) -> 29000
A25: Warhousing
A26: Forklift | B26: 30000
A27: Shelving | B27: 10000
A28: Misc | B28: 10000
A30: Total | B30: =SUM(B26:B28) -> 50000
A33: Facilty renovation
A34: Nuemacitc air system | B34: 40000
A35: Renvoations | B35: 75000
A37: Total | B37: =SUM(B34:B35) -> 115000
A40: Entire facitly build out | B40: =SUM(B37,B30,B22,B12) -> 550000

Sheet Notes
A9: Note #
A11: 1

Sheet Up front costs
A9: Up front costs
A11: Landing pages
A12: Video
A13: Editing
A14: Face book ads A&B testing
A15: New flavors
A16: Website optmization
A20: Total up front cost | B20: =SUM(B11:B17) -> 0
A23: Kaltec Equipment needs
A24: Candy stove

Sheet CAC
A1: Cost to sample 100 gym 20% Success
A3: Bars sampled to acquire | B3: 600 | C3: #ERROR!
A4: Cost of employee | C4: 2500
C5: =SUM(C3+C4) -> #VALUE!
C8: Rev gen
A9: Gyms contacted | B9: 100
A10: gyms accquired | B10: 20 | C10: 7000
A11: CAC | B11: =C5/B10 -> #VALUE!
C17: =SUM(B15*B11) -> #VALUE!

Sheet Capital
D1: Marketing Expenses
A2: Capitial invesment | B2: 0 | F2: Working Captial | G2: =SUM(B2+B3-E12) -> -28000
A3: Account blance | D3: Landing pages | E3: 3500
D4: Video | E4: 5000
A5: Capital Investment 2nd round | D5: Editing | E5: 2000
D6: Face book ads A&B testing | E6: 2500
D7: New flavors | E7: ?
A8: Marketing | D8: Website optmization | E8: 15000
A9: Packaging
A10: Working Captial
D12: Total up front cost | E12: =SUM(E3:E10) -> 28000
D15: Kaltec Equipment needs
D16: Candy stove | E16: 600

Sheet Cash flow
A1: CASH FLOW | B1: 43648 | C1: 43680 | D1: 43712 | E1: 43743 | F1: 43775 | G1: 43806 | H1: 43831 | I1: 43863 | J1: 43893 | K1: 43925
A4: Wokring Capital | B4: =SUM(Capital!G2) -> -28000 | C4: =SUM(B10) -> #REF! | D4: =SUM(C10) -> #REF! | E4: =SUM(D10) -> #REF! | F4: =SUM(E10) -> #REF! | G4: =SUM(F10) -> #REF! | H4: =SUM(G10) -> #REF! | I4: =SUM(H10) -> #REF! | J4: =SUM(I10) -> #REF!
A6: Gross Projected Revenue | B6: #REF! | C6: #REF! | D6: #REF! | E6: #REF! | F6: #REF! | G6: #REF! | H6: #REF! | I6: #REF! | J6: #REF!
A7: Expense | B7: #REF! | C7: #REF! | D7: #REF! | E7: #REF! | F7: #REF! | G7: #REF! | H7: #REF! | I7: #REF! | J7: #REF!
A8: Cash Flow | B8: =SUM(B6-B7) -> #REF! | C8: =SUM(C6-C7) -> #REF! | D8: =SUM(D6-D7) -> #REF! | E8: =SUM(E6-E7) -> #REF! | F8: =SUM(F6-F7) -> #REF! | G8: =SUM(G6-G7) -> #REF! | H8: =SUM(H6-H7) -> #REF! | I8: =SUM(I6-I7) -> #REF! | J8: =SUM(J6-J7) -> #REF!
A10: End of Month balance | B10: =SUM(B4+B6-B7) -> #REF! | C10: =SUM(C4+C6-C7) -> #REF! | D10: =SUM(D4+D6-D7) -> #REF! | E10: =SUM(E4+E6-E7) -> #REF! | F10: =SUM(F4+F6-F7) -> #REF! | G10: =SUM(G4+G6-G7) -> #REF! | H10: =SUM(H4+H6-H7) -> #REF! | I10: =SUM(I4+I6-I7) -> #REF! | J10: =SUM(J4+J6-J7) -> #REF!

Sheet Brand Ambassisdors 
B1: Cost | C1: bar | D1: Followers | E1: Enagement rate average
A2: Ripped Barbie | B2: 25 | C2: 10 | D2: 111000 | E2: 0.025
A3: Philip Dore | B3: 25 | C3: 10
A4: Caitlin Foresman | B4: 25 | C4: 10 | D4: 33500 | E4: 0.033
A5: Thomas Karlick | B5: 25 | C5: 10
A6: Meredith Burns | B6: 25 | C6: 10 | D6: 78700 | E6: 0.035
A7: Paige Miller | B7: 25 | C7: 10 | D7: 2199 | E7: 0.1
A8: Kineesa | B8: 25 | C8: 10 | D8: 116000 | E8: 0.034
A9: Cody Hendricks | B9: 25 | C9: 10 | D9: 52100
A10: Jeff Nicoles | B10: 25 | C10: 10 | D10: 23500
A11: Jessica | D11: 36100
A12: Kenny Santucci | D12: 117000 | E12: 0.021
A13: Rudy Reyes | D13: 69900
A14: Real world | D14: 1000000 | E14: 0.03
B16: =SUM(B2:B10) -> 225 | C16: =SUM(C2:C10) -> 90

Sheet Cost of bar break down
A1: Bar cost break down per bar
A2: ingredients | B2: 0.85
A3: flow wrap and label | B3: 0.25
A4: display box | B4: 0.1
A5: Shipper box | B5: 0.25
A6: total material cost per bar | B6: =SUM(B2:B5) -> 1.45
A9: Labor costs
A10: Bakery toll daily | B10: 300 | H10: 1394
A11: Hourly labor per person | B11: 20 | H11: 1560
A12: Daily (8hours) labor cost of 4 person team | B12: =SUM(B11*4*8) -> 640 | E12: =SUM(B12*2) -> 1280 | F12: 246.5 | G12: =SUM(E12:F12) -> 1526.5 | H12: 1697
H13: =SUM(H10:H12) -> 4651
A14: Total cost per day | B14: =SUM(B10,B12) -> 940 | E14: 2963
A16: Avergae production run time 1.5 days | E16: 5363 | I16: =SUM(E16/H13) -> 1.1530854
A18: Total cost per run. | B18: =SUM(B14*2)+B12 -> 2520

Sheet EOS
A2: Economy of scale
A3: Trays per run (42bars per tray) | B3: 60 | C3: 75 | D3: 100 | E3: 120 | F3: 150 | G3: 175 | H3: 200 | I3: 250
A4: Bars produced per run | B4: 2500 | C4: 3150 | D4: 4200 | E4: 5000 | F4: 6300 | G4: 7300 | H4: 8400 | I4: 25500
A6: labor cost per bar | B6: 1.25 | C6: =SUM('Cost of bar break down'!B18/C4) -> 0.8 | D6: =SUM('Cost of bar break down'!B18/D4) -> 0.6 | E6: =SUM('Cost of bar break down'!B18/E4) -> 0.504 | F6: =SUM('Cost of bar break down'!B18/F4) -> 0.4 | G6: =SUM('Cost of bar break down'!B18/G4) -> 0.34520548 | H6: =SUM('Cost of bar break down'!B18/H4) -> 0.3 | I6: =SUM('Cost of bar break down'!B18/I4) -> 0.098823529
A8: total cost per bar | B8: =SUM('Cost of bar break down'!B6+B6) -> 2.7 | C8: =SUM('Cost of bar break down'!B6+C6) -> 2.25 | D8: =SUM('Cost of bar break down'!B6+D6) -> 2.05 | E8: =SUM('Cost of bar break down'!B6+E6) -> 1.954 | F8: =SUM('Cost of bar break down'!B6+F6) -> 1.85 | G8: =SUM('Cost of bar break down'!B6+G6) -> 1.7952055 | H8: =SUM('Cost of bar break down'!B6+H6) -> 1.75 | I8: =SUM('Cost of bar break down'!B6+I6) -> 1.5488235
A13: Single bar price point $1.25
B16: =+B4/B3 -> 41.666667 | C16: =+C4/C3 -> 42 | D16: =+D4/D3 -> 42 | E16: =+E4/E3 -> 41.666667 | F16: =+F4/F3 -> 42 | G16: =+G4/G3 -> 41.714286 | H16: =+H4/H3 -> 42 | I16: =+I4/I3 -> 102

Sheet Marketing expenses 
A1: Maketing expense
A3: Annual Net Gym Vaule | B3: 1200
A4: Annual Net Customer Vaule | B4: 70
A6: Swage and apparel | B6: Cost per item | C6: Amount
A7: Tee shirts | B7: 10 | C7: 300 | D7: =SUM(B7*C7) -> 3000
A8: Hats | B8: 15 | C8: 66 | D8: =SUM(B8*C8) -> 990
A9: Silkies | B9: 12 | C9: 40 | D9: =SUM(B9*C9) -> 480
A10: Stickers and Patches | B10: 1 | C10: 1000 | D10: =SUM(B10*C10) -> 1000
A11: Gym banner (per gym) | B11: 150 | C11: 30 | D11: =SUM(B11*C11) -> 4500
A12: Branded Wood create | B12: 50 | C12: 30 | D12: =SUM(B12*C12) -> 1500
B14: Cost
A15: Email regargeting campaige | B15: 2000
B16: Month 1 | C16: Month 2 | D16: Month 3
A17: Ad email Generation | B17: 800 | C17: 800 | D17: 800
A18: Converstion rate | B18: 0.03 | C18: 0.03 | D18: 0.03 | E18: Total Customers Created
A19: Customers created | B19: =SUM(B17*B18) -> 24 | C19: =SUM(C17*C18) -> 24 | D19: =SUM(D17*D18) -> 24 | E19: =SUM(B19:D19) -> 72
A20: Goss revenue generated | B20: =SUM(B19*40) -> 960 | C20: =SUM(C19*40) -> 960 | D20: =SUM(D19*40) -> 960
A21: Annual customer Vaule | B21: =SUM(B4) -> 70
E22: 12 month ROI
E23: =SUM(E19*B21-B15) -> 3040
A24: Content Creation | B24: Cost per Item | C24: One video per month
A25: Video edit | B25: 350 | C25: =SUM(B25*12) -> 4200
A26: Asset collection | B26: 200 | C26: =SUM(B26*12) -> 2400
A30: Event Marketing Kit
A31: Branded Table cloth | B31: 350
A32: Branded Tent | B32: 1000
A33: Banner and pop ups | B33: 200
A34: Back Drop | B34: 750
A35: Design | B35: 500
A36: Event Kit total | B36: =SUM(B31:B35) -> 2800
A38: Events | B38: Both Cost | C38: Attendees | D38: Customer Converstion | E38: Estimated customers acquired
A39: WODAPOLOZA Jan 2019 | B39: 5000 | C39: 30000 | D39: 0.02 | E39: =SUM(C39*D39) -> 600
A40: Product Give away. | B40: 1800 | D40: Averge Sale Vaule | E40: 40
B41: Tees | C41: Hats | D41: Product sales. | E41: =SUM(E39*E40) -> 24000
A42: Apparel | B42: 200 | C42: 20 | D42: Apparel sales | E42: 3100
A43: Shipping Product | B43: 1000
D44: Total gross | E44: =SUM(E40:E43) -> 27140
D45: Net after COG | E45: 5890
A46: Event personel needed 3 | B46: $150 per day | C46: per person
A47: Total for three days | B47: 1350 | E47: 12 Month Event ROI
A48: Travel | B48: 1000 | D48: Customers retainted | E48: 300
A49: Hotel | B49: 300 | D49: Gyms acquired | E49: 10
A51: Total cost | B51: =SUM(B49,B48,B47,B43,B40,B39) -> 10450 | D51: Net vaule | E51: =SUM(E48*B21) -> 21000
D52: Net gym vaule | E52: =SUM(B3*E49) -> 12000
D53: total | E53: =SUM(E51:E52) -> 33000
B55: Both | C55: Attendees | D55: Customer Converstion | E55: Estimated customers acquired
A56: Arnold classic March 2019 | B56: 10000 | C56: 200000 | D56: 0.005 | E56: =SUM(C56*D56) -> 1000
A57: Product Give away. | B57: 4000 | D57: Averge Sale Vaule | E57: 40
B58: Tees | C58: Hats | D58: Product sales. | E58: =SUM(E56*E57) -> 40000
A59: Apparel | B59: 500 | C59: 100 | D59: Apparel sales | E59: 15000
A60: Shipping Product | B60: 2000
D61: Total gross | E61: =SUM(E57:E60) -> 55040
D62: COG | E62: =SUM(E56*18) -> 18000
D63: Net after COG | E63: =SUM(E61-E62) -> 37040
A64: Event personel needed 4 | B64: $150 per day | C64: per person
A65: Total for three days | B65: 1350 | E65: 12 Month Event ROI
A66: Travel | B66: 1000 | D66: Customers retainted | E66: =SUM(E56/2) -> 500
A67: Hotel | B67: 600 | D67: Gyms acquired | E67: 30
A69: Total cost | B69: =SUM(B67,B66,B65,B60,B57,B56) -> 18950 | D69: Net vaule | E69: =SUM(E66*B4) -> 35000
D70: Net gym vaule | E70: =SUM(B3*E67) -> 36000
D71: total | E71: =SUM(E69:E70) -> 71000
A77: Gym mailing campaige | B77: Cost | C77: Gym list tristate | D77: Converstion rate | E77: Gyms Aquired
A78: Gym sample Kit | C78: 200 | D78: 0.05 | E78: =SUM(C78*D78) -> 10
A79: 3 bars | B79: 5.4
A80: Flyer | B80: 0.3 | D80: 12 month ROI | E80: =SUM(B3*E78) -> 12000
A81: Shipping | B81: 7
A82: Gym kit cost | B82: =SUM(B78:B81) -> 12.7
A84: Campaige cost | B84: =SUM(B82*C78) -> 2540
A89: Total Marketing Spend | B89: =SUM(B84,B51,B15,D12,D11,D8,D7,D9,C25,C26,B69,B36,D10) -> 54810
A91: Total Marketing ROI | B91: =SUM(E80,E53,E45,E23,E71,E63) -> 161970
A92: Net profit | B92: =SUM(B91-B89) -> 107160
