Workbook

Sheet Explaination
B2: Basis for the cashforecast are as follows
B4: Customer Acquisition Cost (CAC)
C5: Current: $22.00 | M5: Refer to Task B file
C6: Projections: The company conservatively models CAC increasing as spend scales ($30 in Yr 1, up to $45 by Yr 4). | M6: Refer to C1 investor presentation file
B8: Revenue & Profitability
C9: First-Year Revenue: Customers are expected to spend $100 in their first year. | M9: Refer to Task B file
C10: Gross Margin: The current retail price is $4.80 per bar with a production cost of $2.20, representing a healthy margin that is expected to improve with co-packer efficiencies. | M10: Refer to Task B file
C11: Lifetime Value (LTV): The current LTV is calculated over a 3-year period of sales. | M11: Refer to C1 investor presentation file
B13: Marketing Strategy & Efficiency
C14: Efficiency: Marketing spend is targeted to average 15–16% of total revenue. | M14: Refer to C1 investor presentation file
C15: Channels: Primary focus is on paid digital (Meta, Google, TikTok) and a robust influencer network of over 120 ambassadors with a reach of 1.5M followers. | M15: Refer to C1 investor presentation file
C16: Retention: 40% of customers currently re-order within 30 days, which significantly drives down the long-term effective CAC. | M16: Refer to C1 investor presentation file
B18: Payback Period Calculation
C19: To show the lender the "ability to repay," you can highlight that the cost to acquire a customer ($22) is recovered multiple times over within the first year of that customer's relationship, as they generate approximately $60.00 in gross profit ($100 revenue × 60% margin) in Year 1 alone. | M19: Refer to C1 investor presentation file
B21: To be "lender-ready," it is crucial to show how your raw data translates into the metrics provided in the summary. Below are the detailed calculation steps based on the current performance and future projections found in the C1 Investor Presentation.
B23: Customer Acquisition Cost (CAC)
C24: Formula: Total Marketing Spend / Total New Customers
C25: Current Data: The presentation explicitly states the current CAC is $22.00.
C26: Projected Step-by-Step: For Year 1 projections, the total marketing spend for new customers is $450,000, and the expected number of new customers is 15,000.
C27: $450,000 ÷ 15,000 = $30.00 CAC (Projected Year 1). | M27: Refer to C1 investor presentation file
B29: Average First-Year Revenue Per Customer
C30: Formula: Total Revenue from New Customers / Number of New Customers
C31: Projected Step-by-Step: The presentation projects Year 1 customer spend to be $100.00.
C32: This is expected to grow as expected and reaching a projected $150.00 by Year 2. | M32: Refer to C1 investor presentation file
B34: Gross Margin Percentage
C35: Formula: ((Revenue - Cost of Goods Sold) / Revenue) x 100 | H35: Calculation
C36: Current Product Level: * Retail Price: $4.80. | H36: ='P&L Cash Flow Annual'!D17/'P&L Cash Flow Annual'!D15 -> 0.70016711 | I36: ='P&L Cash Flow Annual'!E17/'P&L Cash Flow Annual'!E15 -> 0.69052346 | J36: ='P&L Cash Flow Annual'!F17/'P&L Cash Flow Annual'!F15 -> 0.63437342 | K36: =(H36+I36+J36)/3 -> 0.67502133
C37: Cost to Produce (COGS): $2.20.
C38: Calculation: (($4.80 - $2.20) / $4.80) = 54.2%.
C39: Company-Wide Projection: The financial table shows a current company COGS of 40% (meaning a 60% margin).
C40: Target: Management expects margins to stabilize at ~67.50% from Year 2 onward due to co-packer efficiencies. | M40: Refer to C1 investor presentation file
B42: Approximate Payback Period
C43: Formula: CAC / (First-Year Revenue x Gross Margin %)
C44: Calculation:
C45: CAC: $22.00.
C46: First-Year Gross Profit: $100.00 Revenue x 60% Margin = $60.00 profit.
C47: Calculation: $22.00 / $60.00 = 0.36 years.
C48: Result: ~4.3 months to earn back the cost of acquiring the customer.
C49: Note: Using the conservative Year 1 projection ($30 CAC / $60 Profit), the payback is 6 months.
B51: Historical Return on Ad Spend (ROAS)
C52: Formula: Total Revenue / Total Ad Spend (often represented as LTV / CAC for long-term health)
C53: Current Metric: The presentation highlights a 9.6x Return on Ad Spend.
C54: Calculation Context: This is derived from the Lifetime Value (LTV) over 3 years of sales being 9.6 times the Customer Acquisition Cost ($212 LTV / $22 CAC).
B56: SBA Loan Service Assumptions
C57: Based on your parameters, a $200,000 loan at 11% interest over 10 years results in:
C58: Monthly Payment: ~$2,755
C59: Annual Debt Service: ~$33,060
C61: Year 1
C62: Metric | D62: Conservative Case | E62: Base Case | F62: Optimistic Case | H62: Calculation
C63: Revenue (A) | D63: =G114 -> 113683.33 | E63: =G115 -> 125141.67 | F63: =G116 -> 138891.67 | K63: ='P&L Cash Flow Annual'!F15/9 -> 109108.73 | L63: 109100 | M63: Avg Rev 2025 rounded off
C64: COGS % (B) | D64: =K36 -> 0.67502133 | E64: =K36 -> 0.67502133 | F64: =K36 -> 0.67502133 | G64: Refer to C1 investor presentation file
C65: COGS $ (C) | D65: =D63*D64 -> 76738.675 | E65: =E63*E64 -> 84473.294 | F65: =F63*F64 -> 93754.837
C66: Calculation: | D66: (A × B) | E66: (A × B) | F66: (A × B) | H66: Calculation
C67: Marketing % (D) | D67: =K67 -> 0.17991334 | E67: =K67 -> 0.17991334 | F67: =K67 -> 0.17991334 | H67: ='P&L Cash Flow Annual'!D28/'P&L Cash Flow Annual'!D15 -> 0.16101863 | I67: ='P&L Cash Flow Annual'!E28/'P&L Cash Flow Annual'!E15 -> 0.23842142 | J67: ='P&L Cash Flow Annual'!F28/'P&L Cash Flow Annual'!F15 -> 0.14029995 | K67: =(H67+I67+J67)/3 -> 0.17991334
C68: Marketing $ (E) | D68: =D63*D67 -> 20453.148 | E68: =E63*E67 -> 22514.655 | F68: =F63*F67 -> 24988.463
C69: Calculation: | D69: (A × D) | E69: (A × D) | F69: (A × D) | H69: Calculation
C70: OpEx/G&A (F) | D70: =L70 -> 39500 | E70: =L70 -> 39500 | F70: =L70 -> 39500 | H70: ='P&L Cash Flow Annual'!D21/12 -> 23269.861 | I70: ='P&L Cash Flow Annual'!E21/12 -> 47711.024 | J70: ='P&L Cash Flow Annual'!F21/9 -> 47368.069 | K70: =(H70+I70+J70)/3 -> 39449.651 | L70: 39500 | M70: Avg OPEX and rounded off
C71: Total Exp (G) | D71: =D65+D68+D70 -> 136691.82 | E71: =E65+E68+E70 -> 146487.95 | F71: =F65+F68+F70 -> 158243.3
C72: Calculation: | D72: (C + E + F) | E72: (C + E + F) | F72: (C + E + F)
C73: Net Cash Flow | D73: =D63-D71 -> -23008.489 | E73: =E63-E71 -> -21346.282 | F73: =F63-F71 -> -19351.634
C74: Calculation: | D74: (A - G) | E74: (A - G) | F74: (A - G)
C76: Year 2
C77: Metric | D77: Conservative Case | E77: Base Case | F77: Optimistic Case
C78: Revenue (A) | D78: =D63*1.38 -> 156883 | E78: =E63*1.4 -> 175198.33 | F78: =F63*1.49 -> 206948.58
C79: COGS % (B) | D79: =K36 -> 0.67502133 | E79: =K36 -> 0.67502133 | F79: =K36 -> 0.67502133
C80: COGS $ (C) | D80: =D78*D79 -> 105899.37 | E80: =E78*E79 -> 118262.61 | F80: =F78*F79 -> 139694.71
C81: Marketing % (D) | D81: =K67 -> 0.17991334 | E81: =K67 -> 0.17991334 | F81: =K67 -> 0.17991334
C82: Marketing $ (E) | D82: =D78*D81 -> 28225.344 | E82: =E78*E81 -> 31520.516 | F82: =F78*F81 -> 37232.81
C83: OpEx/G&A (F) | D83: =L70 -> 39500 | E83: =L70 -> 39500 | F83: =L70 -> 39500
C84: Total Exp (G) | D84: =D78-D80-D82-D83 -> -16741.715 | E84: =E78-E80-E82-E83 -> -14084.795 | F84: =F78-F80-F82-F83 -> -9478.9343
C85: Net Cash Flow | D85: 16850 | E85: 30600 | F85: 52500
C87: Revenue groth rate has been taken from
C88: Expected Growth: The global snack bar market was valued at $28 billion in 2024 and is projected to grow at a 4.47% CAGR during the forecast period (2025-2033)1 | M88: Refer to C1 investor presentation file
I89: Growth rate
C90: Scenario | D90: Growth Rate (r) | E90: Current market | F90: Calculation | G90: Projected | I90: Per year | J90: Per month
C91: Conservative (Bear) | D91: 0.025 | E91: 28 | F91: =(1 + 0.025)^9 -> 1.248863 | G91: =E91*F91 -> 34.968163 | H91: $34.97$ Billion | I91: =D91 -> 0.025 | J91: =I91/12 -> 0.0020833333
C92: Base Case (Industry) | D92: 0.0447 | E92: 28 | F92: =(1 + 0.0447)^9 -> 1.4822599 | G92: =E92*F92 -> 41.503276 | H92: $41.50$ Billion | I92: =D92 -> 0.0447 | J92: =I92/12 -> 0.003725 | M92: Refer to C1 investor presentation file
C93: Optimistic (Bull) | D93: 0.065 | E93: 28 | F93: =(1 + 0.065)^9 -> 1.7625704 | G93: =E93*F93 -> 49.351971 | H93: $49.35$ Billion | I93: =D93 -> 0.065 | J93: =I93/12 -> 0.0054166667
B98: The Debt Service Coverage Ratio (DSCR) Calculation
C99: This is the single most important number for your lender. It proves you can afford the loan.
C100: Formula: Monthly Net Cash Flow ÷ Monthly SBA Payment ($2,755)
C101: Conservative Year 1: $8,500 ÷ $2,755 = 3.08x.
C102: Base Year 1: $15,000 ÷ $2,755 = 5.44x.
C103: Base Year 2: $30,600 ÷ $2,755 = 11.10x.
C106: Year | D106: Marketing & Ad Spend (A) | E106: Total Revenue (B) | F106: Est. Customers (B ÷ $85 AOV) | G106: Calculated CAC
C107: 2022 | D107: 151846.35 | E107: 882471.77 | F107: =E107/85 -> 10382.021 | G107: =D107/F107 -> 14.625895
C108: 2023 | D108: 112474.76 | E108: 698520.16 | F108: =E108/85 -> 8217.8842 | G108: =D108/F108 -> 13.686584
C109: 2024 | D109: 241812.9 | E109: 1014224.7 | F109: =E109/85 -> 11932.056 | G109: =D109/F109 -> 20.265821 | I109: Refer to C1 investor presentation file
B111: The Current Baseline (2025 YTD average): ~$109,100/month.
C113: Case | D113: Revenue Calculation (The "Base") | G113: Projected Revenue/Month
C114: Conservative | D114: Baseline ($109k) + (SBA Ad Spend (200,000*55%) × 1.0x ROAS) | E114: 109100 | F114: =(200000*55%)/24 -> 4583.3333 | G114: =E114+F114 -> 113683.33
C115: Base Case | D115: Baseline ($109k) + (SBA Ad Spend (200,000*55%) × 3.5x ROAS) | E115: 109100 | F115: =(200000*55%)/24 -> 4583.3333 | G115: =E115+(F115*3.5) -> 125141.67
C116: Optimistic | D116: Baseline ($109k) + (SBA Ad Spend (200,000*55%) × 6.5x ROAS) | E116: 109100 | F116: =(200000*55%)/24 -> 4583.3333 | G116: =E116+(F116*6.5) -> 138891.67

Sheet P&L Cash Flow Annual
A2: CONDITION ONE NUTRITION
A3: Cash Flow Annual
D7: Actual | E7: Actual | F7: Actual | G7: Conservative Case | I7: Base Case | K7: Optimistic Case
B8: 2021 | C8: 2022 | D8: 2023 | E8: 2024 | F8: 2025 | G8: 2026 | H8: 2027 | I8: 2026 | J8: 2027 | K8: 2026 | L8: 2027
A10: Sales
A11: Gyms | B11: =SUM('P&L Cash Flow Monthly'!K11:V11) -> 133087.11 | C11: =+'P&L Cash Flow Monthly'!W11+'P&L Cash Flow Monthly'!X11+'P&L Cash Flow Monthly'!Y11+'P&L Cash Flow Monthly'!Z11+'P&L Cash Flow Monthly'!AA11+'P&L Cash Flow Monthly'!AB11+'P&L Cash Flow Monthly'!AC11+'P&L Cash Flow Monthly'!AD11+'P&L Cash Flow Monthly'!AE11+'P&L Cash Flow Monthly'!AF11+'P&L Cash Flow Monthly'!AG11+'P&L Cash Flow Monthly'!AH11 -> 127294.62 | D11: =+'P&L Cash Flow Monthly'!AI11+'P&L Cash Flow Monthly'!AJ11+'P&L Cash Flow Monthly'!AK11+'P&L Cash Flow Monthly'!AL11+'P&L Cash Flow Monthly'!AM11+'P&L Cash Flow Monthly'!AN11+'P&L Cash Flow Monthly'!AO11+'P&L Cash Flow Monthly'!AP11+'P&L Cash Flow Monthly'!AQ11+'P&L Cash Flow Monthly'!AR11+'P&L Cash Flow Monthly'!AS11+'P&L Cash Flow Monthly'!AT11 -> 90473.632 | E11: =+'P&L Cash Flow Monthly'!AU11+'P&L Cash Flow Monthly'!AV11+'P&L Cash Flow Monthly'!AW11+'P&L Cash Flow Monthly'!AX11+'P&L Cash Flow Monthly'!AY11+'P&L Cash Flow Monthly'!AZ11+'P&L Cash Flow Monthly'!BA11+'P&L Cash Flow Monthly'!BB11+'P&L Cash Flow Monthly'!BC11+'P&L Cash Flow Monthly'!BD11+'P&L Cash Flow Monthly'!BE11+'P&L Cash Flow Monthly'!BF11 -> 132743.05 | F11: =+'P&L Cash Flow Monthly'!BG11+'P&L Cash Flow Monthly'!BH11+'P&L Cash Flow Monthly'!BI11+'P&L Cash Flow Monthly'!BJ11+'P&L Cash Flow Monthly'!BK11+'P&L Cash Flow Monthly'!BL11+'P&L Cash Flow Monthly'!BM11+'P&L Cash Flow Monthly'!BN11+'P&L Cash Flow Monthly'!BO11+'P&L Cash Flow Monthly'!BP11+'P&L Cash Flow Monthly'!BQ11+'P&L Cash Flow Monthly'!BR11 -> 128606.49 | G11: =SUM('P&L Cash Flow Monthly'!BS11:CD11) -> 201224.06 | H11: =SUM('P&L Cash Flow Monthly'!CE11:CP11) -> 317836.39 | I11: =SUM('P&L Cash Flow Monthly'!BU11:CF11) -> 220357.86 | J11: =SUM('P&L Cash Flow Monthly'!CG11:CR11) -> 275043.54 | K11: =SUM('P&L Cash Flow Monthly'!BW11:CH11) -> 239899.73 | L11: =SUM('P&L Cash Flow Monthly'!CI11:CT11) -> 228638.96
A12: E-commerce | B12: =SUM('P&L Cash Flow Monthly'!K12:V12) -> 910216.47 | C12: =+'P&L Cash Flow Monthly'!W12+'P&L Cash Flow Monthly'!X12+'P&L Cash Flow Monthly'!Y12+'P&L Cash Flow Monthly'!Z12+'P&L Cash Flow Monthly'!AA12+'P&L Cash Flow Monthly'!AB12+'P&L Cash Flow Monthly'!AC12+'P&L Cash Flow Monthly'!AD12+'P&L Cash Flow Monthly'!AE12+'P&L Cash Flow Monthly'!AF12+'P&L Cash Flow Monthly'!AG12+'P&L Cash Flow Monthly'!AH12 -> 891020.34 | D12: =+'P&L Cash Flow Monthly'!AI12+'P&L Cash Flow Monthly'!AJ12+'P&L Cash Flow Monthly'!AK12+'P&L Cash Flow Monthly'!AL12+'P&L Cash Flow Monthly'!AM12+'P&L Cash Flow Monthly'!AN12+'P&L Cash Flow Monthly'!AO12+'P&L Cash Flow Monthly'!AP12+'P&L Cash Flow Monthly'!AQ12+'P&L Cash Flow Monthly'!AR12+'P&L Cash Flow Monthly'!AS12+'P&L Cash Flow Monthly'!AT12 -> 633273.42 | E12: =+'P&L Cash Flow Monthly'!AU12+'P&L Cash Flow Monthly'!AV12+'P&L Cash Flow Monthly'!AW12+'P&L Cash Flow Monthly'!AX12+'P&L Cash Flow Monthly'!AY12+'P&L Cash Flow Monthly'!AZ12+'P&L Cash Flow Monthly'!BA12+'P&L Cash Flow Monthly'!BB12+'P&L Cash Flow Monthly'!BC12+'P&L Cash Flow Monthly'!BD12+'P&L Cash Flow Monthly'!BE12+'P&L Cash Flow Monthly'!BF12 -> 929159.32 | F12: =+'P&L Cash Flow Monthly'!BG12+'P&L Cash Flow Monthly'!BH12+'P&L Cash Flow Monthly'!BI12+'P&L Cash Flow Monthly'!BJ12+'P&L Cash Flow Monthly'!BK12+'P&L Cash Flow Monthly'!BL12+'P&L Cash Flow Monthly'!BM12+'P&L Cash Flow Monthly'!BN12+'P&L Cash Flow Monthly'!BO12+'P&L Cash Flow Monthly'!BP12+'P&L Cash Flow Monthly'!BQ12+'P&L Cash Flow Monthly'!BR12 -> 900203.45 | G12: =SUM('P&L Cash Flow Monthly'!BS12:CD12) -> 1408526.4 | H12: =SUM('P&L Cash Flow Monthly'!CE12:CP12) -> 2224812.7 | I12: =SUM('P&L Cash Flow Monthly'!BU12:CF12) -> 1542463 | J12: =SUM('P&L Cash Flow Monthly'!CG12:CR12) -> 1925269.8 | K12: =SUM('P&L Cash Flow Monthly'!BW12:CH12) -> 1679256.1 | L12: =SUM('P&L Cash Flow Monthly'!CI12:CT12) -> 1600444.7
A15: Sales | B15: =SUM(B11:B12) -> 1043303.6 | C15: =SUM(C11:C12) -> 1018315 | D15: ='P&L 2023'!N10 -> 698520.16 | E15: ='P&L 2024'!N10 -> 1014224.7 | F15: ='P&L 2025'!K13 -> 981978.58 | G15: ='Forecast P&L 2026 1'!N11 -> 1380067.3 | H15: ='Forecast P&L 2027 1'!N11 -> 1904492.9 | I15: ='Forecast P&L 2026 2'!N11 -> 1532639.7 | J15: ='Forecast P&L 2027 2'!N11 -> 2145695.5 | K15: ='Forecast P&L 2026 3'!N11 -> 1717102.9 | L15: ='Forecast P&L 2027 3'!N11 -> 2558483.4
A17: Cost of goods sold | B17: =SUM('P&L Cash Flow Monthly'!K17:V17) -> 748803.02 | C17: =+'P&L Cash Flow Monthly'!W17+'P&L Cash Flow Monthly'!X17+'P&L Cash Flow Monthly'!Y17+'P&L Cash Flow Monthly'!Z17+'P&L Cash Flow Monthly'!AA17+'P&L Cash Flow Monthly'!AB17+'P&L Cash Flow Monthly'!AC17+'P&L Cash Flow Monthly'!AD17+'P&L Cash Flow Monthly'!AE17+'P&L Cash Flow Monthly'!AF17+'P&L Cash Flow Monthly'!AG17+'P&L Cash Flow Monthly'!AH17 -> 716210.63 | D17: ='P&L 2023'!N15 -> 489080.84 | E17: ='P&L 2024'!N16 -> 700345.97 | F17: ='P&L 2025'!K18 -> 622941.11 | G17: ='Forecast P&L 2026 1'!N16 -> 938445.78 | H17: ='Forecast P&L 2027 1'!N16 -> 1295055.2 | I17: ='Forecast P&L 2026 2'!N16 -> 1042195 | J17: ='Forecast P&L 2027 2'!N16 -> 1459072.9 | K17: ='Forecast P&L 2026 3'!N16 -> 1167630 | L17: ='Forecast P&L 2027 3'!N16 -> 1739768.7
A19: Gross margin | B19: =+B15-B17 -> 294500.56 | C19: =+C15-C17 -> 302104.32 | D19: =+D15-D17 -> 209439.32 | E19: =+E15-E17 -> 313878.76 | F19: =+F15-F17 -> 359037.47 | G19: =+G15-G17 -> 441621.55 | H19: =+H15-H17 -> 609437.73 | I19: =+I15-I17 -> 490444.69 | ... L19: =+L15-L17 -> 818714.68
A21: Expenses (see tab for detail) | B21: =SUM('P&L Cash Flow Monthly'!K21:V21) -> 654881.9 | C21: =+'P&L Cash Flow Monthly'!W21+'P&L Cash Flow Monthly'!X21+'P&L Cash Flow Monthly'!Y21+'P&L Cash Flow Monthly'!Z21+'P&L Cash Flow Monthly'!AA21+'P&L Cash Flow Monthly'!AB21+'P&L Cash Flow Monthly'!AC21+'P&L Cash Flow Monthly'!AD21+'P&L Cash Flow Monthly'!AE21+'P&L Cash Flow Monthly'!AF21+'P&L Cash Flow Monthly'!AG21+'P&L Cash Flow Monthly'!AH21 -> 648488.75 | D21: ='P&L 2023'!N41 -> 279238.33 | E21: ='P&L 2024'!N45+'P&L 2024'!N49 -> 572532.29 | F21: ='P&L 2025'!K54 -> 426312.62 | G21: ='Forecast P&L 2026 1'!N52 -> 722412.12 | H21: ='Forecast P&L 2027 1'!N52 -> 816808.72 | I21: ='Forecast P&L 2026 2'!N52 -> 749875.14 | J21: ='Forecast P&L 2027 2'!N52 -> 852428.4 | K21: ='Forecast P&L 2026 3'!N52 -> 783078.53 | L21: ='Forecast P&L 2027 3'!N52 -> 934527.01
A23: Net income/EBITDA | B23: =+B19-B21 -> -360381.34 | C23: =+C19-C21 -> -346384.42 | D23: =+D19-D21 -> -69799.01 | E23: =+E19-E21 -> -258653.53 | F23: =+F19-F21 -> -67275.15 | G23: =+G19-G21 -> -280790.57 | H23: =+H19-H21 -> -207370.99 | I23: =+I19-I21 -> -259430.45 | ... L23: =+L19-L21 -> -115812.33
A25: Adjustments to convert net income to cash flow
A26: COGS | B26: =SUM('P&L Cash Flow Monthly'!K26:V26) -> 748803.02 | C26: =+'P&L Cash Flow Monthly'!W26+'P&L Cash Flow Monthly'!X26+'P&L Cash Flow Monthly'!Y26+'P&L Cash Flow Monthly'!Z26+'P&L Cash Flow Monthly'!AA26+'P&L Cash Flow Monthly'!AB26+'P&L Cash Flow Monthly'!AC26+'P&L Cash Flow Monthly'!AD26+'P&L Cash Flow Monthly'!AE26+'P&L Cash Flow Monthly'!AF26+'P&L Cash Flow Monthly'!AG26+'P&L Cash Flow Monthly'!AH26 -> 716210.63 | D26: ='P&L 2023'!N15 -> 489080.84 | E26: ='P&L 2024'!N16 -> 700345.97 | F26: ='P&L 2025'!K18 -> 622941.11 | G26: ='Forecast P&L 2026 1'!N16 -> 938445.78 | H26: ='Forecast P&L 2027 1'!N16 -> 1295055.2 | I26: ='Forecast P&L 2026 2'!N16 -> 1042195 | J26: ='Forecast P&L 2027 2'!N16 -> 1459072.9 | K26: ='Forecast P&L 2026 3'!N16 -> 1167630 | L26: ='Forecast P&L 2027 3'!N16 -> 1739768.7
A27: Payment for COGS | B27: =SUM('P&L Cash Flow Monthly'!K27:V27) -> -773403.12 | C27: =+'P&L Cash Flow Monthly'!W27+'P&L Cash Flow Monthly'!X27+'P&L Cash Flow Monthly'!Y27+'P&L Cash Flow Monthly'!Z27+'P&L Cash Flow Monthly'!AA27+'P&L Cash Flow Monthly'!AB27+'P&L Cash Flow Monthly'!AC27+'P&L Cash Flow Monthly'!AD27+'P&L Cash Flow Monthly'!AE27+'P&L Cash Flow Monthly'!AF27+'P&L Cash Flow Monthly'!AG27+'P&L Cash Flow Monthly'!AH27 -> -695924.67 | D27: =-'P&L 2023'!N15 -> -489080.84 | E27: =-'P&L 2024'!N16 -> -700345.97 | F27: =-'P&L 2025'!K18 -> -622941.11 | G27: =-'Forecast P&L 2026 1'!N16 -> -938445.78 | H27: =-'Forecast P&L 2027 1'!N16 -> -1295055.2 | I27: =-I26 -> -1042195 | J27: =-J26 -> -1459072.9 | K27: =-K26 -> -1167630 | L27: =-L26 -> -1739768.7
A28: Marketing ad spend | B28: =SUM('P&L Cash Flow Monthly'!K28:V28) -> 175000 | C28: =+'P&L Cash Flow Monthly'!W28+'P&L Cash Flow Monthly'!X28+'P&L Cash Flow Monthly'!Y28+'P&L Cash Flow Monthly'!Z28+'P&L Cash Flow Monthly'!AA28+'P&L Cash Flow Monthly'!AB28+'P&L Cash Flow Monthly'!AC28+'P&L Cash Flow Monthly'!AD28+'P&L Cash Flow Monthly'!AE28+'P&L Cash Flow Monthly'!AF28+'P&L Cash Flow Monthly'!AG28+'P&L Cash Flow Monthly'!AH28 -> 118000 | D28: ='P&L 2023'!N18 -> 112474.76 | E28: ='P&L 2024'!N19 -> 241812.9 | F28: ='P&L 2025'!K21+'P&L 2025'!K35 -> 137771.55 | G28: ='Forecast P&L 2026 1'!N33 -> 248412.12 | H28: ='Forecast P&L 2027 1'!N33 -> 342808.72 | I28: ='Forecast P&L 2026 2'!N33 -> 275875.14 | J28: ='Forecast P&L 2027 2'!N33 -> 378428.4 | K28: ='Forecast P&L 2026 3'!N33 -> 309078.53 | L28: ='Forecast P&L 2027 3'!N33 -> 460527.01
A29: Payment for Marketing ad spend | B29: =SUM('P&L Cash Flow Monthly'!K29:V29) -> -170000 | C29: =+'P&L Cash Flow Monthly'!W29+'P&L Cash Flow Monthly'!X29+'P&L Cash Flow Monthly'!Y29+'P&L Cash Flow Monthly'!Z29+'P&L Cash Flow Monthly'!AA29+'P&L Cash Flow Monthly'!AB29+'P&L Cash Flow Monthly'!AC29+'P&L Cash Flow Monthly'!AD29+'P&L Cash Flow Monthly'!AE29+'P&L Cash Flow Monthly'!AF29+'P&L Cash Flow Monthly'!AG29+'P&L Cash Flow Monthly'!AH29 -> -118000 | D29: =-'P&L 2023'!N18 -> -112474.76 | E29: =-'P&L 2024'!N19 -> -241812.9 | F29: =-'P&L 2025'!K21-'P&L 2025'!K35 -> -137771.55 | G29: =-'Forecast P&L 2026 1'!N33 -> -248412.12 | H29: =-'Forecast P&L 2027 1'!N33 -> -342808.72 | I29: =-I28 -> -275875.14 | J29: =-J28 -> -378428.4 | K29: =-K28 -> -309078.53 | L29: =-L28 -> -460527.01
A30: Initial up front costs | B30: =SUM('P&L Cash Flow Monthly'!K30:V30) -> 0 | C30: =+'P&L Cash Flow Monthly'!W30+'P&L Cash Flow Monthly'!X30+'P&L Cash Flow Monthly'!Y30+'P&L Cash Flow Monthly'!Z30+'P&L Cash Flow Monthly'!AA30+'P&L Cash Flow Monthly'!AB30+'P&L Cash Flow Monthly'!AC30+'P&L Cash Flow Monthly'!AD30+'P&L Cash Flow Monthly'!AE30+'P&L Cash Flow Monthly'!AF30+'P&L Cash Flow Monthly'!AG30+'P&L Cash Flow Monthly'!AH30 -> 0 | D30: =+'P&L Cash Flow Monthly'!AI30+'P&L Cash Flow Monthly'!AJ30+'P&L Cash Flow Monthly'!AK30+'P&L Cash Flow Monthly'!AL30+'P&L Cash Flow Monthly'!AM30+'P&L Cash Flow Monthly'!AN30+'P&L Cash Flow Monthly'!AO30+'P&L Cash Flow Monthly'!AP30+'P&L Cash Flow Monthly'!AQ30+'P&L Cash Flow Monthly'!AR30+'P&L Cash Flow Monthly'!AS30+'P&L Cash Flow Monthly'!AT30 -> 0 | E30: =+'P&L Cash Flow Monthly'!AU30+'P&L Cash Flow Monthly'!AV30+'P&L Cash Flow Monthly'!AW30+'P&L Cash Flow Monthly'!AX30+'P&L Cash Flow Monthly'!AY30+'P&L Cash Flow Monthly'!AZ30+'P&L Cash Flow Monthly'!BA30+'P&L Cash Flow Monthly'!BB30+'P&L Cash Flow Monthly'!BC30+'P&L Cash Flow Monthly'!BD30+'P&L Cash Flow Monthly'!BE30+'P&L Cash Flow Monthly'!BF30 -> 0 | F30: =+'P&L Cash Flow Monthly'!BG30+'P&L Cash Flow Monthly'!BH30+'P&L Cash Flow Monthly'!BI30+'P&L Cash Flow Monthly'!BJ30+'P&L Cash Flow Monthly'!BK30+'P&L Cash Flow Monthly'!BL30+'P&L Cash Flow Monthly'!BM30+'P&L Cash Flow Monthly'!BN30+'P&L Cash Flow Monthly'!BO30+'P&L Cash Flow Monthly'!BP30+'P&L Cash Flow Monthly'!BQ30+'P&L Cash Flow Monthly'!BR30 -> 0 | G30: =SUM('P&L Cash Flow Monthly'!BS30:CD30) -> 0 | H30: =SUM('P&L Cash Flow Monthly'!CE30:CP30) -> 0 | I30: =SUM('P&L Cash Flow Monthly'!BU30:CF30) -> 0 | J30: =SUM('P&L Cash Flow Monthly'!CG30:CR30) -> 0 | K30: =SUM('P&L Cash Flow Monthly'!BW30:CH30) -> 0 | L30: =SUM('P&L Cash Flow Monthly'!CI30:CT30) -> 0
A31: Tax distribution | B31: =SUM('P&L Cash Flow Monthly'!K31:V31) -> 0 | C31: =+'P&L Cash Flow Monthly'!W31+'P&L Cash Flow Monthly'!X31+'P&L Cash Flow Monthly'!Y31+'P&L Cash Flow Monthly'!Z31+'P&L Cash Flow Monthly'!AA31+'P&L Cash Flow Monthly'!AB31+'P&L Cash Flow Monthly'!AC31+'P&L Cash Flow Monthly'!AD31+'P&L Cash Flow Monthly'!AE31+'P&L Cash Flow Monthly'!AF31+'P&L Cash Flow Monthly'!AG31+'P&L Cash Flow Monthly'!AH31 -> 0 | D31: =+'P&L Cash Flow Monthly'!AI31+'P&L Cash Flow Monthly'!AJ31+'P&L Cash Flow Monthly'!AK31+'P&L Cash Flow Monthly'!AL31+'P&L Cash Flow Monthly'!AM31+'P&L Cash Flow Monthly'!AN31+'P&L Cash Flow Monthly'!AO31+'P&L Cash Flow Monthly'!AP31+'P&L Cash Flow Monthly'!AQ31+'P&L Cash Flow Monthly'!AR31+'P&L Cash Flow Monthly'!AS31+'P&L Cash Flow Monthly'!AT31 -> 0 | E31: =+'P&L Cash Flow Monthly'!AU31+'P&L Cash Flow Monthly'!AV31+'P&L Cash Flow Monthly'!AW31+'P&L Cash Flow Monthly'!AX31+'P&L Cash Flow Monthly'!AY31+'P&L Cash Flow Monthly'!AZ31+'P&L Cash Flow Monthly'!BA31+'P&L Cash Flow Monthly'!BB31+'P&L Cash Flow Monthly'!BC31+'P&L Cash Flow Monthly'!BD31+'P&L Cash Flow Monthly'!BE31+'P&L Cash Flow Monthly'!BF31 -> 0 | F31: =+'P&L Cash Flow Monthly'!BG31+'P&L Cash Flow Monthly'!BH31+'P&L Cash Flow Monthly'!BI31+'P&L Cash Flow Monthly'!BJ31+'P&L Cash Flow Monthly'!BK31+'P&L Cash Flow Monthly'!BL31+'P&L Cash Flow Monthly'!BM31+'P&L Cash Flow Monthly'!BN31+'P&L Cash Flow Monthly'!BO31+'P&L Cash Flow Monthly'!BP31+'P&L Cash Flow Monthly'!BQ31+'P&L Cash Flow Monthly'!BR31 -> 0 | G31: =SUM('P&L Cash Flow Monthly'!BS31:CD31) -> 0 | H31: =SUM('P&L Cash Flow Monthly'!CE31:CP31) -> 0 | I31: =SUM('P&L Cash Flow Monthly'!BU31:CF31) -> 0 | J31: =SUM('P&L Cash Flow Monthly'!CG31:CR31) -> 0 | K31: =SUM('P&L Cash Flow Monthly'!BW31:CH31) -> 0 | L31: =SUM('P&L Cash Flow Monthly'!CI31:CT31) -> 0
A32: Capital investment | B32: =SUM('P&L Cash Flow Monthly'!K32:V32) -> 400000 | C32: =+'P&L Cash Flow Monthly'!W32+'P&L Cash Flow Monthly'!X32+'P&L Cash Flow Monthly'!Y32+'P&L Cash Flow Monthly'!Z32+'P&L Cash Flow Monthly'!AA32+'P&L Cash Flow Monthly'!AB32+'P&L Cash Flow Monthly'!AC32+'P&L Cash Flow Monthly'!AD32+'P&L Cash Flow Monthly'!AE32+'P&L Cash Flow Monthly'!AF32+'P&L Cash Flow Monthly'!AG32+'P&L Cash Flow Monthly'!AH32 -> 285000 | D32: 0 | E32: 0 | F32: 0 | G32: 0 | H32: 0 | I32: 0 | J32: 0 | K32: 0 | L32: 0
A35: Annual cash flow | B35: =SUM(B23:B33) -> 20018.56 | C35: =SUM(C23:C33) -> -41098.458 | D35: =SUM(D23:D33) -> -69799.01 | E35: =SUM(E23:E33) -> -258653.53 | F35: =SUM(F23:F33) -> -67275.15 | G35: =SUM(G23:G33) -> -280790.57 | H35: =SUM(H23:H33) -> -207370.99 | I35: =SUM(I23:I33) -> -259430.45 | ... L35: =SUM(L23:L33) -> -115812.33
A37: Cash beginning of year | B37: ='P&L Cash Flow Monthly'!K37:K38 -> 179360.01 | C37: =+B39 -> 199378.57 | D37: =+C39 -> 158280.11 | E37: =+D39 -> 88481.099 | F37: =+E39 -> -170172.43 | G37: =+F39 -> -237447.58 | H37: =+G39 -> -518238.16 | I37: =F39 -> -237447.58 | J37: =+I39 -> -496878.03 | K37: =F39 -> -237447.58 | L37: =+K39 -> -471053.17
A39: Cash end of year | B39: =SUM(B35:B37) -> 199378.57 | C39: =SUM(C35:C37) -> 158280.11 | D39: =SUM(D35:D37) -> 88481.099 | E39: =SUM(E35:E37) -> -170172.43 | F39: =SUM(F35:F37) -> -237447.58 | G39: =SUM(G35:G37) -> -518238.16 | H39: =SUM(H35:H37) -> -725609.15 | I39: =SUM(I35:I37) -> -496878.03 | ... L39: =SUM(L35:L37) -> -586865.5
A42: Gross Profit % | B42: =B19/B15 -> 0.28227695 | C42: =C19/C15 -> 0.29667081 | D42: =D19/D15 -> 0.29983289 | E42: =E19/E15 -> 0.30947654 | F42: =F19/F15 -> 0.36562658 | G42: =G19/G15 -> 0.32 | H42: =H19/H15 -> 0.32 | I42: =I19/I15 -> 0.32 | ... L42: =L19/L15 -> 0.32
A44: Net Profit % | B44: =B23/B15 -> -0.34542328 | C44: =C23/C15 -> -0.34015451 | D44: =D23/D15 -> -0.099924117 | E44: =E23/E15 -> -0.25502586 | F44: =F23/F15 -> -0.068509794 | G44: =G23/G15 -> -0.2034615 | H44: =H23/H15 -> -0.10888515 | I44: =I23/I15 -> -0.16927035 | ... L44: =L23/L15 -> -0.045266008

Sheet P&L 2023
A1: Profit and Loss
A2: CONDITION ONE NUTRITION
A3: January-December, 2023
A5: Distribution account | B5: January 2023 | C5: February 2023 | D5: March 2023 | E5: April 2023 | F5: May 2023 | G5: June 2023 | H5: July 2023 | I5: August 2023 | J5: September 2023 | K5: October 2023 | L5: November 2023 | M5: December 2023 | N5: Total
A6: Income
A7: ECOMM Shopify Sales | B7: 38494.09 | C7: 38975.46 | D7: 40272.08 | E7: 39289.76 | F7: 45363.98 | G7: 37019.49 | H7: 33126.59 | I7: 34208.34 | J7: 34963.64 | K7: 39857.42 | L7: 31189.46 | M7: 25844.71 | N7: =B7+C7+D7+E7+F7+G7+H7+I7+J7+K7+L7+M7 -> 438605.02
A8: ECOMM Stripe Sales | B8: 13274.09 | C8: 12506.95 | D8: 12325.37 | E8: 11750.9 | F8: 12206.23 | G8: 22275.27 | H8: 10778.6 | I8: 10212.1 | J8: 8828.2 | K8: 10980.48 | L8: 8961.04 | M8: 8397.83 | N8: =B8+C8+D8+E8+F8+G8+H8+I8+J8+K8+L8+M8 -> 142497.06
A9: Sales of Product Income | B9: 12881.98 | C9: 10976.16 | D9: 17053.45 | E9: 9871.58 | F9: 11461.91 | G9: 9255.24 | H9: 7947.77 | I9: 11218.93 | J9: 8514.89 | K9: 7229.84 | L9: 5731.43 | M9: 5274.9 | N9: =B9+C9+D9+E9+F9+G9+H9+I9+J9+K9+L9+M9 -> 117418.08
A10: Total for Income | B10: =B7+B8+B9 -> 64650.16 | C10: =C7+C8+C9 -> 62458.57 | D10: =D7+D8+D9 -> 69650.9 | E10: =E7+E8+E9 -> 60912.24 | F10: =F7+F8+F9 -> 69032.12 | G10: =G7+G8+G9 -> 68550 | H10: =H7+H8+H9 -> 51852.96 | I10: =I7+I8+I9 -> 55639.37 | ... M10: =M7+M8+M9 -> 39517.44 | N10: =B10+C10+D10+E10+F10+G10+H10+I10+J10+K10+L10+M10 -> 698520.16
A11: Cost of Goods Sold
A12: Cost of Goods Sold | B12: 9830.06 | C12: 4846.43 | D12: 6421.92 | E12: 5062.07 | F12: 9072.82 | G12: 21527.56 | H12: 3192.68 | I12: 6884.36 | J12: 6525.22 | K12: 4673.06 | L12: 6165.75 | M12: 3400.01 | N12: =B12+C12+D12+E12+F12+G12+H12+I12+J12+K12+L12+M12 -> 87601.94
A13: Cost of labor - COS | B13: 21313.32 | C13: 19655.04 | D13: 29025.69 | E13: 22415.16 | F13: 37154.41 | G13: 20582.67 | H13: 27827.68 | I13: 15103.16 | J13: 22847.3 | K13: 29059.41 | L13: 13292.4 | M13: 22140.3 | N13: =B13+C13+D13+E13+F13+G13+H13+I13+J13+K13+L13+M13 -> 280416.54
A14: Freight & Delivery | B14: 12227.15 | C14: 11168.19 | D14: 11427.15 | E14: 10447.15 | F14: 12647.15 | G14: 9997.58 | H14: 9617.58 | I14: 9292.2 | J14: 8662.58 | K14: 10589.49 | L14: 8341.68 | M14: 6644.46 | N14: =B14+C14+D14+E14+F14+G14+H14+I14+J14+K14+L14+M14 -> 121062.36
A15: Total for Cost of Goods Sold | B15: =B12+B13+B14 -> 43370.53 | C15: =C12+C13+C14 -> 35669.66 | D15: =D12+D13+D14 -> 46874.76 | E15: =E12+E13+E14 -> 37924.38 | F15: =F12+F13+F14 -> 58874.38 | G15: =G12+G13+G14 -> 52107.81 | H15: =H12+H13+H14 -> 40637.94 | I15: =I12+I13+I14 -> 31279.72 | ... M15: =M12+M13+M14 -> 32184.77 | N15: =B15+C15+D15+E15+F15+G15+H15+I15+J15+K15+L15+M15 -> 489080.84
A16: Gross Profit | B16: =B10-B15 -> 21279.63 | C16: =C10-C15 -> 26788.91 | D16: =D10-D15 -> 22776.14 | E16: =E10-E15 -> 22987.86 | F16: =F10-F15 -> 10157.74 | G16: =G10-G15 -> 16442.19 | H16: =H10-H15 -> 11215.02 | I16: =I10-I15 -> 24359.65 | ... M16: =M10-M15 -> 7332.67 | N16: =B16+C16+D16+E16+F16+G16+H16+I16+J16+K16+L16+M16 -> 209439.32
A17: Expenses
A18: Advertising | B18: 10528.67 | C18: 8399.45 | D18: 10489.99 | E18: 9517.54 | F18: 12295.44 | G18: 10471.82 | H18: 11041.51 | I18: 8400.46 | J18: 7646.38 | K18: 8822.12 | L18: 8185.99 | M18: 6675.39 | N18: =B18+C18+D18+E18+F18+G18+H18+I18+J18+K18+L18+M18 -> 112474.76
A19: Automobile Expense | B19: 134.95 | C19: 34.95 | D19: 34.95 | E19: 34.95 | F19: 41.95 | G19: 34.95 | H19: 34.95 | I19: 34.95 | J19: 168.4 | K19: 34.95 | L19: 260.51 | M19: 34.95 | N19: =B19+C19+D19+E19+F19+G19+H19+I19+J19+K19+L19+M19 -> 885.41
A20: Gas | B20: 390.44 | C20: 78.73 | D20: 655.56 | E20: 412.28 | F20: 222.22 | G20: 77.3 | H20: 488.01 | I20: 285 | J20: 210.07 | K20: 220.48 | L20: 91.58 | M20: 210.47 | N20: =B20+C20+D20+E20+F20+G20+H20+I20+J20+K20+L20+M20 -> 3342.14
A21: Parking | D21: 12 | F21: 31 | H21: 6 | K21: 12 | L21: 69.89 | N21: =B21+C21+D21+E21+F21+G21+H21+I21+J21+K21+L21+M21 -> 130.89
A22: Total for Automobile Expense | B22: =B19+B20+B21 -> 525.39 | C22: =C19+C20+C21 -> 113.68 | D22: =D19+D20+D21 -> 702.51 | E22: =E19+E20+E21 -> 447.23 | F22: =F19+F20+F21 -> 295.17 | G22: =G19+G20+G21 -> 112.25 | H22: =H19+H20+H21 -> 528.96 | I22: =I19+I20+I21 -> 319.95 | ... M22: =M19+M20+M21 -> 245.42 | N22: =B22+C22+D22+E22+F22+G22+H22+I22+J22+K22+L22+M22 -> 4358.44
A23: Bank Fees | B23: 597.22 | C23: 25 | D23: 48.33 | E23: 10.5 | F23: 5.5 | G23: 140.26 | H23: 5 | I23: 12.59 | J23: 3 | K23: 8.5 | L23: 11.5 | M23: 69.43 | N23: =B23+C23+D23+E23+F23+G23+H23+I23+J23+K23+L23+M23 -> 936.83
A24: Computer Expense | B24: 1047.15 | C24: 1047.15 | D24: 1047.15 | E24: 31.5 | F24: 31.5 | G24: 31.5 | H24: 31.5 | I24: 31.5 | J24: 31.5 | K24: 31.5 | L24: 31.5 | M24: 31.5 | N24: =B24+C24+D24+E24+F24+G24+H24+I24+J24+K24+L24+M24 -> 3424.95
A25: Entertainment | B25: 267.58 | C25: 239.57 | D25: 188.91 | E25: 121.6 | F25: 299.43 | G25: 266.44 | H25: 207.92 | I25: 207.3 | J25: 201.16 | K25: 506.11 | L25: 290.82 | M25: 254.35 | N25: =B25+C25+D25+E25+F25+G25+H25+I25+J25+K25+L25+M25 -> 3051.19
A26: Insurance | B26: 289.45 | C26: 289.45 | D26: 289.45 | E26: 289.45 | G26: 751.93 | H26: 190.3 | I26: 211.1 | J26: 195.9 | K26: 195.9 | M26: 212.21 | N26: =B26+C26+D26+E26+F26+G26+H26+I26+J26+K26+L26+M26 -> 2915.14
A27: Legal Fees | G27: -27423.93 | N27: =B27+C27+D27+E27+F27+G27+H27+I27+J27+K27+L27+M27 -> -27423.93
A28: Lodging | H28: 168.96 | I28: 410 | J28: 322.6 | L28: 203.39 | M28: 1602.73 | N28: =B28+C28+D28+E28+F28+G28+H28+I28+J28+K28+L28+M28 -> 2707.68
A29: Meals | B29: 1771.68 | C29: 492.77 | D29: 991.72 | E29: 905.42 | F29: 1701.01 | G29: 272.73 | H29: 1331.02 | I29: 1118.22 | J29: 978.5 | K29: 1180.99 | L29: 3051.54 | M29: 1505.61 | N29: =B29+C29+D29+E29+F29+G29+H29+I29+J29+K29+L29+M29 -> 15301.21
A30: Membership | B30: 315.26 | C30: 76.25 | D30: 129.66 | E30: 52.99 | F30: 670.7 | G30: 576.54 | H30: 128.66 | I30: 109.83 | J30: 153.08 | K30: 172.36 | L30: 447.91 | M30: 362.85 | N30: =B30+C30+D30+E30+F30+G30+H30+I30+J30+K30+L30+M30 -> 3196.09
A31: Merchant Fees | B31: 580.51 | C31: 497.06 | D31: 567.17 | E31: 1530.02 | F31: 1921.19 | G31: 1737.28 | H31: 1734.04 | I31: 1235.65 | J31: 1377.13 | K31: 1635.07 | L31: 1272.28 | M31: 1117.23 | N31: =B31+C31+D31+E31+F31+G31+H31+I31+J31+K31+L31+M31 -> 15204.63
A32: Miscellaneous | B32: 100 | C32: 100 | D32: 217.58 | E32: 74.6 | F32: 295.8 | H32: 322.24 | I32: 33.87 | J32: 71.48 | K32: 1273.99 | L32: 38.39 | M32: 42.18 | N32: =B32+C32+D32+E32+F32+G32+H32+I32+J32+K32+L32+M32 -> 2570.13
A33: Office Expense | B33: 1927.76 | C33: 862.69 | D33: 1223.66 | E33: 1444.2 | F33: 2878.46 | G33: 1415.34 | H33: 2803.85 | I33: 2429.02 | J33: 2922.94 | K33: 3447.64 | L33: 3161.42 | M33: 4844.87 | N33: =B33+C33+D33+E33+F33+G33+H33+I33+J33+K33+L33+M33 -> 29361.85
A34: Other General & Administrative | B34: 150.42 | E34: 27 | F34: 123.46 | G34: 568.55 | L34: 612.18 | M34: 35.33 | N34: =B34+C34+D34+E34+F34+G34+H34+I34+J34+K34+L34+M34 -> 1516.94
A35: Outside Consultants | B35: 6149.92 | C35: 3667.4 | D35: 10485.47 | E35: 6325.84 | F35: 2658.38 | G35: 5163.31 | H35: 7868.78 | I35: 6908.67 | J35: 7011.66 | K35: 5530.32 | L35: 4736.19 | M35: 4406.58 | N35: =B35+C35+D35+E35+F35+G35+H35+I35+J35+K35+L35+M35 -> 70912.52
A36: Postage | B36: 1000 | I36: 100 | L36: 100 | N36: =B36+C36+D36+E36+F36+G36+H36+I36+J36+K36+L36+M36 -> 1200
A37: Purchases | E37: 261.46 | I37: 275.92 | N37: =B37+C37+D37+E37+F37+G37+H37+I37+J37+K37+L37+M37 -> 537.38
A38: Rent | B38: 1150 | C38: 1150 | D38: 1150 | E38: 1150 | F38: 1150 | G38: 1250 | H38: 1150 | I38: 1150 | J38: 1150 | K38: 1150 | L38: 1150 | M38: 1150 | N38: =B38+C38+D38+E38+F38+G38+H38+I38+J38+K38+L38+M38 -> 13900
A39: Travel | B39: 1598.84 | C39: 264.72 | D39: 2564.48 | E39: 846.81 | F39: 970.06 | G39: 608.78 | H39: 1903.07 | I39: 2827.87 | J39: 402.41 | K39: 556.97 | L39: 3140.57 | M39: 1371.96 | N39: =B39+C39+D39+E39+F39+G39+H39+I39+J39+K39+L39+M39 -> 17056.54
A40: Uber | B40: 16.24 | C40: 55.45 | D40: 407.41 | E40: 321.31 | F40: 716.12 | G40: 691.21 | H40: 457.76 | I40: 16.24 | J40: 563.06 | K40: 852.62 | L40: 856.85 | M40: 1081.71 | N40: =B40+C40+D40+E40+F40+G40+H40+I40+J40+K40+L40+M40 -> 6035.98
A41: Total for Expenses | B41: =B18+B22+B23+B24+B25+B26+B27+B28+B29+B30+B31+B32+B33+B34+B35+B36+B37+B38+B39+B40 -> 28016.09 | C41: =C18+C22+C23+C24+C25+C26+C27+C28+C29+C30+C31+C32+C33+C34+C35+C36+C37+C38+C39+C40 -> 17280.64 | D41: =D18+D22+D23+D24+D25+D26+D27+D28+D29+D30+D31+D32+D33+D34+D35+D36+D37+D38+D39+D40 -> 30503.49 | E41: =E18+E22+E23+E24+E25+E26+E27+E28+E29+E30+E31+E32+E33+E34+E35+E36+E37+E38+E39+E40 -> 23357.47 | F41: =F18+F22+F23+F24+F25+F26+F27+F28+F29+F30+F31+F32+F33+F34+F35+F36+F37+F38+F39+F40 -> 26012.22 | G41: =G18+G22+G23+G24+G25+G26+G27+G28+G29+G30+G31+G32+G33+G34+G35+G36+G37+G38+G39+G40 -> -3365.99 | H41: =H18+H22+H23+H24+H25+H26+H27+H28+H29+H30+H31+H32+H33+H34+H35+H36+H37+H38+H39+H40 -> 29873.57 | I41: =I18+I22+I23+I24+I25+I26+I27+I28+I29+I30+I31+I32+I33+I34+I35+I36+I37+I38+I39+I40 -> 25798.19 | ... M41: =M18+M22+M23+M24+M25+M26+M27+M28+M29+M30+M31+M32+M33+M34+M35+M36+M37+M38+M39+M40 -> 25009.35 | N41: =B41+C41+D41+E41+F41+G41+H41+I41+J41+K41+L41+M41 -> 279238.33
A42: Net Operating Income | B42: =B16-B41 -> -6736.46 | C42: =C16-C41 -> 9508.27 | D42: =D16-D41 -> -7727.35 | E42: =E16-E41 -> -369.61 | F42: =F16-F41 -> -15854.48 | G42: =G16-G41 -> 19808.18 | H42: =H16-H41 -> -18658.55 | I42: =I16-I41 -> -1438.54 | ... M42: =M16-M41 -> -17676.68 | N42: =B42+C42+D42+E42+F42+G42+H42+I42+J42+K42+L42+M42 -> -69799.01
A43: Net Other Income
A44: Net Income | B44: -6736.46 | C44: 9508.27 | D44: -7727.35 | E44: -369.61 | F44: -15854.48 | G44: 19808.18 | H44: -18658.55 | I44: -1438.54 | J44: -9137.64 | K44: -11885.74 | L44: -9630.41 | M44: -17676.68 | N44: =B44+C44+D44+E44+F44+G44+H44+I44+J44+K44+L44+M44 -> -69799.01
A48: Cash Basis Friday, December 19, 2025 11:49 PM GMT+05:00

Sheet P&L 2024
A1: Profit and Loss
A2: CONDITION ONE NUTRITION
A3: January-December, 2024
A5: Distribution account | B5: January 2024 | C5: February 2024 | D5: March 2024 | E5: April 2024 | F5: May 2024 | G5: June 2024 | H5: July 2024 | I5: August 2024 | J5: September 2024 | K5: October 2024 | L5: November 2024 | M5: December 2024 | N5: Total
A6: Income
A7: ECOMM PayPal Sales | B7: 6531.2 | C7: 7665.3 | D7: 12243.7 | E7: 10368.2 | F7: 10717.1 | G7: 10363.3 | H7: 13924.5 | I7: 12899.7 | J7: 12099.13 | K7: 9860.72 | L7: 14666.64 | M7: 7736.37 | N7: =B7+C7+D7+E7+F7+G7+H7+I7+J7+K7+L7+M7 -> 129075.86
A8: ECOMM Shopify Sales | B8: 36475.75 | C8: 33157.12 | D8: 50289.19 | E8: 59130.24 | F8: 61029.36 | G8: 50245.98 | H8: 76604.43 | I8: 101727.59 | J8: 74239.13 | K8: 94252.6 | L8: 89715.51 | M8: 78334.59 | N8: =B8+C8+D8+E8+F8+G8+H8+I8+J8+K8+L8+M8 -> 805201.49
A9: ECOMM Stripe Sales | B9: 6044.39 | C9: 5859.82 | D9: 6172.42 | E9: 6268.65 | F9: 6478.62 | G9: 7302.77 | H9: 6180.55 | I9: 7171.18 | J9: 7755.7 | K9: 6276.58 | L9: 9566.41 | M9: 4870.29 | N9: =B9+C9+D9+E9+F9+G9+H9+I9+J9+K9+L9+M9 -> 79947.38
A10: Total for Income | B10: =B7+B8+B9 -> 49051.34 | C10: =C7+C8+C9 -> 46682.24 | D10: =D7+D8+D9 -> 68705.31 | E10: =E7+E8+E9 -> 75767.09 | F10: =F7+F8+F9 -> 78225.08 | G10: =G7+G8+G9 -> 67912.05 | H10: =H7+H8+H9 -> 96709.48 | I10: =I7+I8+I9 -> 121798.47 | ... M10: =M7+M8+M9 -> 90941.25 | N10: =B10+C10+D10+E10+F10+G10+H10+I10+J10+K10+L10+M10 -> 1014224.7 | P10: =SUM(K10:M10) -> 315279.71
A11: Cost of Goods Sold
A12: Cost of Goods Sold | B12: 10599.06 | C12: 7570.31 | D12: 16788.95 | E12: 5196.38 | F12: 26828.8 | G12: 12294.59 | H12: 17129.39 | I12: 14817.35 | J12: 15713.13 | K12: 14554.12 | L12: 15101.89 | M12: 20698.3 | N12: =B12+C12+D12+E12+F12+G12+H12+I12+J12+K12+L12+M12 -> 177292.27
A13: Cost of labor - COS | B13: 6679.55 | C13: 14791.25 | D13: 14931.31 | E13: 26319.79 | F13: 29678.04 | G13: 9649.56 | H13: 21267.59 | I13: 41625 | J13: 38381.12 | K13: 38231.7 | L13: 22542.15 | M13: 16518.02 | N13: =B13+C13+D13+E13+F13+G13+H13+I13+J13+K13+L13+M13 -> 280615.08
A14: Freight & Delivery | B14: 9855.79 | C14: 9195.52 | D14: 14967.36 | E14: 16673.67 | F14: 13933.27 | G14: 14902.22 | H14: 20371.57 | I14: 29760.77 | J14: 17575.42 | K14: 26315.55 | L14: 19544.48 | M14: 21776.65 | N14: =B14+C14+D14+E14+F14+G14+H14+I14+J14+K14+L14+M14 -> 214872.27
A15: Supplies | B15: 693.11 | C15: 6539.95 | D15: 1589.12 | E15: 6329.32 | F15: 1692.47 | G15: 1341.67 | H15: 6822.47 | J15: 2558.24 | N15: =B15+C15+D15+E15+F15+G15+H15+I15+J15+K15+L15+M15 -> 27566.35
A16: Total for Cost of Goods Sold | B16: =B12+B13+B14+B15 -> 27827.51 | C16: =C12+C13+C14+C15 -> 38097.03 | D16: =D12+D13+D14+D15 -> 48276.74 | E16: =E12+E13+E14+E15 -> 54519.16 | F16: =F12+F13+F14+F15 -> 72132.58 | G16: =G12+G13+G14+G15 -> 38188.04 | H16: =H12+H13+H14+H15 -> 65591.02 | I16: =I12+I13+I14+I15 -> 86203.12 | ... M16: =M12+M13+M14+M15 -> 58992.97 | N16: =B16+C16+D16+E16+F16+G16+H16+I16+J16+K16+L16+M16 -> 700345.97
A17: Gross Profit | B17: =B10-B16 -> 21223.83 | C17: =C10-C16 -> 8585.21 | D17: =D10-D16 -> 20428.57 | E17: =E10-E16 -> 21247.93 | F17: =F10-F16 -> 6092.5 | G17: =G10-G16 -> 29724.01 | H17: =H10-H16 -> 31118.46 | I17: =I10-I16 -> 35595.35 | ... M17: =M10-M16 -> 31948.28 | N17: =B17+C17+D17+E17+F17+G17+H17+I17+J17+K17+L17+M17 -> 313878.76
A18: Expenses
A19: Advertising | B19: 8551.71 | C19: 14213.97 | D19: 26013.99 | E19: 27214.61 | F19: 18271.27 | G19: 21703.28 | H19: 33654.05 | I19: 26668.44 | J19: 16603.84 | K19: 15276.9 | L19: 16349.7 | M19: 17291.14 | N19: =B19+C19+D19+E19+F19+G19+H19+I19+J19+K19+L19+M19 -> 241812.9
A20: Automobile Expense | B20: 732.81 | C20: 109.94 | D20: 384.2 | E20: 225.41 | F20: 53.45 | G20: 65.95 | H20: 115.45 | I20: 34.95 | K20: 213.14 | L20: 326.37 | M20: 169.61 | N20: =B20+C20+D20+E20+F20+G20+H20+I20+J20+K20+L20+M20 -> 2431.28
A21: Gas | B21: 514.89 | C21: 300.52 | D21: 310.97 | E21: 247.49 | F21: 483.32 | G21: 376.6 | H21: 274.22 | I21: 149.86 | J21: 111.08 | K21: 788 | L21: 489.56 | M21: 332.13 | N21: =B21+C21+D21+E21+F21+G21+H21+I21+J21+K21+L21+M21 -> 4378.64
A22: Parking | B22: 46 | C22: 15 | D22: 42.05 | F22: 90.42 | G22: 10 | H22: 18 | J22: 10.99 | K22: 18.5 | L22: 40.99 | M22: 130.11 | N22: =B22+C22+D22+E22+F22+G22+H22+I22+J22+K22+L22+M22 -> 422.06
A23: Total for Automobile Expense | B23: =B20+B21+B22 -> 1293.7 | C23: =C20+C21+C22 -> 425.46 | D23: =D20+D21+D22 -> 737.22 | E23: =E20+E21+E22 -> 472.9 | F23: =F20+F21+F22 -> 627.19 | G23: =G20+G21+G22 -> 452.55 | H23: =H20+H21+H22 -> 407.67 | I23: =I20+I21+I22 -> 184.81 | ... M23: =M20+M21+M22 -> 631.85 | N23: =B23+C23+D23+E23+F23+G23+H23+I23+J23+K23+L23+M23 -> 7231.98
A24: Bank Fees | B24: 120.75 | C24: 78 | D24: 129 | E24: 800 | F24: 189.41 | G24: 270.47 | H24: 190.31 | I24: 125.85 | J24: 298.33 | K24: 542.02 | L24: 541.14 | M24: 351.37 | N24: =B24+C24+D24+E24+F24+G24+H24+I24+J24+K24+L24+M24 -> 3636.65
A25: Computer Expense | H25: 446.44 | M25: 1097.1 | N25: =B25+C25+D25+E25+F25+G25+H25+I25+J25+K25+L25+M25 -> 1543.54
A26: Entertainment | B26: 97.75 | C26: 455.06 | D26: 574.93 | E26: 538.71 | F26: 825 | G26: 451.6 | H26: 558.61 | I26: 291.63 | J26: 596.26 | K26: 320.45 | L26: 502.23 | M26: 912.17 | N26: =B26+C26+D26+E26+F26+G26+H26+I26+J26+K26+L26+M26 -> 6124.4
A27: Insurance | B27: 197.16 | C27: 197.16 | D27: 197.16 | E27: 197.16 | F27: 197.15 | G27: 212.21 | H27: 197.16 | I27: 197.16 | J27: 197.16 | K27: 197.16 | L27: 197.15 | M27: 225.21 | N27: =B27+C27+D27+E27+F27+G27+H27+I27+J27+K27+L27+M27 -> 2409
A28: Interest Expense | F28: 872.73 | N28: =B28+C28+D28+E28+F28+G28+H28+I28+J28+K28+L28+M28 -> 872.73
A29: Legal Fees | B29: 314.56 | C29: 2475.55 | D29: 567.89 | E29: 300.64 | F29: 2000 | J29: 302.42 | L29: 6878.91 | M29: 1350 | N29: =B29+C29+D29+E29+F29+G29+H29+I29+J29+K29+L29+M29 -> 14189.97
A30: Lodging | B30: 726.32 | E30: 778.51 | G30: 271.43 | J30: 1842.41 | K30: 1974.51 | L30: 220.13 | M30: 351.82 | N30: =B30+C30+D30+E30+F30+G30+H30+I30+J30+K30+L30+M30 -> 6165.13
A31: Meals | B31: 1316.46 | C31: 2111.18 | D31: 2247.95 | E31: 3053.35 | F31: 2640.27 | G31: 2741.4 | H31: 2212.51 | I31: 1678.79 | J31: 2044.36 | K31: 3038.47 | L31: 3004.16 | M31: 2681.32 | N31: =B31+C31+D31+E31+F31+G31+H31+I31+J31+K31+L31+M31 -> 28770.22
A32: Medical | C32: 7.29 | E32: 24.48 | F32: 131.03 | G32: 154.29 | I32: 49.41 | J32: 16.73 | K32: 74.39 | L32: 8.04 | N32: =B32+C32+D32+E32+F32+G32+H32+I32+J32+K32+L32+M32 -> 465.66
A33: Membership | B33: 634.31 | C33: 353.7 | D33: 357.24 | E33: 424.82 | F33: 544.24 | G33: 341.99 | H33: 581.28 | I33: 567.18 | J33: 445.66 | K33: 617.26 | L33: 376.41 | M33: 443.67 | N33: =B33+C33+D33+E33+F33+G33+H33+I33+J33+K33+L33+M33 -> 5687.76
A34: Merchant Fees | B34: 266.44 | C34: 232.57 | D34: 259.77 | E34: 256.63 | F34: 235.82 | G34: 273.39 | H34: 259.79 | I34: 272.16 | J34: 657.61 | K34: 246.13 | L34: 225.76 | M34: 279.44 | N34: =B34+C34+D34+E34+F34+G34+H34+I34+J34+K34+L34+M34 -> 3465.51
A35: Miscellaneous | C35: 1398.52 | D35: 484.94 | F35: 257.94 | G35: 640.89 | I35: 85 | K35: 732.8 | L35: 28 | M35: 284.64 | N35: =B35+C35+D35+E35+F35+G35+H35+I35+J35+K35+L35+M35 -> 3912.73
A36: Office Expense | B36: 5292.03 | C36: 1602.12 | D36: 3917.07 | E36: 7906.62 | F36: 5206.57 | G36: 3742.68 | H36: 3715.91 | I36: 4619.77 | J36: 3863.51 | K36: 5555.69 | L36: 3426.34 | M36: 2695.48 | N36: =B36+C36+D36+E36+F36+G36+H36+I36+J36+K36+L36+M36 -> 51543.79
A37: Other General & Administrative | B37: 1160.25 | C37: 1131.89 | D37: 611.29 | E37: 760.89 | F37: 810.65 | G37: 1009.51 | H37: 1058.38 | I37: 547.84 | J37: 804.93 | K37: 765.08 | L37: 785.61 | M37: 388.41 | N37: =B37+C37+D37+E37+F37+G37+H37+I37+J37+K37+L37+M37 -> 9834.73
A38: Outside Consultants | B38: 12806.9 | C38: 11616.82 | D38: 14175.45 | E38: 14118.97 | F38: 15500.81 | G38: 11481.87 | H38: 14564.08 | I38: 14855.07 | J38: 13306.16 | K38: 12193.87 | L38: 9452.45 | M38: 6462.6 | N38: =B38+C38+D38+E38+F38+G38+H38+I38+J38+K38+L38+M38 -> 150535.05
A39: Prime Video | B39: 129.17 | C39: 62.94 | D39: 62.94 | E39: 62.94 | F39: 62.94 | G39: 62.94 | H39: 88.8 | I39: 51.24 | J39: 67.43 | K39: 31.26 | L39: 151.71 | M39: 126.86 | N39: =B39+C39+D39+E39+F39+G39+H39+I39+J39+K39+L39+M39 -> 961.17
A40: Rent | B40: 1150 | C40: 1150 | D40: 1150 | E40: 1150 | F40: 1300 | G40: 1300 | H40: 1300 | I40: 1400 | J40: 1300 | K40: 1300 | L40: 1300 | M40: 1300 | N40: =B40+C40+D40+E40+F40+G40+H40+I40+J40+K40+L40+M40 -> 15100
A41: Software & Apps | B41: 319.92 | C41: 317.81 | D41: 317.81 | E41: 317.81 | F41: 317.81 | G41: 299.81 | H41: 317.81 | I41: 65.18 | J41: 320.81 | K41: 86.18 | L41: 320.81 | M41: 350.8 | N41: =B41+C41+D41+E41+F41+G41+H41+I41+J41+K41+L41+M41 -> 3352.56
A42: Travel | B42: 604.53 | C42: 1116.99 | D42: 882.81 | E42: 543.11 | F42: 423.2 | G42: 28.75 | H42: 224.1 | I42: 581.1 | J42: 514.83 | K42: 801.88 | L42: 196.96 | M42: 2927.62 | N42: =B42+C42+D42+E42+F42+G42+H42+I42+J42+K42+L42+M42 -> 8845.88
A43: Uber | B43: 655.72 | D43: 556.85 | F43: 445.24 | I43: 693.14 | J43: 139.04 | K43: 429 | L43: 335.66 | M43: 1567.99 | N43: =B43+C43+D43+E43+F43+G43+H43+I43+J43+K43+L43+M43 -> 4822.64
A44: Uncategorized Expenses | J44: 5000 | L44: -5000 | N44: =B44+C44+D44+E44+F44+G44+H44+I44+J44+K44+L44+M44 -> 0
A45: Total for Expenses | B45: =B19+B23+B24+B25+B26+B27+B28+B29+B30+B31+B32+B33+B34+B35+B36+B37+B38+B39+B40+B41+B42+B43+B44 -> 35637.68 | C45: =C19+C23+C24+C25+C26+C27+C28+C29+C30+C31+C32+C33+C34+C35+C36+C37+C38+C39+C40+C41+C42+C43+C44 -> 38947.03 | D45: =D19+D23+D24+D25+D26+D27+D28+D29+D30+D31+D32+D33+D34+D35+D36+D37+D38+D39+D40+D41+D42+D43+D44 -> 53244.31 | E45: =E19+E23+E24+E25+E26+E27+E28+E29+E30+E31+E32+E33+E34+E35+E36+E37+E38+E39+E40+E41+E42+E43+E44 -> 58922.15 | F45: =F19+F23+F24+F25+F26+F27+F28+F29+F30+F31+F32+F33+F34+F35+F36+F37+F38+F39+F40+F41+F42+F43+F44 -> 50859.27 | G45: =G19+G23+G24+G25+G26+G27+G28+G29+G30+G31+G32+G33+G34+G35+G36+G37+G38+G39+G40+G41+G42+G43+G44 -> 45439.06 | H45: =H19+H23+H24+H25+H26+H27+H28+H29+H30+H31+H32+H33+H34+H35+H36+H37+H38+H39+H40+H41+H42+H43+H44 -> 59776.9 | I45: =I19+I23+I24+I25+I26+I27+I28+I29+I30+I31+I32+I33+I34+I35+I36+I37+I38+I39+I40+I41+I42+I43+I44 -> 52933.77 | ... M45: =M19+M23+M24+M25+M26+M27+M28+M29+M30+M31+M32+M33+M34+M35+M36+M37+M38+M39+M40+M41+M42+M43+M44 -> 41719.49 | N45: =B45+C45+D45+E45+F45+G45+H45+I45+J45+K45+L45+M45 -> 571284
A46: Net Operating Income | B46: =B17-B45 -> -14413.85 | C46: =C17-C45 -> -30361.82 | D46: =D17-D45 -> -32815.74 | E46: =E17-E45 -> -37674.22 | F46: =F17-F45 -> -44766.77 | G46: =G17-G45 -> -15715.05 | H46: =H17-H45 -> -28658.44 | I46: =I17-I45 -> -17338.42 | ... M46: =M17-M45 -> -9771.21 | N46: =B46+C46+D46+E46+F46+G46+H46+I46+J46+K46+L46+M46 -> -257405.24
A47: Other Expenses
A48: Other Miscellaneous Expense | E48: 586.99 | F48: 459.5 | J48: 201.8 | N48: =B48+C48+D48+E48+F48+G48+H48+I48+J48+K48+L48+M48 -> 1248.29
A49: Total for Other Expenses | E49: =E48 -> 586.99 | F49: =F48 -> 459.5 | J49: =J48 -> 201.8 | N49: =B49+C49+D49+E49+F49+G49+H49+I49+J49+K49+L49+M49 -> 1248.29
A50: Net Other Income | E50: -586.99 | F50: -459.5 | J50: -201.8 | N50: =B50+C50+D50+E50+F50+G50+H50+I50+J50+K50+L50+M50 -> -1248.29
A51: Net Income | B51: -14413.85 | C51: -30361.82 | D51: -32815.74 | E51: -38261.21 | F51: -45226.27 | G51: -15715.05 | H51: -28658.44 | I51: -17338.42 | J51: -28779.31 | K51: -13914.16 | L51: 16601.95 | M51: -9771.21 | N51: -258653.53
A55: Cash Basis Friday, December 19, 2025 11:48 PM GMT+05:00

Sheet P&L 2025
A1: Profit and Loss
A2: CONDITION ONE NUTRITION
A3: January-September, 2025
A5: Distribution account | B5: January 2025 | C5: February 2025 | D5: March 2025 | E5: April 2025 | F5: May 2025 | G5: June 2025 | H5: July 2025 | I5: August 2025 | J5: September 2025 | K5: Total
A6: Income
A7: ECOMM PayPal Sales | B7: 9846.19 | C7: 8222.59 | D7: 10931.57 | E7: 7336.88 | F7: 8746.5 | G7: 6475.07 | H7: 31376.34 | I7: 8500.4 | J7: 3691.54 | K7: =B7+C7+D7+E7+F7+G7+H7+I7+J7 -> 95127.08
A8: ECOMM Shopify Sales | B8: 78228.28 | C8: 84622.71 | D8: 85481.54 | E8: 93550.18 | F8: 90910.6 | G8: 77453.01 | H8: 81559.75 | I8: 83637.63 | J8: 77933.06 | K8: =B8+C8+D8+E8+F8+G8+H8+I8+J8 -> 753376.76
A9: ECOMM Stripe Sales | B9: 5089.66 | C9: 4564.74 | D9: 4753.17 | E9: 4315.47 | F9: 4825.21 | G9: 3739 | H9: 5864.1 | I9: 4395.99 | J9: 4902.3 | K9: =B9+C9+D9+E9+F9+G9+H9+I9+J9 -> 42449.64
A10: other income | J10: 88312.98 | K10: =B10+C10+D10+E10+F10+G10+H10+I10+J10 -> 88312.98
A11: Sales of Product Income | D11: 1000 | I11: 1887.12 | K11: =B11+C11+D11+E11+F11+G11+H11+I11+J11 -> 2887.12
A12: Sales Tax | J12: -175 | K12: =B12+C12+D12+E12+F12+G12+H12+I12+J12 -> -175
A13: Total for Income | B13: =B7+B8+B9+B10+B11+B12 -> 93164.13 | C13: =C7+C8+C9+C10+C11+C12 -> 97410.04 | D13: =D7+D8+D9+D10+D11+D12 -> 102166.28 | E13: =E7+E8+E9+E10+E11+E12 -> 105202.53 | F13: =F7+F8+F9+F10+F11+F12 -> 104482.31 | G13: =G7+G8+G9+G10+G11+G12 -> 87667.08 | H13: =H7+H8+H9+H10+H11+H12 -> 118800.19 | I13: =I7+I8+I9+I10+I11+I12 -> 98421.14 | J13: =J7+J8+J9+J10+J11+J12 -> 174664.88 | K13: =B13+C13+D13+E13+F13+G13+H13+I13+J13 -> 981978.58 | M13: 315279.71
A14: Cost of Goods Sold | M14: =K13+M13 -> 1297258.3
A15: Cost of Goods Sold | B15: 55595.51 | C15: 19437.42 | D15: 35862.31 | E15: 10195 | F15: 3190.72 | G15: 20272.18 | H15: 23157.25 | I15: 36491.43 | J15: 14859.42 | K15: =B15+C15+D15+E15+F15+G15+H15+I15+J15 -> 219061.24 | M15: 1297258.3
A16: Cost of labor - COS | B16: 13643.19 | C16: 21253.38 | D16: 18362.06 | E16: 24565.16 | F16: 25264.22 | G16: 36343.86 | H16: 35746.97 | I16: 20412.24 | J16: 33044.81 | K16: =B16+C16+D16+E16+F16+G16+H16+I16+J16 -> 228635.89
A17: Freight & Delivery | B17: 20956.85 | C17: 17755.68 | D17: 21502.45 | E17: 21331.07 | F17: 20822.5 | G17: 17028.05 | H17: 20249.71 | I17: 18782.91 | J17: 16814.76 | K17: =B17+C17+D17+E17+F17+G17+H17+I17+J17 -> 175243.98
A18: Total for Cost of Goods Sold | B18: =B15+B16+B17 -> 90195.55 | C18: =C15+C16+C17 -> 58446.48 | D18: =D15+D16+D17 -> 75726.82 | E18: =E15+E16+E17 -> 56091.23 | F18: =F15+F16+F17 -> 49277.44 | G18: =G15+G16+G17 -> 73644.09 | H18: =H15+H16+H17 -> 79153.93 | I18: =I15+I16+I17 -> 75686.58 | J18: =J15+J16+J17 -> 64718.99 | K18: =B18+C18+D18+E18+F18+G18+H18+I18+J18 -> 622941.11
A19: Gross Profit | B19: =B13-B18 -> 2968.58 | C19: =C13-C18 -> 38963.56 | D19: =D13-D18 -> 26439.46 | E19: =E13-E18 -> 49111.3 | F19: =F13-F18 -> 55204.87 | G19: =G13-G18 -> 14022.99 | H19: =H13-H18 -> 39646.26 | I19: =I13-I18 -> 22734.56 | J19: =J13-J18 -> 109945.89 | K19: =B19+C19+D19+E19+F19+G19+H19+I19+J19 -> 359037.47
A20: Expenses
A21: Advertising | B21: 3391.24 | C21: 3474.67 | D21: 3388.02 | E21: 3329.16 | F21: 3324.67 | G21: 3419.34 | H21: 3403.39 | I21: 3332.2 | J21: 2185.4 | K21: =B21+C21+D21+E21+F21+G21+H21+I21+J21 -> 29248.09
A22: Automobile Expense | B22: 333.27 | C22: 312.4 | D22: 2940.77 | E22: 198.16 | F22: 828.98 | G22: 925.81 | H22: 448.37 | I22: 70.98 | J22: 53.21 | K22: =B22+C22+D22+E22+F22+G22+H22+I22+J22 -> 6111.95
A23: Gas | B23: 145.76 | C23: 228.77 | D23: 44.8 | E23: 47.56 | F23: 57.73 | G23: 90.03 | H23: 154.73 | I23: 117.8 | J23: 143.64 | K23: =B23+C23+D23+E23+F23+G23+H23+I23+J23 -> 1030.82
A24: Parking | F24: 32.95 | G24: 5.55 | H24: 5.5 | I24: 54.9 | J24: 24.11 | K24: =B24+C24+D24+E24+F24+G24+H24+I24+J24 -> 123.01
A25: Total for Automobile Expense | B25: =B22+B23+B24 -> 479.03 | C25: =C22+C23+C24 -> 541.17 | D25: =D22+D23+D24 -> 2985.57 | E25: =E22+E23+E24 -> 245.72 | F25: =F22+F23+F24 -> 919.66 | G25: =G22+G23+G24 -> 1021.39 | H25: =H22+H23+H24 -> 608.6 | I25: =I22+I23+I24 -> 243.68 | J25: =J22+J23+J24 -> 220.96 | K25: =B25+C25+D25+E25+F25+G25+H25+I25+J25 -> 7265.78
A26: Bank Fees | B26: 350.51 | C26: 468.04 | D26: 34.34 | E26: 167.61 | F26: 132.5 | G26: 81 | H26: 123.5 | I26: 110.48 | J26: 164.79 | K26: =B26+C26+D26+E26+F26+G26+H26+I26+J26 -> 1632.77
A27: Charitable & Donations | B27: 100 | F27: 500 | K27: =B27+C27+D27+E27+F27+G27+H27+I27+J27 -> 600
A28: Computer Expense | B28: 1242.25 | C28: 1215.1 | D28: 1323.73 | K28: =B28+C28+D28+E28+F28+G28+H28+I28+J28 -> 3781.08
A29: Dues & Subscriptions | E29: 2926.52 | F29: 2930.88 | G29: 3060.02 | H29: 3460.53 | I29: 6263.39 | J29: 9870.73 | K29: =B29+C29+D29+E29+F29+G29+H29+I29+J29 -> 28512.07
A30: Entertainment | B30: 861.91 | C30: 1003.35 | D30: 794.78 | E30: 1849.72 | F30: 1259.74 | G30: 1258.36 | H30: 2105.3 | I30: -108.44 | J30: 576.72 | K30: =B30+C30+D30+E30+F30+G30+H30+I30+J30 -> 9601.44
A31: Insurance | B31: 210.16 | C31: 210.16 | D31: 210.16 | E31: 210.16 | F31: 210.15 | G31: 225.21 | H31: 459.16 | I31: 210.16 | J31: 210.16 | K31: =B31+C31+D31+E31+F31+G31+H31+I31+J31 -> 2155.48
A32: Interest Expense | F32: 113.63 | G32: 111.54 | H32: 103.77 | I32: 86.92 | J32: 109.89 | K32: =B32+C32+D32+E32+F32+G32+H32+I32+J32 -> 525.75
A33: Legal Fees | B33: 350 | C33: 2935 | D33: 2154.36 | E33: 1725 | F33: 1963.01 | H33: 0 | I33: 1485 | J33: 1382.5 | K33: =B33+C33+D33+E33+F33+G33+H33+I33+J33 -> 11994.87
A34: Lodging | C34: 996.81 | D34: 214.52 | F34: 329.98 | G34: 749.34 | H34: 883.99 | J34: 416.59 | K34: =B34+C34+D34+E34+F34+G34+H34+I34+J34 -> 3591.23
A35: Marketing | B35: 12527.64 | C35: 11451.74 | D35: 13331.05 | E35: 12428.63 | F35: 12634.9 | G35: 13097.47 | H35: 13495.17 | I35: 10945.97 | J35: 8610.89 | K35: =B35+C35+D35+E35+F35+G35+H35+I35+J35 -> 108523.46
A36: Meals | B36: 1557.66 | C36: 2154.85 | D36: 2264.46 | E36: 4565.74 | F36: 3101.83 | G36: 2601.58 | H36: 3463.33 | I36: 3155.15 | J36: 1852.36 | K36: =B36+C36+D36+E36+F36+G36+H36+I36+J36 -> 24716.96
A37: Medical | B37: 230.18 | C37: 1068.82 | D37: 200.15 | E37: 65 | F37: 54.48 | H37: 2543.15 | K37: =B37+C37+D37+E37+F37+G37+H37+I37+J37 -> 4161.78
A38: Membership | B38: 242.7 | C38: 117.52 | D38: 679.64 | E38: 1254 | F38: 247.75 | G38: 353.53 | H38: 735.43 | I38: 635 | J38: 257.74 | K38: =B38+C38+D38+E38+F38+G38+H38+I38+J38 -> 4523.31
A39: Merchant Fees | B39: 189.4 | C39: 179.53 | D39: 184.93 | E39: 267.13 | F39: 177.15 | G39: 136.4 | H39: 191.07 | K39: =B39+C39+D39+E39+F39+G39+H39+I39+J39 -> 1325.61
A40: Stripe Fee | D40: 15.06 | E40: 19.54 | F40: 37.29 | G40: 36.55 | H40: 164.98 | I40: 264.79 | J40: 162.29 | K40: =B40+C40+D40+E40+F40+G40+H40+I40+J40 -> 700.5
A41: Total for Merchant Fees | B41: =B39+B40 -> 189.4 | C41: =C39+C40 -> 179.53 | D41: =D39+D40 -> 199.99 | E41: =E39+E40 -> 286.67 | F41: =F39+F40 -> 214.44 | G41: =G39+G40 -> 172.95 | H41: =H39+H40 -> 356.05 | I41: =I39+I40 -> 264.79 | J41: =J39+J40 -> 162.29 | K41: =B41+C41+D41+E41+F41+G41+H41+I41+J41 -> 2026.11
A42: Miscellaneous | B42: 56 | C42: 295.84 | D42: 769.98 | E42: 628.56 | F42: 613.72 | G42: 418.44 | H42: 1140.62 | I42: 1468.45 | J42: 115.3 | K42: =B42+C42+D42+E42+F42+G42+H42+I42+J42 -> 5506.91 | L42: =K42 -> 5506.91
A43: Office Expense | B43: 3523.13 | C43: 2438.47 | D43: 2519.05 | E43: 3643.93 | F43: 3369.71 | G43: 4938.32 | H43: 6234.16 | I43: 4888.79 | J43: 4205.66 | K43: =B43+C43+D43+E43+F43+G43+H43+I43+J43 -> 35761.22 | L43: =K43 -> 35761.22
A44: Other General & Administrative | B44: 464 | C44: 464 | D44: 464 | E44: 500.97 | F44: 301.59 | G44: 965.29 | H44: 2595.51 | I44: 1518.24 | J44: 678.5 | K44: =B44+C44+D44+E44+F44+G44+H44+I44+J44 -> 7952.1
A45: Outside Consultants | B45: 13666.26 | C45: 9018.1 | D45: 5506.33 | E45: 6100.09 | F45: 11181.38 | G45: 8575.8 | H45: 12746.79 | I45: 6337.01 | J45: 4807 | K45: =B45+C45+D45+E45+F45+G45+H45+I45+J45 -> 77938.76
A46: Paypal fees | D46: 381 | E46: 321.22 | F46: 472.16 | G46: 354.41 | H46: 285.27 | I46: 397.62 | J46: 193.92 | K46: =B46+C46+D46+E46+F46+G46+H46+I46+J46 -> 2405.6
A47: Postage | D47: 142.52 | K47: =B47+C47+D47+E47+F47+G47+H47+I47+J47 -> 142.52
A48: Prime Video | B48: 62.95 | C48: 119.96 | D48: 98.19 | K48: =B48+C48+D48+E48+F48+G48+H48+I48+J48 -> 281.1 | L48: =K48 -> 281.1
A49: Professional Fees | E49: 1209 | F49: 1375 | G49: 1375 | H49: 1375 | I49: 766.97 | J49: 129.95 | K49: =B49+C49+D49+E49+F49+G49+H49+I49+J49 -> 6230.92
A50: Rent | B50: 1300 | C50: 1300 | D50: 1300 | E50: 1500 | F50: 1300 | G50: 1300 | H50: 1300 | I50: 1300 | J50: 1300 | K50: =B50+C50+D50+E50+F50+G50+H50+I50+J50 -> 11900
A51: Software & Apps | B51: 165.66 | C51: 372.51 | D51: 3353.51 | K51: =B51+C51+D51+E51+F51+G51+H51+I51+J51 -> 3891.68
A52: Travel | B52: 3267.84 | C52: 4615.43 | D52: 2493.36 | E52: 3868.78 | F52: 3055.06 | G52: 1187.77 | H52: 2990.1 | I52: 3637.23 | J52: 4311.06 | K52: =B52+C52+D52+E52+F52+G52+H52+I52+J52 -> 29426.63 | L52: =K52 -> 29426.63
A53: Uber | D53: 2015 | K53: =B53+C53+D53+E53+F53+G53+H53+I53+J53 -> 2015 | L53: =K53 -> 2015
A54: Total for Expenses | B54: =B21+B25+B26+B27+B28+B29+B30+B31+B32+B33+B34+B35+B36+B37+B38+B41+B42+B43+B44+B45+B46+B47+B48+B49+B50+B51+B52+B53 -> 44238.52 | C54: =C21+C25+C26+C27+C28+C29+C30+C31+C32+C33+C34+C35+C36+C37+C38+C41+C42+C43+C44+C45+C46+C47+C48+C49+C50+C51+C52+C53 -> 44441.07 | D54: =D21+D25+D26+D27+D28+D29+D30+D31+D32+D33+D34+D35+D36+D37+D38+D41+D42+D43+D44+D45+D46+D47+D48+D49+D50+D51+D52+D53 -> 46823.71 | E54: =E21+E25+E26+E27+E28+E29+E30+E31+E32+E33+E34+E35+E36+E37+E38+E41+E42+E43+E44+E45+E46+E47+E48+E49+E50+E51+E52+E53 -> 46826.48 | F54: =F21+F25+F26+F27+F28+F29+F30+F31+F32+F33+F34+F35+F36+F37+F38+F41+F42+F43+F44+F45+F46+F47+F48+F49+F50+F51+F52+F53 -> 49606.24 | G54: =G21+G25+G26+G27+G28+G29+G30+G31+G32+G33+G34+G35+G36+G37+G38+G41+G42+G43+G44+G45+G46+G47+G48+G49+G50+G51+G52+G53 -> 45266.76 | H54: =H21+H25+H26+H27+H28+H29+H30+H31+H32+H33+H34+H35+H36+H37+H38+H41+H42+H43+H44+H45+H46+H47+H48+H49+H50+H51+H52+H53 -> 60408.82 | I54: =I21+I25+I26+I27+I28+I29+I30+I31+I32+I33+I34+I35+I36+I37+I38+I41+I42+I43+I44+I45+I46+I47+I48+I49+I50+I51+I52+I53 -> 46938.61 | J54: =J21+J25+J26+J27+J28+J29+J30+J31+J32+J33+J34+J35+J36+J37+J38+J41+J42+J43+J44+J45+J46+J47+J48+J49+J50+J51+J52+J53 -> 41762.41 | K54: =B54+C54+D54+E54+F54+G54+H54+I54+J54 -> 426312.62 | L54: =SUM(L42:L53) -> 72990.86 | M54: =L54/K54 -> 0.1712144
A55: Net Operating Income | B55: =B19-B54 -> -41269.94 | C55: =C19-C54 -> -5477.51 | D55: =D19-D54 -> -20384.25 | E55: =E19-E54 -> 2284.82 | F55: =F19-F54 -> 5598.63 | G55: =G19-G54 -> -31243.77 | H55: =H19-H54 -> -20762.56 | I55: =I19-I54 -> -24204.05 | J55: =J19-J54 -> 68183.48 | K55: =B55+C55+D55+E55+F55+G55+H55+I55+J55 -> -67275.15
A56: Net Other Income
A57: Net Income | B57: -41269.94 | C57: -5477.51 | D57: -20384.25 | E57: 2284.82 | F57: 5598.63 | G57: -31243.77 | H57: -20762.56 | I57: -24204.05 | J57: 68183.48 | K57: =B57+C57+D57+E57+F57+G57+H57+I57+J57 -> -67275.15
A61: Cash Basis Saturday, December 20, 2025 12:10 AM GMT+05:00

Sheet Forecast P&L 2026 1
A2: Projection for the year 2026 (Conservative)
A3: Distribution account | B3: 46023 | C3: 46054 | D3: 46082 | E3: 46113 | F3: 46143 | G3: 46174 | H3: 46204 | I3: 46235 | J3: 46266 | K3: 46296 | L3: 46327 | M3: 46357 | N3: Total
A4: Income
A5: ECOMM PayPal Sales | B5: 13575.9 | C5: 14161.3 | D5: 16279.6 | E5: 11816.7 | F5: 12651.6 | G5: 13008 | H5: 23490.5 | I5: 11091.1 | J5: 8654.4 | K5: 10333.8 | L5: 14941.2 | M5: 10005 | N5: =SUM(B5:M5) -> 160009.1
A6: ECOMM Shopify Sales | B6: 89997.77 | C6: 89941.4 | D6: 89539.3 | E6: 95505.4 | F6: 94595.2 | G6: 93247.4 | H6: 85112.8 | I6: 97195.4 | J6: 71397.7 | K6: 98936 | L6: 91400.3 | M6: 100050 | N6: =SUM(B6:M6) -> 1096918.7
A7: ECOMM Stripe Sales | B7: 10109.68 | C7: 9819.3 | D7: 7783.7 | E7: 7078.9 | F7: 7394.5 | G7: 8626.6 | H7: 6520 | I7: 5972.6 | J7: 6386.8 | K7: 6580.3 | L7: 9740.2 | M7: 6282.2 | N7: =SUM(B7:M7) -> 92294.78
A8: other income | B8: - | C8: - | D8: - | E8: - | F8: - | G8: - | H8: - | I8: - | J8: 29226.3 | K8: - | L8: - | M8: - | N8: =SUM(B8:M8) -> 29226.3
A9: Sales of Product Income | B9: - | C9: - | D9: 559.4 | E9: - | F9: - | G9: - | H9: - | I9: 1106.4 | J9: - | K9: - | L9: - | M9: - | N9: =SUM(B9:M9) -> 1665.8
A10: Sales Tax | B10: - | C10: - | D10: - | E10: - | F10: - | G10: - | H10: - | I10: - | J10: - | K10: - | L10: - | M10: - | N10: -
A11: Total for Income | B11: =Explaination!D63 -> 113683.33 | C11: =B11*100.21% -> 113922.07 | D11: =C11*100.21% -> 114161.3 | E11: =D11*100.21% -> 114401.04 | F11: =E11*100.21% -> 114641.29 | G11: =F11*100.21% -> 114882.03 | H11: =G11*100.21% -> 115123.28 | I11: =H11*100.21% -> 115365.04 | J11: =I11*100.21% -> 115607.31 | ... M11: =L11*100.21% -> 116337.17 | N11: =SUM(B11:M11) -> 1380067.3
A12: Cost of Goods Sold
A13: Cost of Goods Sold | B13: 38546.92 | C13: 20578.3 | D13: 31880.17 | E13: 10777.03 | F13: 17021.22 | G13: 23327.39 | H13: 21673.44 | I13: 25653.65 | J13: 17345.43 | K13: 7027 | L13: 10160.03 | M13: 6803.4 | N13: =SUM(B13:M13) -> 230793.98
A14: Cost of labor - COS | B14: 15124.52 | C14: 29123.35 | D14: 21416.61 | E14: 35812.35 | F14: 36020.81 | G14: 29146.19 | H14: 30368.6 | I14: 29518.71 | J14: 40393.72 | K14: 67276.46 | L14: 62152.21 | M14: 68033.98 | N14: =SUM(B14:M14) -> 464387.51
A15: Freight & Delivery | B15: 23633.23 | C15: 27765.36 | D15: 24332.91 | E15: 31203.33 | F15: 24914.05 | G15: 25646.21 | H15: 26241.8 | I15: 23275.87 | J15: 20873.82 | K15: 4474.59 | L15: 6623.36 | M15: 4271.9 | N15: =SUM(B15:M15) -> 243256.43
A16: Total for Cost of Goods Sold | B16: =B11*68% -> 77304.667 | C16: =C11*68% -> 77467.006 | D16: =D11*68% -> 77629.687 | E16: =E11*68% -> 77792.71 | F16: =F11*68% -> 77956.074 | G16: =G11*68% -> 78119.782 | H16: =H11*68% -> 78283.834 | I16: =I11*68% -> 78448.23 | ... M16: =M11*68% -> 79109.273 | N16: =SUM(B16:M16) -> 938445.78
A17: Gross Profit | B17: =B11-B16 -> 36378.667 | C17: =C11-C16 -> 36455.062 | D17: =D11-D16 -> 36531.618 | E17: =E11-E16 -> 36608.334 | F17: =F11-F16 -> 36685.211 | G17: =G11-G16 -> 36762.25 | H17: =H11-H16 -> 36839.451 | I17: =I11-I16 -> 36916.814 | ... N17: =N11-N16 -> 441621.55
A18: Expenses
A19: Advertising | B19: 4596.65 | C19: 4691.63 | D19: 4344.96 | E19: 4272.29 | F19: 4030.35 | G19: 4545.76 | H19: 3392.88 | I19: 3372.29 | J19: 3155.95 | K19: 3372.29 | L19: 4272.29 | M19: 4545.76 | N19: =SUM(B19:M19) -> 48593.1
A20: Automobile Expense | B20: 451.73 | C20: 423.75 | D20: 424.05 | E20: 269.17 | F20: 1126.87 | G20: 1127.68 | H20: 610.37 | I20: 96.7 | J20: 72.54 | K20: 310.31 | L20: 423.75 | M20: 195.82 | N20: =SUM(B20:M20) -> 5532.74
A21: Gas | B21: 197.57 | C21: 310.31 | D21: 60.81 | E21: 64.6 | F21: 78.48 | G21: 122.47 | H21: 210.63 | I21: 160.48 | J21: 195.82 | K21: 60.81 | L21: 64.6 | M21: 78.48 | N21: =SUM(B21:M21) -> 1605.06
A22: Parking | B22: 11.11 | C22: 15.4 | D22: 32.95 | E22: 18.56 | F22: 15.4 | G22: 5.55 | H22: 24.11 | I22: 5.55 | J22: 32.95 | K22: 15.4 | L22: 32.95 | M22: 24.11 | N22: =SUM(B22:M22) -> 234.04
A23: Total for Automobile Expense | B23: =B20+B21+B22 -> 660.41 | C23: =C20+C21+C22 -> 749.46 | D23: =D20+D21+D22 -> 517.81 | E23: =E20+E21+E22 -> 352.33 | F23: =F20+F21+F22 -> 1220.75 | G23: =G20+G21+G22 -> 1255.7 | H23: =H20+H21+H22 -> 845.11 | I23: =I20+I21+I22 -> 262.73 | ... M23: =M20+M21+M22 -> 298.41 | N23: =SUM(B23:M23) -> 7371.84
A24: Bank Fees | B24: 475.1 | C24: 634.86 | D24: 61.61 | E24: 227.68 | F24: 180.11 | G24: 230.19 | H24: 168.12 | I24: 150.51 | J24: 224.65 | K24: 475.1 | L24: 61.61 | M24: 227.68 | N24: =SUM(B24:M24) -> 3117.22
A25: Charitable & Donations | B25: 89.94 | C25: 90.01 | D25: 168.14 | E25: 78.12 | F25: 90.2 | G25: 90.27 | H25: 90.33 | I25: 90.4 | J25: 90.46 | K25: 90.53 | L25: 90.6 | M25: 90.66 | N25: =SUM(B25:M25) -> 1149.66
A26: Computer Expense | B26: 479.7 | C26: 480.05 | D26: 480.39 | E26: 480.74 | F26: 481.08 | G26: 481.43 | H26: 481.78 | I26: 482.13 | J26: 482.47 | K26: 482.82 | L26: 483.17 | M26: 483.53 | N26: =SUM(B26:M26) -> 5779.29
A27: Dues & Subscriptions | B27: 1683.8 | C27: 1680.17 | D27: 1441.18 | E27: 1622.49 | F27: 1683.79 | G27: 1685.01 | H27: 1686.22 | I27: 1687.44 | J27: 1688.66 | K27: 1689.88 | L27: 1691.11 | M27: 1692.34 | N27: =SUM(B27:M27) -> 19932.09
A28: Entertainment | B28: 1168.27 | C28: 1360.96 | D28: 1078.83 | E28: 2512.6 | F28: 1712.42 | G28: 1711.78 | H28: 2841.96 | I28: 1711.78 | J28: 786.23 | K28: 1711.78 | L28: 1360.96 | M28: 1078.83 | N28: =SUM(B28:M28) -> 19036.4
A29: Insurance | B29: 284.86 | C29: 285.07 | D29: 285.27 | E29: 285.47 | F29: 285.67 | G29: 306.36 | H29: 625.06 | I29: 286.3 | J29: 286.51 | K29: 285.07 | L29: 306.36 | M29: 285.07 | N29: =SUM(B29:M29) -> 3807.07
A30: Interest Expense | B30: 599.63 | C30: 600.06 | D30: 569.49 | E30: 600.92 | F30: 501.35 | G30: 601.79 | H30: 602.22 | I30: 602.66 | J30: 603.09 | K30: 603.53 | L30: 603.97 | M30: 604.41 | N30: =SUM(B30:M30) -> 7093.12
A31: Legal Fees | B31: 474.41 | C31: 3981.09 | D31: 2924.31 | E31: 475.43 | F31: 2344.87 | G31: 474.41 | H31: 975.43 | I31: 2023 | J31: 1884.73 | K31: 3981.09 | L31: 809.5 | M31: 2344.87 | N31: =SUM(B31:M31) -> 22693.14
A32: Lodging | B32: 809.5 | C32: 600.06 | D32: 600.49 | E32: 600.92 | F32: 601.35 | G32: 601.79 | H32: 602.22 | I32: 602.66 | J32: 603.09 | K32: 603.53 | L32: 603.97 | M32: 604.41 | N32: =SUM(B32:M32) -> 7433.99
A33: Marketing | B33: =B11*18% -> 20463 | C33: =C11*18% -> 20505.972 | D33: =D11*18% -> 20549.035 | E33: =E11*18% -> 20592.188 | F33: =F11*18% -> 20635.431 | G33: =G11*18% -> 20678.766 | H33: =H11*18% -> 20722.191 | I33: =I11*18% -> 20765.708 | ... M33: =M11*18% -> 20940.69 | N33: =SUM(B33:M33) -> 248412.12
A34: Meals | B34: 2111.33 | C34: 2922.88 | D34: 2924.98 | E34: 4201.95 | F34: 4216.46 | G34: 3338.99 | H34: 2120.45 | I34: 4298.23 | J34: 2525.28 | K34: 2111.33 | L34: 4216.46 | M34: 2924.98 | N34: =SUM(B34:M34) -> 37913.32
A35: Medical | B35: 312 | C35: 312.22 | D35: 271.68 | E35: 88.29 | F35: 74.06 | G35: 88.29 | H35: 74.06 | I35: 88.29 | J35: 312 | K35: 271.68 | L35: 312 | M35: 271.68 | N35: =SUM(B35:M35) -> 2476.25
A36: Membership | B36: 328.97 | C36: 159.41 | D36: 922.54 | E36: 1703.39 | F36: 336.78 | G36: 480.92 | H36: 337.26 | I36: 865.05 | J36: 351.37 | K36: 336.78 | L36: 337.26 | M36: 336.78 | N36: =SUM(B36:M36) -> 6496.51
A37: Merchant Fees | B37: 256.72 | C37: 243.52 | D37: 251.02 | E37: 362.86 | F37: 240.81 | G37: 185.55 | H37: 260.1 | I37: 258.02 | J37: 258.2 | K37: 258.39 | L37: 258.58 | M37: 258.77 | N37: =SUM(B37:M37) -> 3092.54
A38: Stripe Fee | B38: 98.53 | C38: 98.6 | D38: 98.67 | E38: 98.74 | F38: 98.81 | G38: 98.88 | H38: 98.95 | I38: 103.03 | J38: 99.1 | K38: 99.17 | L38: 99.24 | M38: 99.31 | N38: =SUM(B38:M38) -> 1191.03
A39: Total for Merchant Fees | B39: =B37+B38 -> 355.25 | C39: =C37+C38 -> 342.12 | D39: =D37+D38 -> 349.69 | E39: =E37+E38 -> 461.6 | F39: =F37+F38 -> 339.62 | G39: =G37+G38 -> 284.43 | H39: =H37+H38 -> 359.05 | I39: =I37+I38 -> 361.05 | ... M39: =M37+M38 -> 358.08 | N39: =SUM(B39:M39) -> 4283.57
A40: Miscellaneous | B40: 75.91 | C40: 401.28 | D40: 401.57 | E40: 385.86 | F40: 834.26 | G40: 569.21 | H40: 569.63 | I40: 1553.86 | J40: 157.19 | K40: 157.3 | L40: 157.41 | M40: 571.69 | N40: =SUM(B40:M40) -> 5835.17
A41: Office Expense | B41: 4775.42 | C41: 3307.59 | D41: 3309.96 | E41: 3302.34 | F41: 4580.6 | G41: 6447.72 | H41: 4580.6 | I41: 4290.42 | J41: 5431.48 | K41: 3302.34 | L41: 3243.59 | M41: 3272.34 | N41: =SUM(B41:M41) -> 49844.4
A42: Other General & Administrative | B42: 628.93 | C42: 629.38 | D42: 629.83 | E42: 680.5 | F42: 409.96 | G42: 1313.11 | H42: 3533.29 | I42: 2068.28 | J42: 924.98 | K42: 1313.11 | L42: 2068.28 | M42: 1313.11 | N42: =SUM(B42:M42) -> 15512.76
A43: Outside Consultants | B43: 14391.12 | C43: 10801.08 | D43: 12610.3 | E43: 10215.67 | F43: 8418.96 | G43: 7823.24 | H43: 8431.11 | I43: 8376.93 | J43: 13871.14 | K43: 12361.13 | L43: 11475.39 | M43: 12269.46 | N43: =SUM(B43:M43) -> 131045.53
A44: Paypal fees | B44: 338.36 | C44: 338.6 | D44: 338.85 | E44: 339.09 | F44: 339.33 | G44: 339.58 | H44: 339.82 | I44: 340.07 | J44: 340.31 | K44: 340.56 | L44: 340.81 | M44: 341.06 | N44: =SUM(B44:M44) -> 4076.44
A45: Postage | B45: 20.05 | C45: 20.06 | D45: 20.07 | E45: 20.09 | F45: 20.1 | G45: 20.1 | H45: 20.1 | I45: 20.1 | J45: 20.1 | K45: 20.1 | L45: 20.1 | M45: 20.1 | N45: =SUM(B45:M45) -> 241.07
A46: Prime Video | B46: 39.54 | C46: 39.57 | D46: 39.59 | E46: 39.62 | F46: 29.65 | G46: 39.68 | H46: 39.71 | I46: 39.74 | J46: 39.77 | K46: 39.8 | L46: 39.82 | M46: 39.85 | N46: =SUM(B46:M46) -> 466.34
A47: Professional Fees | B47: 179.89 | C47: 300.03 | D47: 300.25 | E47: 1642.27 | F47: 1869.1 | G47: 1870.45 | H47: 1871.8 | I47: 1044.84 | J47: 177.16 | K47: 300.25 | L47: 1207.94 | M47: 604.41 | N47: =SUM(B47:M47) -> 11368.39
A48: Rent | B48: 1798.89 | C48: 1660.18 | D48: 1801.47 | E48: 1802.77 | F48: 1804.06 | G48: 1805.36 | H48: 1806.67 | I48: 1807.97 | J48: 1809.28 | K48: 1810.59 | L48: 1811.9 | M48: 1813.22 | N48: =SUM(B48:M48) -> 21532.36
A49: Software & Apps | B49: 224.54 | C49: 505.28 | D49: 505.64 | E49: 505.64 | F49: 505.64 | G49: 505.64 | H49: 505.64 | I49: 505.64 | J49: 505.64 | K49: 505.64 | L49: 505.64 | M49: 505.64 | N49: =SUM(B49:M49) -> 5786.22
A50: Travel | B50: 2452.22 | C50: 2452.22 | D50: 2452.22 | E50: 2452.22 | F50: 2452.22 | G50: 2436.22 | H50: 2452.22 | I50: 2452.22 | J50: 2452.22 | K50: 2452.22 | L50: 2452.22 | M50: 2452.22 | N50: =SUM(B50:M50) -> 29410.64
A51: Uber | B51: 149.91 | C51: 150.01 | D51: 150.12 | E51: 150.23 | F51: 150.34 | G51: 150.45 | H51: 150.56 | I51: 150.66 | J51: 150.77 | K51: 150.88 | L51: 150.99 | M51: 151.1 | N51: =SUM(B51:M51) -> 1806.02
A52: Total for Expenses | B52: =B33+Explaination!L70 -> 59963 | C52: =39500+C33 -> 60005.972 | D52: =39500+D33 -> 60049.035 | E52: =39500+E33 -> 60092.188 | F52: =39500+F33 -> 60135.431 | G52: =39500+G33 -> 60178.766 | H52: =39500+H33 -> 60222.191 | I52: =39500+I33 -> 60265.708 | J52: =39500+J33 -> 60309.316 | ... M52: =39500+M33 -> 60440.69 | N52: =SUM(B52:M52) -> 722412.12
A53: Net Operating Income
A54: Net Other Income
A55: Net Income | B55: =B17-B52 -> -23584.333 | C55: =C17-C52 -> -23550.91 | D55: =D17-D52 -> -23517.417 | E55: =E17-E52 -> -23483.854 | F55: =F17-F52 -> -23450.22 | G55: =G17-G52 -> -23416.515 | H55: =H17-H52 -> -23382.74 | I55: =I17-I52 -> -23348.894 | ... N55: =N17-N52 -> -280790.57

Sheet Forecast P&L 2026 2
A2: Projection for the year 2026 (Base)
A3: Distribution account | B3: 46023 | C3: 46054 | D3: 46082 | E3: 46113 | F3: 46143 | G3: 46174 | H3: 46204 | I3: 46235 | J3: 46266 | K3: 46296 | L3: 46327 | M3: 46357 | N3: Total
A4: Income
A5: ECOMM PayPal Sales | B5: 14944.22 | C5: 15613.53 | D5: 17977.74 | E5: 13070.12 | F5: 14015.92 | G5: 14433.79 | H5: 26106.86 | I5: 12346.07 | J5: 9649.06 | K5: 11539.9 | L5: 16711.67 | M5: 11208.4 | N5: =SUM(B5:M5) -> 177617.28
A6: ECOMM Shopify Sales | B6: 99068.8 | C6: 99164.87 | D6: 98879.11 | E6: 105635.96 | F6: 104796.24 | G6: 103468 | H6: 94592.61 | I6: 108193.41 | J6: 79603.47 | K6: 110482.91 | L6: 102230.72 | M6: 112083.98 | N6: =SUM(B6:M6) -> 1218200.1
A7: ECOMM Stripe Sales | B7: 11128.65 | C7: 10826.29 | D7: 8595.6 | E7: 7829.81 | F7: 8191.91 | G7: 9572.2 | H7: 7246.17 | I7: 6648.42 | J7: 7120.88 | K7: 7348.28 | L7: 10894.4 | M7: 7037.83 | N7: =SUM(B7:M7) -> 102440.44
A8: other income | B8: - | C8: - | D8: - | E8: - | F8: - | G8: - | H8: - | I8: - | J8: 32585.34 | K8: - | L8: - | M8: - | N8: =SUM(B8:M8) -> 32585.34
A9: Sales of Product Income | B9: - | C9: - | D9: 617.74 | E9: - | F9: - | G9: - | H9: - | I9: 1231.54 | J9: - | K9: - | L9: - | M9: - | N9: =SUM(B9:M9) -> 1849.28
A10: Sales Tax | B10: - | C10: - | D10: - | E10: - | F10: - | G10: - | H10: - | I10: - | J10: - | K10: - | L10: - | M10: - | N10: -
A11: Total for Income | B11: =Explaination!E63 -> 125141.67 | C11: =B11*100.37% -> 125604.69 | D11: =C11*100.37% -> 126069.43 | E11: =D11*100.37% -> 126535.89 | F11: =E11*100.37% -> 127004.07 | G11: =F11*100.37% -> 127473.98 | H11: =G11*100.37% -> 127945.64 | I11: =H11*100.37% -> 128419.04 | J11: =I11*100.37% -> 128894.19 | ... M11: =L11*100.37% -> 130330.21 | N11: =SUM(B11:M11) -> 1532639.7
A12: Cost of Goods Sold
A13: Cost of Goods Sold | B13: 42432.13 | C13: 22688.59 | D13: 35205.57 | E13: 11920.18 | F13: 18856.77 | G13: 25884.25 | H13: 24087.41 | I13: 28556.46 | J13: 19338.96 | K13: 7847.13 | L13: 11363.93 | M13: 7621.71 | N13: =SUM(B13:M13) -> 255803.09
A14: Cost of labor - COS | B14: 16648.94 | C14: 32109.93 | D14: 23650.57 | E14: 39611.07 | F14: 39905.25 | G14: 32340.83 | H14: 33751.03 | I14: 32858.87 | J14: 45036.21 | K14: 75128.38 | L14: 69516.89 | M14: 76217.11 | N14: =SUM(B14:M14) -> 516775.08
A15: Freight & Delivery | B15: 26015.26 | C15: 30612.67 | D15: 26871.07 | E15: 34513.15 | F15: 27600.75 | G15: 28457.23 | H15: 29164.59 | I15: 25909.62 | J15: 23272.88 | K15: 4996.83 | L15: 7408.19 | M15: 4785.73 | N15: =SUM(B15:M15) -> 269607.97
A16: Total for Cost of Goods Sold | B16: =B11*68% -> 85096.333 | C16: =C11*68% -> 85411.19 | D16: =D11*68% -> 85727.211 | E16: =E11*68% -> 86044.402 | F16: =F11*68% -> 86362.766 | G16: =G11*68% -> 86682.308 | H16: =H11*68% -> 87003.033 | I16: =I11*68% -> 87324.944 | ... M16: =M11*68% -> 88624.544 | N16: =SUM(B16:M16) -> 1042195
A17: Gross Profit | B17: =B11-B16 -> 40045.333 | C17: =C11-C16 -> 40193.501 | D17: =D11-D16 -> 40342.217 | E17: =E11-E16 -> 40491.483 | F17: =F11-F16 -> 40641.302 | G17: =G11-G16 -> 40791.675 | H17: =H11-H16 -> 40942.604 | I17: =I11-I16 -> 41094.091 | ... N17: =N11-N16 -> 490444.69
A18: Expenses
A19: Advertising | B19: 4754.76 | C19: 4282.91 | D19: 4754.76 | E19: 4545.76 | F19: 4272.29 | G19: 3155.95 | H19: 4282.91 | I19: 4030.35 | J19: 3155.95 | K19: 4307.62 | L19: 4754.76 | M19: 4272.29 | N19: =SUM(B19:M19) -> 50570.31
A20: Automobile Expense | B20: 424.05 | C20: 807.41 | D20: 610.37 | E20: 1127.68 | F20: 423.75 | G20: 72.54 | H20: 812.89 | I20: 1126.87 | J20: 72.54 | K20: 816.23 | L20: 424.05 | M20: 423.75 | N20: =SUM(B20:M20) -> 7142.13
A21: Gas | B21: 60.81 | C21: 621.09 | D21: 210.63 | E21: 122.47 | F21: 64.6 | G21: 195.82 | H21: 625.3 | I21: 78.48 | J21: 195.82 | K21: 627.87 | L21: 60.81 | M21: 64.6 | N21: =SUM(B21:M21) -> 2928.3
A22: Parking | B22: 32.95 | C22: 62.11 | D22: 24.11 | E22: 5.55 | F22: 32.95 | G22: 32.95 | H22: 62.53 | I22: 15.4 | J22: 32.95 | K22: 62.79 | L22: 32.95 | M22: 32.95 | N22: =SUM(B22:M22) -> 430.19
A23: Total for Automobile Expense | B23: =B20+B21+B22 -> 517.81 | C23: =C20+C21+C22 -> 1490.61 | D23: =D20+D21+D22 -> 845.11 | E23: =E20+E21+E22 -> 1255.7 | F23: =F20+F21+F22 -> 521.3 | G23: =G20+G21+G22 -> 301.31 | H23: =H20+H21+H22 -> 1500.72 | I23: =I20+I21+I22 -> 1220.75 | ... M23: =M20+M21+M22 -> 521.3 | N23: =SUM(B23:M23) -> 10500.62
A24: Bank Fees | B24: 475.1 | C24: 227.68 | D24: 168.12 | E24: 230.19 | F24: 61.61 | G24: 224.65 | H24: 250.12 | I24: 180.11 | J24: 224.65 | K24: 251.15 | L24: 475.1 | M24: 61.61 | N24: =SUM(B24:M24) -> 2830.09
A25: Charitable & Donations | B25: 89.94 | C25: 90.66 | D25: 90.33 | E25: 90.27 | F25: 90.6 | G25: 90.46 | H25: 90.27 | I25: 90.2 | J25: 90.46 | K25: 816.23 | L25: 89.94 | M25: 90.6 | N25: =SUM(B25:M25) -> 1809.96
A26: Computer Expense | B26: 479.7 | C26: 483.53 | D26: 481.78 | E26: 481.43 | F26: 483.17 | G26: 482.47 | H26: 781.63 | I26: 481.08 | J26: 482.47 | K26: 816.23 | L26: 479.7 | M26: 483.17 | N26: =SUM(B26:M26) -> 6416.36
A27: Dues & Subscriptions | B27: 1683.8 | C27: 1522.34 | D27: 1686.22 | E27: 1685.01 | F27: 1691.11 | G27: 1688.66 | H27: 781.63 | I27: 1683.79 | J27: 1688.66 | K27: 816.23 | L27: 1683.8 | M27: 1691.11 | N27: =SUM(B27:M27) -> 18302.36
A28: Entertainment | B28: 1168.27 | C28: 1078.83 | D28: 2841.96 | E28: 1711.78 | F28: 1360.96 | G28: 786.23 | H28: 781.63 | I28: 1712.42 | J28: 786.23 | K28: 816.23 | L28: 1168.27 | M28: 1360.96 | N28: =SUM(B28:M28) -> 15573.77
A29: Insurance | B29: 284.86 | C29: 285.07 | D29: 625.06 | E29: 306.36 | F29: 306.36 | G29: 286.51 | H29: 286.51 | I29: 285.67 | J29: 286.51 | K29: 816.23 | L29: 284.86 | M29: 306.36 | N29: =SUM(B29:M29) -> 4360.36
A30: Interest Expense | B30: 599.63 | C30: 604.41 | D30: 602.22 | E30: 601.79 | F30: 603.97 | G30: 603.09 | H30: 781.63 | I30: 501.35 | J30: 603.09 | K30: 816.23 | L30: 599.63 | M30: 603.97 | N30: =SUM(B30:M30) -> 7521.01
A31: Legal Fees | B31: 474.41 | C31: 2344.87 | D31: 975.43 | E31: 474.41 | F31: 809.5 | G31: 1884.73 | H31: 1250.6 | I31: 2344.87 | J31: 1884.73 | K31: 1255.74 | L31: 474.41 | M31: 809.5 | N31: =SUM(B31:M31) -> 14983.2
A32: Lodging | B32: 809.5 | C32: 604.41 | D32: 602.22 | E32: 601.79 | F32: 603.97 | G32: 603.09 | H32: 781.63 | I32: 601.35 | J32: 603.09 | K32: 816.23 | L32: 809.5 | M32: 603.97 | N32: =SUM(B32:M32) -> 8040.75
A33: Marketing | B33: =B11*18% -> 22525.5 | C33: =C11*18% -> 22608.844 | D33: =D11*18% -> 22692.497 | E33: =E11*18% -> 22776.459 | F33: =F11*18% -> 22860.732 | G33: =G11*18% -> 22945.317 | H33: =H11*18% -> 23030.215 | I33: =I11*18% -> 23115.426 | ... M33: =M11*18% -> 23459.438 | N33: =SUM(B33:M33) -> 275875.14
A34: Meals | B34: 2922.88 | C34: 2924.98 | D34: 2120.45 | E34: 3338.99 | F34: 4216.46 | G34: 2525.28 | H34: 2949.69 | I34: 4216.46 | J34: 2525.28 | K34: 2110.23 | L34: 2922.88 | M34: 4216.46 | N34: =SUM(B34:M34) -> 36990.04
A35: Medical | B35: 312.22 | C35: 271.68 | D35: 74.06 | E35: 88.29 | F35: 312 | G35: 312 | H35: 781.63 | I35: 74.06 | J35: 312 | K35: 816.23 | L35: 312.22 | M35: 312 | N35: =SUM(B35:M35) -> 3978.39
A36: Membership | B36: 159.41 | C36: 336.78 | D36: 337.26 | E36: 480.92 | F36: 337.26 | G36: 351.37 | H36: 1222.67 | I36: 336.78 | J36: 351.37 | K36: 816.23 | L36: 159.41 | M36: 337.26 | N36: =SUM(B36:M36) -> 5226.72
A37: Merchant Fees | B37: 243.52 | C37: 258.77 | D37: 260.1 | E37: 185.55 | F37: 258.58 | G37: 258.2 | H37: 781.63 | I37: 240.81 | J37: 258.2 | K37: 816.23 | L37: 243.52 | M37: 258.58 | N37: =SUM(B37:M37) -> 4063.69
A38: Stripe Fee | B38: 98.6 | C38: 99.31 | D38: 98.95 | E38: 98.88 | F38: 99.24 | G38: 99.1 | H38: 781.63 | I38: 98.81 | J38: 99.1 | K38: 816.23 | L38: 98.6 | M38: 99.24 | N38: =SUM(B38:M38) -> 2587.69
A39: Total for Merchant Fees | B39: =B37+B38 -> 342.12 | C39: =C37+C38 -> 358.08 | D39: =D37+D38 -> 359.05 | E39: =E37+E38 -> 284.43 | F39: =F37+F38 -> 357.82 | G39: =G37+G38 -> 357.3 | H39: =H37+H38 -> 1563.26 | I39: =I37+I38 -> 339.62 | ... M39: =M37+M38 -> 357.82 | N39: =SUM(B39:M39) -> 6651.38
A40: Miscellaneous | B40: 385.86 | C40: 571.69 | D40: 569.63 | E40: 569.21 | F40: 157.41 | G40: 157.19 | H40: 781.63 | I40: 834.26 | J40: 157.19 | K40: 816.23 | L40: 385.86 | M40: 157.41 | N40: =SUM(B40:M40) -> 5543.57
A41: Office Expense | B41: 3302.34 | C41: 3272.34 | D41: 4440.6 | E41: 6447.72 | F41: 3243.59 | G41: 5431.48 | H41: 5170.08 | I41: 4580.6 | J41: 5431.48 | K41: 3858.44 | L41: 2535.33 | M41: 3243.59 | N41: =SUM(B41:M41) -> 50957.59
A42: Other General & Administrative | B42: 680.5 | C42: 1313.11 | D42: 3533.29 | E42: 1313.11 | F42: 2068.28 | G42: 924.98 | H42: 781.63 | I42: 409.96 | J42: 924.98 | K42: 816.23 | L42: 680.5 | M42: 2068.28 | N42: =SUM(B42:M42) -> 15514.85
A43: Outside Consultants | B43: 11215.7 | C43: 12269.46 | D43: 8431.11 | E43: 7823.24 | F43: 11475.39 | G43: 13841.14 | H43: 8431.11 | I43: 8418.96 | J43: 13871.14 | K43: 8468.68 | L43: 13871.14 | M43: 11475.39 | N43: =SUM(B43:M43) -> 129592.46
A44: Paypal fees | B44: 339.09 | C44: 341.06 | D44: 339.82 | E44: 339.58 | F44: 340.81 | G44: 340.31 | H44: 781.63 | I44: 339.33 | J44: 306.31 | K44: 816.23 | L44: 339.09 | M44: 340.81 | N44: =SUM(B44:M44) -> 4964.07
A45: Postage | B45: 20.09 | C45: 20.1 | D45: 20.1 | E45: 20.1 | F45: 20.1 | G45: 20.1 | H45: 20.1 | I45: 20.1 | J45: 20.1 | K45: 816.23 | L45: 20.09 | M45: 20.1 | N45: =SUM(B45:M45) -> 1037.31
A46: Prime Video | B46: 39.62 | C46: 39.85 | D46: 39.71 | E46: 39.68 | F46: 39.82 | G46: 39.77 | H46: 781.63 | I46: 29.65 | J46: 39.77 | K46: 816.23 | L46: 39.62 | M46: 39.82 | N46: =SUM(B46:M46) -> 1985.17
A47: Professional Fees | B47: 1642.27 | C47: 604.41 | D47: 1871.8 | E47: 1870.45 | F47: 1207.94 | G47: 177.16 | H47: 781.63 | I47: 1869.1 | J47: 177.16 | K47: 816.23 | L47: 1642.27 | M47: 1207.94 | N47: =SUM(B47:M47) -> 13868.36
A48: Rent | B48: 1802.77 | C48: 1813.22 | D48: 1806.67 | E48: 1805.36 | F48: 1811.9 | G48: 1809.28 | H48: 1693.26 | I48: 1804.06 | J48: 1809.28 | K48: 1569.67 | L48: 1802.77 | M48: 1811.9 | N48: =SUM(B48:M48) -> 21340.14
A49: Software & Apps | B49: 505.64 | C49: 505.64 | D49: 505.64 | E49: 505.64 | F49: 505.64 | G49: 505.64 | H49: 781.63 | I49: 505.64 | J49: 505.64 | K49: 816.23 | L49: 505.64 | M49: 505.64 | N49: =SUM(B49:M49) -> 6654.26
A50: Travel | B50: 2452.22 | C50: 2452.22 | D50: 1226.02 | E50: 2436.22 | F50: 2452.22 | G50: 2452.22 | H50: 781.63 | I50: 2452.22 | J50: 2452.22 | K50: 816.23 | L50: 2452.22 | M50: 2452.22 | N50: =SUM(B50:M50) -> 24877.86
A51: Uber | B51: 150.23 | C51: 151.1 | D51: 150.56 | E51: 150.45 | F51: 150.99 | G51: 150.77 | H51: 625.3 | I51: 150.34 | J51: 150.77 | K51: 627.87 | L51: 150.23 | M51: 150.99 | N51: =SUM(B51:M51) -> 2759.6
A52: Total for Expenses | B52: =Explaination!E70+B33 -> 62025.5 | C52: =39500+C33 -> 62108.844 | D52: =39500+D33 -> 62192.497 | E52: =39500+E33 -> 62276.459 | F52: =39500+F33 -> 62360.732 | G52: =39500+G33 -> 62445.317 | H52: =39500+H33 -> 62530.215 | I52: =39500+I33 -> 62615.426 | J52: =39500+J33 -> 62700.953 | ... M52: =39500+M33 -> 62959.438 | N52: =SUM(B52:M52) -> 749875.14
A53: Net Operating Income
A54: Net Other Income
A55: Net Income | B55: =B17-B52 -> -21980.167 | C55: =C17-C52 -> -21915.343 | D55: =D17-D52 -> -21850.28 | E55: =E17-E52 -> -21784.976 | F55: =F17-F52 -> -21719.43 | G55: =G17-G52 -> -21653.642 | H55: =H17-H52 -> -21587.611 | I55: =I17-I52 -> -21521.335 | ... N55: =N17-N52 -> -259430.45

Sheet Forecast P&L 2026 3
A2: Projection for the year 2026 (Optimistic)
A3: Distribution account | B3: 46023 | C3: 46054 | D3: 46082 | E3: 46113 | F3: 46143 | G3: 46174 | H3: 46204 | I3: 46235 | J3: 46266 | K3: 46296 | L3: 46327 | M3: 46357 | N3: Total
A4: Income
A5: ECOMM PayPal Sales | B5: 16586.22 | C5: 17358.42 | D5: 20020.7 | E5: 14580.04 | F5: 15661.59 | G5: 16155.84 | H5: 29271.07 | I5: 13865.88 | J5: 10855.22 | K5: 13004.42 | L5: 18864.42 | M5: 12673.67 | N5: =SUM(B5:M5) -> 198897.49
A6: ECOMM Shopify Sales | B6: 109954.03 | C6: 110247.07 | D6: 110115.56 | E6: 117839.5 | F6: 117100.77 | G6: 115812.4 | H6: 106057.46 | I6: 121512.16 | J6: 89554.19 | K6: 124504.2 | L6: 115399.85 | M6: 126736.68 | N6: =SUM(B6:M6) -> 1364833.9
A7: ECOMM Stripe Sales | B7: 12351.42 | C7: 12036.19 | D7: 9572.39 | E7: 8734.35 | F7: 9153.75 | G7: 10714.22 | H7: 8124.42 | I7: 7466.84 | J7: 8011.02 | K7: 8280.84 | L7: 12297.79 | M7: 7957.88 | N7: =SUM(B7:M7) -> 114701.11
A8: other income | B8: - | C8: - | D8: - | E8: - | F8: - | G8: - | H8: - | I8: - | J8: 36658.63 | K8: - | L8: - | M8: - | N8: =SUM(B8:M8) -> 36658.63
A9: Sales of Product Income | B9: - | C9: - | D9: 687.94 | E9: - | F9: - | G9: - | H9: - | I9: 1383.14 | J9: - | K9: - | L9: - | M9: - | N9: =SUM(B9:M9) -> 2071.08
A10: Sales Tax | B10: - | C10: - | D10: - | E10: - | F10: - | G10: - | H10: - | I10: - | J10: - | K10: - | L10: - | M10: - | N10: -
A11: Total for Income | B11: =Explaination!F63 -> 138891.67 | C11: =B11*100.54% -> 139641.68 | D11: =C11*100.54% -> 140395.75 | E11: =D11*100.54% -> 141153.88 | F11: =E11*100.54% -> 141916.11 | G11: =F11*100.54% -> 142682.46 | H11: =G11*100.54% -> 143452.95 | I11: =H11*100.54% -> 144227.59 | J11: =I11*100.54% -> 145006.42 | ... M11: =L11*100.54% -> 147368.23 | N11: =SUM(B11:M11) -> 1717102.9
A12: Cost of Goods Sold
A13: Cost of Goods Sold | B13: 47094.38 | C13: 25224.16 | D13: 39206.28 | E13: 13297.25 | F13: 21070.82 | G13: 28972.41 | H13: 27006.86 | I13: 32071.8 | J13: 21756.4 | K13: 8843.01 | L13: 12827.81 | M13: 8618.09 | N13: =SUM(B13:M13) -> 285989.27
A14: Cost of labor - COS | B14: 18478.25 | C14: 35698.38 | D14: 26338.18 | E14: 44187.12 | F14: 44590.68 | G14: 36199.3 | H14: 37841.74 | I14: 36903.84 | J14: 50665.9 | K14: 84662.85 | L14: 78471.9 | M14: 86180.94 | N14: =SUM(B14:M14) -> 580219.08
A15: Freight & Delivery | B15: 28873.7 | C15: 34033.8 | D15: 29924.65 | E15: 38500.27 | F15: 30841.46 | G15: 31852.36 | H15: 32699.41 | I15: 29099.13 | J15: 26182.07 | K15: 5630.97 | L15: 8362.5 | M15: 5411.36 | N15: =SUM(B15:M15) -> 301411.68
A16: Total for Cost of Goods Sold | B16: =B11*68% -> 94446.333 | C16: =C11*68% -> 94956.344 | D16: =D11*68% -> 95469.108 | E16: =E11*68% -> 95984.641 | F16: =F11*68% -> 96502.958 | G16: =G11*68% -> 97024.074 | H16: =H11*68% -> 97548.004 | I16: =I11*68% -> 98074.763 | ... M16: =M11*68% -> 100210.4 | N16: =SUM(B16:M16) -> 1167630
A17: Gross Profit | B17: =B11-B16 -> 44445.333 | C17: =C11-C16 -> 44685.338 | D17: =D11-D16 -> 44926.639 | E17: =E11-E16 -> 45169.243 | F17: =F11-F16 -> 45413.157 | G17: =G11-G16 -> 45658.388 | H17: =H11-H16 -> 45904.943 | I17: =I11-I16 -> 46152.83 | ... N17: =N11-N16 -> 549472.94
A18: Expenses
A19: Advertising | B19: 4944.48 | C19: 4440.17 | D19: 4754.76 | E19: 4545.76 | F19: 4272.29 | G19: 3155.95 | H19: 4440.17 | I19: 4030.35 | J19: 3155.95 | K19: 4510.38 | L19: 4754.76 | M19: 4272.29 | N19: =SUM(B19:M19) -> 51277.31
A20: Automobile Expense | B20: 424.05 | C20: 840.26 | D20: 610.37 | E20: 1127.68 | F20: 423.75 | G20: 72.54 | H20: 849.18 | I20: 1126.87 | J20: 72.54 | K20: 854.65 | L20: 424.05 | M20: 423.75 | N20: =SUM(B20:M20) -> 7249.69
A21: Gas | B21: 60.81 | C21: 646.36 | D21: 210.63 | E21: 122.47 | F21: 64.6 | G21: 195.82 | H21: 653.22 | I21: 78.48 | J21: 195.82 | K21: 657.42 | L21: 60.81 | M21: 64.6 | N21: =SUM(B21:M21) -> 3011.04
A22: Parking | B22: 32.95 | C22: 64.64 | D22: 24.11 | E22: 5.55 | F22: 32.95 | G22: 32.95 | H22: 65.32 | I22: 15.4 | J22: 32.95 | K22: 65.74 | L22: 32.95 | M22: 32.95 | N22: =SUM(B22:M22) -> 438.46
A23: Total for Automobile Expense | B23: =B20+B21+B22 -> 517.81 | C23: =C20+C21+C22 -> 1551.26 | D23: =D20+D21+D22 -> 845.11 | E23: =E20+E21+E22 -> 1255.7 | F23: =F20+F21+F22 -> 521.3 | G23: =G20+G21+G22 -> 301.31 | H23: =H20+H21+H22 -> 1567.72 | I23: =I20+I21+I22 -> 1220.75 | ... M23: =M20+M21+M22 -> 521.3 | N23: =SUM(B23:M23) -> 10699.19
A24: Bank Fees | B24: 478.1 | C24: 227.68 | D24: 168.12 | E24: 230.19 | F24: 61.61 | G24: 224.65 | H24: 261.29 | I24: 180.11 | J24: 224.65 | K24: 262.97 | L24: 475.1 | M24: 61.61 | N24: =SUM(B24:M24) -> 2856.08
A25: Charitable & Donations | B25: 89.94 | C25: 90.66 | D25: 90.33 | E25: 90.27 | F25: 90.6 | G25: 90.46 | H25: 90.27 | I25: 90.2 | J25: 90.46 | K25: 854.65 | L25: 89.94 | M25: 90.6 | N25: =SUM(B25:M25) -> 1848.38
A26: Computer Expense | B26: 479.7 | C26: 483.53 | D26: 481.78 | E26: 481.43 | F26: 483.17 | G26: 482.47 | H26: 481.43 | I26: 481.08 | J26: 482.47 | K26: 854.65 | L26: 479.7 | M26: 483.17 | N26: =SUM(B26:M26) -> 6154.58
A27: Dues & Subscriptions | B27: 1683.8 | C27: 1522.34 | D27: 1686.22 | E27: 1685.01 | F27: 1691.11 | G27: 1688.66 | H27: 816.52 | I27: 1683.79 | J27: 1688.66 | K27: 854.65 | L27: 1683.8 | M27: 1691.11 | N27: =SUM(B27:M27) -> 18375.67
A28: Entertainment | B28: 1168.27 | C28: 1078.83 | D28: 2841.96 | E28: 1711.78 | F28: 1360.96 | G28: 786.23 | H28: 816.52 | I28: 1712.42 | J28: 786.23 | K28: 854.65 | L28: 1168.27 | M28: 1360.96 | N28: =SUM(B28:M28) -> 15647.08
A29: Insurance | B29: 284.86 | C29: 285.07 | D29: 625.06 | E29: 306.36 | F29: 306.36 | G29: 286.51 | H29: 286.51 | I29: 285.67 | J29: 286.51 | K29: 854.65 | L29: 284.86 | M29: 306.36 | N29: =SUM(B29:M29) -> 4398.78
A30: Interest Expense | B30: 599.63 | C30: 604.41 | D30: 602.22 | E30: 601.79 | F30: 603.97 | G30: 603.09 | H30: 601.79 | I30: 501.35 | J30: 603.09 | K30: 854.65 | L30: 599.63 | M30: 603.97 | N30: =SUM(B30:M30) -> 7379.59
A31: Legal Fees | B31: 474.41 | C31: 2344.87 | D31: 975.43 | E31: 474.41 | F31: 809.5 | G31: 1884.73 | H31: 1306.43 | I31: 2344.87 | J31: 1884.73 | K31: 1314.84 | L31: 474.41 | M31: 809.5 | N31: =SUM(B31:M31) -> 15098.13
A32: Lodging | B32: 809.5 | C32: 624 | D32: 602.22 | E32: 601.79 | F32: 603.97 | G32: 603.09 | H32: 624 | I32: 601.35 | J32: 603.09 | K32: 854.65 | L32: 809.5 | M32: 603.97 | N32: =SUM(B32:M32) -> 7941.13
A33: Marketing | B33: =B11*18% -> 25000.5 | C33: =C11*18% -> 25135.503 | D33: =D11*18% -> 25271.234 | E33: =E11*18% -> 25407.699 | F33: =F11*18% -> 25544.901 | G33: =G11*18% -> 25682.843 | H33: =H11*18% -> 25821.53 | I33: =I11*18% -> 25960.967 | ... M33: =M11*18% -> 26526.282 | N33: =SUM(B33:M33) -> 309078.53
A34: Meals | B34: 2922.88 | C34: 2924.98 | D34: 2120.45 | E34: 3338.99 | F34: 4216.46 | G34: 2525.28 | H34: 3081.36 | I34: 4216.46 | J34: 2525.28 | K34: 2209.55 | L34: 2922.88 | M34: 4216.46 | N34: =SUM(B34:M34) -> 37221.03
A35: Medical | B35: 312.22 | C35: 271.68 | D35: 74.06 | E35: 88.29 | F35: 312 | G35: 312 | H35: 816.52 | I35: 74.06 | J35: 312 | K35: 854.65 | L35: 312.22 | M35: 312 | N35: =SUM(B35:M35) -> 4051.7
A36: Membership | B36: 159.41 | C36: 336.78 | D36: 337.26 | E36: 480.92 | F36: 337.26 | G36: 351.37 | H36: 1222.67 | I36: 336.78 | J36: 351.37 | K36: 854.65 | L36: 159.41 | M36: 337.26 | N36: =SUM(B36:M36) -> 5265.14
A37: Merchant Fees | B37: 243.52 | C37: 258.77 | D37: 260.1 | E37: 185.55 | F37: 258.58 | G37: 258.2 | H37: 313 | I37: 240.81 | J37: 258.2 | K37: 854.65 | L37: 243.52 | M37: 258.58 | N37: =SUM(B37:M37) -> 3633.48
A38: Stripe Fee | B38: 98.6 | C38: 99.31 | D38: 98.95 | E38: 98.88 | F38: 99.24 | G38: 99.1 | H38: 816.52 | I38: 98.81 | J38: 99.1 | K38: 854.65 | L38: 98.6 | M38: 99.24 | N38: =SUM(B38:M38) -> 2661
A39: Total for Merchant Fees | B39: =B37+B38 -> 342.12 | C39: =C37+C38 -> 358.08 | D39: =D37+D38 -> 359.05 | E39: =E37+E38 -> 284.43 | F39: =F37+F38 -> 357.82 | G39: =G37+G38 -> 357.3 | H39: =H37+H38 -> 1129.52 | I39: =I37+I38 -> 339.62 | ... M39: =M37+M38 -> 357.82 | N39: =SUM(B39:M39) -> 6294.48
A40: Miscellaneous | B40: 385.86 | C40: 571.69 | D40: 569.63 | E40: 569.21 | F40: 157.41 | G40: 157.19 | H40: 816.52 | I40: 834.26 | J40: 157.19 | K40: 854.65 | L40: 385.86 | M40: 157.41 | N40: =SUM(B40:M40) -> 5616.88
A41: Office Expense | B41: 3302.34 | C41: 3272.34 | D41: 4440.6 | E41: 6447.72 | F41: 3243.59 | G41: 5431.48 | H41: 5373.86 | I41: 4580.6 | J41: 5431.48 | K41: 4040.06 | L41: 2535.33 | M41: 3243.59 | N41: =SUM(B41:M41) -> 51342.99
A42: Other General & Administrative | B42: 680.5 | C42: 1313.11 | D42: 3533.29 | E42: 1313.11 | F42: 2068.28 | G42: 924.98 | H42: 816.52 | I42: 409.96 | J42: 924.98 | K42: 854.65 | L42: 680.5 | M42: 2068.28 | N42: =SUM(B42:M42) -> 15588.16
A43: Outside Consultants | B43: 12912.1 | C43: 11269.46 | D43: 8431.11 | E43: 7823.24 | F43: 11475.39 | G43: 13841.14 | H43: 8431.11 | I43: 8418.96 | J43: 13871.14 | K43: 9864.69 | L43: 13871.14 | M43: 11475.39 | N43: =SUM(B43:M43) -> 131684.87
A44: Paypal fees | B44: 339.09 | C44: 341.06 | D44: 339.82 | E44: 339.58 | F44: 340.81 | G44: 340.31 | H44: 816.52 | I44: 339.33 | J44: 306.31 | K44: 340.31 | L44: 339.09 | M44: 340.81 | N44: =SUM(B44:M44) -> 4523.04
A45: Postage | B45: 20.09 | C45: 20.1 | D45: 20.1 | E45: 20.1 | F45: 20.1 | G45: 20.1 | H45: 20.1 | I45: 20.1 | J45: 20.1 | K45: 20.1 | L45: 20.09 | M45: 20.1 | N45: =SUM(B45:M45) -> 241.18
A46: Prime Video | B46: 39.62 | C46: 39.85 | D46: 39.71 | E46: 39.68 | F46: 39.82 | G46: 39.77 | H46: 816.52 | I46: 29.65 | J46: 39.77 | K46: 39.77 | L46: 39.62 | M46: 39.82 | N46: =SUM(B46:M46) -> 1243.6
A47: Professional Fees | B47: 1642.27 | C47: 604.41 | D47: 1871.8 | E47: 1870.45 | F47: 1207.94 | G47: 177.16 | H47: 816.52 | I47: 1869.1 | J47: =177.16+0.86 -> 178.02 | K47: 177.16 | L47: 1642.27 | M47: 1207.94 | N47: =SUM(B47:M47) -> 13265.04
A48: Rent | B48: 1802.77 | C48: 1813.22 | D48: 1806.67 | E48: 1805.36 | F48: 1811.9 | G48: 1809.28 | H48: 1763.04 | I48: 1804.06 | J48: 1809.28 | K48: 1663.55 | L48: 1802.77 | M48: 1811.9 | N48: =SUM(B48:M48) -> 21503.8
A49: Software & Apps | B49: 505.64 | C49: 505.64 | D49: 505.64 | E49: 505.64 | F49: 505.64 | G49: 505.64 | H49: 816.52 | I49: 505.64 | J49: 505.64 | K49: 854.65 | L49: 505.64 | M49: 505.64 | N49: =SUM(B49:M49) -> 6727.57 | R49: =39499.14-39500 -> -0.86
A50: Travel | B50: 2452.22 | C50: 2452.22 | D50: 1226.02 | E50: 2436.22 | F50: 2452.22 | G50: 2452.22 | H50: 816.52 | I50: 2452.22 | J50: 2452.22 | K50: 854.65 | L50: 2452.22 | M50: 2452.22 | N50: =SUM(B50:M50) -> 24951.17
A51: Uber | B51: 150.23 | C51: 151.1 | D51: 150.56 | E51: 150.45 | F51: 150.99 | G51: 150.77 | H51: 653.22 | I51: 150.34 | J51: 150.77 | K51: 657.42 | L51: 150.23 | M51: 150.99 | N51: =SUM(B51:M51) -> 2817.07
A52: Total for Expenses | B52: =Explaination!F70+B33 -> 64500.5 | C52: =39500+C33 -> 64635.503 | D52: =39500+D33 -> 64771.234 | E52: =39500+E33 -> 64907.699 | F52: =39500+F33 -> 65044.901 | G52: =39500+G33 -> 65182.843 | H52: =39500+H33 -> 65321.53 | I52: =39500+I33 -> 65460.967 | J52: =39500+J33 -> 65601.156 | ... M52: =39500+M33 -> 66026.282 | N52: =SUM(B52:M52) -> 783078.53
A53: Net Operating Income
A54: Net Other Income
A55: Net Income | B55: =B17-B52 -> -20055.167 | C55: =C17-C52 -> -19950.165 | D55: =D17-D52 -> -19844.595 | E55: =E17-E52 -> -19738.456 | F55: =F17-F52 -> -19631.744 | G55: =G17-G52 -> -19524.455 | H55: =H17-H52 -> -19416.587 | I55: =I17-I52 -> -19308.137 | ... N55: =N17-N52 -> -233605.59

Sheet Forecast P&L 2027 1
A2: Projection for the year 2027 (Conservative)
A3: Distribution account | B3: 46388 | C3: 46419 | D3: 46447 | E3: 46478 | F3: 46508 | G3: 46539 | H3: 46569 | I3: 46600 | J3: 46631 | K3: 46661 | L3: 46692 | M3: 46722 | N3: Total
A4: Income
A5: ECOMM PayPal Sales | B5: 18734.72 | C5: 19542.59 | D5: 22465.88 | E5: 16307.03 | F5: 17459.19 | G5: 17951.06 | H5: 32416.89 | I5: 15305.68 | J5: 11863.07 | K5: 14260.68 | L5: 20634.88 | M5: 13806.89 | N5: =SUM(B5:M5) -> 220748.56
A6: ECOMM Shopify Sales | B6: 124196.92 | C6: 124119.19 | D6: 123564.23 | E6: 131797.49 | F6: 130541.38 | G6: 128681.37 | H6: 117455.67 | I6: 134129.62 | J6: 98528.77 | K6: 136531.64 | L6: 126132.43 | M6: 138068.95 | N6: =SUM(B6:M6) -> 1513747.7
A7: ECOMM Stripe Sales | B7: 13951.36 | C7: 13550.67 | D7: 10741.48 | E7: 9768.92 | F7: 10204.4 | G7: 11904.78 | H7: 8997.57 | I7: 8242.18 | J7: 8813.84 | K7: 9080.79 | L7: 13441.52 | M7: 8669.45 | N7: =SUM(B7:M7) -> 127366.96
A8: other income | B8: - | C8: - | D8: - | E8: - | F8: - | G8: - | H8: - | I8: - | J8: 40332.33 | K8: - | L8: - | M8: - | N8: =SUM(B8:M8) -> 40332.33
A9: Sales of Product Income | B9: - | C9: - | D9: 771.96 | E9: - | F9: - | G9: - | H9: - | I9: 1526.76 | J9: - | K9: - | L9: - | M9: - | N9: =SUM(B9:M9) -> 2298.72
A10: Sales Tax | B10: - | C10: - | D10: - | E10: - | F10: - | G10: - | H10: - | I10: - | J10: - | K10: - | L10: - | M10: - | N10: -
A11: Total for Income | B11: =Explaination!D78 -> 156883 | C11: =B11*100.21% -> 157212.45 | D11: =C11*100.21% -> 157542.6 | E11: =D11*100.21% -> 157873.44 | F11: =E11*100.21% -> 158204.97 | G11: =F11*100.21% -> 158537.2 | H11: =G11*100.21% -> 158870.13 | I11: =H11*100.21% -> 159203.76 | J11: =I11*100.21% -> 159538.09 | ... M11: =L11*100.21% -> 160545.29 | N11: =SUM(B11:M11) -> 1904492.9
A12: Cost of Goods Sold
A13: Cost of Goods Sold | B13: 53194.75 | C13: 28398.06 | D13: 43994.63 | E13: 14872.3 | F13: 23489.28 | G13: 32191.8 | H13: 29909.34 | I13: 35402.04 | J13: 23936.69 | K13: 9697.26 | L13: 14020.84 | M13: 9388.69 | N13: =SUM(B13:M13) -> 318495.68
A14: Cost of labor - COS | B14: 20871.84 | C14: 40190.22 | D14: 29554.92 | E14: 49421.05 | F14: 49708.71 | G14: 40221.74 | H14: 41908.67 | I14: 40735.83 | J14: 55743.33 | K14: 92841.52 | L14: 85781.05 | M14: 93886.89 | N14: =SUM(B14:M14) -> 640865.77
A15: Freight & Delivery | B15: 32613.85 | C15: 38316.19 | D15: 33579.42 | E15: 43060.59 | F15: 34381.39 | G15: 35391.77 | H15: 36213.68 | I15: 32120.69 | J15: 28805.88 | K15: 6174.94 | L15: 9140.24 | M15: 5895.22 | N15: =SUM(B15:M15) -> 335693.86
A16: Total for Cost of Goods Sold | B16: =B11*68% -> 106680.44 | C16: =C11*68% -> 106904.47 | D16: =D11*68% -> 107128.97 | E16: =E11*68% -> 107353.94 | F16: =F11*68% -> 107579.38 | G16: =G11*68% -> 107805.3 | H16: =H11*68% -> 108031.69 | I16: =I11*68% -> 108258.56 | ... M16: =M11*68% -> 109170.8 | N16: =SUM(B16:M16) -> 1295055.2
A17: Gross Profit | B17: =B11-B16 -> 50202.56 | C17: =C11-C16 -> 50307.985 | D17: =D11-D16 -> 50413.632 | E17: =E11-E16 -> 50519.501 | F17: =F11-F16 -> 50625.592 | G17: =G11-G16 -> 50731.905 | H17: =H11-H16 -> 50838.442 | I17: =I11-I16 -> 50945.203 | ... N17: =N11-N16 -> 609437.73
A18: Expenses
A19: Advertising | B19: 4944.48 | C19: 4440.17 | D19: 4754.76 | E19: 4545.76 | F19: 4272.29 | G19: 3155.95 | H19: 4440.17 | I19: 4030.35 | J19: 3155.95 | K19: 4510.38 | L19: 4754.76 | M19: 4272.29 | N19: =SUM(B19:M19) -> 51277.31
A20: Automobile Expense | B20: 424.05 | C20: 840.26 | D20: 610.37 | E20: 1127.68 | F20: 423.75 | G20: 72.54 | H20: 849.18 | I20: 1126.87 | J20: 72.54 | K20: 854.65 | L20: 424.05 | M20: 423.75 | N20: =SUM(B20:M20) -> 7249.69
A21: Gas | B21: 60.81 | C21: 646.36 | D21: 210.63 | E21: 125 | F21: 64.6 | G21: 195.82 | H21: 653.22 | I21: 78.48 | J21: 195.82 | K21: 657.42 | L21: 60.81 | M21: 64.6 | N21: =SUM(B21:M21) -> 3013.57
A22: Parking | B22: 32.95 | C22: 64.64 | D22: 24.11 | E22: 5.55 | F22: 32.95 | G22: 32.95 | H22: 65.32 | I22: 15.4 | J22: 32.95 | K22: 65.74 | L22: 32.95 | M22: 32.95 | N22: =SUM(B22:M22) -> 438.46
A23: Total for Automobile Expense | B23: =B20+B21+B22 -> 517.81 | C23: =C20+C21+C22 -> 1551.26 | D23: =D20+D21+D22 -> 845.11 | E23: =E20+E21+E22 -> 1258.23 | F23: =F20+F21+F22 -> 521.3 | G23: =G20+G21+G22 -> 301.31 | H23: =H20+H21+H22 -> 1567.72 | I23: =I20+I21+I22 -> 1220.75 | ... M23: =M20+M21+M22 -> 521.3 | N23: =SUM(B23:M23) -> 10701.72
A24: Bank Fees | B24: 478.1 | C24: 227.68 | D24: 168.12 | E24: 230.19 | F24: 61.61 | G24: 224.65 | H24: 261.29 | I24: 180.11 | J24: 224.65 | K24: 262.97 | L24: 475.1 | M24: 61.61 | N24: =SUM(B24:M24) -> 2856.08
A25: Charitable & Donations | B25: 89.94 | C25: 90.66 | D25: 90.33 | E25: 90.27 | F25: 90.6 | G25: 90.46 | H25: 90.27 | I25: 90.2 | J25: 90.46 | K25: 854.65 | L25: 89.94 | M25: 90.6 | N25: =SUM(B25:M25) -> 1848.38
A26: Computer Expense | B26: 479.7 | C26: 483.53 | D26: 481.78 | E26: 481.43 | F26: 483.17 | G26: 482.47 | H26: 481.43 | I26: 481.08 | J26: 482.47 | K26: 854.65 | L26: 479.7 | M26: 483.17 | N26: =SUM(B26:M26) -> 6154.58
A27: Dues & Subscriptions | B27: 1683.8 | C27: 1522.34 | D27: 1686.22 | E27: 1685.01 | F27: 1691.11 | G27: 1688.66 | H27: 816.52 | I27: 1683.79 | J27: 1688.66 | K27: 854.65 | L27: 1683.8 | M27: 1691.11 | N27: =SUM(B27:M27) -> 18375.67
A28: Entertainment | B28: 1168.27 | C28: 1078.83 | D28: 2841.96 | E28: 1711.78 | F28: 1360.96 | G28: 786.23 | H28: 816.52 | I28: 1712.42 | J28: 786.23 | K28: 854.65 | L28: 1168.27 | M28: 1360.96 | N28: =SUM(B28:M28) -> 15647.08
A29: Insurance | B29: 284.86 | C29: 285.07 | D29: 625.06 | E29: 306.36 | F29: 306.36 | G29: 286.51 | H29: 286.51 | I29: 285.67 | J29: 286.51 | K29: 854.65 | L29: 284.86 | M29: 306.36 | N29: =SUM(B29:M29) -> 4398.78
A30: Interest Expense | B30: 599.63 | C30: 604.41 | D30: 602.22 | E30: 601.79 | F30: 603.97 | G30: 603.09 | H30: 601.79 | I30: 501.35 | J30: 603.09 | K30: 854.65 | L30: 599.63 | M30: 603.97 | N30: =SUM(B30:M30) -> 7379.59
A31: Legal Fees | B31: 474.41 | C31: 2344.87 | D31: 975.43 | E31: 474.41 | F31: 809.5 | G31: 1884.73 | H31: 1306.43 | I31: 2344.87 | J31: 1884.73 | K31: 1314.84 | L31: 474.41 | M31: 809.5 | N31: =SUM(B31:M31) -> 15098.13
A32: Lodging | B32: 809.5 | C32: 624 | D32: 602.22 | E32: 601.79 | F32: 603.97 | G32: 603.09 | H32: 624 | I32: 601.35 | J32: 603.09 | K32: 854.65 | L32: 809.5 | M32: 603.97 | N32: =SUM(B32:M32) -> 7941.13
A33: Marketing | B33: =B11*18% -> 28238.94 | C33: =C11*18% -> 28298.242 | D33: =D11*18% -> 28357.668 | E33: =E11*18% -> 28417.219 | F33: =F11*18% -> 28476.895 | G33: =G11*18% -> 28536.697 | H33: =H11*18% -> 28596.624 | I33: =I11*18% -> 28656.677 | ... M33: =M11*18% -> 28898.152 | N33: =SUM(B33:M33) -> 342808.72
A34: Meals | B34: 2922.88 | C34: 2924.98 | D34: 2120.45 | E34: 3338.99 | F34: 4216.46 | G34: 2525.28 | H34: 3081.36 | I34: 4216.46 | J34: 2525.28 | K34: 2209.55 | L34: 2922.88 | M34: 4216.46 | N34: =SUM(B34:M34) -> 37221.03
A35: Medical | B35: 312.22 | C35: 271.68 | D35: 74.06 | E35: 88.29 | F35: 312 | G35: 312 | H35: 816.52 | I35: 74.06 | J35: 312 | K35: 854.65 | L35: 312.22 | M35: 312 | N35: =SUM(B35:M35) -> 4051.7
A36: Membership | B36: 159.41 | C36: 336.78 | D36: 337.26 | E36: 480.92 | F36: 337.26 | G36: 351.37 | H36: 1222.67 | I36: 336.78 | J36: 351.37 | K36: 854.65 | L36: 159.41 | M36: 337.26 | N36: =SUM(B36:M36) -> 5265.14
A37: Merchant Fees | B37: 243.52 | C37: 258.77 | D37: 260.1 | E37: 185.55 | F37: 258.58 | G37: 258.2 | H37: 313 | I37: 240.81 | J37: 258.2 | K37: 854.65 | L37: 243.52 | M37: 258.58 | N37: =SUM(B37:M37) -> 3633.48
A38: Stripe Fee | B38: 98.6 | C38: 99.31 | D38: 98.95 | E38: 98.88 | F38: 99.24 | G38: 99.1 | H38: 816.52 | I38: 98.81 | J38: 99.1 | K38: 854.65 | L38: 98.6 | M38: 99.24 | N38: =SUM(B38:M38) -> 2661
A39: Total for Merchant Fees | B39: =B37+B38 -> 342.12 | C39: =C37+C38 -> 358.08 | D39: =D37+D38 -> 359.05 | E39: =E37+E38 -> 284.43 | F39: =F37+F38 -> 357.82 | G39: =G37+G38 -> 357.3 | H39: =H37+H38 -> 1129.52 | I39: =I37+I38 -> 339.62 | ... M39: =M37+M38 -> 357.82 | N39: =SUM(B39:M39) -> 6294.48
A40: Miscellaneous | B40: 385.86 | C40: 571.69 | D40: 570.9 | E40: 569.21 | F40: 157.41 | G40: 154.1 | H40: 816.52 | I40: 834.26 | J40: 157.19 | K40: 854.65 | L40: 388.2 | M40: 157.41 | N40: =SUM(B40:M40) -> 5617.4
A41: Office Expense | B41: 3302.34 | C41: 3272.34 | D41: 4440.6 | E41: 6447.72 | F41: 3243.59 | G41: 5431.48 | H41: 5373.86 | I41: 4580.6 | J41: 5431.48 | K41: 4040.06 | L41: 2535.33 | M41: 3243.59 | N41: =SUM(B41:M41) -> 51342.99
A42: Other General & Administrative | B42: 680.5 | C42: 1313.11 | D42: 3533.29 | E42: 1313.11 | F42: 2068.28 | G42: 924.98 | H42: 816.52 | I42: 409.96 | J42: 924.98 | K42: 854.65 | L42: 680.5 | M42: 2068.28 | N42: =SUM(B42:M42) -> 15588.16
A43: Outside Consultants | B43: 12912.1 | C43: 11269.46 | D43: 8431.11 | E43: 7823.24 | F43: 11475.39 | G43: 13841.14 | H43: 8431.11 | I43: 8418.96 | J43: 13871.14 | K43: 9864.69 | L43: 13871.14 | M43: 11475.39 | N43: =SUM(B43:M43) -> 131684.87
A44: Paypal fees | B44: 339.09 | C44: 344.5 | D44: 339.82 | E44: 339.58 | F44: 340.81 | G44: 340.31 | H44: 816.52 | I44: 339.33 | J44: 306.31 | K44: 340.31 | L44: 339.09 | M44: 340.81 | N44: =SUM(B44:M44) -> 4526.48
A45: Postage | B45: 20.22 | C45: 20.1 | D45: 20.1 | E45: 20.1 | F45: 20.1 | G45: 20.1 | H45: 20.1 | I45: 20.1 | J45: 20.1 | K45: 20.1 | L45: 20.09 | M45: 20.1 | N45: =SUM(B45:M45) -> 241.31
A46: Prime Video | B46: 39.62 | C46: 39.85 | D46: 39.71 | E46: 39.68 | F46: 39.82 | G46: 39.77 | H46: 816.52 | I46: 29.65 | J46: 39.77 | K46: 39.77 | L46: 39.62 | M46: 39.82 | N46: =SUM(B46:M46) -> 1243.6
A47: Professional Fees | B47: 1642.27 | C47: 604.41 | D47: 1871.8 | E47: 1870.45 | F47: 1205.2 | G47: 177.16 | H47: 816.52 | I47: 1869.1 | J47: 177.16 | K47: 177.16 | L47: 1642.27 | M47: 1207.94 | N47: =SUM(B47:M47) -> 13261.44
A48: Rent | B48: 1802.77 | C48: 1813.22 | D48: 1806.67 | E48: 1805.36 | F48: 1811.9 | G48: 1809.28 | H48: 1763.04 | I48: 1804.06 | J48: 1809.28 | K48: 1663.55 | L48: 1802.77 | M48: 1809.2 | N48: =SUM(B48:M48) -> 21501.1
A49: Software & Apps | B49: 505.64 | C49: 505.64 | D49: 505.64 | E49: 505.64 | F49: 505.64 | G49: 505.64 | H49: 816.52 | I49: 505.64 | J49: 505.64 | K49: 854.65 | L49: 505.64 | M49: 505.64 | N49: =SUM(B49:M49) -> 6727.57
A50: Travel | B50: 2452.22 | C50: 2452.22 | D50: 1226.02 | E50: 2436.22 | F50: 2452.22 | G50: 2452.22 | H50: 816.52 | I50: 2439.12 | J50: 2452.22 | K50: 854.65 | L50: 2452.22 | M50: 2452.22 | N50: =SUM(B50:M50) -> 24938.07
A51: Uber | B51: 150.23 | C51: 151.1 | D51: 150.56 | E51: 150.45 | F51: 150.99 | G51: 150.77 | H51: 653.22 | I51: 150.34 | J51: 150.77 | K51: 657.42 | L51: 150.23 | M51: 150.99 | N51: =SUM(B51:M51) -> 2817.07
A52: Total for Expenses | B52: =Explaination!D83+B33 -> 67738.94 | C52: =39500+C33 -> 67798.242 | D52: =39500+D33 -> 67857.668 | E52: =39500+E33 -> 67917.219 | F52: =39500+F33 -> 67976.895 | G52: =39500+G33 -> 68036.697 | H52: =39500+H33 -> 68096.624 | I52: =39500+I33 -> 68156.677 | J52: =39500+J33 -> 68216.856 | ... M52: =39500+M33 -> 68398.152 | N52: =SUM(B52:M52) -> 816808.72
A53: Net Operating Income
A54: Net Other Income
A55: Net Income | B55: =B17-B52 -> -17536.38 | C55: =C17-C52 -> -17490.256 | D55: =D17-D52 -> -17444.036 | E55: =E17-E52 -> -17397.718 | F55: =F17-F52 -> -17351.304 | G55: =G17-G52 -> -17304.791 | H55: =H17-H52 -> -17258.181 | I55: =I17-I52 -> -17211.474 | ... N55: =N17-N52 -> -207370.99

Sheet Forecast P&L 2027 2
A2: Projection for the year 2027 (Base)
A3: Distribution account | B3: 46388 | C3: 46419 | D3: 46447 | E3: 46478 | F3: 46508 | G3: 46539 | H3: 46569 | I3: 46600 | J3: 46631 | K3: 46661 | L3: 46692 | M3: 46722 | N3: Total
A4: Income
A5: ECOMM PayPal Sales | B5: 20921.9 | C5: 21858.94 | D5: 25168.84 | E5: 18298.17 | F5: 19622.29 | G5: 20207.31 | H5: 36549.6 | I5: 17284.49 | J5: 13508.68 | K5: 16155.86 | L5: 23414.33 | M5: 15691.76 | N5: =SUM(B5:M5) -> 248682.17
A6: ECOMM Shopify Sales | B6: 138696.31 | C6: 138830.82 | D6: 138430.75 | E6: 147890.34 | F6: 146714.73 | G6: 144855.19 | H6: 132429.66 | I6: 151470.77 | J6: 111444.86 | K6: 154676.08 | L6: 143123.01 | M6: 156917.57 | N6: =SUM(B6:M6) -> 1705480.1
A7: ECOMM Stripe Sales | B7: 15580.12 | C7: 15156.81 | D7: 12033.84 | E7: 10961.74 | F7: 11468.67 | G7: 13401.07 | H7: 10144.63 | I7: 9307.78 | J7: 9969.24 | K7: 10287.59 | L7: 15252.15 | M7: 9852.96 | N7: =SUM(B7:M7) -> 143416.6
A8: other income | B8: - | C8: - | D8: - | E8: - | F8: - | G8: - | H8: - | I8: - | J8: 45528.48 | K8: - | L8: - | M8: - | N8: =SUM(B8:M8) -> 45528.48
A9: Sales of Product Income | B9: - | C9: - | D9: 864.84 | E9: - | F9: - | G9: - | H9: - | I9: 1724.15 | J9: - | K9: - | L9: - | M9: - | N9: =SUM(B9:M9) -> 2588.99
A10: Sales Tax | B10: - | C10: - | D10: - | E10: - | F10: - | G10: - | H10: - | I10: - | J10: - | K10: - | L10: - | M10: - | N10: -
A11: Total for Income | B11: =Explaination!E78 -> 175198.33 | C11: =B11*100.37% -> 175846.57 | D11: =C11*100.37% -> 176497.2 | E11: =D11*100.37% -> 177150.24 | F11: =E11*100.37% -> 177805.7 | G11: =F11*100.37% -> 178463.58 | H11: =G11*100.37% -> 179123.89 | I11: =H11*100.37% -> 179786.65 | J11: =I11*100.37% -> 180451.86 | ... M11: =L11*100.37% -> 182462.3 | N11: =SUM(B11:M11) -> 2145695.5
A12: Cost of Goods Sold
A13: Cost of Goods Sold | B13: 59404.98 | C13: 31764.03 | D13: 49287.8 | E13: 16688.25 | F13: 26399.48 | G13: 36237.95 | H13: 33722.37 | I13: 39979.04 | J13: 27074.54 | K13: 10985.99 | L13: 15909.51 | M13: 10670.4 | N13: =SUM(B13:M13) -> 358124.34
A14: Cost of labor - COS | B14: 23308.52 | C14: 44953.9 | D14: 33110.8 | E14: 55455.5 | F14: 55867.35 | G14: 45277.16 | H14: 47251.45 | I14: 46002.42 | J14: 63050.7 | K14: 105179.73 | L14: 97323.65 | M14: 106703.95 | N14: =SUM(B14:M14) -> 723485.13
A15: Freight & Delivery | B15: 36421.36 | C15: 42857.74 | D15: 37619.49 | E15: 48318.42 | F15: 38641.05 | G15: 39840.12 | H15: 40830.43 | I15: 36273.47 | J15: 32582.03 | K15: 6995.56 | L15: 10371.46 | M15: 6700.02 | N15: =SUM(B15:M15) -> 377451.15
A16: Total for Cost of Goods Sold | B16: =B11*68% -> 119134.87 | C16: =C11*68% -> 119575.67 | D16: =D11*68% -> 120018.1 | E16: =E11*68% -> 120462.16 | F16: =F11*68% -> 120907.87 | G16: =G11*68% -> 121355.23 | H16: =H11*68% -> 121804.25 | I16: =I11*68% -> 122254.92 | ... M16: =M11*68% -> 124074.36 | N16: =SUM(B16:M16) -> 1459072.9
A17: Gross Profit | B17: =B11-B16 -> 56063.467 | C17: =C11-C16 -> 56270.901 | D17: =D11-D16 -> 56479.104 | E17: =E11-E16 -> 56688.077 | F17: =F11-F16 -> 56897.822 | G17: =G11-G16 -> 57108.344 | H17: =H11-H16 -> 57319.645 | I17: =I11-I16 -> 57531.728 | ... N17: =N11-N16 -> 686622.56
A18: Expenses
A19: Advertising | B19: 4944.48 | C19: 4440.17 | D19: 4754.76 | E19: 4545.76 | F19: 4272.29 | G19: 3155.95 | H19: 4440.17 | I19: 4030.35 | J19: 3155.95 | K19: 4510.38 | L19: 4754.76 | M19: 4272.29 | N19: =SUM(B19:M19) -> 51277.31
A20: Automobile Expense | B20: 424.05 | C20: 840.26 | D20: 610.37 | E20: 1127.68 | F20: 423.75 | G20: 72.54 | H20: 849.18 | I20: 1126.87 | J20: 72.54 | K20: 854.65 | L20: 424.05 | M20: 423.75 | N20: =SUM(B20:M20) -> 7249.69
A21: Gas | B21: 60.81 | C21: 646.36 | D21: 210.63 | E21: 125 | F21: 64.6 | G21: 195.82 | H21: 653.22 | I21: 78.48 | J21: 195.82 | K21: 657.42 | L21: 60.81 | M21: 64.6 | N21: =SUM(B21:M21) -> 3013.57
A22: Parking | B22: 32.95 | C22: 64.64 | D22: 24.11 | E22: 5.55 | F22: 32.95 | G22: 32.95 | H22: 65.32 | I22: 15.4 | J22: 32.95 | K22: 65.74 | L22: 32.95 | M22: 32.95 | N22: =SUM(B22:M22) -> 438.46
A23: Total for Automobile Expense | B23: =B20+B21+B22 -> 517.81 | C23: =C20+C21+C22 -> 1551.26 | D23: =D20+D21+D22 -> 845.11 | E23: =E20+E21+E22 -> 1258.23 | F23: =F20+F21+F22 -> 521.3 | G23: =G20+G21+G22 -> 301.31 | H23: =H20+H21+H22 -> 1567.72 | I23: =I20+I21+I22 -> 1220.75 | ... M23: =M20+M21+M22 -> 521.3 | N23: =SUM(B23:M23) -> 10701.72
A24: Bank Fees | B24: 478.1 | C24: 227.68 | D24: 168.12 | E24: 230.19 | F24: 61.61 | G24: 224.65 | H24: 261.29 | I24: 180.11 | J24: 224.65 | K24: 262.97 | L24: 475.1 | M24: 61.61 | N24: =SUM(B24:M24) -> 2856.08
A25: Charitable & Donations | B25: 89.94 | C25: 90.66 | D25: 90.33 | E25: 90.27 | F25: 90.6 | G25: 90.46 | H25: 90.27 | I25: 90.2 | J25: 90.46 | K25: 854.65 | L25: 89.94 | M25: 90.6 | N25: =SUM(B25:M25) -> 1848.38
A26: Computer Expense | B26: 479.7 | C26: 483.53 | D26: 481.78 | E26: 481.43 | F26: 483.17 | G26: 482.47 | H26: 481.43 | I26: 481.08 | J26: 482.47 | K26: 854.65 | L26: 479.7 | M26: 483.17 | N26: =SUM(B26:M26) -> 6154.58
A27: Dues & Subscriptions | B27: 1683.8 | C27: 1522.34 | D27: 1686.22 | E27: 1685.01 | F27: 1691.11 | G27: 1688.66 | H27: 816.52 | I27: 1683.79 | J27: 1688.66 | K27: 854.65 | L27: 1683.8 | M27: 1691.11 | N27: =SUM(B27:M27) -> 18375.67
A28: Entertainment | B28: 1168.27 | C28: 1078.83 | D28: 2841.96 | E28: 1711.78 | F28: 1360.96 | G28: 786.23 | H28: 816.52 | I28: 1712.42 | J28: 786.23 | K28: 854.65 | L28: 1168.27 | M28: 1360.96 | N28: =SUM(B28:M28) -> 15647.08
A29: Insurance | B29: 284.86 | C29: 285.07 | D29: 625.06 | E29: 306.36 | F29: 306.36 | G29: 286.51 | H29: 286.51 | I29: 285.67 | J29: 286.51 | K29: 854.65 | L29: 284.86 | M29: 306.36 | N29: =SUM(B29:M29) -> 4398.78
A30: Interest Expense | B30: 599.63 | C30: 604.41 | D30: 602.22 | E30: 601.79 | F30: 603.97 | G30: 603.09 | H30: 601.79 | I30: 501.35 | J30: 603.09 | K30: 854.65 | L30: 599.63 | M30: 603.97 | N30: =SUM(B30:M30) -> 7379.59
A31: Legal Fees | B31: 474.41 | C31: 2344.87 | D31: 975.43 | E31: 474.41 | F31: 809.5 | G31: 1884.73 | H31: 1306.43 | I31: 2344.87 | J31: 1884.73 | K31: 1314.84 | L31: 474.41 | M31: 809.5 | N31: =SUM(B31:M31) -> 15098.13
A32: Lodging | B32: 809.5 | C32: 624 | D32: 602.22 | E32: 601.79 | F32: 603.97 | G32: 603.09 | H32: 624 | I32: 601.35 | J32: 603.09 | K32: 854.65 | L32: 809.5 | M32: 603.97 | N32: =SUM(B32:M32) -> 7941.13
A33: Marketing | B33: =B11*18% -> 31535.7 | C33: 31535.7 | D33: 31535.7 | E33: 31535.7 | F33: 31535.7 | G33: 31535.7 | H33: 31535.7 | I33: 31535.7 | J33: 31535.7 | K33: 31535.7 | L33: 31535.7 | M33: 31535.7 | N33: =SUM(B33:M33) -> 378428.4
A34: Meals | B34: 2922.88 | C34: 2924.98 | D34: 2120.45 | E34: 3338.99 | F34: 4216.46 | G34: 2525.28 | H34: 3081.36 | I34: 4216.46 | J34: 2525.28 | K34: 2209.55 | L34: 2922.88 | M34: 4216.46 | N34: =SUM(B34:M34) -> 37221.03
A35: Medical | B35: 312.22 | C35: 271.68 | D35: 74.06 | E35: 88.29 | F35: 312 | G35: 312 | H35: 816.52 | I35: 74.06 | J35: 312 | K35: 854.65 | L35: 312.22 | M35: 312 | N35: =SUM(B35:M35) -> 4051.7
A36: Membership | B36: 159.41 | C36: 336.78 | D36: 337.26 | E36: 480.92 | F36: 337.26 | G36: 351.37 | H36: 1222.67 | I36: 336.78 | J36: 351.37 | K36: 854.65 | L36: 159.41 | M36: 337.26 | N36: =SUM(B36:M36) -> 5265.14
A37: Merchant Fees | B37: 243.52 | C37: 258.77 | D37: 260.1 | E37: 185.55 | F37: 258.58 | G37: 258.2 | H37: 313 | I37: 240.81 | J37: 258.2 | K37: 854.65 | L37: 243.52 | M37: 258.58 | N37: =SUM(B37:M37) -> 3633.48
A38: Stripe Fee | B38: 98.6 | C38: 99.31 | D38: 98.95 | E38: 98.88 | F38: 99.24 | G38: 99.1 | H38: 816.52 | I38: 98.81 | J38: 99.1 | K38: 854.65 | L38: 98.6 | M38: 99.24 | N38: =SUM(B38:M38) -> 2661
A39: Total for Merchant Fees | B39: =B37+B38 -> 342.12 | C39: =C37+C38 -> 358.08 | D39: =D37+D38 -> 359.05 | E39: =E37+E38 -> 284.43 | F39: =F37+F38 -> 357.82 | G39: =G37+G38 -> 357.3 | H39: =H37+H38 -> 1129.52 | I39: =I37+I38 -> 339.62 | ... M39: =M37+M38 -> 357.82 | N39: =SUM(B39:M39) -> 6294.48
A40: Miscellaneous | B40: 385.86 | C40: 571.69 | D40: 570.9 | E40: 569.21 | F40: 157.41 | G40: 154.1 | H40: 816.52 | I40: 834.26 | J40: 157.19 | K40: 854.65 | L40: 388.2 | M40: 157.41 | N40: =SUM(B40:M40) -> 5617.4
A41: Office Expense | B41: 3302.34 | C41: 3272.34 | D41: 4440.6 | E41: 6447.72 | F41: 3243.59 | G41: 5431.48 | H41: 5373.86 | I41: 4580.6 | J41: 5431.48 | K41: 4040.06 | L41: 2535.33 | M41: 3243.59 | N41: =SUM(B41:M41) -> 51342.99
A42: Other General & Administrative | B42: 680.5 | C42: 1313.11 | D42: 3533.29 | E42: 1313.11 | F42: 2068.28 | G42: 924.98 | H42: 816.52 | I42: 409.96 | J42: 924.98 | K42: 854.65 | L42: 680.5 | M42: 2068.28 | N42: =SUM(B42:M42) -> 15588.16
A43: Outside Consultants | B43: 12912.1 | C43: 11269.46 | D43: 8431.11 | E43: 7823.24 | F43: 11475.39 | G43: 13841.14 | H43: 8431.11 | I43: 8418.96 | J43: 13871.14 | K43: 9864.69 | L43: 13871.14 | M43: 11475.39 | N43: =SUM(B43:M43) -> 131684.87
A44: Paypal fees | B44: 339.09 | C44: 344.5 | D44: 339.82 | E44: 339.58 | F44: 340.81 | G44: 340.31 | H44: 816.52 | I44: 339.33 | J44: 306.31 | K44: 340.31 | L44: 339.09 | M44: 340.81 | N44: =SUM(B44:M44) -> 4526.48
A45: Postage | B45: 20.22 | C45: 20.1 | D45: 20.1 | E45: 20.1 | F45: 20.1 | G45: 20.1 | H45: 20.1 | I45: 20.1 | J45: 20.1 | K45: 20.1 | L45: 20.09 | M45: 20.1 | N45: =SUM(B45:M45) -> 241.31
A46: Prime Video | B46: 39.62 | C46: 39.85 | D46: 39.71 | E46: 39.68 | F46: 39.82 | G46: 39.77 | H46: 816.52 | I46: 29.65 | J46: 39.77 | K46: 39.77 | L46: 39.62 | M46: 39.82 | N46: =SUM(B46:M46) -> 1243.6
A47: Professional Fees | B47: 1642.27 | C47: 604.41 | D47: 1871.8 | E47: 1870.45 | F47: 1205.2 | G47: 177.16 | H47: 816.52 | I47: 1869.1 | J47: 177.16 | K47: 177.16 | L47: 1642.27 | M47: 1207.94 | N47: =SUM(B47:M47) -> 13261.44
A48: Rent | B48: 1802.77 | C48: 1813.22 | D48: 1806.67 | E48: 1805.36 | F48: 1811.9 | G48: 1809.28 | H48: 1763.04 | I48: 1804.06 | J48: 1809.28 | K48: 1663.55 | L48: 1802.77 | M48: 1809.2 | N48: =SUM(B48:M48) -> 21501.1
A49: Software & Apps | B49: 505.64 | C49: 505.64 | D49: 505.64 | E49: 505.64 | F49: 505.64 | G49: 505.64 | H49: 816.52 | I49: 505.64 | J49: 505.64 | K49: 854.65 | L49: 505.64 | M49: 505.64 | N49: =SUM(B49:M49) -> 6727.57
A50: Travel | B50: 2452.22 | C50: 2452.22 | D50: 1226.02 | E50: 2436.22 | F50: 2452.22 | G50: 2452.22 | H50: 816.52 | I50: 2439.12 | J50: 2452.22 | K50: 854.65 | L50: 2452.22 | M50: 2452.22 | N50: =SUM(B50:M50) -> 24938.07
A51: Uber | B51: 150.23 | C51: 151.1 | D51: 150.56 | E51: 150.45 | F51: 150.99 | G51: 150.77 | H51: 653.22 | I51: 150.34 | J51: 150.77 | K51: 657.42 | L51: 150.23 | M51: 150.99 | N51: =SUM(B51:M51) -> 2817.07
A52: Total for Expenses | B52: =Explaination!F83+B33 -> 71035.7 | C52: =39500+C33 -> 71035.7 | D52: =39500+D33 -> 71035.7 | E52: =39500+E33 -> 71035.7 | F52: =39500+F33 -> 71035.7 | G52: =39500+G33 -> 71035.7 | H52: =39500+H33 -> 71035.7 | I52: =39500+I33 -> 71035.7 | J52: =39500+J33 -> 71035.7 | ... M52: =39500+M33 -> 71035.7 | N52: =SUM(B52:M52) -> 852428.4
A53: Net Operating Income
A54: Net Other Income
A55: Net Income | B55: =B17-B52 -> -14972.233 | C55: =C17-C52 -> -14764.799 | D55: =D17-D52 -> -14556.596 | E55: =E17-E52 -> -14347.623 | F55: =F17-F52 -> -14137.878 | G55: =G17-G52 -> -13927.356 | H55: =H17-H52 -> -13716.055 | I55: =I17-I52 -> -13503.972 | ... N55: =N17-N52 -> -165805.84

Sheet Forecast P&L 2027 3
A2: Projection for the year 2027 (Optimistic)
A3: Distribution account | B3: 46388 | C3: 46419 | D3: 46447 | E3: 46478 | F3: 46508 | G3: 46539 | H3: 46569 | I3: 46600 | J3: 46631 | K3: 46661 | L3: 46692 | M3: 46722 | N3: Total
A4: Income
A5: ECOMM PayPal Sales | B5: 24713.47 | C5: 25864.05 | D5: 29830.85 | E5: 21724.26 | F5: 23335.76 | G5: 24072.2 | H5: 43613.89 | I5: 20660.17 | J5: 16174.28 | K5: 19376.59 | L5: 28107.99 | M5: 18883.77 | N5: =SUM(B5:M5) -> 296357.28
A6: ECOMM Shopify Sales | B6: 163831.5 | C6: 164268.13 | D6: 164072.19 | E6: 175580.85 | F6: 174480.15 | G6: 172560.48 | H6: 158025.61 | I6: 181053.12 | J6: 133435.75 | K6: 185511.25 | L6: 171945.78 | M6: 188837.66 | N6: =SUM(B6:M6) -> 2033602.5
A7: ECOMM Stripe Sales | B7: 18403.62 | C7: 17933.92 | D7: 14262.86 | E7: 13014.18 | F7: 13639.09 | G7: 15964.19 | H7: 12105.38 | I7: 11125.6 | J7: 11936.42 | K7: 12338.45 | L7: 18323.7 | M7: 11857.25 | N7: =SUM(B7:M7) -> 170904.66
A8: other income | B8: - | C8: - | D8: - | E8: - | F8: - | G8: - | H8: - | I8: - | J8: 54621.35 | K8: - | L8: - | M8: - | N8: =SUM(B8:M8) -> 54621.35
A9: Sales of Product Income | B9: - | C9: - | D9: 1025.03 | E9: - | F9: - | G9: - | H9: - | I9: 2060.88 | J9: - | K9: - | L9: - | M9: - | N9: =SUM(B9:M9) -> 3085.91
A10: Sales Tax | B10: - | C10: - | D10: - | E10: - | F10: - | G10: - | H10: - | I10: - | J10: - | K10: - | L10: - | M10: - | N10: -
A11: Total for Income | B11: =Explaination!F78 -> 206948.58 | C11: =B11*100.54% -> 208066.11 | D11: =C11*100.54% -> 209189.66 | E11: =D11*100.54% -> 210319.29 | F11: =E11*100.54% -> 211455.01 | G11: =F11*100.54% -> 212596.87 | H11: =G11*100.54% -> 213744.89 | I11: =H11*100.54% -> 214899.11 | J11: =I11*100.54% -> 216059.57 | ... M11: =L11*100.54% -> 219578.67 | N11: =SUM(B11:M11) -> 2558483.4
A12: Cost of Goods Sold
A13: Cost of Goods Sold | B13: 70170.63 | C13: 37584 | D13: 58417.35 | E13: 19812.9 | F13: 31395.52 | G13: 43168.89 | H13: 40240.22 | I13: 47786.98 | J13: 32417.03 | K13: 13176.08 | L13: 19113.43 | M13: 12840.96 | N13: =SUM(B13:M13) -> 426123.99
A14: Cost of labor - COS | B14: 27532.6 | C14: 53190.59 | D14: 39243.89 | E14: 65838.81 | F14: 66440.11 | G14: 53936.96 | H14: 56384.19 | I14: 54986.72 | J14: 75492.19 | K14: 126147.65 | L14: 116923.13 | M14: 128409.61 | N14: =SUM(B14:M14) -> 864526.45
A15: Freight & Delivery | B15: 43021.81 | C15: 50710.36 | D15: 44587.73 | E15: 57365.4 | F15: 45953.78 | G15: 47460.02 | H15: 48722.12 | I15: 43357.7 | J15: 39011.28 | K15: 8390.15 | L15: 12460.12 | M15: 8062.93 | N15: =SUM(B15:M15) -> 449103.4
A16: Total for Cost of Goods Sold | B16: =B11*68% -> 140725.04 | C16: =C11*68% -> 141484.95 | D16: =D11*68% -> 142248.97 | E16: =E11*68% -> 143017.11 | F16: =F11*68% -> 143789.41 | G16: =G11*68% -> 144565.87 | H16: =H11*68% -> 145346.53 | I16: =I11*68% -> 146131.4 | ... M16: =M11*68% -> 149313.49 | N16: =SUM(B16:M16) -> 1739768.7
A17: Gross Profit | B17: =B11-B16 -> 66223.547 | C17: =C11-C16 -> 66581.154 | D17: =D11-D16 -> 66940.692 | E17: =E11-E16 -> 67302.172 | F17: =F11-F16 -> 67665.604 | G17: =G11-G16 -> 68030.998 | H17: =H11-H16 -> 68398.365 | I17: =I11-I16 -> 68767.716 | ... N17: =N11-N16 -> 818714.68
A18: Expenses
A19: Advertising | B19: 4944.48 | C19: 4440.17 | D19: 4754.76 | E19: 4545.76 | F19: 4272.29 | G19: 3155.95 | H19: 4440.17 | I19: 4030.35 | J19: 3155.95 | K19: 4510.38 | L19: 4754.76 | M19: 4272.29 | N19: =SUM(B19:M19) -> 51277.31
A20: Automobile Expense | B20: 424.05 | C20: 840.26 | D20: 610.37 | E20: 1127.68 | F20: 423.75 | G20: 72.54 | H20: 849.18 | I20: 1126.87 | J20: 72.54 | K20: 854.65 | L20: 424.05 | M20: 423.75 | N20: =SUM(B20:M20) -> 7249.69
A21: Gas | B21: 60.81 | C21: 646.36 | D21: 210.63 | E21: 125 | F21: 64.6 | G21: 195.82 | H21: 653.22 | I21: 78.48 | J21: 195.82 | K21: 657.42 | L21: 60.81 | M21: 64.6 | N21: =SUM(B21:M21) -> 3013.57
A22: Parking | B22: 32.95 | C22: 64.64 | D22: 24.11 | E22: 5.55 | F22: 32.95 | G22: 32.95 | H22: 65.32 | I22: 15.4 | J22: 32.95 | K22: 65.74 | L22: 32.95 | M22: 32.95 | N22: =SUM(B22:M22) -> 438.46
A23: Total for Automobile Expense | B23: =B20+B21+B22 -> 517.81 | C23: =C20+C21+C22 -> 1551.26 | D23: =D20+D21+D22 -> 845.11 | E23: =E20+E21+E22 -> 1258.23 | F23: =F20+F21+F22 -> 521.3 | G23: =G20+G21+G22 -> 301.31 | H23: =H20+H21+H22 -> 1567.72 | I23: =I20+I21+I22 -> 1220.75 | ... M23: =M20+M21+M22 -> 521.3 | N23: =SUM(B23:M23) -> 10701.72
A24: Bank Fees | B24: 478.1 | C24: 227.68 | D24: 168.12 | E24: 230.19 | F24: 61.61 | G24: 224.65 | H24: 261.29 | I24: 180.11 | J24: 224.65 | K24: 262.97 | L24: 475.1 | M24: 61.61 | N24: =SUM(B24:M24) -> 2856.08
A25: Charitable & Donations | B25: 89.94 | C25: 90.66 | D25: 90.33 | E25: 90.27 | F25: 90.6 | G25: 90.46 | H25: 90.27 | I25: 90.2 | J25: 90.46 | K25: 854.65 | L25: 89.94 | M25: 90.6 | N25: =SUM(B25:M25) -> 1848.38
A26: Computer Expense | B26: 479.7 | C26: 483.53 | D26: 481.78 | E26: 481.43 | F26: 483.17 | G26: 482.47 | H26: 481.43 | I26: 481.08 | J26: 482.47 | K26: 854.65 | L26: 479.7 | M26: 483.17 | N26: =SUM(B26:M26) -> 6154.58
A27: Dues & Subscriptions | B27: 1683.8 | C27: 1522.34 | D27: 1686.22 | E27: 1685.01 | F27: 1691.11 | G27: 1688.66 | H27: 816.52 | I27: 1683.79 | J27: 1688.66 | K27: 854.65 | L27: 1683.8 | M27: 1691.11 | N27: =SUM(B27:M27) -> 18375.67
A28: Entertainment | B28: 1168.27 | C28: 1078.83 | D28: 2841.96 | E28: 1711.78 | F28: 1360.96 | G28: 786.23 | H28: 816.52 | I28: 1712.42 | J28: 786.23 | K28: 854.65 | L28: 1168.27 | M28: 1360.96 | N28: =SUM(B28:M28) -> 15647.08
A29: Insurance | B29: 284.86 | C29: 285.07 | D29: 625.06 | E29: 306.36 | F29: 306.36 | G29: 286.51 | H29: 286.51 | I29: 285.67 | J29: 286.51 | K29: 854.65 | L29: 284.86 | M29: 306.36 | N29: =SUM(B29:M29) -> 4398.78
A30: Interest Expense | B30: 599.63 | C30: 604.41 | D30: 602.22 | E30: 601.79 | F30: 603.97 | G30: 603.09 | H30: 601.79 | I30: 501.35 | J30: 603.09 | K30: 854.65 | L30: 599.63 | M30: 603.97 | N30: =SUM(B30:M30) -> 7379.59
A31: Legal Fees | B31: 474.41 | C31: 2344.87 | D31: 975.43 | E31: 474.41 | F31: 809.5 | G31: 1884.73 | H31: 1306.43 | I31: 2344.87 | J31: 1884.73 | K31: 1314.84 | L31: 474.41 | M31: 809.5 | N31: =SUM(B31:M31) -> 15098.13
A32: Lodging | B32: 809.5 | C32: 624 | D32: 602.22 | E32: 601.79 | F32: 603.97 | G32: 603.09 | H32: 624 | I32: 601.35 | J32: 603.09 | K32: 854.65 | L32: 809.5 | M32: 603.97 | N32: =SUM(B32:M32) -> 7941.13
A33: Marketing | B33: =B11*18% -> 37250.745 | C33: =C11*18% -> 37451.899 | D33: =D11*18% -> 37654.139 | E33: =E11*18% -> 37857.472 | F33: =F11*18% -> 38061.902 | G33: =G11*18% -> 38267.436 | H33: =H11*18% -> 38474.08 | I33: =I11*18% -> 38681.84 | ... M33: =M11*18% -> 39524.16 | N33: =SUM(B33:M33) -> 460527.01
A34: Meals | B34: 2922.88 | C34: 2924.98 | D34: 2120.45 | E34: 3338.99 | F34: 4216.46 | G34: 2525.28 | H34: 3081.36 | I34: 4216.46 | J34: 2525.28 | K34: 2209.55 | L34: 2922.88 | M34: 4216.46 | N34: =SUM(B34:M34) -> 37221.03
A35: Medical | B35: 312.22 | C35: 271.68 | D35: 74.06 | E35: 88.29 | F35: 312 | G35: 312 | H35: 816.52 | I35: 74.06 | J35: 312 | K35: 854.65 | L35: 312.22 | M35: 312 | N35: =SUM(B35:M35) -> 4051.7
A36: Membership | B36: 159.41 | C36: 336.78 | D36: 337.26 | E36: 480.92 | F36: 337.26 | G36: 351.37 | H36: 1222.67 | I36: 336.78 | J36: 351.37 | K36: 854.65 | L36: 159.41 | M36: 337.26 | N36: =SUM(B36:M36) -> 5265.14
A37: Merchant Fees | B37: 243.52 | C37: 258.77 | D37: 260.1 | E37: 185.55 | F37: 258.58 | G37: 258.2 | H37: 313 | I37: 240.81 | J37: 258.2 | K37: 854.65 | L37: 243.52 | M37: 258.58 | N37: =SUM(B37:M37) -> 3633.48
A38: Stripe Fee | B38: 98.6 | C38: 99.31 | D38: 98.95 | E38: 98.88 | F38: 99.24 | G38: 99.1 | H38: 816.52 | I38: 98.81 | J38: 99.1 | K38: 854.65 | L38: 98.6 | M38: 99.24 | N38: =SUM(B38:M38) -> 2661
A39: Total for Merchant Fees | B39: =B37+B38 -> 342.12 | C39: =C37+C38 -> 358.08 | D39: =D37+D38 -> 359.05 | E39: =E37+E38 -> 284.43 | F39: =F37+F38 -> 357.82 | G39: =G37+G38 -> 357.3 | H39: =H37+H38 -> 1129.52 | I39: =I37+I38 -> 339.62 | ... M39: =M37+M38 -> 357.82 | N39: =SUM(B39:M39) -> 6294.48
A40: Miscellaneous | B40: 385.86 | C40: 571.69 | D40: 570.9 | E40: 569.21 | F40: 157.41 | G40: 154.1 | H40: 816.52 | I40: 834.26 | J40: 157.19 | K40: 854.65 | L40: 388.2 | M40: 157.41 | N40: =SUM(B40:M40) -> 5617.4
A41: Office Expense | B41: 3302.34 | C41: 3272.34 | D41: 4440.6 | E41: 6447.72 | F41: 3243.59 | G41: 5431.48 | H41: 5373.86 | I41: 4580.6 | J41: 5431.48 | K41: 4040.06 | L41: 2535.33 | M41: 3243.59 | N41: =SUM(B41:M41) -> 51342.99
A42: Other General & Administrative | B42: 680.5 | C42: 1313.11 | D42: 3533.29 | E42: 1313.11 | F42: 2068.28 | G42: 924.98 | H42: 816.52 | I42: 409.96 | J42: 924.98 | K42: 854.65 | L42: 680.5 | M42: 2068.28 | N42: =SUM(B42:M42) -> 15588.16
A43: Outside Consultants | B43: 12912.1 | C43: 11269.46 | D43: 8431.11 | E43: 7823.24 | F43: 11475.39 | G43: 13841.14 | H43: 8431.11 | I43: 8418.96 | J43: 13871.14 | K43: 9864.69 | L43: 13871.14 | M43: 11475.39 | N43: =SUM(B43:M43) -> 131684.87
A44: Paypal fees | B44: 339.09 | C44: 344.5 | D44: 339.82 | E44: 339.58 | F44: 340.81 | G44: 340.31 | H44: 816.52 | I44: 339.33 | J44: 306.31 | K44: 340.31 | L44: 339.09 | M44: 340.81 | N44: =SUM(B44:M44) -> 4526.48
A45: Postage | B45: 20.22 | C45: 20.1 | D45: 20.1 | E45: 20.1 | F45: 20.1 | G45: 20.1 | H45: 20.1 | I45: 20.1 | J45: 20.1 | K45: 20.1 | L45: 20.09 | M45: 20.1 | N45: =SUM(B45:M45) -> 241.31
A46: Prime Video | B46: 39.62 | C46: 39.85 | D46: 39.71 | E46: 39.68 | F46: 39.82 | G46: 39.77 | H46: 816.52 | I46: 29.65 | J46: 39.77 | K46: 39.77 | L46: 39.62 | M46: 39.82 | N46: =SUM(B46:M46) -> 1243.6
A47: Professional Fees | B47: 1642.27 | C47: 604.41 | D47: 1871.8 | E47: 1870.45 | F47: 1205.2 | G47: 177.16 | H47: 816.52 | I47: 1869.1 | J47: 177.16 | K47: 177.16 | L47: 1642.27 | M47: 1207.94 | N47: =SUM(B47:M47) -> 13261.44
A48: Rent | B48: 1802.77 | C48: 1813.22 | D48: 1806.67 | E48: 1805.36 | F48: 1811.9 | G48: 1809.28 | H48: 1763.04 | I48: 1804.06 | J48: 1809.28 | K48: 1663.55 | L48: 1802.77 | M48: 1809.2 | N48: =SUM(B48:M48) -> 21501.1
A49: Software & Apps | B49: 505.64 | C49: 505.64 | D49: 505.64 | E49: 505.64 | F49: 505.64 | G49: 505.64 | H49: 816.52 | I49: 505.64 | J49: 505.64 | K49: 854.65 | L49: 505.64 | M49: 505.64 | N49: =SUM(B49:M49) -> 6727.57
A50: Travel | B50: 2452.22 | C50: 2452.22 | D50: 1226.02 | E50: 2436.22 | F50: 2452.22 | G50: 2452.22 | H50: 816.52 | I50: 2439.12 | J50: 2452.22 | K50: 854.65 | L50: 2452.22 | M50: 2452.22 | N50: =SUM(B50:M50) -> 24938.07
A51: Uber | B51: 150.23 | C51: 151.1 | D51: 150.56 | E51: 150.45 | F51: 150.99 | G51: 150.77 | H51: 653.22 | I51: 150.34 | J51: 150.77 | K51: 657.42 | L51: 150.23 | M51: 150.99 | N51: =SUM(B51:M51) -> 2817.07
A52: Total for Expenses | B52: =Explaination!F83+B33 -> 76750.745 | C52: =39500+C33 -> 76951.899 | D52: =39500+D33 -> 77154.139 | E52: =39500+E33 -> 77357.472 | F52: =39500+F33 -> 77561.902 | G52: =39500+G33 -> 77767.436 | H52: =39500+H33 -> 77974.08 | I52: =39500+I33 -> 78181.84 | J52: =39500+J33 -> 78390.722 | ... M52: =39500+M33 -> 79024.16 | N52: =SUM(B52:M52) -> 934527.01
A53: Net Operating Income
A54: Net Other Income
A55: Net Income | B55: =B17-B52 -> -10527.198 | C55: =C17-C52 -> -10370.745 | D55: =D17-D52 -> -10213.447 | E55: =E17-E52 -> -10055.3 | F55: =F17-F52 -> -9896.2985 | G55: =G17-G52 -> -9736.4385 | H55: =H17-H52 -> -9575.7152 | I55: =I17-I52 -> -9414.1241 | ... N55: =N17-N52 -> -115812.33

Sheet P&L Cash Flow Monthly
A2: Condition One | N2: Condition One | AA2: Condition One | AN2: Condition One
A3: Cash Flow Monthly | N3: Cash Flow Monthly | AA3: Cash Flow Monthly | AN3: Cash Flow Monthly
B8: 43951 | C8: 43982 | D8: 44012 | E8: 44043 | F8: 44074 | G8: 44104 | H8: 44135 | I8: 44165 | J8: 44196 | K8: 44227 | L8: 44255 | M8: 44286 | N8: 44316 | O8: 44347 | P8: 44377 | Q8: 44408 | R8: 44439 | S8: 44469 | T8: 44500 | U8: 44530 | V8: 44561 | W8: 44592 | X8: 44620 | Y8: 44651 | Z8: 44681 | AA8: 44712 | AB8: 44742 | AC8: 44773 | AD8: 44804 | AE8: 44834 | AF8: 44865 | AG8: 44895 | AH8: 44926 | AI8: 44957 | AJ8: 44985 | AK8: 45016 | AL8: 45046 | AM8: 45077 | AN8: 45107 | AO8: 45138 | AP8: 45169 | AQ8: 45199 | AR8: 45230 | AS8: 45260 | AT8: 45291 | AU8: 45322 | AV8: 45351 | AW8: 45382 | AX8: 45412 | AY8: 45443 | AZ8: 45473 | BA8: 45504 | BB8: 45535 | BC8: 45565 | BD8: 45596 | BE8: 45626 | BF8: 45657 | BG8: 45688 | BH8: 45716 | BI8: 45747 | BJ8: 45777 | BK8: 45808 | BL8: 45838 | BM8: 45869 | BN8: 45900 | BO8: 45930 | BP8: 45961 | BQ8: 45991 | BR8: 46022 | BS8: 46053 | BT8: 46081 | BU8: 46112 | BV8: 46142 | BW8: 46173 | BX8: 46203 | BY8: 46234 | BZ8: 46265 | CA8: 46295 | CB8: 46326 | CC8: 46356 | CD8: 46387 | CE8: 46418 | CF8: 46446 | CG8: 46477 | CH8: 46507 | CI8: 46538 | CJ8: 46568 | CK8: 46599 | CL8: 46630 | CM8: 46660 | CN8: 46691 | CO8: 46721 | CP8: 46752 | CQ8: 46753 | CR8: 46754 | CS8: 46755
A10: Sales
A11: Gyms | C11: =+'Rev 2'!V13 -> 65.084987 | D11: =+'Rev 2'!W13 -> 782.69595 | E11: =+'Rev 2'!X13 -> 1192.7594 | F11: =+'Rev 2'!Y13 -> 1545.4617 | G11: =+'Rev 2'!Z13 -> 1523.2111 | H11: =+'Rev 2'!AA13 -> 2184.1721 | I11: =+'Rev 2'!AB13 -> 4280.355 | J11: =+'Rev 2'!AC13 -> 4144.1221 | ... CP11: =+'Rev 2'!DI13 -> 31502.36
A12: E-commerce | B12: 2770.21 | C12: 3324.68 | D12: 5292.33 | E12: 10996.11 | F12: 17836.54 | G12: 20272.6 | H12: 20869.28 | I12: 34588 | J12: 22500 | K12: 25500 | L12: =+'Rev 2'!AE18 -> 59003.591 | M12: =+'Rev 2'!AF18 -> 83902.828 | N12: =+'Rev 2'!AG18 -> 83920.74 | O12: =+'Rev 2'!AH18 -> 73894.487 | P12: =+'Rev 2'!AI18 -> 63868.234 | Q12: =+'Rev 2'!AJ18 -> 59100.083 | R12: =+'Rev 2'!AK18 -> 67881.498 | S12: =+'Rev 2'!AL18 -> 83839.023 | ... CP12: =+'Rev 2'!DI18 -> 220513.02
A15: Sales | B15: =SUM(B11:B13) -> 2770.21 | C15: =SUM(C11:C13) -> 3389.765 | D15: =SUM(D11:D13) -> 6075.026 | E15: =SUM(E11:E13) -> 12188.869 | F15: =SUM(F11:F13) -> 19382.002 | G15: =SUM(G11:G13) -> 21795.811 | H15: =SUM(H11:H13) -> 23053.452 | I15: =SUM(I11:I13) -> 38868.355 | ... CS15: =SUM(CS11:CS13) -> 0
A17: Cost of goods sold | B17: =+'Rev 2'!U21*COGS!B28 -> 0 | C17: =+'Rev 2'!V21*COGS!B28 -> 440.90018 | D17: =+COGS!B23 -> 5339.791 | E17: =+COGS!C23 -> 8139.1572 | F17: =+COGS!D23 -> 9928.9536 | G17: =+COGS!E23 -> 9785.9566 | H17: =+COGS!F23 -> 14033.733 | I17: =+COGS!G23 -> 24081.317 | J17: =+COGS!H23 -> 23314.78 | K17: =+COGS!I23 -> 37659.495 | ... CP17: =+COGS!CN23 -> 110676.53
A19: Gross margin | B19: =+B15-B17 -> 2770.21 | C19: =+C15-C17 -> 2948.8648 | D19: =+D15-D17 -> 735.23493 | E19: =+E15-E17 -> 4049.7121 | F19: =+F15-F17 -> 9453.0481 | G19: =+G15-G17 -> 12009.854 | H19: =+H15-H17 -> 9019.7195 | I19: =+I15-I17 -> 14787.038 | ... CP19: =+CP15-CP17 -> 141338.84
A21: Expenses (see tab for detail) | B21: =+'Expenses 2'!B102 -> 29693.703 | C21: =+'Expenses 2'!C102 -> 26720.251 | D21: =+'Expenses 2'!D102 -> 26835.315 | E21: =+'Expenses 2'!E102 -> 25597.293 | F21: =+'Expenses 2'!F102 -> 25905.519 | G21: =+'Expenses 2'!G102 -> 27008.951 | H21: =+'Expenses 2'!H102 -> 32062.84 | I21: =+'Expenses 2'!I102 -> 40740.509 | ... CP21: =+'Expenses 2'!CP102 -> 118398.86
A23: Net income/EBITDA | B23: =+B19-B21 -> -26923.494 | C23: =+C19-C21 -> -23771.387 | D23: =+D19-D21 -> -26100.08 | E23: =+E19-E21 -> -21547.581 | F23: =+F19-F21 -> -16452.471 | G23: =+G19-G21 -> -14999.096 | H23: =+H19-H21 -> -23043.121 | I23: =+I19-I21 -> -25953.471 | ... CP23: =+CP19-CP21 -> 22939.985
A25: Adjustments to convert net income to cash flow
A26: COGS | B26: =+B17 -> 0 | C26: =+C17 -> 440.90018 | D26: =+D17 -> 5339.791 | E26: =+E17 -> 8139.1572 | F26: =+F17 -> 9928.9536 | G26: =+G17 -> 9785.9566 | H26: =+H17 -> 14033.733 | I26: =+I17 -> 24081.317 | ... CP26: =+CP17 -> 110676.53
A27: Payment for COGS | B27: =-COGS!B32-COGS!B23 -> -6120.4822 | C27: =-COGS!C23 -> -8139.1572 | D27: =-COGS!D23 -> -9928.9536 | E27: =-COGS!E23 -> -9785.9566 | F27: =-COGS!F23 -> -14033.733 | G27: =-COGS!G23 -> -24081.317 | H27: =-COGS!H23 -> -23314.78 | I27: =-COGS!I23 -> -37659.495 | J27: =-COGS!J23 -> -47427.648 | ... CP27: =-COGS!CP23 -> -110676.53
A28: Marketing ad spend | B28: ='Expenses 2'!B89 -> 1500 | C28: ='Expenses 2'!C89 -> 3500 | D28: ='Expenses 2'!D89 -> 3500 | E28: ='Expenses 2'!E89 -> 2000 | F28: ='Expenses 2'!F89 -> 2000 | G28: ='Expenses 2'!G89 -> 3000 | H28: ='Expenses 2'!H89 -> 5000 | I28: ='Expenses 2'!I89 -> 12000 | ... AG28: ='Expenses 2'!AG89 -> 10000 | AH28: ='Expenses 2'!AH28 -> 10000 | AI28: ='Expenses 2'!AI28 -> 10000 | AJ28: ='Expenses 2'!AJ28 -> 5000 | AK28: ='Expenses 2'!AK28 -> 5000 | AL28: ='Expenses 2'!AL28 -> 5000 | AM28: ='Expenses 2'!AM28 -> 7000 | AN28: ='Expenses 2'!AN28 -> 7000 | AO28: ='Expenses 2'!AO28 -> 7000 | ... CP28: ='Expenses 2'!CP28 -> 50000
A29: Payment for Marketing ad spend | B29: =-'Expenses 2'!C89 -> -3500 | C29: =-'Expenses 2'!D89 -> -3500 | D29: =-'Expenses 2'!E89 -> -2000 | E29: =-'Expenses 2'!F89 -> -2000 | F29: =-'Expenses 2'!G89 -> -3000 | G29: =-'Expenses 2'!H89 -> -5000 | H29: =-'Expenses 2'!I89 -> -12000 | I29: =-'Expenses 2'!J89 -> -2000 | ... AF29: =-'Expenses 2'!AG89 -> -10000 | AG29: =-'Expenses 2'!AH28 -> -10000 | AH29: =-'Expenses 2'!AI28 -> -10000 | AI29: =-'Expenses 2'!AJ28 -> -5000 | AJ29: =-'Expenses 2'!AK28 -> -5000 | AK29: =-'Expenses 2'!AL28 -> -5000 | AL29: =-'Expenses 2'!AM28 -> -7000 | AM29: =-'Expenses 2'!AN28 -> -7000 | AN29: =-'Expenses 2'!AO28 -> -7000 | ... CO29: =-'Expenses 2'!CP28 -> -50000 | CP29: =-'Expenses 2'!CQ89 -> 0
A30: Initial up front costs | B30: =-'Up front costs'!B20 -> 0
A31: Tax distribution | K31: =-Taxes!D32 -> 0 | L31: =-Taxes!E32 -> 0 | M31: =-Taxes!F32 -> 0 | N31: =-Taxes!G32 -> 0 | O31: =-Taxes!H32 -> 0 | P31: =-Taxes!I32 -> 0 | Q31: =-Taxes!J32 -> 0 | R31: =-Taxes!K32 -> 0 | ... CP31: =-Taxes!CI32 -> 0
A32: Capital investment | B32: 375000 | J32: 100000 | N32: 10000 | O32: 50000 | P32: 80000 | R32: 260000 | W32: 150000 | AA32: 35000 | AB32: 100000 | AL32: 25000 | AN32: -139589 | AO32: 25000 | AR32: 25000 | AT32: 50000 | AU32: 100000 | AV32: 150000 | AW32: 0 | AX32: 0 | AY32: 0 | AZ32: 0 | BA32: 0 | BC32: -15000 | BD32: 80000 | BE32: 100000 | BF32: -15000 | BG32: -15000 | BH32: -15000 | BI32: -15000 | BJ32: -15000 | BK32: -15000 | BL32: -15000 | BM32: -15000 | BN32: -15000 | BO32: -15000 | BP32: -15000 | BQ32: -15000 | BR32: 150000 | BT32: 0 | BU32: 0 | BV32: 0 | BW32: 0 | BX32: 0 | BY32: 0 | BZ32: 0 | CA32: 0 | CB32: 0 | CC32: 0 | CD32: 0 | CE32: 0 | CF32: 0 | CG32: 0 | CH32: 0 | CI32: 0 | CJ32: 0
L33: Note 1
A35: Monthly cash flow | B35: =SUM(B23:B33) -> 339956.02 | C35: =SUM(C23:C33) -> -31469.644 | D35: =SUM(D23:D33) -> -29189.242 | E35: =SUM(E23:E33) -> -23194.38 | F35: =SUM(F23:F33) -> -21557.25 | G35: =SUM(G23:G33) -> -31294.457 | H35: =SUM(H23:H33) -> -39324.169 | I35: =SUM(I23:I33) -> -29531.649 | ... CP35: =SUM(CP23:CP33) -> 72939.985
A37: Cash beginning of month | B37: 6965 | C37: =+B39 -> 346921.02 | D37: =+C39 -> 315451.38 | E37: =+D39 -> 286262.14 | F37: =+E39 -> 263067.76 | G37: =+F39 -> 241510.51 | H37: =+G39 -> 210216.05 | I37: =+H39 -> 170891.88 | J37: =+I39 -> 141360.23 | ... CP37: =+CO39 -> 83102.656
A39: Cash end of month | B39: =SUM(B35:B37) -> 346921.02 | C39: =SUM(C35:C37) -> 315451.38 | D39: =SUM(D35:D37) -> 286262.14 | E39: =SUM(E35:E37) -> 263067.76 | F39: =SUM(F35:F37) -> 241510.51 | G39: =SUM(G35:G37) -> 210216.05 | H39: =SUM(H35:H37) -> 170891.88 | I39: =SUM(I35:I37) -> 141360.23 | ... CP39: =SUM(CP35:CP37) -> 156042.64
A42: Gross Profit % | B42: =B19/B15 -> 1 | C42: =C19/C15 -> 0.86993193 | D42: =D19/D15 -> 0.12102581 | E42: =E19/E15 -> 0.33224674 | F42: =F19/F15 -> 0.487723 | G42: =G19/G15 -> 0.55101664 | H42: =H19/H15 -> 0.39125245 | I42: =I19/I15 -> 0.38043899 | ... CP42: =CP19/CP15 -> 0.5608342
A44: Net Profit % | B44: =B23/B15 -> -9.7189359 | C44: =C23/C15 -> -7.0126946 | D44: =D23/D15 -> -4.2962911 | E44: =E23/E15 -> -1.767808 | F44: =F23/F15 -> -0.84885302 | G44: =G23/G15 -> -0.68816416 | H44: =H23/H15 -> -0.99955186 | I44: =I23/I15 -> -0.66772755 | ... CP44: =CP23/CP15 -> 0.09102613
BQ49: =SUM(BF32,BG32,BH32,BJ32,BK32,BL32,BM31,BM31,BM32,BN32,BO32,BP32,BQ32,) -> -165000

Sheet Rev 2
A2: Condition One
A3: I
D8: March | E8: April | F8: May | G8: June | H8: July | I8: August | J8: Spetember | K8: October | L8: Novemeber | M8: December | N8: January | O8: February | P8: March | Q8: April | R8: May | S8: June | T8: 43647 | U8: =+'P&L Cash Flow Monthly'!B8 -> 43951 | V8: =+'P&L Cash Flow Monthly'!C8 -> 43982 | W8: =+'P&L Cash Flow Monthly'!D8 -> 44012 | X8: =+'P&L Cash Flow Monthly'!E8 -> 44043 | Y8: =+'P&L Cash Flow Monthly'!F8 -> 44074 | Z8: =+'P&L Cash Flow Monthly'!G8 -> 44104 | AA8: =+'P&L Cash Flow Monthly'!H8 -> 44135 | AB8: =+'P&L Cash Flow Monthly'!I8 -> 44165 | ... DI8: =+'P&L Cash Flow Monthly'!CP8 -> 46752 | DJ8: 46783 | DK8: 46811 | DL8: 46843
A13: Effect on gross sales by increasing sales over base selling procew per bar | V13: =+V21*$I25+$J29 -> 65.084987 | W13: =+W21*$I25+$J29 -> 782.69595 | X13: =+X21*$I25+$J29 -> 1192.7594 | Y13: =+Y21*$I25+$J29 -> 1545.4617 | Z13: =+Z21*$I25+$J29 -> 1523.2111 | AA13: =+AA21*$I25+$J29 -> 2184.1721 | AB13: =+AB21*$I25+$J29 -> 4280.355 | AC13: =+AC21*$I25+$J29 -> 4144.1221 | ... DL13: =+DL21*$I25+$J29 -> 0.5
A16: E-Commerce Revenue
A17: Number of customers added | T17: 80 | V17: ='Expenses 2'!C89/V42 -> 11.666667 | W17: ='Expenses 2'!D89/W42 -> 129.62963 | X17: ='Expenses 2'!E89/X42 -> 74.074074 | Y17: ='Expenses 2'!F89/Y42 -> 74.074074 | Z17: ='Expenses 2'!G89/Z42 -> 111.11111 | AA17: ='Expenses 2'!H89/AA42 -> 185.18519 | AB17: ='Expenses 2'!I89/AB42 -> 444.44444 | AC17: ='Expenses 2'!J89/AC42 -> 74.074074 | ... AZ17: ='Expenses 2'!AG89/AZ42 -> 285.71429 | BA17: ='Expenses 2'!AH28/BA42 -> 285.71429 | BB17: ='Expenses 2'!AI28/BB42 -> 250 | BC17: ='Expenses 2'!AJ28/BC42 -> 125 | BD17: ='Expenses 2'!AK28/BD42 -> 125 | BE17: ='Expenses 2'!AL28/BE42 -> 125 | BF17: ='Expenses 2'!AM28/BF42 -> 175 | BG17: ='Expenses 2'!AN28/BG42 -> 175 | BH17: ='Expenses 2'!AO28/BH42 -> 200 | ... DI17: ='Expenses 2'!CP28/DI42 -> 1250
A18: Ecommcer rev | V18: =+V530 -> 452.09491 | W18: =+W530 -> 5475.3717 | X18: =+X530 -> 8345.8155 | Y18: =+Y530 -> 10814.732 | Z18: =+Z530 -> 10658.978 | AA18: =+AA530 -> 15285.705 | AB18: =+AB530 -> 29958.985 | AC18: =+AC530 -> 29005.355 | ... DI18: =+DI530 -> 220513.02
A19: Bars sold | T19: =SUM(T17*10) -> 800 | V19: =+V18*$B32 -> 129.16997 | W19: =+W18*$B32 -> 1564.3919 | X19: =+X18*$B32 -> 2384.5187 | Y19: =+Y18*$B32 -> 3089.9233 | Z19: =+Z18*$B32 -> 3045.4222 | AA19: =+AA18*$B32 -> 4367.3442 | AB19: =+AB18*$B32 -> 8559.71 | AC19: =+AC18*$B32 -> 8287.2442 | ... DI19: =+DI18*$B32 -> 63003.719 | DJ19: =DI19 -> 63003.719 | DK19: =DJ19 -> 63003.719 | DL19: =DK19 -> 63003.719
A21: Total Bars Sold per month | V21: =+V19+V14 -> 129.16997 | W21: =+W19+W14 -> 1564.3919 | X21: =+X19+X14 -> 2384.5187 | Y21: =+Y19+Y14 -> 3089.9233 | Z21: =+Z19+Z14 -> 3045.4222 | AA21: =+AA19+AA14 -> 4367.3442 | AB21: =+AB19+AB14 -> 8559.71 | AC21: =+AC19+AC14 -> 8287.2442 | ... DI21: =+DI19+DI14 -> 63003.719
A23: Total Gross Revenue per month. | I23: % sales | V23: =+V13+V18 -> 517.17989 | W23: =+W13+W18 -> 6258.0676 | X23: =+X13+X18 -> 9538.5749 | Y23: =+Y13+Y18 -> 12360.193 | Z23: =+Z13+Z18 -> 12182.189 | AA23: =+AA13+AA18 -> 17469.877 | AB23: =+AB13+AB18 -> 34239.34 | AC23: =+AC13+AC18 -> 33149.477 | ... DI23: =+DI13+DI18 -> 252015.38 | DJ23: =DI23 -> 252015.38 | DK23: =DJ23 -> 252015.38 | DL23: =DK23 -> 252015.38
D24: Base selling price | H24: =+B31 -> 3.5 | I24: 0.5 | J24: =+H24*I24 -> 1.75
D25: Higher selling price | H25: 4.5 | I25: 0.5 | J25: =+H25*I25 -> 2.25
H26: 0
D28: New weighted average selling price | J28: =+J24+J25 -> 4
D29: Adjustment to selling proce | J29: =+J28-B31 -> 0.5
A30: ECOMM Figures
A31: Price per bar | B31: 3.5 | C31: 3.7
A32: Bars per $1 of sales | B32: =1/B31 -> 0.28571429
A35: GYMs figures
A36: Whole sale price per bar | B36: 2.5
A37: Bars per minum order | B37: 60
A38: Minum gym order value | B38: =SUM(B36*B37) -> 150
A42: Cost to Acquire customer | U42: 30 | V42: 300 | W42: 27 | X42: 27 | Y42: 27 | Z42: 27 | AA42: 27 | AB42: 27 | AC42: 27 | AD42: 24 | AE42: 24 | AF42: 24 | AG42: 27 | AH42: 27 | AI42: 27 | AJ42: 27 | AK42: 27 | AL42: 27 | AM42: 27 | AN42: 30 | AO42: 30 | AP42: 27 | AQ42: 27 | AR42: 27 | AS42: 27 | AT42: 27 | AU42: 27 | AV42: 27 | AW42: 27 | AX42: 27 | AY42: 27 | AZ42: 35 | BA42: 35 | BB42: 40 | BC42: 40 | BD42: 40 | BE42: 40 | BF42: 40 | BG42: 40 | BH42: 35 | BI42: 35 | BJ42: 35 | BK42: 35 | BL42: 40 | BM42: 40 | BN42: 40 | BO42: 50 | BP42: 50 | BQ42: 50 | BR42: 45 | BS42: 45 | BT42: 40 | BU42: 35 | BV42: 35 | BW42: 35 | BX42: 40 | BY42: 40 | BZ42: 35 | CA42: 35 | CB42: 35 | CC42: 35 | CD42: 35 | CE42: 35 | CF42: 35 | CG42: 35 | CH42: 35 | CI42: 35 | CJ42: 35 | CK42: 35 | CL42: 35 | CM42: 35 | CN42: 35 | CO42: 35 | CP42: 35 | CQ42: 35 | CR42: 35 | CS42: 35 | CT42: 35 | CU42: 35 | CV42: 35 | CW42: 35 | CX42: 40 | CY42: 40 | CZ42: 40 | DA42: 40 | DB42: 40 | DC42: 40 | DD42: 40 | DE42: 40 | DF42: 40 | DG42: 40 | DH42: 40 | DI42: 40
A44: Cost to aquire gym | B44: =SUM(CAC!B10) -> 20
A47: Total gyms | B47: =SUM(D10:M10) -> 0
A49: Gym attrition rate per year | B49: 0.1
A53: New customers | U53: ='Expenses 2'!B89/U42 -> 50 | V53: ='Expenses 2'!C89/V42 -> 11.666667 | W53: ='Expenses 2'!D89/W42 -> 129.62963 | X53: ='Expenses 2'!E89/X42 -> 74.074074 | Y53: ='Expenses 2'!F89/Y42 -> 74.074074 | Z53: ='Expenses 2'!G89/Z42 -> 111.11111 | AA53: ='Expenses 2'!H89/AA42 -> 185.18519 | AB53: ='Expenses 2'!I89/AB42 -> 444.44444 | ... AZ53: ='Expenses 2'!AG89/AZ42 -> 285.71429 | BA53: ='Expenses 2'!AH28/BA42 -> 285.71429 | BB53: ='Expenses 2'!AI28/BB42 -> 250 | BC53: ='Expenses 2'!AJ28/BC42 -> 125 | BD53: ='Expenses 2'!AK28/BD42 -> 125 | BE53: ='Expenses 2'!AL28/BE42 -> 125 | BF53: ='Expenses 2'!AM28/BF42 -> 175 | BG53: ='Expenses 2'!AN28/BG42 -> 175 | BH53: ='Expenses 2'!AO28/BH42 -> 200 | ... DI53: ='Expenses 2'!CP28/DI42 -> 1250
A54: Total active customers | U54: =U53 -> 50 | V54: =U54+V53 -> 61.666667 | W54: =V54+W53 -> 191.2963 | X54: =W54+X53 -> 265.37037 | Y54: =X54+Y53 -> 339.44444 | Z54: =Y54+Z53 -> 450.55556 | AA54: =Z54+AA53 -> 635.74074 | AB54: =AA54+AB53 -> 1080.1852 | AC54: =AB54+AC53 -> 1154.2593 | ... DI54: =DH54+DI53 -> 45886.931
B56: # years | U56: % new customers | V56: # months | W56: Total LT value | X56: Monthly LT value | Y56: wieghted average
A57: Values for each new customers | AB57: First months sales new customers | AD57: =($U58*$X58+$U59*$X59+$U60*$X60+$U61*$X61)*AD53 -> 24219.37 | AE57: =($U58*$X58+$U59*$X59+$U60*$X60+$U61*$X61)*AE53 -> 27448.619 | AF57: =($U58*$X58+$U59*$X59+$U60*$X60+$U61*$X61)*AF53 -> 27448.619 | AG57: =($U58*$X58+$U59*$X59+$U60*$X60+$U61*$X61)*AG53 -> 21528.329 | AH57: =($U58*$X58+$U59*$X59+$U60*$X60+$U61*$X61)*AH53 -> 14352.219 | AI57: =($U58*$X58+$U59*$X59+$U60*$X60+$U61*$X61)*AI53 -> 14352.219 | AJ57: =($U58*$X58+$U59*$X59+$U60*$X60+$U61*$X61)*AJ53 -> 14352.219 | AK57: =($U58*$X58+$U59*$X59+$U60*$X60+$U61*$X61)*AK53 -> 21528.329 | ... DI57: =($U58*$X58+$U59*$X59+$U60*$X60+$U61*$X61)*DI53 -> 48438.74
B58: 3.5 | U58: 0.01 | V58: =+B58*12 -> 42 | W58: 1774 | X58: =+W58/V58 -> 42.238095 | Y58: =W58*U58 -> 17.74
B59: 2.5 | U59: 0.035 | V59: =+B59*12 -> 30 | W59: 1075 | X59: =+W59/V59 -> 35.833333 | Y59: =W59*U59 -> 37.625 | AB59: Social media account manager | AD59: 2000 | AE59: 2000 | AF59: 2000 | AG59: =IF(AG57<83333,AG57*0.1,100000/12) -> 2152.8329 | AH59: =IF(AH57<83333,AH57*0.1,100000/12) -> 1435.2219 | AI59: =IF(AI57<83333,AI57*0.1,100000/12) -> 1435.2219 | AJ59: =IF(AJ57<83333,AJ57*0.1,100000/12) -> 1435.2219 | AK59: =IF(AK57<83333,AK57*0.1,100000/12) -> 2152.8329 | AL59: =IF(AL57<83333,AL57*0.1,100000/12) -> 2870.4439 | AM59: =IF(AM57<83333,AM57*0.1,100000/12) -> 4305.6658 | AN59: =IF(AN57<83333,AN57*0.1,100000/12) -> 1033.3598 | ... DI59: =IF(DI57<83333,DI57*0.1,100000/12) -> 4843.874
B60: 1.5 | U60: 0.08 | V60: =+B60*12 -> 18 | W60: 598 | X60: =+W60/V60 -> 33.222222 | Y60: =W60*U60 -> 47.84
B61: 0.25 | U61: 0.875 | V61: =+B61*12 -> 3 | W61: 118 | X61: =+W61/V61 -> 39.333333 | Y61: =W61*U61 -> 103.25
U64: =SUM(U58:U63) -> 1 | Y64: =SUM(Y58:Y61) -> 206.455
U68: From
A69: Returning Customers | U69: =+U8 -> 43951 | V69: =+#REF!-#REF!*#REF!/12 -> #REF! | W69: =IF(V69>0.005,(V69-#REF!*#REF!/12),0) -> #REF! | X69: =IF(W69>0.005,(W69-#REF!*#REF!/12),0) -> #REF! | Y69: =IF(X69>0.005,(X69-#REF!*#REF!/12),0) -> #REF! | Z69: =IF(Y69>0.005,(Y69-#REF!*#REF!/12),0) -> #REF! | AA69: =IF(Z69>0.005,(Z69-#REF!*#REF!/12),0) -> #REF! | AB69: =IF(AA69>0.005,(AA69-#REF!*#REF!/12),0) -> #REF! | AC69: =IF(AB69>0.005,(AB69-#REF!*#REF!/12),0) -> #REF! | AD69: =IF(AC69>0.005,(AC69-#REF!*#REF!/12),0) -> #REF! | ... CB69: =IF(CA69>0.005,(CA69-#REF!*#REF!/12),0) -> #REF!
U70: 43982 | V70: =+U17*#REF! -> #REF! | W70: =IF(V70>0.005,(V70-$V70*#REF!/12),0) -> #REF! | X70: =IF(W70>0.005,(W70-$V70*#REF!/12),0) -> #REF! | Y70: =IF(X70>0.005,(X70-$V70*#REF!/12),0) -> #REF! | Z70: =IF(Y70>0.005,(Y70-$V70*#REF!/12),0) -> #REF! | AA70: =IF(Z70>0.005,(Z70-$V70*#REF!/12),0) -> #REF! | AB70: =IF(AA70>0.005,(AA70-$V70*#REF!/12),0) -> #REF! | AC70: =IF(AB70>0.005,(AB70-$V70*#REF!/12),0) -> #REF! | AD70: =IF(AC70>0.005,(AC70-$V70*#REF!/12),0) -> #REF! | ... CB70: =IF(CA70>0.005,(CA70-$V70*#REF!/12),0) -> #REF!
U71: 44012 | W71: =+V$17*#REF! -> #REF! | X71: =IF(W71>0.005,(W71-$W71*#REF!/12),0) -> #REF! | Y71: =IF(X71>0.005,(X71-$W71*#REF!/12),0) -> #REF! | Z71: =IF(Y71>0.005,(Y71-$W71*#REF!/12),0) -> #REF! | AA71: =IF(Z71>0.005,(Z71-$W71*#REF!/12),0) -> #REF! | AB71: =IF(AA71>0.005,(AA71-$W71*#REF!/12),0) -> #REF! | AC71: =IF(AB71>0.005,(AB71-$W71*#REF!/12),0) -> #REF! | AD71: =IF(AC71>0.005,(AC71-$W71*#REF!/12),0) -> #REF! | AE71: =IF(AD71>0.005,(AD71-$W71*#REF!/12),0) -> #REF! | ... CB71: =IF(CA71>0.005,(CA71-$W71*#REF!/12),0) -> #REF!
U72: 44043 | X72: =+W$17*#REF! -> #REF! | Y72: =IF(X72>0.005,(X72-$X72*#REF!/12),0) -> #REF! | Z72: =IF(Y72>0.005,(Y72-$X72*#REF!/12),0) -> #REF! | AA72: =IF(Z72>0.005,(Z72-$X72*#REF!/12),0) -> #REF! | AB72: =IF(AA72>0.005,(AA72-$X72*#REF!/12),0) -> #REF! | AC72: =IF(AB72>0.005,(AB72-$X72*#REF!/12),0) -> #REF! | AD72: =IF(AC72>0.005,(AC72-$X72*#REF!/12),0) -> #REF! | AE72: =IF(AD72>0.005,(AD72-$X72*#REF!/12),0) -> #REF! | AF72: =IF(AE72>0.005,(AE72-$X72*#REF!/12),0) -> #REF! | ... CB72: =IF(CA72>0.005,(CA72-$X72*#REF!/12),0) -> #REF!
U73: 44074 | Y73: =+X$17*#REF! -> #REF! | Z73: =IF(Y73>0.005,(Y73-$Y73*#REF!/12),0) -> #REF! | AA73: =IF(Z73>0.005,(Z73-$Y73*#REF!/12),0) -> #REF! | AB73: =IF(AA73>0.005,(AA73-$Y73*#REF!/12),0) -> #REF! | AC73: =IF(AB73>0.005,(AB73-$Y73*#REF!/12),0) -> #REF! | AD73: =IF(AC73>0.005,(AC73-$Y73*#REF!/12),0) -> #REF! | AE73: =IF(AD73>0.005,(AD73-$Y73*#REF!/12),0) -> #REF! | AF73: =IF(AE73>0.005,(AE73-$Y73*#REF!/12),0) -> #REF! | AG73: =IF(AF73>0.005,(AF73-$Y73*#REF!/12),0) -> #REF! | ... CB73: =IF(CA73>0.005,(CA73-$Y73*#REF!/12),0) -> #REF!
U74: 44104 | Z74: =+Y$17*#REF! -> #REF! | AA74: =IF(Z74>0.005,(Z74-$Z74*#REF!/12),0) -> #REF! | AB74: =IF(AA74>0.005,(AA74-$Z74*#REF!/12),0) -> #REF! | AC74: =IF(AB74>0.005,(AB74-$Z74*#REF!/12),0) -> #REF! | AD74: =IF(AC74>0.005,(AC74-$Z74*#REF!/12),0) -> #REF! | AE74: =IF(AD74>0.005,(AD74-$Z74*#REF!/12),0) -> #REF! | AF74: =IF(AE74>0.005,(AE74-$Z74*#REF!/12),0) -> #REF! | AG74: =IF(AF74>0.005,(AF74-$Z74*#REF!/12),0) -> #REF! | AH74: =IF(AG74>0.005,(AG74-$Z74*#REF!/12),0) -> #REF! | ... CB74: =IF(CA74>0.005,(CA74-$Z74*#REF!/12),0) -> #REF!
U75: 44135 | AA75: =+Z$17*#REF! -> #REF! | AB75: =IF(AA75>0.005,(AA75-$AA75*#REF!/12),0) -> #REF! | AC75: =IF(AB75>0.005,(AB75-$AA75*#REF!/12),0) -> #REF! | AD75: =IF(AC75>0.005,(AC75-$AA75*#REF!/12),0) -> #REF! | AE75: =IF(AD75>0.005,(AD75-$AA75*#REF!/12),0) -> #REF! | AF75: =IF(AE75>0.005,(AE75-$AA75*#REF!/12),0) -> #REF! | AG75: =IF(AF75>0.005,(AF75-$AA75*#REF!/12),0) -> #REF! | AH75: =IF(AG75>0.005,(AG75-$AA75*#REF!/12),0) -> #REF! | AI75: =IF(AH75>0.005,(AH75-$AA75*#REF!/12),0) -> #REF! | ... CB75: =IF(CA75>0.005,(CA75-$AA75*#REF!/12),0) -> #REF!
U76: 44165 | AB76: =+AA$17*#REF! -> #REF! | AC76: =IF(AB76>0.005,(AB76-$AB76*#REF!/12),0) -> #REF! | AD76: =IF(AC76>0.005,(AC76-$AB76*#REF!/12),0) -> #REF! | AE76: =IF(AD76>0.005,(AD76-$AB76*#REF!/12),0) -> #REF! | AF76: =IF(AE76>0.005,(AE76-$AB76*#REF!/12),0) -> #REF! | AG76: =IF(AF76>0.005,(AF76-$AB76*#REF!/12),0) -> #REF! | AH76: =IF(AG76>0.005,(AG76-$AB76*#REF!/12),0) -> #REF! | AI76: =IF(AH76>0.005,(AH76-$AB76*#REF!/12),0) -> #REF! | AJ76: =IF(AI76>0.005,(AI76-$AB76*#REF!/12),0) -> #REF! | ... CB76: =IF(CA76>0.005,(CA76-$AB76*#REF!/12),0) -> #REF!
U77: 44196 | AC77: =+AB$17*#REF! -> #REF! | AD77: =IF(AC77>0.005,(AC77-$AC77*#REF!/12),0) -> #REF! | AE77: =IF(AD77>0.005,(AD77-$AC77*#REF!/12),0) -> #REF! | AF77: =IF(AE77>0.005,(AE77-$AC77*#REF!/12),0) -> #REF! | AG77: =IF(AF77>0.005,(AF77-$AC77*#REF!/12),0) -> #REF! | AH77: =IF(AG77>0.005,(AG77-$AC77*#REF!/12),0) -> #REF! | AI77: =IF(AH77>0.005,(AH77-$AC77*#REF!/12),0) -> #REF! | AJ77: =IF(AI77>0.005,(AI77-$AC77*#REF!/12),0) -> #REF! | AK77: =IF(AJ77>0.005,(AJ77-$AC77*#REF!/12),0) -> #REF! | ... CB77: =IF(CA77>0.005,(CA77-$AC77*#REF!/12),0) -> #REF!
U78: 44227 | AD78: =+AC$17*#REF! -> #REF! | AE78: =IF(AD78>0.005,(AD78-$AD78*#REF!/12),0) -> #REF! | AF78: =IF(AE78>0.005,(AE78-$AD78*#REF!/12),0) -> #REF! | AG78: =IF(AF78>0.005,(AF78-$AD78*#REF!/12),0) -> #REF! | AH78: =IF(AG78>0.005,(AG78-$AD78*#REF!/12),0) -> #REF! | AI78: =IF(AH78>0.005,(AH78-$AD78*#REF!/12),0) -> #REF! | AJ78: =IF(AI78>0.005,(AI78-$AD78*#REF!/12),0) -> #REF! | AK78: =IF(AJ78>0.005,(AJ78-$AD78*#REF!/12),0) -> #REF! | AL78: =IF(AK78>0.005,(AK78-$AD78*#REF!/12),0) -> #REF! | ... CB78: =IF(CA78>0.005,(CA78-$AD78*#REF!/12),0) -> #REF!
U79: 44255 | AE79: =+AD$17*#REF! -> #REF! | AF79: =IF(AE79>0.005,(AE79-$AE79*#REF!/12),0) -> #REF! | AG79: =IF(AF79>0.005,(AF79-$AE79*#REF!/12),0) -> #REF! | AH79: =IF(AG79>0.005,(AG79-$AE79*#REF!/12),0) -> #REF! | AI79: =IF(AH79>0.005,(AH79-$AE79*#REF!/12),0) -> #REF! | AJ79: =IF(AI79>0.005,(AI79-$AE79*#REF!/12),0) -> #REF! | AK79: =IF(AJ79>0.005,(AJ79-$AE79*#REF!/12),0) -> #REF! | AL79: =IF(AK79>0.005,(AK79-$AE79*#REF!/12),0) -> #REF! | AM79: =IF(AL79>0.005,(AL79-$AE79*#REF!/12),0) -> #REF! | ... CB79: =IF(CA79>0.005,(CA79-$AE79*#REF!/12),0) -> #REF!
U80: 44286 | AF80: =+AE$17*#REF! -> #REF! | AG80: =IF(AF80>0.005,(AF80-$AF80*#REF!/12),0) -> #REF! | AH80: =IF(AG80>0.005,(AG80-$AF80*#REF!/12),0) -> #REF! | AI80: =IF(AH80>0.005,(AH80-$AF80*#REF!/12),0) -> #REF! | AJ80: =IF(AI80>0.005,(AI80-$AF80*#REF!/12),0) -> #REF! | AK80: =IF(AJ80>0.005,(AJ80-$AF80*#REF!/12),0) -> #REF! | AL80: =IF(AK80>0.005,(AK80-$AF80*#REF!/12),0) -> #REF! | AM80: =IF(AL80>0.005,(AL80-$AF80*#REF!/12),0) -> #REF! | AN80: =IF(AM80>0.005,(AM80-$AF80*#REF!/12),0) -> #REF! | ... CB80: =IF(CA80>0.005,(CA80-$AF80*#REF!/12),0) -> #REF!
U81: 44316 | AG81: =+AF$17*#REF! -> #REF! | AH81: =IF(AG81>0.005,(AG81-$AG81*#REF!/12),0) -> #REF! | AI81: =IF(AH81>0.005,(AH81-$AG81*#REF!/12),0) -> #REF! | AJ81: =IF(AI81>0.005,(AI81-$AG81*#REF!/12),0) -> #REF! | AK81: =IF(AJ81>0.005,(AJ81-$AG81*#REF!/12),0) -> #REF! | AL81: =IF(AK81>0.005,(AK81-$AG81*#REF!/12),0) -> #REF! | AM81: =IF(AL81>0.005,(AL81-$AG81*#REF!/12),0) -> #REF! | AN81: =IF(AM81>0.005,(AM81-$AG81*#REF!/12),0) -> #REF! | AO81: =IF(AN81>0.005,(AN81-$AG81*#REF!/12),0) -> #REF! | ... CC81: =IF(CB81>0.005,(CB81-$AG81*#REF!/12),0) -> #REF!
U82: 44347 | AH82: =+AG$17*#REF! -> #REF! | AI82: =IF(AH82>0.005,(AH82-$AH82*#REF!/12),0) -> #REF! | AJ82: =IF(AI82>0.005,(AI82-$AH82*#REF!/12),0) -> #REF! | AK82: =IF(AJ82>0.005,(AJ82-$AH82*#REF!/12),0) -> #REF! | AL82: =IF(AK82>0.005,(AK82-$AH82*#REF!/12),0) -> #REF! | AM82: =IF(AL82>0.005,(AL82-$AH82*#REF!/12),0) -> #REF! | AN82: =IF(AM82>0.005,(AM82-$AH82*#REF!/12),0) -> #REF! | AO82: =IF(AN82>0.005,(AN82-$AH82*#REF!/12),0) -> #REF! | AP82: =IF(AO82>0.005,(AO82-$AH82*#REF!/12),0) -> #REF! | ... CD82: =IF(CC82>0.005,(CC82-$AH82*#REF!/12),0) -> #REF!
U83: 44377 | AI83: =+AH$17*#REF! -> #REF! | AJ83: =IF(AI83>0.005,(AI83-$AI83*#REF!/12),0) -> #REF! | AK83: =IF(AJ83>0.005,(AJ83-$AI83*#REF!/12),0) -> #REF! | AL83: =IF(AK83>0.005,(AK83-$AI83*#REF!/12),0) -> #REF! | AM83: =IF(AL83>0.005,(AL83-$AI83*#REF!/12),0) -> #REF! | AN83: =IF(AM83>0.005,(AM83-$AI83*#REF!/12),0) -> #REF! | AO83: =IF(AN83>0.005,(AN83-$AI83*#REF!/12),0) -> #REF! | AP83: =IF(AO83>0.005,(AO83-$AI83*#REF!/12),0) -> #REF! | AQ83: =IF(AP83>0.005,(AP83-$AI83*#REF!/12),0) -> #REF! | ... CE83: =IF(CD83>0.005,(CD83-$AI83*#REF!/12),0) -> #REF!
U84: 44408 | AJ84: =+AI$17*#REF! -> #REF! | AK84: =IF(AJ84>0.005,(AJ84-$AJ84*#REF!/12),0) -> #REF! | AL84: =IF(AK84>0.005,(AK84-$AJ84*#REF!/12),0) -> #REF! | AM84: =IF(AL84>0.005,(AL84-$AJ84*#REF!/12),0) -> #REF! | AN84: =IF(AM84>0.005,(AM84-$AJ84*#REF!/12),0) -> #REF! | AO84: =IF(AN84>0.005,(AN84-$AJ84*#REF!/12),0) -> #REF! | AP84: =IF(AO84>0.005,(AO84-$AJ84*#REF!/12),0) -> #REF! | AQ84: =IF(AP84>0.005,(AP84-$AJ84*#REF!/12),0) -> #REF! | AR84: =IF(AQ84>0.005,(AQ84-$AJ84*#REF!/12),0) -> #REF! | ... CF84: =IF(CE84>0.005,(CE84-$AJ84*#REF!/12),0) -> #REF!
U85: 44439 | AK85: =+AJ$17*#REF! -> #REF! | AL85: =IF(AK85>0.005,(AK85-$AK85*#REF!/12),0) -> #REF! | AM85: =IF(AL85>0.005,(AL85-$AK85*#REF!/12),0) -> #REF! | AN85: =IF(AM85>0.005,(AM85-$AK85*#REF!/12),0) -> #REF! | AO85: =IF(AN85>0.005,(AN85-$AK85*#REF!/12),0) -> #REF! | AP85: =IF(AO85>0.005,(AO85-$AK85*#REF!/12),0) -> #REF! | AQ85: =IF(AP85>0.005,(AP85-$AK85*#REF!/12),0) -> #REF! | AR85: =IF(AQ85>0.005,(AQ85-$AK85*#REF!/12),0) -> #REF! | AS85: =IF(AR85>0.005,(AR85-$AK85*#REF!/12),0) -> #REF! | ... CG85: =IF(CF85>0.005,(CF85-$AK85*#REF!/12),0) -> #REF!
U86: 44469 | AL86: =+AK$17*#REF! -> #REF! | AM86: =IF(AL86>0.005,(AL86-$AL86*#REF!/12),0) -> #REF! | AN86: =IF(AM86>0.005,(AM86-$AL86*#REF!/12),0) -> #REF! | AO86: =IF(AN86>0.005,(AN86-$AL86*#REF!/12),0) -> #REF! | AP86: =IF(AO86>0.005,(AO86-$AL86*#REF!/12),0) -> #REF! | AQ86: =IF(AP86>0.005,(AP86-$AL86*#REF!/12),0) -> #REF! | AR86: =IF(AQ86>0.005,(AQ86-$AL86*#REF!/12),0) -> #REF! | AS86: =IF(AR86>0.005,(AR86-$AL86*#REF!/12),0) -> #REF! | AT86: =IF(AS86>0.005,(AS86-$AL86*#REF!/12),0) -> #REF! | ... CH86: =IF(CG86>0.005,(CG86-$AL86*#REF!/12),0) -> #REF!
U87: 44500 | AM87: =+AL$17*#REF! -> #REF! | AN87: =IF(AM87>0.005,(AM87-$AM87*#REF!/12),0) -> #REF! | AO87: =IF(AN87>0.005,(AN87-$AM87*#REF!/12),0) -> #REF! | AP87: =IF(AO87>0.005,(AO87-$AM87*#REF!/12),0) -> #REF! | AQ87: =IF(AP87>0.005,(AP87-$AM87*#REF!/12),0) -> #REF! | AR87: =IF(AQ87>0.005,(AQ87-$AM87*#REF!/12),0) -> #REF! | AS87: =IF(AR87>0.005,(AR87-$AM87*#REF!/12),0) -> #REF! | AT87: =IF(AS87>0.005,(AS87-$AM87*#REF!/12),0) -> #REF! | AU87: =IF(AT87>0.005,(AT87-$AM87*#REF!/12),0) -> #REF! | ... CI87: =IF(CH87>0.005,(CH87-$AM87*#REF!/12),0) -> #REF!
U88: 44530 | AN88: =+AM$17*#REF! -> #REF! | AO88: =IF(AN88>0.005,(AN88-$AN88*#REF!/12),0) -> #REF! | AP88: =IF(AO88>0.005,(AO88-$AN88*#REF!/12),0) -> #REF! | AQ88: =IF(AP88>0.005,(AP88-$AN88*#REF!/12),0) -> #REF! | AR88: =IF(AQ88>0.005,(AQ88-$AN88*#REF!/12),0) -> #REF! | AS88: =IF(AR88>0.005,(AR88-$AN88*#REF!/12),0) -> #REF! | AT88: =IF(AS88>0.005,(AS88-$AN88*#REF!/12),0) -> #REF! | AU88: =IF(AT88>0.005,(AT88-$AN88*#REF!/12),0) -> #REF! | AV88: =IF(AU88>0.005,(AU88-$AN88*#REF!/12),0) -> #REF! | ... CJ88: =IF(CI88>0.005,(CI88-$AN88*#REF!/12),0) -> #REF!
U89: 44561 | AO89: =+AN$17*#REF! -> #REF! | AP89: =IF(AO89>0.005,(AO89-$AO89*#REF!/12),0) -> #REF! | AQ89: =IF(AP89>0.005,(AP89-$AO89*#REF!/12),0) -> #REF! | AR89: =IF(AQ89>0.005,(AQ89-$AO89*#REF!/12),0) -> #REF! | AS89: =IF(AR89>0.005,(AR89-$AO89*#REF!/12),0) -> #REF! | AT89: =IF(AS89>0.005,(AS89-$AO89*#REF!/12),0) -> #REF! | AU89: =IF(AT89>0.005,(AT89-$AO89*#REF!/12),0) -> #REF! | AV89: =IF(AU89>0.005,(AU89-$AO89*#REF!/12),0) -> #REF! | AW89: =IF(AV89>0.005,(AV89-$AO89*#REF!/12),0) -> #REF! | ... CK89: =IF(CJ89>0.005,(CJ89-$AO89*#REF!/12),0) -> #REF!
U90: 44592 | AP90: =+AO$17*#REF! -> #REF! | AQ90: =IF(AP90>0.005,(AP90-$AP90*#REF!/12),0) -> #REF! | AR90: =IF(AQ90>0.005,(AQ90-$AP90*#REF!/12),0) -> #REF! | AS90: =IF(AR90>0.005,(AR90-$AP90*#REF!/12),0) -> #REF! | AT90: =IF(AS90>0.005,(AS90-$AP90*#REF!/12),0) -> #REF! | AU90: =IF(AT90>0.005,(AT90-$AP90*#REF!/12),0) -> #REF! | AV90: =IF(AU90>0.005,(AU90-$AP90*#REF!/12),0) -> #REF! | AW90: =IF(AV90>0.005,(AV90-$AP90*#REF!/12),0) -> #REF! | AX90: =IF(AW90>0.005,(AW90-$AP90*#REF!/12),0) -> #REF! | ... CL90: =IF(CK90>0.005,(CK90-$AP90*#REF!/12),0) -> #REF!
U91: 44620 | AQ91: =+AP$17*#REF! -> #REF! | AR91: =IF(AQ91>0.005,(AQ91-$AQ91*#REF!/12),0) -> #REF! | AS91: =IF(AR91>0.005,(AR91-$AQ91*#REF!/12),0) -> #REF! | AT91: =IF(AS91>0.005,(AS91-$AQ91*#REF!/12),0) -> #REF! | AU91: =IF(AT91>0.005,(AT91-$AQ91*#REF!/12),0) -> #REF! | AV91: =IF(AU91>0.005,(AU91-$AQ91*#REF!/12),0) -> #REF! | AW91: =IF(AV91>0.005,(AV91-$AQ91*#REF!/12),0) -> #REF! | AX91: =IF(AW91>0.005,(AW91-$AQ91*#REF!/12),0) -> #REF! | AY91: =IF(AX91>0.005,(AX91-$AQ91*#REF!/12),0) -> #REF! | ... CM91: =IF(CL91>0.005,(CL91-$AQ91*#REF!/12),0) -> #REF!
U92: 44651 | AR92: =+AQ$17*#REF! -> #REF! | AS92: =IF(AR92>0.005,(AR92-$AR92*#REF!/12),0) -> #REF! | AT92: =IF(AS92>0.005,(AS92-$AR92*#REF!/12),0) -> #REF! | AU92: =IF(AT92>0.005,(AT92-$AR92*#REF!/12),0) -> #REF! | AV92: =IF(AU92>0.005,(AU92-$AR92*#REF!/12),0) -> #REF! | AW92: =IF(AV92>0.005,(AV92-$AR92*#REF!/12),0) -> #REF! | AX92: =IF(AW92>0.005,(AW92-$AR92*#REF!/12),0) -> #REF! | AY92: =IF(AX92>0.005,(AX92-$AR92*#REF!/12),0) -> #REF! | AZ92: =IF(AY92>0.005,(AY92-$AR92*#REF!/12),0) -> #REF! | ... CN92: =IF(CM92>0.005,(CM92-$AR92*#REF!/12),0) -> #REF!
U93: 44681 | AS93: =+AR$17*#REF! -> #REF! | AT93: =IF(AS93>0.005,(AS93-$AS93*#REF!/12),0) -> #REF! | AU93: =IF(AT93>0.005,(AT93-$AS93*#REF!/12),0) -> #REF! | AV93: =IF(AU93>0.005,(AU93-$AS93*#REF!/12),0) -> #REF! | AW93: =IF(AV93>0.005,(AV93-$AS93*#REF!/12),0) -> #REF! | AX93: =IF(AW93>0.005,(AW93-$AS93*#REF!/12),0) -> #REF! | AY93: =IF(AX93>0.005,(AX93-$AS93*#REF!/12),0) -> #REF! | AZ93: =IF(AY93>0.005,(AY93-$AS93*#REF!/12),0) -> #REF! | BA93: =IF(AZ93>0.005,(AZ93-$AS93*#REF!/12),0) -> #REF! | ... CO93: =IF(CN93>0.005,(CN93-$AS93*#REF!/12),0) -> #REF!
U94: 44712 | AT94: =+AS$17*#REF! -> #REF! | AU94: =IF(AT94>0.005,(AT94-$AT94*#REF!/12),0) -> #REF! | AV94: =IF(AU94>0.005,(AU94-$AT94*#REF!/12),0) -> #REF! | AW94: =IF(AV94>0.005,(AV94-$AT94*#REF!/12),0) -> #REF! | AX94: =IF(AW94>0.005,(AW94-$AT94*#REF!/12),0) -> #REF! | AY94: =IF(AX94>0.005,(AX94-$AT94*#REF!/12),0) -> #REF! | AZ94: =IF(AY94>0.005,(AY94-$AT94*#REF!/12),0) -> #REF! | BA94: =IF(AZ94>0.005,(AZ94-$AT94*#REF!/12),0) -> #REF! | BB94: =IF(BA94>0.005,(BA94-$AT94*#REF!/12),0) -> #REF! | ... CP94: =IF(CO94>0.005,(CO94-$AT94*#REF!/12),0) -> #REF!
U95: 44742 | AU95: =+AT$17*#REF! -> #REF! | AV95: =IF(AU95>0.005,(AU95-$AU95*#REF!/12),0) -> #REF! | AW95: =IF(AV95>0.005,(AV95-$AU95*#REF!/12),0) -> #REF! | AX95: =IF(AW95>0.005,(AW95-$AU95*#REF!/12),0) -> #REF! | AY95: =IF(AX95>0.005,(AX95-$AU95*#REF!/12),0) -> #REF! | AZ95: =IF(AY95>0.005,(AY95-$AU95*#REF!/12),0) -> #REF! | BA95: =IF(AZ95>0.005,(AZ95-$AU95*#REF!/12),0) -> #REF! | BB95: =IF(BA95>0.005,(BA95-$AU95*#REF!/12),0) -> #REF! | BC95: =IF(BB95>0.005,(BB95-$AU95*#REF!/12),0) -> #REF! | ... CQ95: =IF(CP95>0.005,(CP95-$AU95*#REF!/12),0) -> #REF!
U96: 44773 | AV96: =+AU$17*#REF! -> #REF! | AW96: =IF(AV96>0.005,(AV96-$AV96*#REF!/12),0) -> #REF! | AX96: =IF(AW96>0.005,(AW96-$AV96*#REF!/12),0) -> #REF! | AY96: =IF(AX96>0.005,(AX96-$AV96*#REF!/12),0) -> #REF! | AZ96: =IF(AY96>0.005,(AY96-$AV96*#REF!/12),0) -> #REF! | BA96: =IF(AZ96>0.005,(AZ96-$AV96*#REF!/12),0) -> #REF! | BB96: =IF(BA96>0.005,(BA96-$AV96*#REF!/12),0) -> #REF! | BC96: =IF(BB96>0.005,(BB96-$AV96*#REF!/12),0) -> #REF! | BD96: =IF(BC96>0.005,(BC96-$AV96*#REF!/12),0) -> #REF! | ... CR96: =IF(CQ96>0.005,(CQ96-$AV96*#REF!/12),0) -> #REF!
U97: 44804 | AW97: =+AV$17*#REF! -> #REF! | AX97: =IF(AW97>0.005,(AW97-$AW97*#REF!/12),0) -> #REF! | AY97: =IF(AX97>0.005,(AX97-$AW97*#REF!/12),0) -> #REF! | AZ97: =IF(AY97>0.005,(AY97-$AW97*#REF!/12),0) -> #REF! | BA97: =IF(AZ97>0.005,(AZ97-$AW97*#REF!/12),0) -> #REF! | BB97: =IF(BA97>0.005,(BA97-$AW97*#REF!/12),0) -> #REF! | BC97: =IF(BB97>0.005,(BB97-$AW97*#REF!/12),0) -> #REF! | BD97: =IF(BC97>0.005,(BC97-$AW97*#REF!/12),0) -> #REF! | BE97: =IF(BD97>0.005,(BD97-$AW97*#REF!/12),0) -> #REF! | ... CS97: =IF(CR97>0.005,(CR97-$AW97*#REF!/12),0) -> #REF!
U98: 44834 | AX98: =+AW$17*#REF! -> #REF! | AY98: =IF(AX98>0.005,(AX98-$AX98*#REF!/12),0) -> #REF! | AZ98: =IF(AY98>0.005,(AY98-$AX98*#REF!/12),0) -> #REF! | BA98: =IF(AZ98>0.005,(AZ98-$AX98*#REF!/12),0) -> #REF! | BB98: =IF(BA98>0.005,(BA98-$AX98*#REF!/12),0) -> #REF! | BC98: =IF(BB98>0.005,(BB98-$AX98*#REF!/12),0) -> #REF! | BD98: =IF(BC98>0.005,(BC98-$AX98*#REF!/12),0) -> #REF! | BE98: =IF(BD98>0.005,(BD98-$AX98*#REF!/12),0) -> #REF! | BF98: =IF(BE98>0.005,(BE98-$AX98*#REF!/12),0) -> #REF! | ... CT98: =IF(CS98>0.005,(CS98-$AX98*#REF!/12),0) -> #REF!
U99: 44865 | AY99: =+AX$17*#REF! -> #REF! | AZ99: =IF(AY99>0.005,(AY99-$AY99*#REF!/12),0) -> #REF! | BA99: =IF(AZ99>0.005,(AZ99-$AY99*#REF!/12),0) -> #REF! | BB99: =IF(BA99>0.005,(BA99-$AY99*#REF!/12),0) -> #REF! | BC99: =IF(BB99>0.005,(BB99-$AY99*#REF!/12),0) -> #REF! | BD99: =IF(BC99>0.005,(BC99-$AY99*#REF!/12),0) -> #REF! | BE99: =IF(BD99>0.005,(BD99-$AY99*#REF!/12),0) -> #REF! | BF99: =IF(BE99>0.005,(BE99-$AY99*#REF!/12),0) -> #REF! | BG99: =IF(BF99>0.005,(BF99-$AY99*#REF!/12),0) -> #REF! | ... CU99: =IF(CT99>0.005,(CT99-$AY99*#REF!/12),0) -> #REF!
U100: 44895 | AZ100: =+AY$17*#REF! -> #REF! | BA100: =IF(AZ100>0.005,(AZ100-$AZ100*#REF!/12),0) -> #REF! | BB100: =IF(BA100>0.005,(BA100-$AZ100*#REF!/12),0) -> #REF! | BC100: =IF(BB100>0.005,(BB100-$AZ100*#REF!/12),0) -> #REF! | BD100: =IF(BC100>0.005,(BC100-$AZ100*#REF!/12),0) -> #REF! | BE100: =IF(BD100>0.005,(BD100-$AZ100*#REF!/12),0) -> #REF! | BF100: =IF(BE100>0.005,(BE100-$AZ100*#REF!/12),0) -> #REF! | BG100: =IF(BF100>0.005,(BF100-$AZ100*#REF!/12),0) -> #REF! | BH100: =IF(BG100>0.005,(BG100-$AZ100*#REF!/12),0) -> #REF! | ... CV100: =IF(CU100>0.005,(CU100-$AZ100*#REF!/12),0) -> #REF!
U101: 44926 | BA101: =+AZ$17*#REF! -> #REF! | BB101: =IF(BA101>0.005,(BA101-$BA101*#REF!/12),0) -> #REF! | BC101: =IF(BB101>0.005,(BB101-$BA101*#REF!/12),0) -> #REF! | BD101: =IF(BC101>0.005,(BC101-$BA101*#REF!/12),0) -> #REF! | BE101: =IF(BD101>0.005,(BD101-$BA101*#REF!/12),0) -> #REF! | BF101: =IF(BE101>0.005,(BE101-$BA101*#REF!/12),0) -> #REF! | BG101: =IF(BF101>0.005,(BF101-$BA101*#REF!/12),0) -> #REF! | BH101: =IF(BG101>0.005,(BG101-$BA101*#REF!/12),0) -> #REF! | BI101: =IF(BH101>0.005,(BH101-$BA101*#REF!/12),0) -> #REF! | ... CW101: =IF(CV101>0.005,(CV101-$BA101*#REF!/12),0) -> #REF!
U102: 44957 | BB102: =+BA$17*#REF! -> #REF! | BC102: =IF(BB102>0.005,(BB102-$BB102*#REF!/12),0) -> #REF! | BD102: =IF(BC102>0.005,(BC102-$BB102*#REF!/12),0) -> #REF! | BE102: =IF(BD102>0.005,(BD102-$BB102*#REF!/12),0) -> #REF! | BF102: =IF(BE102>0.005,(BE102-$BB102*#REF!/12),0) -> #REF! | BG102: =IF(BF102>0.005,(BF102-$BB102*#REF!/12),0) -> #REF! | BH102: =IF(BG102>0.005,(BG102-$BB102*#REF!/12),0) -> #REF! | BI102: =IF(BH102>0.005,(BH102-$BB102*#REF!/12),0) -> #REF! | BJ102: =IF(BI102>0.005,(BI102-$BB102*#REF!/12),0) -> #REF! | ... CX102: =IF(CW102>0.005,(CW102-$BB102*#REF!/12),0) -> #REF!
U103: 44985 | BC103: =+BB$17*#REF! -> #REF! | BD103: =IF(BC103>0.005,(BC103-$BC103*#REF!/12),0) -> #REF! | BE103: =IF(BD103>0.005,(BD103-$BC103*#REF!/12),0) -> #REF! | BF103: =IF(BE103>0.005,(BE103-$BC103*#REF!/12),0) -> #REF! | BG103: =IF(BF103>0.005,(BF103-$BC103*#REF!/12),0) -> #REF! | BH103: =IF(BG103>0.005,(BG103-$BC103*#REF!/12),0) -> #REF! | BI103: =IF(BH103>0.005,(BH103-$BC103*#REF!/12),0) -> #REF! | BJ103: =IF(BI103>0.005,(BI103-$BC103*#REF!/12),0) -> #REF! | BK103: =IF(BJ103>0.005,(BJ103-$BC103*#REF!/12),0) -> #REF! | ... CY103: =IF(CX103>0.005,(CX103-$BC103*#REF!/12),0) -> #REF!
U104: 45016 | BD104: =+BC$17*#REF! -> #REF! | BE104: =IF(BD104>0.005,(BD104-$BD104*#REF!/12),0) -> #REF! | BF104: =IF(BE104>0.005,(BE104-$BD104*#REF!/12),0) -> #REF! | BG104: =IF(BF104>0.005,(BF104-$BD104*#REF!/12),0) -> #REF! | BH104: =IF(BG104>0.005,(BG104-$BD104*#REF!/12),0) -> #REF! | BI104: =IF(BH104>0.005,(BH104-$BD104*#REF!/12),0) -> #REF! | BJ104: =IF(BI104>0.005,(BI104-$BD104*#REF!/12),0) -> #REF! | BK104: =IF(BJ104>0.005,(BJ104-$BD104*#REF!/12),0) -> #REF! | BL104: =IF(BK104>0.005,(BK104-$BD104*#REF!/12),0) -> #REF! | ... CZ104: =IF(CY104>0.005,(CY104-$BD104*#REF!/12),0) -> #REF!
U105: 45046 | BE105: =+BD$17*#REF! -> #REF! | BF105: =IF(BE105>0.005,(BE105-$BE105*#REF!/12),0) -> #REF! | BG105: =IF(BF105>0.005,(BF105-$BE105*#REF!/12),0) -> #REF! | BH105: =IF(BG105>0.005,(BG105-$BE105*#REF!/12),0) -> #REF! | BI105: =IF(BH105>0.005,(BH105-$BE105*#REF!/12),0) -> #REF! | BJ105: =IF(BI105>0.005,(BI105-$BE105*#REF!/12),0) -> #REF! | BK105: =IF(BJ105>0.005,(BJ105-$BE105*#REF!/12),0) -> #REF! | BL105: =IF(BK105>0.005,(BK105-$BE105*#REF!/12),0) -> #REF! | BM105: =IF(BL105>0.005,(BL105-$BE105*#REF!/12),0) -> #REF! | ... DA105: =IF(CZ105>0.005,(CZ105-$BE105*#REF!/12),0) -> #REF!
U106: 45077 | BF106: =+BE$17*#REF! -> #REF! | BG106: =IF(BF106>0.005,(BF106-$BF106*#REF!/12),0) -> #REF! | BH106: =IF(BG106>0.005,(BG106-$BF106*#REF!/12),0) -> #REF! | BI106: =IF(BH106>0.005,(BH106-$BF106*#REF!/12),0) -> #REF! | BJ106: =IF(BI106>0.005,(BI106-$BF106*#REF!/12),0) -> #REF! | BK106: =IF(BJ106>0.005,(BJ106-$BF106*#REF!/12),0) -> #REF! | BL106: =IF(BK106>0.005,(BK106-$BF106*#REF!/12),0) -> #REF! | BM106: =IF(BL106>0.005,(BL106-$BF106*#REF!/12),0) -> #REF! | BN106: =IF(BM106>0.005,(BM106-$BF106*#REF!/12),0) -> #REF! | ... DB106: =IF(DA106>0.005,(DA106-$BF106*#REF!/12),0) -> #REF!
U107: 45107 | BG107: =+BF$17*#REF! -> #REF! | BH107: =IF(BG107>0.005,(BG107-$BG107*#REF!/12),0) -> #REF! | BI107: =IF(BH107>0.005,(BH107-$BG107*#REF!/12),0) -> #REF! | BJ107: =IF(BI107>0.005,(BI107-$BG107*#REF!/12),0) -> #REF! | BK107: =IF(BJ107>0.005,(BJ107-$BG107*#REF!/12),0) -> #REF! | BL107: =IF(BK107>0.005,(BK107-$BG107*#REF!/12),0) -> #REF! | BM107: =IF(BL107>0.005,(BL107-$BG107*#REF!/12),0) -> #REF! | BN107: =IF(BM107>0.005,(BM107-$BG107*#REF!/12),0) -> #REF! | BO107: =IF(BN107>0.005,(BN107-$BG107*#REF!/12),0) -> #REF! | ... DC107: =IF(DB107>0.005,(DB107-$BG107*#REF!/12),0) -> #REF!
U108: 45138 | BH108: =+BG$17*#REF! -> #REF! | BI108: =IF(BH108>0.005,(BH108-$BH108*#REF!/12),0) -> #REF! | BJ108: =IF(BI108>0.005,(BI108-$BH108*#REF!/12),0) -> #REF! | BK108: =IF(BJ108>0.005,(BJ108-$BH108*#REF!/12),0) -> #REF! | BL108: =IF(BK108>0.005,(BK108-$BH108*#REF!/12),0) -> #REF! | BM108: =IF(BL108>0.005,(BL108-$BH108*#REF!/12),0) -> #REF! | BN108: =IF(BM108>0.005,(BM108-$BH108*#REF!/12),0) -> #REF! | BO108: =IF(BN108>0.005,(BN108-$BH108*#REF!/12),0) -> #REF! | BP108: =IF(BO108>0.005,(BO108-$BH108*#REF!/12),0) -> #REF! | ... DD108: =IF(DC108>0.005,(DC108-$BH108*#REF!/12),0) -> #REF!
U109: 45169 | BI109: =+BH$17*#REF! -> #REF! | BJ109: =IF(BI109>0.005,(BI109-$BI109*#REF!/12),0) -> #REF! | BK109: =IF(BJ109>0.005,(BJ109-$BI109*#REF!/12),0) -> #REF! | BL109: =IF(BK109>0.005,(BK109-$BI109*#REF!/12),0) -> #REF! | BM109: =IF(BL109>0.005,(BL109-$BI109*#REF!/12),0) -> #REF! | BN109: =IF(BM109>0.005,(BM109-$BI109*#REF!/12),0) -> #REF! | BO109: =IF(BN109>0.005,(BN109-$BI109*#REF!/12),0) -> #REF! | BP109: =IF(BO109>0.005,(BO109-$BI109*#REF!/12),0) -> #REF! | BQ109: =IF(BP109>0.005,(BP109-$BI109*#REF!/12),0) -> #REF! | ... DE109: =IF(DD109>0.005,(DD109-$BI109*#REF!/12),0) -> #REF!
U110: 45199 | BJ110: =+BI$17*#REF! -> #REF! | BK110: =IF(BJ110>0.005,(BJ110-$BJ110*#REF!/12),0) -> #REF! | BL110: =IF(BK110>0.005,(BK110-$BJ110*#REF!/12),0) -> #REF! | BM110: =IF(BL110>0.005,(BL110-$BJ110*#REF!/12),0) -> #REF! | BN110: =IF(BM110>0.005,(BM110-$BJ110*#REF!/12),0) -> #REF! | BO110: =IF(BN110>0.005,(BN110-$BJ110*#REF!/12),0) -> #REF! | BP110: =IF(BO110>0.005,(BO110-$BJ110*#REF!/12),0) -> #REF! | BQ110: =IF(BP110>0.005,(BP110-$BJ110*#REF!/12),0) -> #REF! | BR110: =IF(BQ110>0.005,(BQ110-$BJ110*#REF!/12),0) -> #REF! | ... DF110: =IF(DE110>0.005,(DE110-$BJ110*#REF!/12),0) -> #REF!
U111: 45230 | BK111: =+BJ$17*#REF! -> #REF! | BL111: =IF(BK111>0.005,(BK111-$BK111*#REF!/12),0) -> #REF! | BM111: =IF(BL111>0.005,(BL111-$BL111*#REF!/12),0) -> #REF! | BN111: =IF(BM111>0.005,(BM111-$BK111*#REF!/12),0) -> #REF! | BO111: =IF(BN111>0.005,(BN111-$BK111*#REF!/12),0) -> #REF! | BP111: =IF(BO111>0.005,(BO111-$BK111*#REF!/12),0) -> #REF! | BQ111: =IF(BP111>0.005,(BP111-$BK111*#REF!/12),0) -> #REF! | BR111: =IF(BQ111>0.005,(BQ111-$BK111*#REF!/12),0) -> #REF! | BS111: =IF(BR111>0.005,(BR111-$BK111*#REF!/12),0) -> #REF! | BT111: =IF(BS111>0.005,(BS111-$BK111*#REF!/12),0) -> #REF! | BU111: =IF(BT111>0.005,(BT111-$BK111*#REF!/12),0) -> #REF! | ... DG111: =IF(DF111>0.005,(DF111-$BK111*#REF!/12),0) -> #REF!
U112: 45260 | BL112: =+BK$17*#REF! -> #REF! | BM112: =IF(BL112>0.005,(BL112-$BL112*#REF!/12),0) -> #REF! | BN112: =IF(BM112>0.005,(BM112-$BL112*#REF!/12),0) -> #REF! | BO112: =IF(BN112>0.005,(BN112-$BL112*#REF!/12),0) -> #REF! | BP112: =IF(BO112>0.005,(BO112-$BL112*#REF!/12),0) -> #REF! | BQ112: =IF(BP112>0.005,(BP112-$BL112*#REF!/12),0) -> #REF! | BR112: =IF(BQ112>0.005,(BQ112-$BL112*#REF!/12),0) -> #REF! | BS112: =IF(BR112>0.005,(BR112-$BL112*#REF!/12),0) -> #REF! | BT112: =IF(BS112>0.005,(BS112-$BL112*#REF!/12),0) -> #REF! | ... DI112: =IF(DH112>0.005,(DH112-$BL112*#REF!/12),0) -> #REF!
U113: 45291 | BM113: =+BL$17*#REF! -> #REF! | BN113: =IF(BM113>0.005,(BM113-$BM113*#REF!/12),0) -> #REF! | BO113: =IF(BN113>0.005,(BN113-$BM113*#REF!/12),0) -> #REF! | BP113: =IF(BO113>0.005,(BO113-$BM113*#REF!/12),0) -> #REF! | BQ113: =IF(BP113>0.005,(BP113-$BM113*#REF!/12),0) -> #REF! | BR113: =IF(BQ113>0.005,(BQ113-$BM113*#REF!/12),0) -> #REF! | BS113: =IF(BR113>0.005,(BR113-$BM113*#REF!/12),0) -> #REF! | BT113: =IF(BS113>0.005,(BS113-$BM113*#REF!/12),0) -> #REF! | BU113: =IF(BT113>0.005,(BT113-$BM113*#REF!/12),0) -> #REF! | ... DI113: =IF(DH113>0.005,(DH113-$BM113*#REF!/12),0) -> #REF!
U114: 45322 | BN114: =+BM$17*#REF! -> #REF! | BO114: =IF(BN114>0.005,(BN114-$BN114*#REF!/12),0) -> #REF! | BP114: =IF(BO114>0.005,(BO114-$BN114*#REF!/12),0) -> #REF! | BQ114: =IF(BP114>0.005,(BP114-$BN114*#REF!/12),0) -> #REF! | BR114: =IF(BQ114>0.005,(BQ114-$BN114*#REF!/12),0) -> #REF! | BS114: =IF(BR114>0.005,(BR114-$BN114*#REF!/12),0) -> #REF! | BT114: =IF(BS114>0.005,(BS114-$BN114*#REF!/12),0) -> #REF! | BU114: =IF(BT114>0.005,(BT114-$BN114*#REF!/12),0) -> #REF! | BV114: =IF(BU114>0.005,(BU114-$BN114*#REF!/12),0) -> #REF! | ... DJ114: =IF(DI114>0.005,(DI114-$BN114*#REF!/12),0) -> #REF!
U115: 45351 | BO115: =+BN$17*#REF! -> #REF! | BP115: =IF(BO115>0.005,(BO115-$BO115*#REF!/12),0) -> #REF! | BQ115: =IF(BP115>0.005,(BP115-$BO115*#REF!/12),0) -> #REF! | BR115: =IF(BQ115>0.005,(BQ115-$BO115*#REF!/12),0) -> #REF! | BS115: =IF(BR115>0.005,(BR115-$BO115*#REF!/12),0) -> #REF! | BT115: =IF(BS115>0.005,(BS115-$BO115*#REF!/12),0) -> #REF! | BU115: =IF(BT115>0.005,(BT115-$BO115*#REF!/12),0) -> #REF! | BV115: =IF(BU115>0.005,(BU115-$BO115*#REF!/12),0) -> #REF! | BW115: =IF(BV115>0.005,(BV115-$BO115*#REF!/12),0) -> #REF! | ... DK115: =IF(DJ115>0.005,(DJ115-$BO115*#REF!/12),0) -> #REF!
U116: 45382 | BP116: =+BO$17*#REF! -> #REF! | BQ116: =IF(BP116>0.005,(BP116-$BP116*#REF!/12),0) -> #REF! | BR116: =IF(BQ116>0.005,(BQ116-$BP116*#REF!/12),0) -> #REF! | BS116: =IF(BR116>0.005,(BR116-$BP116*#REF!/12),0) -> #REF! | BT116: =IF(BS116>0.005,(BS116-$BP116*#REF!/12),0) -> #REF! | BU116: =IF(BT116>0.005,(BT116-$BP116*#REF!/12),0) -> #REF! | BV116: =IF(BU116>0.005,(BU116-$BP116*#REF!/12),0) -> #REF! | BW116: =IF(BV116>0.005,(BV116-$BP116*#REF!/12),0) -> #REF! | BX116: =IF(BW116>0.005,(BW116-$BP116*#REF!/12),0) -> #REF! | ... DL116: =IF(DK116>0.005,(DK116-$BP116*#REF!/12),0) -> #REF!
U117: 45412 | BQ117: =+BP$17*#REF! -> #REF! | BR117: =IF(BQ117>0.005,(BQ117-$BQ117*#REF!/12),0) -> #REF! | BS117: =IF(BR117>0.005,(BR117-$BQ117*#REF!/12),0) -> #REF! | BT117: =IF(BS117>0.005,(BS117-$BQ117*#REF!/12),0) -> #REF! | BU117: =IF(BT117>0.005,(BT117-$BQ117*#REF!/12),0) -> #REF! | BV117: =IF(BU117>0.005,(BU117-$BQ117*#REF!/12),0) -> #REF! | BW117: =IF(BV117>0.005,(BV117-$BQ117*#REF!/12),0) -> #REF! | BX117: =IF(BW117>0.005,(BW117-$BQ117*#REF!/12),0) -> #REF! | BY117: =IF(BX117>0.005,(BX117-$BQ117*#REF!/12),0) -> #REF! | ... DM117: =IF(DL117>0.005,(DL117-$BQ117*#REF!/12),0) -> #REF!
U118: 45443 | BR118: =+BQ$17*#REF! -> #REF! | BS118: =IF(BR118>0.005,(BR118-$BR118*#REF!/12),0) -> #REF! | BT118: =IF(BS118>0.005,(BS118-$BR118*#REF!/12),0) -> #REF! | BU118: =IF(BT118>0.005,(BT118-$BR118*#REF!/12),0) -> #REF! | BV118: =IF(BU118>0.005,(BU118-$BR118*#REF!/12),0) -> #REF! | BW118: =IF(BV118>0.005,(BV118-$BR118*#REF!/12),0) -> #REF! | BX118: =IF(BW118>0.005,(BW118-$BR118*#REF!/12),0) -> #REF! | BY118: =IF(BX118>0.005,(BX118-$BR118*#REF!/12),0) -> #REF! | BZ118: =IF(BY118>0.005,(BY118-$BR118*#REF!/12),0) -> #REF! | ... DN118: =IF(DM118>0.005,(DM118-$BR118*#REF!/12),0) -> #REF!
U119: 45473 | BS119: =+BR$17*#REF! -> #REF! | BT119: =IF(BS119>0.005,(BS119-$BS119*#REF!/12),0) -> #REF! | BU119: =IF(BT119>0.005,(BT119-$BS119*#REF!/12),0) -> #REF! | BV119: =IF(BU119>0.005,(BU119-$BS119*#REF!/12),0) -> #REF! | BW119: =IF(BV119>0.005,(BV119-$BS119*#REF!/12),0) -> #REF! | BX119: =IF(BW119>0.005,(BW119-$BS119*#REF!/12),0) -> #REF! | BY119: =IF(BX119>0.005,(BX119-$BS119*#REF!/12),0) -> #REF! | BZ119: =IF(BY119>0.005,(BY119-$BS119*#REF!/12),0) -> #REF! | CA119: =IF(BZ119>0.005,(BZ119-$BS119*#REF!/12),0) -> #REF! | ... DO119: =IF(DN119>0.005,(DN119-$BS119*#REF!/12),0) -> #REF!
U120: 45504 | BT120: =+BS$17*#REF! -> #REF! | BU120: =IF(BT120>0.005,(BT120-$BT120*#REF!/12),0) -> #REF! | BV120: =IF(BU120>0.005,(BU120-$BT120*#REF!/12),0) -> #REF! | BW120: =IF(BV120>0.005,(BV120-$BT120*#REF!/12),0) -> #REF! | BX120: =IF(BW120>0.005,(BW120-$BT120*#REF!/12),0) -> #REF! | BY120: =IF(BX120>0.005,(BX120-$BT120*#REF!/12),0) -> #REF! | BZ120: =IF(BY120>0.005,(BY120-$BT120*#REF!/12),0) -> #REF! | CA120: =IF(BZ120>0.005,(BZ120-$BT120*#REF!/12),0) -> #REF! | CB120: =IF(CA120>0.005,(CA120-$BT120*#REF!/12),0) -> #REF! | ... DP120: =IF(DO120>0.005,(DO120-$BT120*#REF!/12),0) -> #REF!
U121: 45535 | BU121: =+BT$17*#REF! -> #REF! | BV121: =IF(BU121>0.005,(BU121-$BU121*#REF!/12),0) -> #REF! | BW121: =IF(BV121>0.005,(BV121-$BU121*#REF!/12),0) -> #REF! | BX121: =IF(BW121>0.005,(BW121-$BU121*#REF!/12),0) -> #REF! | BY121: =IF(BX121>0.005,(BX121-$BU121*#REF!/12),0) -> #REF! | BZ121: =IF(BY121>0.005,(BY121-$BU121*#REF!/12),0) -> #REF! | CA121: =IF(BZ121>0.005,(BZ121-$BU121*#REF!/12),0) -> #REF! | CB121: =IF(CA121>0.005,(CA121-$BU121*#REF!/12),0) -> #REF! | CC121: =IF(CB121>0.005,(CB121-$BU121*#REF!/12),0) -> #REF! | ... DQ121: =IF(DP121>0.005,(DP121-$BU121*#REF!/12),0) -> #REF!
U122: 45565 | BV122: =+BU$17*#REF! -> #REF! | BW122: =IF(BV122>0.005,(BV122-$BV122*#REF!/12),0) -> #REF! | BX122: =IF(BW122>0.005,(BW122-$BV122*#REF!/12),0) -> #REF! | BY122: =IF(BX122>0.005,(BX122-$BV122*#REF!/12),0) -> #REF! | BZ122: =IF(BY122>0.005,(BY122-$BV122*#REF!/12),0) -> #REF! | CA122: =IF(BZ122>0.005,(BZ122-$BV122*#REF!/12),0) -> #REF! | CB122: =IF(CA122>0.005,(CA122-$BV122*#REF!/12),0) -> #REF! | CC122: =IF(CB122>0.005,(CB122-$BV122*#REF!/12),0) -> #REF! | CD122: =IF(CC122>0.005,(CC122-$BV122*#REF!/12),0) -> #REF! | ... DR122: =IF(DQ122>0.005,(DQ122-$BV122*#REF!/12),0) -> #REF!
U123: 45596 | BW123: =+BV$17*#REF! -> #REF! | BX123: =IF(BW123>0.005,(BW123-$BW123*#REF!/12),0) -> #REF! | BY123: =IF(BX123>0.005,(BX123-$BW123*#REF!/12),0) -> #REF! | BZ123: =IF(BY123>0.005,(BY123-$BW123*#REF!/12),0) -> #REF! | CA123: =IF(BZ123>0.005,(BZ123-$BW123*#REF!/12),0) -> #REF! | CB123: =IF(CA123>0.005,(CA123-$BW123*#REF!/12),0) -> #REF! | CC123: =IF(CB123>0.005,(CB123-$BW123*#REF!/12),0) -> #REF! | CD123: =IF(CC123>0.005,(CC123-$BW123*#REF!/12),0) -> #REF! | CE123: =IF(CD123>0.005,(CD123-$BW123*#REF!/12),0) -> #REF! | ... DS123: =IF(DR123>0.005,(DR123-$BW123*#REF!/12),0) -> #REF!
U124: 45626 | BX124: =+BW$17*#REF! -> #REF! | BY124: =IF(BX124>0.005,(BX124-$BX124*#REF!/12),0) -> #REF! | BZ124: =IF(BY124>0.005,(BY124-$BX124*#REF!/12),0) -> #REF! | CA124: =IF(BZ124>0.005,(BZ124-$BX124*#REF!/12),0) -> #REF! | CB124: =IF(CA124>0.005,(CA124-$BX124*#REF!/12),0) -> #REF! | CC124: =IF(CB124>0.005,(CB124-$BX124*#REF!/12),0) -> #REF! | CD124: =IF(CC124>0.005,(CC124-$BX124*#REF!/12),0) -> #REF! | CE124: =IF(CD124>0.005,(CD124-$BX124*#REF!/12),0) -> #REF! | CF124: =IF(CE124>0.005,(CE124-$BX124*#REF!/12),0) -> #REF! | ... DT124: =IF(DS124>0.005,(DS124-$BX124*#REF!/12),0) -> #REF!
U125: 45657 | BY125: =+BX$17*#REF! -> #REF! | BZ125: =IF(BY125>0.005,(BY125-$BY125*#REF!/12),0) -> #REF! | CA125: =IF(BZ125>0.005,(BZ125-$BY125*#REF!/12),0) -> #REF! | CB125: =IF(CA125>0.005,(CA125-$BY125*#REF!/12),0) -> #REF! | CC125: =IF(CB125>0.005,(CB125-$BY125*#REF!/12),0) -> #REF! | CD125: =IF(CC125>0.005,(CC125-$BY125*#REF!/12),0) -> #REF! | CE125: =IF(CD125>0.005,(CD125-$BY125*#REF!/12),0) -> #REF! | CF125: =IF(CE125>0.005,(CE125-$BY125*#REF!/12),0) -> #REF! | CG125: =IF(CF125>0.005,(CF125-$BY125*#REF!/12),0) -> #REF! | ... DU125: =IF(DT125>0.005,(DT125-$BY125*#REF!/12),0) -> #REF!
U126: 45688 | BZ126: =+BY$17*#REF! -> #REF! | CA126: =IF(BZ126>0.005,(BZ126-$BZ126*#REF!/12),0) -> #REF! | CB126: =IF(CA126>0.005,(CA126-$BZ126*#REF!/12),0) -> #REF! | CC126: =IF(CB126>0.005,(CB126-$BZ126*#REF!/12),0) -> #REF! | CD126: =IF(CC126>0.005,(CC126-$BZ126*#REF!/12),0) -> #REF! | CE126: =IF(CD126>0.005,(CD126-$BZ126*#REF!/12),0) -> #REF! | CF126: =IF(CE126>0.005,(CE126-$BZ126*#REF!/12),0) -> #REF! | CG126: =IF(CF126>0.005,(CF126-$BZ126*#REF!/12),0) -> #REF! | CH126: =IF(CG126>0.005,(CG126-$BZ126*#REF!/12),0) -> #REF! | ... DV126: =IF(DU126>0.005,(DU126-$BZ126*#REF!/12),0) -> #REF!
U127: 45716 | CA127: =+BZ$17*#REF! -> #REF! | CB127: =IF(CA127>0.005,(CA127-$CA127*#REF!/12),0) -> #REF! | CC127: =IF(CB127>0.005,(CB127-$CA127*#REF!/12),0) -> #REF! | CD127: =IF(CC127>0.005,(CC127-$CA127*#REF!/12),0) -> #REF! | CE127: =IF(CD127>0.005,(CD127-$CA127*#REF!/12),0) -> #REF! | CF127: =IF(CE127>0.005,(CE127-$CA127*#REF!/12),0) -> #REF! | CG127: =IF(CF127>0.005,(CF127-$CA127*#REF!/12),0) -> #REF! | CH127: =IF(CG127>0.005,(CG127-$CA127*#REF!/12),0) -> #REF! | CI127: =IF(CH127>0.005,(CH127-$CA127*#REF!/12),0) -> #REF! | ... DW127: =IF(DV127>0.005,(DV127-$CA127*#REF!/12),0) -> #REF!
U128: 45747
U129: 45777
U130: 45808
U131: 45838
U132: 45869
...

Sheet COGS
A3: COGS Projections
B9: =+'P&L Cash Flow Monthly'!B8 -> 43951 | C9: =+'P&L Cash Flow Monthly'!C8 -> 43982 | D9: =+'P&L Cash Flow Monthly'!D8 -> 44012 | E9: =+'P&L Cash Flow Monthly'!E8 -> 44043 | F9: =+'P&L Cash Flow Monthly'!F8 -> 44074 | G9: =+'P&L Cash Flow Monthly'!G8 -> 44104 | H9: =+'P&L Cash Flow Monthly'!H8 -> 44135 | I9: =+'P&L Cash Flow Monthly'!I8 -> 44165 | ... CP9: =+'P&L Cash Flow Monthly'!CP8 -> 46752
A10: Labor & Fullment cost per bar | B10: 2.25 | C10: 2.25 | D10: 2.05 | E10: 2.05 | F10: 2.05 | G10: 1.65 | H10: 1.65 | I10: 1.65 | J10: 1.65 | K10: 1.65 | L10: 1.65 | M10: 1.65 | N10: 1.65 | O10: 1.65 | P10: 1.65 | Q10: 1.65 | R10: 1.65 | S10: 1.65 | T10: 1.65 | U10: 1.65 | V10: 1.65 | W10: 1.65 | X10: 1.65 | Y10: 1.65 | Z10: 1.65 | AA10: 1.65 | AB10: 1.65 | AC10: 1.65 | AD10: 1.65 | AE10: 1.65 | AF10: 1.65 | AG10: 1.25 | AH10: 1.25 | AI10: 1.25 | AJ10: 1.25 | AK10: 1.25 | AL10: 1.25 | AM10: 1.25 | AN10: 1.25 | AO10: 1.25 | AP10: 1.25 | AQ10: 1.25 | AR10: 1.25 | AS10: 1.25 | AT10: 1.25 | AU10: 1.25 | AV10: 1.25 | AW10: 1.25 | AX10: 1.25 | AY10: 1.25 | AZ10: 1.25 | BA10: 1.25 | BB10: 1.25 | BC10: 1.25 | BD10: 1.25 | BE10: 1.25 | BF10: 1.25 | BG10: 0.94 | BH10: 0.94 | BI10: 0.94 | BJ10: 0.94 | BK10: 0.94 | BL10: 0.94 | BM10: 0.94 | BN10: 0.94 | BO10: 0.94 | BP10: 0.94 | BQ10: 0.94 | BR10: 0.94 | BS10: 0.94 | BT10: 0.94 | BU10: 0.94 | BV10: 0.94 | BW10: 0.94 | BX10: 0.94 | BY10: 0.94 | BZ10: 0.94 | CA10: 0.94 | CB10: 0.94 | CC10: 0.94 | CD10: 0.94 | CE10: 0.94 | CF10: 0.94 | CG10: 0.94 | CH10: 0.94 | CI10: 0.94 | CJ10: 0.94 | CK10: 0.94 | CL10: 0.94 | CM10: 0.94 | CN10: 0.94 | CO10: 0.94 | CP10: 0.94
A12: Ingredients and packging cost per bar | B12: =+$B41 -> 1.1633333 | C12: =+$B41 -> 1.1633333 | D12: =+$B41 -> 1.1633333 | E12: =+$B41 -> 1.1633333 | F12: =+$B41 -> 1.1633333 | G12: =+$B41 -> 1.1633333 | H12: =+$B41 -> 1.1633333 | I12: =+$B41 -> 1.1633333 | ... L12: =+$B41 -> 1.1633333 | M12: =+B41 -> 1.1633333 | N12: =+B41 -> 1.1633333 | O12: =+$B41 -> 1.1633333 | P12: =+$B41 -> 1.1633333 | Q12: =+$B41 -> 1.1633333 | R12: =+$B41 -> 1.1633333 | S12: =+$B41 -> 1.1633333 | T12: =+$B41 -> 1.1633333 | U12: =+$B41 -> 1.1633333 | V12: =+$B41 -> 1.1633333 | ... BL12: =+$B41 -> 1.1633333 | BM12: =+$C41 -> 0.81666667 | BN12: =+$C41 -> 0.81666667 | BO12: =+$C41 -> 0.81666667 | BP12: =+$C41 -> 0.81666667 | BQ12: =+$C41 -> 0.81666667 | BR12: =+$C41 -> 0.81666667 | BS12: =+$C41 -> 0.81666667 | BT12: =+$C41 -> 0.81666667 | ... CP12: =+$C41 -> 0.81666667
A14: total cost per bar | B14: =+B10+$B41 -> 3.4133333 | C14: =+C10+$B41 -> 3.4133333 | D14: =+D10+$B41 -> 3.2133333 | E14: =+E10+$B41 -> 3.2133333 | F14: =+F10+$B41 -> 3.2133333 | G14: =+G10+$B41 -> 2.8133333 | H14: =+H10+$B41 -> 2.8133333 | I14: =SUM(I10:I12) -> 2.8133333 | J14: =SUM(J10:J12) -> 2.8133333 | K14: =SUM(K10:K12) -> 2.8133333 | L14: =SUM(L10:L12) -> 2.8133333 | M14: =SUM(M10:M12) -> 2.8133333 | N14: =SUM(N10:N12) -> 2.8133333 | O14: =SUM(O10:O12) -> 2.8133333 | P14: =SUM(P10:P12) -> 2.8133333 | ... CP14: =SUM(CP10:CP12) -> 1.7566667
A17: For sales in month | B17: =+D9 -> 44012 | C17: =+E9 -> 44043 | D17: =+F9 -> 44074 | E17: =+G9 -> 44104 | F17: =+H9 -> 44135 | G17: =+I9 -> 44165 | H17: =+J9 -> 44196 | I17: =+K9 -> 44227 | ... CP17: =+CR9
A19: Produced third month prior to sale
A20: Ingredietns Purchase three months forward
A21: # bars produced | B21: =+'Rev 2'!W19 -> 1564.3919 | C21: =+'Rev 2'!X19 -> 2384.5187 | D21: =+'Rev 2'!Y19 -> 3089.9233 | E21: =+'Rev 2'!Z19 -> 3045.4222 | F21: =+'Rev 2'!AA19 -> 4367.3442 | G21: =+'Rev 2'!AB19 -> 8559.71 | H21: =+'Rev 2'!AC19 -> 8287.2442 | I21: =+'Rev 2'!AD19 -> 13386.077 | ... CP21: =+'Rev 2'!DK19 -> 63003.719
B23: =+B21*B14 -> 5339.791 | C23: =+C21*C14 -> 8139.1572 | D23: =+D21*D14 -> 9928.9536 | E23: =+E21*E14 -> 9785.9566 | F23: =+F21*F14 -> 14033.733 | G23: =+G21*G14 -> 24081.317 | H23: =+H21*H14 -> 23314.78 | I23: =+I21*I14 -> 37659.495 | ... CP23: =+CP21*CP14 -> 110676.53
A26: Additional production month 1
A27: # bars to be sold months 1 and 2 | B27: =+'Rev 2'!V19+'Rev 2'!W19 -> 1693.5619
A28: Cost per bar | B28: =+B14 -> 3.4133333
B29: =+B27*B28 -> 5780.6912
A30: Cost of inventory on hand | B30: -5000
A31: Additional production costs for first
A32: two months sales | B32: =SUM(B29:B30) -> 780.6912
C34: economy of scale
C35: %30 reduction
A36: Bar cost break down per bar
A37: ingredients | B37: 0.95 | C37: 0.65
A38: flow wrap and label | B38: 0.13 | C38: 0.1
A39: display box | B39: =0.15/6 -> 0.025 | C39: =+B39*0.8 -> 0.02
A40: Shipper box | B40: =0.35/6 -> 0.058333333 | C40: =+B40*0.8 -> 0.046666667
A41: total material cost per bar | B41: =SUM(B37:B40) -> 1.1633333 | C41: =SUM(C37:C40) -> 0.81666667

Sheet Expenses 2
A4: Expense Projections
B9: =+'P&L Cash Flow Monthly'!B8 -> 43951 | C9: =+'P&L Cash Flow Monthly'!C8 -> 43982 | D9: =+'P&L Cash Flow Monthly'!D8 -> 44012 | E9: =+'P&L Cash Flow Monthly'!E8 -> 44043 | F9: =+'P&L Cash Flow Monthly'!F8 -> 44074 | G9: =+'P&L Cash Flow Monthly'!G8 -> 44104 | H9: =+'P&L Cash Flow Monthly'!H8 -> 44135 | I9: =+'P&L Cash Flow Monthly'!I8 -> 44165 | ... CP9: =+'P&L Cash Flow Monthly'!CP8 -> 46752
A10: Expense
A13: Salaries
A14: Executive
A15: COO | AJ15: 0 | AL15: 0 | AU15: 2000 | AV15: 2000 | AW15: 2000 | AX15: 2000 | AY15: 2000 | AZ15: 2000 | BA15: 2000 | BB15: 2000 | BC15: 2000 | BD15: 2000 | BE15: 2000 | BF15: 2000 | BG15: 2000 | BH15: 2000 | BI15: 2000 | BJ15: 2000 | BK15: 2000 | BL15: 2000 | BM15: 2000 | BN15: 3000 | BO15: 3000 | BP15: 3000 | BQ15: 3000 | BR15: 3000 | BS15: 3000 | BT15: 3000 | BU15: 3000 | BV15: 3000 | BW15: 3000 | BX15: 3000 | BY15: 3000 | BZ15: 3000 | CA15: 3000 | CB15: 3000 | CC15: 3000 | CD15: 3000 | CE15: 6000 | CF15: 6000 | CG15: 6000 | CH15: 6000 | CI15: 6000 | CJ15: 6000 | CK15: 6000 | CL15: 6000 | CM15: 6000 | CN15: 6000 | CO15: 6000 | CP15: 6000
A16: CFO
A17: Sales
A18: Director
A19: Sales representive | AO19: 0
A20: Marketing | AO20: 0
A21: Director | AJ21: 0 | AK21: 0 | AL21: 0 | AM21: 0 | AN21: 0 | AO21: 0 | AP21: 0 | AQ21: 0 | AR21: 0 | AS21: 0 | AT21: 0 | AU21: 0 | AV21: 0 | AW21: 0 | AX21: 0 | AY21: 0 | AZ21: 0 | BA21: 0 | BB21: 0 | BC21: 0 | BD21: 0 | BE21: 0 | BF21: 0 | BG21: 0 | BH21: 0 | BI21: 0 | BJ21: 0 | BK21: 0 | BL21: 0 | BM21: 0 | BN21: 0 | BO21: 0 | BP21: 0 | BQ21: 0 | BR21: 0 | BS21: 0 | BT21: 0 | BU21: 0 | BV21: 0 | BW21: 0 | BX21: 0 | BY21: 0 | BZ21: 0 | CA21: 0 | CB21: 0 | CC21: 0 | CD21: 0 | CE21: 0 | CF21: 0 | CG21: 0 | CH21: 0 | CI21: 0 | CJ21: 0 | CK21: 0 | CL21: 0 | CM21: 0 | CN21: 0 | CO21: 0 | CP21: 0 | CQ21: 0
A22: SEO manager | AI22: 1500 | AJ22: 1500 | AK22: 1500 | AL22: 1500 | AM22: 1500 | AN22: 1500 | AO22: 1500 | AP22: 1500 | AQ22: 1500 | AR22: 1500 | AS22: 1500 | AT22: 1500 | AU22: 1500 | AV22: 1500 | AW22: 1500 | AX22: 1500 | AY22: 1500 | AZ22: 1500 | BA22: 1500 | BB22: 1500 | BC22: 1500 | BD22: 1500 | BE22: 1500 | BF22: 1500 | BG22: 1500 | BH22: 1500 | BI22: 1500 | BJ22: 1500 | BK22: 1500 | BL22: 1500 | BM22: 1500 | BN22: 1500 | BO22: 1500 | BP22: 1500 | BQ22: 3000 | BR22: 3000 | BS22: 3000 | BT22: 3000 | BU22: 3000 | BV22: 3000 | BW22: 3000 | BX22: 3000 | BY22: 3000 | BZ22: 3000 | CA22: 3000 | CB22: 3000 | CC22: 3000 | CD22: 3000 | CE22: 3000 | CF22: 3000 | CG22: 3000 | CH22: 3000 | CI22: 3000 | CJ22: 3000 | CK22: 3000 | CL22: 3000 | CM22: 3000 | CN22: 3000 | CO22: 3000 | CP22: 3000
A23: Social media manager | B23: 3000 | C23: 3000 | D23: 3000 | E23: 3000 | F23: 3000 | G23: 3000 | H23: 3000 | I23: 3000 | J23: 3000 | K23: 3000 | L23: 3000 | M23: 3000 | N23: 3000 | O23: 3000 | P23: 3000 | Q23: 3000 | R23: 3000 | S23: 3000 | T23: 3000 | U23: 3000 | V23: 3000 | W23: 3000 | X23: 3000 | Y23: 3000 | Z23: 3000 | AA23: 3000 | AB23: 3000 | AC23: 3000 | AD23: 3000 | AE23: 3000 | AF23: 3000 | AG23: 3000 | AI23: 1500 | AJ23: 1500 | AK23: 1500 | AL23: 1500 | AM23: 1500 | AN23: 1500 | AO23: 1500 | AP23: 1500 | AQ23: 1500 | AR23: 1500 | AS23: 1500 | AT23: 1500 | AU23: 1500 | AV23: 1500 | AW23: 1500 | AX23: 1500 | AY23: 1500 | AZ23: 1500 | BA23: 1500 | BB23: 1500 | BC23: 1500 | BD23: 1500 | BE23: 1500 | BF23: 1500 | BG23: 1500 | BH23: 1500 | BI23: 1500 | BJ23: 1500 | BK23: 1500 | BL23: 1500 | BM23: 1500 | BN23: 1500 | BO23: 1500 | BP23: 2000 | BQ23: 2000 | BR23: 2000 | BS23: 2000 | BT23: 2000 | BU23: 2000 | BV23: 2000 | BW23: 2000 | BX23: 2000 | BY23: 2000 | BZ23: 2000 | CA23: 2000 | CB23: 2000 | CC23: 2000 | CD23: 2000 | CE23: 2000 | CF23: 2000 | CG23: 2000 | CH23: 2000 | CI23: 2000 | CJ23: 2000 | CK23: 2000 | CL23: 2000 | CM23: 2000 | CN23: 2000 | CO23: 2000 | CP23: 2000
A24: Tier 1 customer support
A26: Marketing expenses
A27: Content creation | AH27: 0 | AI27: 1000 | AJ27: 1000 | AK27: 1000 | AL27: 1000 | AM27: 1000 | AN27: 1000 | AO27: 1000 | AP27: 10000 | AQ27: 2000 | AR27: 2000 | AS27: 2000 | AT27: 2000 | AU27: 2000 | AV27: 2000 | AW27: 2000 | AX27: 2000 | AY27: 2000 | AZ27: 2000 | BA27: 2000 | BB27: 5000 | BC27: 5000 | BD27: 5000 | BE27: 5000 | BF27: 5000 | BG27: 5000 | BH27: 5000 | BI27: 5000 | BJ27: 3000 | BK27: 3000 | BL27: 3000 | BM27: 3000 | BN27: 3000 | BO27: 3000 | BP27: 3000 | BQ27: 3000 | BR27: 3000 | BS27: 3000 | BT27: 3000 | BU27: 3000 | BV27: 3000 | BW27: 3000 | BX27: 3000 | BY27: 3000 | BZ27: 3000 | CA27: 3000 | CB27: 3000 | CC27: 3000 | CD27: 3000 | CE27: 3000 | CF27: 3000 | CG27: 3000 | CH27: 10000 | CI27: 10000 | CJ27: 10000 | CK27: 10000 | CL27: 10000 | CM27: 10000 | CN27: 10000 | CO27: 10000 | CP27: 10000
A28: Marketing at spend | AH28: 10000 | AI28: 10000 | AJ28: 5000 | AK28: 5000 | AL28: 5000 | AM28: 7000 | AN28: 7000 | AO28: 7000 | AP28: 7000 | AQ28: 7000 | AR28: 7000 | AS28: 7000 | AT28: 5000 | AU28: 8000 | AV28: 15000 | AW28: 25000 | AX28: 25000 | AY28: 25000 | AZ28: 25000 | BA28: 25000 | BB28: 25000 | BC28: 15000 | BD28: 15000 | BE28: 15000 | BF28: 15000 | BG28: 25000 | BH28: 10000 | BI28: 10000 | BJ28: 10000 | BK28: 10000 | BL28: 10000 | BM28: 10000 | BN28: 10000 | BO28: 10000 | BP28: 15000 | BQ28: 15000 | BR28: 15000 | BS28: 15000 | BT28: 15000 | BU28: 20000 | BV28: 25000 | BW28: 25000 | BX28: 25000 | BY28: 30000 | BZ28: 30000 | CA28: 30000 | CB28: 30000 | CC28: 30000 | CD28: 30000 | CE28: 35000 | CF28: 35000 | CG28: 40000 | CH28: 40000 | CI28: 40000 | CJ28: 45000 | CK28: 45000 | CL28: 50000 | CM28: 50000 | CN28: 50000 | CO28: 50000 | CP28: 50000
A29: Instagram
A30: Facebook
A31: TikTok
A32: Brand Ambassador | AH32: 0 | AI32: 0 | AJ32: 0 | AK32: 0 | AL32: 0 | AM32: 0 | AN32: 0 | AO32: 0 | AP32: 0 | AQ32: 0 | AR32: 0 | AS32: 0 | AT32: 0 | AU32: 0 | AV32: 0 | AW32: 0 | AX32: 0 | AY32: 0 | AZ32: 0 | BA32: 0 | BB32: 0 | BC32: 0 | BD32: 0 | BE32: 0 | BF32: 0 | BG32: 0 | BH32: 0 | BI32: 0 | BJ32: 0 | BK32: 0 | BL32: 0 | BM32: 0 | BN32: 0 | BO32: 0 | BP32: 0 | BQ32: 0 | BR32: 0 | BS32: 0 | BT32: 0 | BU32: 0 | BV32: 0 | BW32: 0 | BX32: 0 | BY32: 0 | BZ32: 0 | CA32: 0 | CB32: 0 | CC32: 0 | CD32: 0 | CE32: 0 | CF32: 0 | CG32: 0 | CH32: 0 | CI32: 0 | CJ32: 0 | CK32: 0 | CL32: 0 | CM32: 0 | CN32: 0 | CO32: 0 | CP32: 0 | CQ32: 0 | CR32: 0 | CS32: 0 | CT32: 0 | CU32: 0 | CV32: 0 | CW32: 0 | CX32: 0
A33: Operations
A34: Website maintenance and design | AH34: 1500 | AI34: 1500 | AJ34: 1500 | AK34: 1500 | AL34: 1500 | AM34: 1500 | AN34: 1500 | AO34: 1500 | AP34: 1500 | AQ34: 1500 | AR34: 1500 | AS34: 1500 | AT34: 1500 | AU34: 2500 | AV34: 2500 | AW34: 2500 | AX34: 2500 | AY34: 2500 | AZ34: 2500 | BA34: 2500 | BB34: 2500 | BC34: 2500 | BD34: 2500 | BE34: 2500 | BF34: 2500 | BG34: 2500 | BH34: 2500 | BI34: 2500 | BJ34: 2500 | BK34: 2500 | BL34: 2500 | BM34: 2500 | BN34: 2500 | BO34: 2500 | BP34: 2500 | BQ34: 2500 | BR34: 2500 | BS34: 2500 | BT34: 2500 | BU34: 2500 | BV34: 2500 | BW34: 2500 | BX34: 2500 | BY34: 2500 | BZ34: 2500 | CA34: 2500 | CB34: 2500 | CC34: 2500 | CD34: 2500 | CE34: 2500 | CF34: 2500 | CG34: 2500 | CH34: 2500 | CI34: 2500 | CJ34: 2500 | CK34: 2500 | CL34: 2500 | CM34: 2500 | CN34: 2500 | CO34: 2500 | CP34: 2500
A35: Website hosting
A36: Website utility and operations platform | AH36: 0 | AI36: 0 | AJ36: 0 | AK36: 0 | AL36: 0 | AM36: 0 | AN36: 0 | AO36: 0 | AP36: 0 | AQ36: 0 | AR36: 0 | AS36: 0 | AT36: 0 | AU36: 0 | AV36: 2000 | AW36: 2000 | AX36: 2000 | AY36: 2000 | AZ36: 2000 | BA36: 2000 | BB36: 2000 | BC36: 2000 | BD36: 2000 | BE36: 2000 | BF36: 2000 | BG36: 2000 | BH36: 2000 | BI36: 2000 | BJ36: 2000 | BK36: 2000 | BL36: 2000 | BM36: 2000 | BN36: 2000 | BO36: 2000 | BP36: 2000 | BQ36: 1000 | BR36: 1000 | BS36: 1000 | BT36: 1000 | BU36: 1000 | BV36: 1000 | BW36: 1000 | BX36: 1000 | BY36: 1000 | BZ36: 1000 | CA36: 1000 | CB36: 1000 | CC36: 1000 | CD36: 1000 | CE36: 1000 | CF36: 1000 | CG36: 1000 | CH36: 1000 | CI36: 1000 | CJ36: 1000 | CK36: 1000 | CL36: 1000 | CM36: 1000 | CN36: 1000 | CO36: 1000 | CP36: 1000
A37: Marketing events and sponsorships
A38: Public relations | AI38: 0 | AJ38: 0 | AK38: 0 | AL38: 0 | AM38: 0 | AN38: 0 | AO38: 0 | AP38: 0 | AQ38: 0 | AR38: 0 | AS38: 0 | AT38: 0 | AU38: 0 | AV38: 0 | AW38: 0 | AX38: 0 | AY38: 0 | AZ38: 0 | BA38: 0 | BB38: 0 | BC38: 0 | BD38: 0 | BE38: 0 | BF38: 0 | BG38: 0 | BH38: 0 | BI38: 0 | BJ38: 0 | BK38: 0 | BL38: 0 | BM38: 0 | BN38: 0 | BO38: 0 | BP38: 0 | BQ38: 0 | BR38: 0 | BS38: 0 | BT38: 0 | BU38: 0 | BV38: 0 | BW38: 0 | BX38: 0 | BY38: 0 | BZ38: 0 | CA38: 0 | CB38: 0 | CC38: 0 | CD38: 0 | CE38: 0 | CF38: 0 | CG38: 0 | CH38: 0 | CI38: 0 | CJ38: 0 | CK38: 0 | CL38: 0 | CM38: 0 | CN38: 0 | CO38: 0 | CP38: 0
A40: Selling and G&A expenses
A41: Salaries
A42: Officer, administration and customer service | AH42: 3000 | AI42: 3000 | AJ42: 3000 | AK42: 3000 | AL42: 3000 | AM42: 3000 | AN42: 3000 | AO42: 3000 | AP42: 3000 | AQ42: 3000 | AR42: 3000 | AS42: 3000 | AT42: 3000 | AU42: 3000 | AV42: 3000 | AW42: 3000 | AX42: 3000 | AY42: 3000 | AZ42: 3000 | BA42: 3000 | BB42: 3000 | BC42: 3000 | BD42: 3000 | BE42: 3000 | BF42: 3000 | BG42: 5000 | BH42: 5000 | BI42: 5000 | BJ42: 5000 | BK42: 5000 | BL42: 5000 | BM42: 5000 | BN42: 5000 | BO42: 5000 | BP42: 5000 | BQ42: 5000 | BR42: 5000 | BS42: 5000 | BT42: 5000 | BU42: 5000 | BV42: 5000 | BW42: 5000 | BX42: 5000 | BY42: 5000 | BZ42: 5000 | CA42: 5000 | CB42: 5000 | CC42: 5000 | CD42: 5000 | CE42: 5000 | CF42: 5000 | CG42: 5000 | CH42: 5000 | CI42: 5000 | CJ42: 5000 | CK42: 5000 | CL42: 5000 | CM42: 5000 | CN42: 5000 | CO42: 5000 | CP42: 5000
A43: Credit card processing fees | AH43: =+'P&L Cash Flow Monthly'!AH15*0.04 -> 3593.9679 | AI43: =+'P&L Cash Flow Monthly'!AI15*0.04 -> 3113.516 | AJ43: =+'P&L Cash Flow Monthly'!AJ15*0.04 -> 2813.6804 | AK43: =+'P&L Cash Flow Monthly'!AK15*0.04 -> 2489.2217 | AL43: =+'P&L Cash Flow Monthly'!AL15*0.04 -> 2171.707 | AM43: =+'P&L Cash Flow Monthly'!AM15*0.04 -> 2227.1673 | AN43: =+'P&L Cash Flow Monthly'!AN15*0.04 -> 2303.862 | AO43: =+'P&L Cash Flow Monthly'!AO15*0.04 -> 2380.6574 | ... CP43: =+'P&L Cash Flow Monthly'!CP15*0.04 -> 10080.615
A44: Warehousing | AH44: 200 | AI44: 200 | AJ44: 200 | AK44: 200 | AL44: 200 | AM44: 200 | AN44: 200 | AO44: 200 | AP44: 200 | AQ44: 200 | AR44: 200 | AS44: 200 | AT44: 200 | AU44: 1200 | AV44: 1200 | AW44: 1200 | AX44: 1200 | AY44: 1200 | AZ44: 1200 | BA44: 1200 | BB44: 1200 | BC44: 1200 | BD44: 1200 | BE44: 1200 | BF44: 1200 | BG44: 1200 | BH44: 1200 | BI44: 1200 | BJ44: 1200 | BK44: 1200 | BL44: 1200 | BM44: 1200 | BN44: 1200 | BO44: 1200 | BP44: 1200 | BQ44: 2400 | BR44: 2400 | BS44: 5500 | BT44: 5500 | BU44: 5500 | BV44: 5500 | BW44: 5500 | BX44: 5500 | BY44: 5500 | BZ44: 5500 | CA44: 5500 | CB44: 5500 | CC44: 5500 | CD44: 5500 | CE44: 5500 | CF44: 5500 | CG44: 5500 | CH44: 5500 | CI44: 5500 | CJ44: 5500 | CK44: 5500 | CL44: 5500 | CM44: 5500 | CN44: 5500 | CO44: 5500 | CP44: 5500
A45: E-commerce platform (ie Shopify) | AH45: 1200 | AI45: 1200 | AJ45: 1200 | AK45: 1200 | AL45: 1200 | AM45: 1200 | AN45: 1200 | AO45: 1200 | AP45: 1200 | AQ45: 1200 | AR45: 1200 | AS45: 1200 | AT45: 1200 | AU45: 1200 | AV45: 1200 | AW45: 1200 | AX45: 1200 | AY45: 1200 | AZ45: 1200 | BA45: 1200 | BB45: 1200 | BC45: 1200 | BD45: 1200 | BE45: 1200 | BF45: 1200 | BG45: 1200 | BH45: 1200 | BI45: 1200 | BJ45: 1200 | BK45: 1200 | BL45: 1200 | BM45: 1200 | BN45: 1200 | BO45: 1200 | BP45: 1200 | BQ45: 1200 | BR45: 1200 | BS45: 1200 | BT45: 1200 | BU45: 1200 | BV45: 1200 | BW45: 1200 | BX45: 1200 | BY45: 1200 | BZ45: 1200 | CA45: 1200 | CB45: 1200 | CC45: 1200 | CD45: 1200 | CE45: 1200 | CF45: 1200 | CG45: 1200 | CH45: 1200 | CI45: 1200 | CJ45: 1200 | CK45: 1200 | CL45: 1200 | CM45: 1200 | CN45: 1200 | CO45: 1200 | CP45: 1200
A46: Rent | AH46: 1300 | AI46: 1300 | AJ46: 1300 | AK46: 1300 | AL46: 1300 | AM46: 1300 | AN46: 1300 | AO46: 1300 | AP46: 1300 | AQ46: 1300 | AR46: 1300 | AS46: 1300 | AT46: 1300 | AU46: 1300 | AV46: 1300 | AW46: 1300 | AX46: 1300 | AY46: 1300 | AZ46: 1300 | BA46: 1300 | BB46: 1300 | BC46: 1300 | BD46: 1300 | BE46: 1300 | BF46: 1300 | BG46: 1300 | BH46: 1300 | BI46: 1300 | BJ46: 1300 | BK46: 1300 | BL46: 1300 | BM46: 1300 | BN46: 1300 | BO46: 1300 | BP46: 1300 | BQ46: 5000 | BR46: 5000 | BS46: 5000 | BT46: 5000 | BU46: 5000 | BV46: 5000 | BW46: 5000 | BX46: 5000 | BY46: 5000 | BZ46: 5000 | CA46: 5000 | CB46: 5000 | CC46: 5000 | CD46: 5000 | CE46: 5000 | CF46: 5000 | CG46: 5000 | CH46: 5000 | CI46: 5000 | CJ46: 5000 | CK46: 5000 | CL46: 5000 | CM46: 5000 | CN46: 5000 | CO46: 5000 | CP46: 5000
A47: Utilities | AH47: 200 | AI47: 200 | AJ47: 200 | AK47: 200 | AL47: 200 | AM47: 1500 | AN47: 1500 | AO47: 1500 | AP47: 1500 | AQ47: 1500 | AR47: 1500 | AS47: 1500 | AT47: 1500 | AU47: 1500 | AV47: 1500 | AW47: 1500 | AX47: 1500 | AY47: 1500 | AZ47: 1500 | BA47: 1500 | BB47: 1500 | BC47: 1500 | BD47: 1500 | BE47: 1500 | BF47: 1500 | BG47: 1500 | BH47: 1500 | BI47: 1500 | BJ47: 1500 | BK47: 1500 | BL47: 1500 | BM47: 1500 | BN47: 1500 | BO47: 1500 | BP47: 3000 | BQ47: 3000 | BR47: 3000 | BS47: 3000 | BT47: 3000 | BU47: 3000 | BV47: 3000 | BW47: 3000 | BX47: 3000 | BY47: 3000 | BZ47: 3000 | CA47: 3000 | CB47: 3000 | CC47: 3000 | CD47: 3000 | CE47: 3000 | CF47: 3000 | CG47: 3000 | CH47: 3000 | CI47: 3000 | CJ47: 3000 | CK47: 3000 | CL47: 3000 | CM47: 3000 | CN47: 3000 | CO47: 3000 | CP47: 3000
A48: Internet, cable and phone | AH48: 400 | AI48: 400 | AJ48: 400 | AK48: 400 | AL48: 400 | AM48: 800 | AN48: 800 | AO48: 800 | AP48: 800 | AQ48: 800 | AR48: 800 | AS48: 800 | AT48: 800 | AU48: 800 | AV48: 800 | AW48: 800 | AX48: 800 | AY48: 800 | AZ48: 800 | BA48: 800 | BB48: 800 | BC48: 800 | BD48: 800 | BE48: 800 | BF48: 800 | BG48: 1400 | BH48: 1400 | BI48: 1400 | BJ48: 1400 | BK48: 1400 | BL48: 1400 | BM48: 1400 | BN48: 1400 | BO48: 1400 | BP48: 1400 | BQ48: 1400 | BR48: 1400 | BS48: 1400 | BT48: 1400 | BU48: 1400 | BV48: 1400 | BW48: 1400 | BX48: 1400 | BY48: 1400 | BZ48: 1400 | CA48: 1400 | CB48: 1400 | CC48: 1400 | CD48: 1400 | CE48: 1400 | CF48: 1400 | CG48: 1400 | CH48: 1400 | CI48: 1400 | CJ48: 1400 | CK48: 1400 | CL48: 1400 | CM48: 1400 | CN48: 1400 | CO48: 1400 | CP48: 1400
A49: Computer | AH49: 500 | AI49: 500 | AJ49: 500 | AK49: 500 | AL49: 500 | AM49: 500 | AN49: 500 | AO49: 500 | AP49: 500 | AQ49: 500 | AR49: 500 | AS49: 500 | AT49: 500 | AU49: 500 | AV49: 500 | AW49: 500 | AX49: 500 | AY49: 500 | AZ49: 500 | BA49: 500 | BB49: 500 | BC49: 500 | BD49: 500 | BE49: 500 | BF49: 500 | BG49: 500 | BH49: 500 | BI49: 500 | BJ49: 500 | BK49: 500 | BL49: 500 | BM49: 500 | BN49: 500 | BO49: 500 | BP49: 500 | BQ49: 2500 | BR49: 2500 | BS49: 2500 | BT49: 2500 | BU49: 2500 | BV49: 2500 | BW49: 2500 | BX49: 2500 | BY49: 2500 | BZ49: 2500 | CA49: 2500 | CB49: 2500 | CC49: 2500 | CD49: 2500 | CE49: 2500 | CF49: 2500 | CG49: 2500 | CH49: 2500 | CI49: 2500 | CJ49: 2500 | CK49: 2500 | CL49: 2500 | CM49: 2500 | CN49: 2500 | CO49: 2500 | CP49: 2500
A50: Insurance | AH50: ='P&L Cash Flow Monthly'!AH15*0.00285 -> 256.07022 | AI50: ='P&L Cash Flow Monthly'!AI15*0.00285 -> 221.83802 | AJ50: ='P&L Cash Flow Monthly'!AJ15*0.00285 -> 200.47473 | AK50: ='P&L Cash Flow Monthly'!AK15*0.00285 -> 177.35704 | AL50: ='P&L Cash Flow Monthly'!AL15*0.00285 -> 154.73413 | AM50: ='P&L Cash Flow Monthly'!AM15*0.00285 -> 158.68567 | AN50: ='P&L Cash Flow Monthly'!AN15*0.00285 -> 164.15017 | AO50: ='P&L Cash Flow Monthly'!AO15*0.00285 -> 169.62184 | ... CP50: ='P&L Cash Flow Monthly'!CP15*0.00285 -> 718.24382
A51: Travel | AH51: 2000 | AI51: 2000 | AJ51: 2000 | AK51: 2000 | AL51: 2000 | AM51: 2000 | AN51: 2000 | AO51: 2000 | AP51: 2000 | AQ51: 2000 | AR51: 2000 | AS51: 2000 | AT51: 2000 | AU51: 2000 | AV51: 2000 | AW51: 2000 | AX51: 2000 | AY51: 2000 | AZ51: 2000 | BA51: 2000 | BB51: 2000 | BC51: 2000 | BD51: 2000 | BE51: 2000 | BF51: 2000 | BG51: 2000 | BH51: 2000 | BI51: 2000 | BJ51: 2000 | BK51: 2000 | BL51: 2000 | BM51: 2000 | BN51: 1000 | BO51: 1000 | BP51: 1000 | BQ51: 1000 | BR51: 1000 | BS51: 1000 | BT51: 1000 | BU51: 1000 | BV51: 1000 | BW51: 1000 | BX51: 1000 | BY51: 1000 | BZ51: 1000 | CA51: 1000 | CB51: 1000 | CC51: 1000 | CD51: 1000 | CE51: 1000 | CF51: 1000 | CG51: 1000 | CH51: 1000 | CI51: 1000 | CJ51: 1000 | CK51: 1000 | CL51: 1000 | CM51: 1000 | CN51: 1000 | CO51: 1000 | CP51: 1000
A52: Accounting | AH52: 500 | AI52: 1000 | AJ52: 1000 | AK52: 1000 | AL52: 1000 | AM52: 1000 | AN52: 1000 | AO52: 1000 | AP52: 1000 | AQ52: 1000 | AR52: 1000 | AS52: 1000 | AT52: 1000 | AU52: 1000 | AV52: 1000 | AW52: 1000 | AX52: 1000 | AY52: 1000 | AZ52: 1000 | BA52: 1000 | BB52: 1000 | BC52: 1000 | BD52: 1000 | BE52: 1000 | BF52: 1000 | BG52: 1000 | BH52: 1000 | BI52: 1000 | BJ52: 1000 | BK52: 1000 | BL52: 1000 | BM52: 1000 | BN52: 1000 | BO52: 1000 | BP52: 1000 | BQ52: 1000 | BR52: 1000 | BS52: 1000 | BT52: 1000 | BU52: 1000 | BV52: 1000 | BW52: 1000 | BX52: 1000 | BY52: 1000 | BZ52: 1000 | CA52: 1000 | CB52: 1000 | CC52: 1000 | CD52: 1000 | CE52: 2000 | CF52: 2000 | CG52: 2000 | CH52: 2000 | CI52: 2000 | CJ52: 2000 | CK52: 2000 | CL52: 2000 | CM52: 2000 | CN52: 2000 | CO52: 2000 | CP52: 2000
A53: Legal | BX53: 1000 | BY53: 1000 | BZ53: 1000 | CA53: 0 | CC53: 1000 | CD53: 1000 | CF53: 1000 | CG53: 1000 | CI53: 1000 | CJ53: 1000 | CK53: 1000 | CL53: 1000 | CM53: 1000 | CN53: 1000 | CO53: 1000 | CP53: 1000
